Workbook

Sheet Cover
B7: Deal Overview: | F7: Table of Contents:
B9: Company: | C9: Apple Inc. | F9: Outputs - Base
B10: Industry: | C10: Consumer Electronics | F10: DCF Model - Base (1)
F11: DCF Model - Bull (2)
B12: Scenario | C12: 1 | F12: DCF Model - Bear (3)
F13: WACC
B14: Implied Equity Value - GGM | C14: =CHOOSE($C$12,'DCF Model - Base (1)'!Q111,'DCF Model - Bull (2)'!Q111,'DCF Model - Bear (3)'!Q111) -> 1063996.9 | F14: Comps
B15: Implied Equity Value - Multiples | C15: =CHOOSE($C$12,'DCF Model - Base (1)'!Q98,'DCF Model - Bull (2)'!Q98,'DCF Model - Bear (3)'!Q98) -> 1390376.5 | F15: Data Given (Recalculated)
B17: Implied Upside - GGM | C17: =CHOOSE($C$12,'DCF Model - Base (1)'!Q113,'DCF Model - Bull (2)'!Q113,'DCF Model - Bear (3)'!Q113) -> -0.78151708
B18: Implied Upside - Multiples | C18: =CHOOSE($C$12,'DCF Model - Base (1)'!Q100,'DCF Model - Bull (2)'!Q100,'DCF Model - Bear (3)'!Q100) -> -0.71449776
B20: Last Modified: | C20: 46298
B22: Authors: | F22: Legend:
B24: Name: | F24: xxx | G24: Hard Coded Figure
B25: Email: | F25: xxx | G25: Soft Coded Figure
B26: Phone Number: | F26: xxx | G26: Reference from Preceding Cell
F27: xxx | G27: Change in Formula/Odd Calculation
F28: xxx | G28: Reference from Other Worksheet

Sheet Outputs - Base
B2: Discounted Cash Flow Output
B3: Company Apple Inc.
B4: All $ in USD millions unless otherwise stated
B6: Discounted Cash Flow | H6: FY2021A | I6: FY2022A | J6: FY2023A | K6: FY2024A | L6: FY2025A | M6: FY2026E | N6: FY2027E | O6: FY2028E | P6: FY2029E | Q6: FY2030E
B8: EBIT | H8: =CHOOSE(Cover!$C$12,'DCF Model - Base (1)'!H51,'DCF Model - Bull (2)'!H51,'DCF Model - Bear (3)'!H51) -> 108949 | I8: =CHOOSE(Cover!$C$12,'DCF Model - Base (1)'!I51,'DCF Model - Bull (2)'!I51,'DCF Model - Bear (3)'!I51) -> 119437 | J8: =CHOOSE(Cover!$C$12,'DCF Model - Base (1)'!J51,'DCF Model - Bull (2)'!J51,'DCF Model - Bear (3)'!J51) -> 114301 | K8: =CHOOSE(Cover!$C$12,'DCF Model - Base (1)'!K51,'DCF Model - Bull (2)'!K51,'DCF Model - Bear (3)'!K51) -> 123216 | L8: =CHOOSE(Cover!$C$12,'DCF Model - Base (1)'!L51,'DCF Model - Bull (2)'!L51,'DCF Model - Bear (3)'!L51) -> 133050 | M8: =CHOOSE(Cover!$C$12,'DCF Model - Base (1)'!M51,'DCF Model - Bull (2)'!M51,'DCF Model - Bear (3)'!M51) -> 136666.18 | N8: =CHOOSE(Cover!$C$12,'DCF Model - Base (1)'!N51,'DCF Model - Bull (2)'!N51,'DCF Model - Bear (3)'!N51) -> 140376.44 | O8: =CHOOSE(Cover!$C$12,'DCF Model - Base (1)'!O51,'DCF Model - Bull (2)'!O51,'DCF Model - Bear (3)'!O51) -> 144183.06 | ... Q8: =CHOOSE(Cover!$C$12,'DCF Model - Base (1)'!Q51,'DCF Model - Bull (2)'!Q51,'DCF Model - Bear (3)'!Q51) -> 150648.74
B9: (+) Depreciation & Amortization | H9: =CHOOSE(Cover!$C$12,'DCF Model - Base (1)'!H68,'DCF Model - Bull (2)'!H68,'DCF Model - Bear (3)'!H68) -> 11284 | I9: =CHOOSE(Cover!$C$12,'DCF Model - Base (1)'!I68,'DCF Model - Bull (2)'!I68,'DCF Model - Bear (3)'!I68) -> 11104 | J9: =CHOOSE(Cover!$C$12,'DCF Model - Base (1)'!J68,'DCF Model - Bull (2)'!J68,'DCF Model - Bear (3)'!J68) -> 11519 | K9: =CHOOSE(Cover!$C$12,'DCF Model - Base (1)'!K68,'DCF Model - Bull (2)'!K68,'DCF Model - Bear (3)'!K68) -> 11445 | L9: =CHOOSE(Cover!$C$12,'DCF Model - Base (1)'!L68,'DCF Model - Bull (2)'!L68,'DCF Model - Bear (3)'!L68) -> 11698 | M9: =CHOOSE(Cover!$C$12,'DCF Model - Base (1)'!M68,'DCF Model - Bull (2)'!M68,'DCF Model - Bear (3)'!M68) -> 12526.292 | N9: =CHOOSE(Cover!$C$12,'DCF Model - Base (1)'!N68,'DCF Model - Bull (2)'!N68,'DCF Model - Bear (3)'!N68) -> 12937.154 | O9: =CHOOSE(Cover!$C$12,'DCF Model - Base (1)'!O68,'DCF Model - Bull (2)'!O68,'DCF Model - Bear (3)'!O68) -> 13361.493 | ... Q9: =CHOOSE(Cover!$C$12,'DCF Model - Base (1)'!Q68,'DCF Model - Bull (2)'!Q68,'DCF Model - Bear (3)'!Q68) -> 14116.88
B10: EBITDA | H10: =CHOOSE(Cover!$C$12,'DCF Model - Base (1)'!H54,'DCF Model - Bull (2)'!H54,'DCF Model - Bear (3)'!H54) -> 120233 | I10: =CHOOSE(Cover!$C$12,'DCF Model - Base (1)'!I54,'DCF Model - Bull (2)'!I54,'DCF Model - Bear (3)'!I54) -> 130541 | J10: =CHOOSE(Cover!$C$12,'DCF Model - Base (1)'!J54,'DCF Model - Bull (2)'!J54,'DCF Model - Bear (3)'!J54) -> 125820 | K10: =CHOOSE(Cover!$C$12,'DCF Model - Base (1)'!K54,'DCF Model - Bull (2)'!K54,'DCF Model - Bear (3)'!K54) -> 134661 | L10: =CHOOSE(Cover!$C$12,'DCF Model - Base (1)'!L54,'DCF Model - Bull (2)'!L54,'DCF Model - Bear (3)'!L54) -> 144748 | M10: =CHOOSE(Cover!$C$12,'DCF Model - Base (1)'!M54,'DCF Model - Bull (2)'!M54,'DCF Model - Bear (3)'!M54) -> 149192.47 | N10: =CHOOSE(Cover!$C$12,'DCF Model - Base (1)'!N54,'DCF Model - Bull (2)'!N54,'DCF Model - Bear (3)'!N54) -> 153313.59 | O10: =CHOOSE(Cover!$C$12,'DCF Model - Base (1)'!O54,'DCF Model - Bull (2)'!O54,'DCF Model - Bear (3)'!O54) -> 157544.55 | ... Q10: =CHOOSE(Cover!$C$12,'DCF Model - Base (1)'!Q54,'DCF Model - Bull (2)'!Q54,'DCF Model - Bear (3)'!Q54) -> 164765.62
B12: NOPAT | H12: =CHOOSE(Cover!$C$12,'DCF Model - Base (1)'!H60,'DCF Model - Bull (2)'!H60,'DCF Model - Bear (3)'!H60) -> 91942.059 | I12: =CHOOSE(Cover!$C$12,'DCF Model - Base (1)'!I60,'DCF Model - Bull (2)'!I60,'DCF Model - Bear (3)'!I60) -> 100792.88 | J12: =CHOOSE(Cover!$C$12,'DCF Model - Base (1)'!J60,'DCF Model - Bull (2)'!J60,'DCF Model - Bear (3)'!J60) -> 96458.611 | K12: =CHOOSE(Cover!$C$12,'DCF Model - Base (1)'!K60,'DCF Model - Bull (2)'!K60,'DCF Model - Bear (3)'!K60) -> 103981.98 | L12: =CHOOSE(Cover!$C$12,'DCF Model - Base (1)'!L60,'DCF Model - Bull (2)'!L60,'DCF Model - Bear (3)'!L60) -> 112280.89 | M12: =CHOOSE(Cover!$C$12,'DCF Model - Base (1)'!M60,'DCF Model - Bull (2)'!M60,'DCF Model - Bear (3)'!M60) -> 115332.59 | N12: =CHOOSE(Cover!$C$12,'DCF Model - Base (1)'!N60,'DCF Model - Bull (2)'!N60,'DCF Model - Bear (3)'!N60) -> 118463.67 | O12: =CHOOSE(Cover!$C$12,'DCF Model - Base (1)'!O60,'DCF Model - Bull (2)'!O60,'DCF Model - Bear (3)'!O60) -> 121676.08 | ... Q12: =CHOOSE(Cover!$C$12,'DCF Model - Base (1)'!Q60,'DCF Model - Bull (2)'!Q60,'DCF Model - Bear (3)'!Q60) -> 127132.47
B13: (+) Depreciation | H13: =H9 -> 11284 | I13: =I9 -> 11104 | J13: =J9 -> 11519 | K13: =K9 -> 11445 | L13: =L9 -> 11698 | M13: =M9 -> 12526.292 | N13: =N9 -> 12937.154 | O13: =O9 -> 13361.493 | ... Q13: =Q9 -> 14116.88
B14: (-) Capital Expenditures | H14: =CHOOSE(Cover!$C$12,'DCF Model - Base (1)'!H65,'DCF Model - Bull (2)'!H65,'DCF Model - Bear (3)'!H65) -> -11085 | I14: =CHOOSE(Cover!$C$12,'DCF Model - Base (1)'!I65,'DCF Model - Bull (2)'!I65,'DCF Model - Bear (3)'!I65) -> -10708 | J14: =CHOOSE(Cover!$C$12,'DCF Model - Base (1)'!J65,'DCF Model - Bull (2)'!J65,'DCF Model - Bear (3)'!J65) -> -10959 | K14: =CHOOSE(Cover!$C$12,'DCF Model - Base (1)'!K65,'DCF Model - Bull (2)'!K65,'DCF Model - Bear (3)'!K65) -> -9447 | L14: =CHOOSE(Cover!$C$12,'DCF Model - Base (1)'!L65,'DCF Model - Bull (2)'!L65,'DCF Model - Bear (3)'!L65) -> -12715 | M14: =CHOOSE(Cover!$C$12,'DCF Model - Base (1)'!M65,'DCF Model - Bull (2)'!M65,'DCF Model - Bear (3)'!M65) -> -11935.043 | N14: =CHOOSE(Cover!$C$12,'DCF Model - Base (1)'!N65,'DCF Model - Bull (2)'!N65,'DCF Model - Bear (3)'!N65) -> -12326.513 | O14: =CHOOSE(Cover!$C$12,'DCF Model - Base (1)'!O65,'DCF Model - Bull (2)'!O65,'DCF Model - Bear (3)'!O65) -> -12730.822 | ... Q14: =CHOOSE(Cover!$C$12,'DCF Model - Base (1)'!Q65,'DCF Model - Bull (2)'!Q65,'DCF Model - Bear (3)'!Q65) -> -13450.554
B15: (-) Change in NWC | H15: =CHOOSE(Cover!$C$12,'DCF Model - Base (1)'!H77,'DCF Model - Bull (2)'!H77,'DCF Model - Bear (3)'!H77) | I15: =CHOOSE(Cover!$C$12,'DCF Model - Base (1)'!I77,'DCF Model - Bull (2)'!I77,'DCF Model - Bear (3)'!I77) -> 9080 | J15: =CHOOSE(Cover!$C$12,'DCF Model - Base (1)'!J77,'DCF Model - Bull (2)'!J77,'DCF Model - Bear (3)'!J77) -> -4213 | K15: =CHOOSE(Cover!$C$12,'DCF Model - Base (1)'!K77,'DCF Model - Bull (2)'!K77,'DCF Model - Bear (3)'!K77) -> 1492 | L15: =CHOOSE(Cover!$C$12,'DCF Model - Base (1)'!L77,'DCF Model - Bull (2)'!L77,'DCF Model - Bear (3)'!L77) -> -3899 | M15: =CHOOSE(Cover!$C$12,'DCF Model - Base (1)'!M77,'DCF Model - Bull (2)'!M77,'DCF Model - Bear (3)'!M77) -> 2243.5174 | N15: =CHOOSE(Cover!$C$12,'DCF Model - Base (1)'!N77,'DCF Model - Bull (2)'!N77,'DCF Model - Bear (3)'!N77) -> 872.75937 | O15: =CHOOSE(Cover!$C$12,'DCF Model - Base (1)'!O77,'DCF Model - Bull (2)'!O77,'DCF Model - Bear (3)'!O77) -> 901.38588 | ... Q15: =CHOOSE(Cover!$C$12,'DCF Model - Base (1)'!Q77,'DCF Model - Bull (2)'!Q77,'DCF Model - Bear (3)'!Q77) -> 766.74642
B16: Unlevered Free Cash Flow | H16: =SUM(H12:H15) -> 92141.059 | I16: =SUM(I12:I15) -> 110268.88 | J16: =SUM(J12:J15) -> 92805.611 | K16: =SUM(K12:K15) -> 107471.98 | L16: =SUM(L12:L15) -> 107364.89 | M16: =SUM(M12:M15) -> 118167.35 | N16: =SUM(N12:N15) -> 119947.07 | O16: =SUM(O12:O15) -> 123208.14 | ... Q16: =SUM(Q12:Q15) -> 128565.54
B18: Date of Valuation | E18: =CHOOSE(Cover!$C$12,'DCF Model - Base (1)'!I9,'DCF Model - Bull (2)'!I9,'DCF Model - Bear (3)'!I9) -> 46298
B19: Date For Discounting Cash Flows | M19: =CHOOSE(Cover!$C$12,'DCF Model - Base (1)'!M82,'DCF Model - Bull (2)'!M82,'DCF Model - Bear (3)'!M82) -> 46660 | N19: =CHOOSE(Cover!$C$12,'DCF Model - Base (1)'!N82,'DCF Model - Bull (2)'!N82,'DCF Model - Bear (3)'!N82) -> 47026 | O19: =CHOOSE(Cover!$C$12,'DCF Model - Base (1)'!O82,'DCF Model - Bull (2)'!O82,'DCF Model - Bear (3)'!O82) -> 47391 | P19: =CHOOSE(Cover!$C$12,'DCF Model - Base (1)'!P82,'DCF Model - Bull (2)'!P82,'DCF Model - Bear (3)'!P82) -> 47756 | Q19: =CHOOSE(Cover!$C$12,'DCF Model - Base (1)'!Q82,'DCF Model - Bull (2)'!Q82,'DCF Model - Bear (3)'!Q82) -> 48121
B20: Period, Stub Adjusted | M20: =CHOOSE(Cover!$C$12,'DCF Model - Base (1)'!M83,'DCF Model - Bull (2)'!M83,'DCF Model - Bear (3)'!M83) -> 1 | N20: =CHOOSE(Cover!$C$12,'DCF Model - Base (1)'!N83,'DCF Model - Bull (2)'!N83,'DCF Model - Bear (3)'!N83) -> 2 | O20: =CHOOSE(Cover!$C$12,'DCF Model - Base (1)'!O83,'DCF Model - Bull (2)'!O83,'DCF Model - Bear (3)'!O83) -> 3 | P20: =CHOOSE(Cover!$C$12,'DCF Model - Base (1)'!P83,'DCF Model - Bull (2)'!P83,'DCF Model - Bear (3)'!P83) -> 4 | Q20: =CHOOSE(Cover!$C$12,'DCF Model - Base (1)'!Q83,'DCF Model - Bull (2)'!Q83,'DCF Model - Bear (3)'!Q83) -> 5
B21: Discount Period, Stub and Mid-Year Adjusted | M21: =CHOOSE(Cover!$C$12,'DCF Model - Base (1)'!M84,'DCF Model - Bull (2)'!M84,'DCF Model - Bear (3)'!M84) -> 0.5 | N21: =CHOOSE(Cover!$C$12,'DCF Model - Base (1)'!N84,'DCF Model - Bull (2)'!N84,'DCF Model - Bear (3)'!N84) -> 1.5 | O21: =CHOOSE(Cover!$C$12,'DCF Model - Base (1)'!O84,'DCF Model - Bull (2)'!O84,'DCF Model - Bear (3)'!O84) -> 2.5 | P21: =CHOOSE(Cover!$C$12,'DCF Model - Base (1)'!P84,'DCF Model - Bull (2)'!P84,'DCF Model - Bear (3)'!P84) -> 3.5 | Q21: =CHOOSE(Cover!$C$12,'DCF Model - Base (1)'!Q84,'DCF Model - Bull (2)'!Q84,'DCF Model - Bear (3)'!Q84) -> 4.5
B22: Discount Rate | H22: =CHOOSE(Cover!$C$12,'DCF Model - Base (1)'!$F$12,'DCF Model - Bull (2)'!$F$12,'DCF Model - Bear (3)'!$F$12) -> 0.14162494 | I22: =CHOOSE(Cover!$C$12,'DCF Model - Base (1)'!$F$12,'DCF Model - Bull (2)'!$F$12,'DCF Model - Bear (3)'!$F$12) -> 0.14162494 | J22: =CHOOSE(Cover!$C$12,'DCF Model - Base (1)'!$F$12,'DCF Model - Bull (2)'!$F$12,'DCF Model - Bear (3)'!$F$12) -> 0.14162494 | K22: =CHOOSE(Cover!$C$12,'DCF Model - Base (1)'!$F$12,'DCF Model - Bull (2)'!$F$12,'DCF Model - Bear (3)'!$F$12) -> 0.14162494 | L22: =CHOOSE(Cover!$C$12,'DCF Model - Base (1)'!$F$12,'DCF Model - Bull (2)'!$F$12,'DCF Model - Bear (3)'!$F$12) -> 0.14162494 | M22: =CHOOSE(Cover!$C$12,'DCF Model - Base (1)'!$F$12,'DCF Model - Bull (2)'!$F$12,'DCF Model - Bear (3)'!$F$12) -> 0.14162494 | N22: =CHOOSE(Cover!$C$12,'DCF Model - Base (1)'!$F$12,'DCF Model - Bull (2)'!$F$12,'DCF Model - Bear (3)'!$F$12) -> 0.14162494 | O22: =CHOOSE(Cover!$C$12,'DCF Model - Base (1)'!$F$12,'DCF Model - Bull (2)'!$F$12,'DCF Model - Bear (3)'!$F$12) -> 0.14162494 | ... Q22: =CHOOSE(Cover!$C$12,'DCF Model - Base (1)'!$F$12,'DCF Model - Bull (2)'!$F$12,'DCF Model - Bear (3)'!$F$12) -> 0.14162494
B23: Present Value of Unlevered Free Cash Flow | M23: =M16/(1+M22)^M21 -> 110595.07 | N23: =N16/(1+N22)^N21 -> 98334.177 | O23: =O16/(1+O22)^O21 -> 88477.079 | P23: =P16/(1+P22)^P21 -> 79296.173 | Q23: =Q16/(1+Q22)^Q21 -> 70838.454
B26: EV Calculation - Multiples Method | F26: EV Calculation - GGM | J26: Multiples Method
B27: WACC | D27: =CHOOSE(Cover!$C$12,'DCF Model - Base (1)'!$F$12,'DCF Model - Bull (2)'!$F$12,'DCF Model - Bear (3)'!$F$12) -> 0.14162494 | F27: WACC | H27: =D27 -> 0.14162494 | J27: Terminal Value % of TEV | L27: =D33/D35 -> 0.67010429
B28: Exit Multiple | D28: =CHOOSE(Cover!$C$12,'DCF Model - Base (1)'!$C$16,'DCF Model - Bull (2)'!$C$16,'DCF Model - Bear (3)'!$C$16) -> 10.699147 | F28: Long Term Growth Rate | H28: =CHOOSE(Cover!$C$12,'DCF Model - Base (1)'!$Q$103,'DCF Model - Bull (2)'!$Q$103,'DCF Model - Bear (3)'!$Q$103) -> 0.025 | J28: PV of UFCF % of TEV | L28: =D30/D35 -> 0.32989571
J29: Implied TV Exit EBITDA Multiple | L29: =D35/Q10 -> 8.2335952
B30: PV of UFCF | D30: =SUM(M23:Q23) -> 447540.96 | F30: PV of UFCF | H30: =D30 -> 447540.96
B31: Final Year EBITDA | D31: =Q10 -> 164765.62 | F31: Final Year UFCF × (1 + g) | H31: =Q16*(1+H28) -> 131779.68
B32: Terminal Value | D32: =D31*D28 -> 1762851.6 | F32: Terminal Value | H32: =H31/(D27-H28) -> 1129944.3
B33: PV of Terminal Value | D33: =D32/(1+D27)^Q20 -> 909072.5 | F33: PV of Terminal Value | H33: =H32/(1+H27)^Q20 -> 582692.97
J34: Gordon Growth Method
B35: Enterprise Value | D35: =D33+D30 -> 1356613.5 | F35: Enterprise Value | H35: =H33+H30 -> 1030233.9 | J35: Terminal Value % of TEV | L35: =H33/H35 -> 0.56559288
B36: (-) Outstanding Debt | D36: =-CHOOSE(Cover!$C$12,'DCF Model - Base (1)'!$AA$18,'DCF Model - Bull (2)'!$AA$18,'DCF Model - Bear (3)'!$AA$18) -> -98657 | F36: (-) Outstanding Debt | H36: =D36 -> -98657 | J36: PV of UFCF % of TEV | L36: =H30/H35 -> 0.43440712
B37: (-) Minority Interest and Preferred Equity | D37: =-CHOOSE(Cover!$C$12,'DCF Model - Base (1)'!$F$20,'DCF Model - Bull (2)'!$F$20,'DCF Model - Bear (3)'!$F$20)-CHOOSE(Cover!$C$12,'DCF Model - Base (1)'!$F$21,'DCF Model - Bull (2)'!$F$21,'DCF Model - Bear (3)'!$F$21) -> 0 | F37: (-) Minority Interest and Preferred Equity | H37: =D37 -> 0
B38: (+) Cash and Non-Operating Assets | D38: =CHOOSE(Cover!$C$12,'DCF Model - Base (1)'!$AA$17,'DCF Model - Bull (2)'!$AA$17,'DCF Model - Bear (3)'!$AA$17)+CHOOSE(Cover!$C$12,'DCF Model - Base (1)'!$AA$19,'DCF Model - Bull (2)'!$AA$19,'DCF Model - Bear (3)'!$AA$19) -> 132420 | F38: (+) Cash and Non-Operating Assets | H38: =D38 -> 132420
B40: Implied Equity Value | D40: =SUM(D35:D38) -> 1390376.5 | F40: Implied Equity Value | H40: =SUM(H35:H38) -> 1063996.9 | J40: Blended
B41: Current Equity Value | D41: =CHOOSE(Cover!$C$12,'DCF Model - Base (1)'!$C$11,'DCF Model - Bull (2)'!$C$11,'DCF Model - Bear (3)'!$C$11) -> 4869931.9 | F41: Current Equity Value | H41: =D41 -> 4869931.9 | J41: Terminal Value % of TEV | L41: =AVERAGE(L35,L27) -> 0.61784858
B42: Implied Upside | D42: =D40/D41 - 1 -> -0.71449776 | F42: Implied Upside | H42: =H40/H41 - 1 -> -0.78151708 | J42: PV of UFCF % of TEV | L42: =AVERAGE(L36,L28) -> 0.38215142
B43: Implied Share Price | D43: =D40/'DCF Model - Base (1)'!$I$16 -> 92.662748 | F43: Implied Share Price | H43: =H40/'DCF Model - Base (1)'!$I$16 -> 70.910924

Sheet DCF Model - Base (1)
B2: Discounted Cash Flow Model
B3: Company Apple Inc.
B4: All $ in USD millions unless otherwise stated
B6: Assumptions
B8: Valuation Summary | E8: Operating Assumptions | H8: Other Inputs
B9: Implied Enterprise Value | C9: =Q94 -> 1356613.5 | E9: CapEx % of Revenue | F9: 0.027768114 | H9: Valuation Date | I9: 46298
B10: Implied EV / EBITDA | C10: =IFERROR(C9/L54,0) -> 9.3722432 | E10: NWC intensity overlay % of Revenue | F10: 0 | H10: Closing Date
B11: Current Equity Value | C11: 4869931.9 | E11: Tax Rate | F11: 0.15610002 | H11: Fiscal Year End | I11: 46291
B12: Implied Equity Value | C12: =C9-AA18+AA17+AA19-F20-F21 -> 1390376.5 | E12: WACC | F12: =WACC!D34 -> 0.14162494
B13: Implied Share Price (Gordon Growth) | C13: =Q111/$I$16 -> 70.910924 | E13: D&A % revenue | F13: 0.029143716 | H13: EBIT Margin Convergence (Years) | I13: 5
B14: Implied Share Price (Exit Multiple) | C14: =C12/$I$16 -> 92.662748 | E14: Stage 1 Revenue Growth | F14: 0.0328 | H14: Revenue Growth Stage 1 (Years) | I14: 3
B15: Terminal Assumptions | E15: Starting EBIT Margin | F15: 0.319708 | H15: Revenue Growth Fade (Years) | I15: 4
B16: Exit EBITDA Multiple | C16: 10.699147 | E16: Forecast Gross Margin | F16: 0.45747548 | H16: Diluted Shares (millions) | I16: 15004.697
B17: Cash and Cash Equivalents | C17: 35934 | E17: Steady-State EBIT Margin | F17: 0.31100812 | H17: Current Share Price | I17: 333.69 | AA17: =C17 -> 35934
B18: Income Statement | H18: FY2021A | I18: FY2022A | J18: FY2023A | K18: FY2024A | L18: FY2025A | M18: FY2026E | N18: FY2027E | O18: FY2028E | P18: FY2029E | Q18: FY2030E | S18: FY'21-22A | T18: FY'23-30E | AA18: 98657
E19: Stage 2 Revenue Growth | F19: 0.01968 | AA19: 96486
B20: Total Revenue | E20: Minority Interest | F20: 0 | H20: ='Data Given (Recalculated)'!G12 -> 365817 | I20: ='Data Given (Recalculated)'!H12 -> 394328 | J20: ='Data Given (Recalculated)'!I12 -> 383285 | K20: ='Data Given (Recalculated)'!J12 -> 391035 | L20: ='Data Given (Recalculated)'!K12 -> 416161 | M20: =L20*(1+M21) -> 429811.08 | N20: =M20*(1+N21) -> 443908.88 | O20: =N20*(1+O21) -> 458469.1 | P20: =O20*(1+P21) -> 472003.1 | Q20: =P20*(1+Q21) -> 484388.46 | S20: =IFERROR((I20/H20)^(1/(COLUMNS(H20:I20)-1))-1,"") -> 0.077937876 | T20: =IFERROR((Q20/J20)^(1/(COLUMNS(J20:Q20)-1))-1,"") -> 0.034009591
B21: % growth | E21: Preferred Equity | F21: 0 | H21: ="" | I21: =IFERROR(I20/H20-1,0) -> 0.077937876 | J21: =IFERROR(J20/I20-1,0) -> -0.028004605 | K21: =IFERROR(K20/J20-1,0) -> 0.020219941 | L21: =IFERROR(L20/K20-1,0) -> 0.064255118 | M21: =$F$14+($F$19-$F$14)*MAX(0,MIN(1,(M$83-$I$14)/$I$15)) -> 0.0328 | N21: =$F$14+($F$19-$F$14)*MAX(0,MIN(1,(N$83-$I$14)/$I$15)) -> 0.0328 | O21: =$F$14+($F$19-$F$14)*MAX(0,MIN(1,(O$83-$I$14)/$I$15)) -> 0.0328 | P21: =$F$14+($F$19-$F$14)*MAX(0,MIN(1,(P$83-$I$14)/$I$15)) -> 0.02952 | Q21: =$F$14+($F$19-$F$14)*MAX(0,MIN(1,(Q$83-$I$14)/$I$15)) -> 0.02624
B23: Cost of Revenue
B24: Cost of Revenue | H24: ='Data Given (Recalculated)'!G16 -> 212981 | I24: ='Data Given (Recalculated)'!H16 -> 223546 | J24: ='Data Given (Recalculated)'!I16 -> 214137 | K24: ='Data Given (Recalculated)'!J16 -> 210352 | L24: ='Data Given (Recalculated)'!K16 -> 201436 | M24: =M20*(1-$F$16)-M27 -> 213018.66 | N24: =N20*(1-$F$16)-N27 -> 220005.68 | O24: =O20*(1-$F$16)-O27 -> 227221.86 | P24: =P20*(1-$F$16)-P27 -> 233929.45 | Q24: =Q20*(1-$F$16)-Q27 -> 240067.76 | S24: =IFERROR((I24/H24)^(1/(COLUMNS(H24:I24)-1))-1,"") -> 0.049605364 | T24: =IFERROR((Q24/J24)^(1/(COLUMNS(J24:Q24)-1))-1,"") -> 0.016463369
B25: % of revenue | H25: =IFERROR(H24/H20,0) -> 0.5822064 | I25: =IFERROR(I24/I20,0) -> 0.56690369 | J25: =IFERROR(J24/J20,0) -> 0.5586887 | K25: =IFERROR(K24/K20,0) -> 0.5379365 | L25: =IFERROR(L24/L20,0) -> 0.48403382 | M25: =IFERROR(M24/M20,0) -> 0.49560999 | N25: =IFERROR(N24/N20,0) -> 0.49560999 | O25: =IFERROR(O24/O20,0) -> 0.49560999 | ... Q25: =IFERROR(Q24/Q20,0) -> 0.49560999
B27: Other Cost of Revenue | H27: ='Data Given (Recalculated)'!G17 -> 0 | I27: ='Data Given (Recalculated)'!H17 -> 0 | J27: ='Data Given (Recalculated)'!I17 -> 0 | K27: ='Data Given (Recalculated)'!J17 -> 0 | L27: ='Data Given (Recalculated)'!K17 -> 19524 | M27: =M20*L28 -> 20164.387 | N27: =N20*M28 -> 20825.779 | O27: =O20*N28 -> 21508.865 | P27: =P20*O28 -> 22143.806 | Q27: =Q20*P28 -> 22724.86 | S27: =IFERROR((I27/H27)^(1/(COLUMNS(H27:I27)-1))-1,"") | T27: =IFERROR((Q27/J27)^(1/(COLUMNS(J27:Q27)-1))-1,"")
B28: % of revenue | H28: =IFERROR(H27/H20,0) -> 0 | I28: =IFERROR(I27/I20,0) -> 0 | J28: =IFERROR(J27/J20,0) -> 0 | K28: =IFERROR(K27/K20,0) -> 0 | L28: =IFERROR(L27/L20,0) -> 0.046914535 | M28: =IFERROR(M27/M20,0) -> 0.046914535 | N28: =IFERROR(N27/N20,0) -> 0.046914535 | O28: =IFERROR(O27/O20,0) -> 0.046914535 | ... Q28: =IFERROR(Q27/Q20,0) -> 0.046914535
B30: Total Cost of Sales | H30: =H24+H27 -> 212981 | I30: =I24+I27 -> 223546 | J30: =J24+J27 -> 214137 | K30: =K24+K27 -> 210352 | L30: =L24+L27 -> 220960 | M30: =M24+M27 -> 233183.05 | N30: =N24+N27 -> 240831.46 | O30: =O24+O27 -> 248730.73 | ... Q30: =Q24+Q27 -> 262792.62
B32: Gross Profit | H32: =H20-H30 -> 152836 | I32: =I20-I30 -> 170782 | J32: =J20-J30 -> 169148 | K32: =K20-K30 -> 180683 | L32: =L20-L30 -> 195201 | M32: =M20-M30 -> 196628.03 | N32: =N20-N30 -> 203077.43 | O32: =O20-O30 -> 209738.37 | ... Q32: =Q20-Q30 -> 221595.84 | S32: =IFERROR((I32/H32)^(1/(COLUMNS(H32:I32)-1))-1,"") -> 0.11741998 | T32: =IFERROR((Q32/J32)^(1/(COLUMNS(J32:Q32)-1))-1,"") -> 0.039337009
B33: % margin | H33: =IFERROR(H32/H20,0) -> 0.4177936 | I33: =IFERROR(I32/I20,0) -> 0.43309631 | J33: =IFERROR(J32/J20,0) -> 0.4413113 | K33: =IFERROR(K32/K20,0) -> 0.4620635 | L33: =IFERROR(L32/L20,0) -> 0.46905164 | M33: =IFERROR(M32/M20,0) -> 0.45747548 | N33: =IFERROR(N32/N20,0) -> 0.45747548 | O33: =IFERROR(O32/O20,0) -> 0.45747548 | ... Q33: =IFERROR(Q32/Q20,0) -> 0.45747548
B35: Operating Expenses
B36: Research & Development | H36: ='Data Given (Recalculated)'!G24 -> 21914 | I36: ='Data Given (Recalculated)'!H24 -> 26251 | J36: ='Data Given (Recalculated)'!I24 -> 29915 | K36: ='Data Given (Recalculated)'!J24 -> 31370 | L36: ='Data Given (Recalculated)'!K24 -> 34550 | M36: =M20*M37 -> 35683.24 | N36: =N20*N37 -> 36853.65 | O36: =O20*O37 -> 38062.45 | P36: =P20*P37 -> 39186.054 | Q36: =Q20*Q37 -> 40214.296 | S36: =IFERROR((I36/H36)^(1/(COLUMNS(H36:I36)-1))-1,"") -> 0.19791001 | T36: =IFERROR((Q36/J36)^(1/(COLUMNS(J36:Q36)-1))-1,"") -> 0.043172003
B37: % of revenue | H37: =IFERROR(H36/H20,0) -> 0.059904269 | I37: =IFERROR(I36/I20,0) -> 0.066571484 | J37: =IFERROR(J36/J20,0) -> 0.078048971 | K37: =IFERROR(K36/K20,0) -> 0.080222998 | L37: =IFERROR(L36/L20,0) -> 0.083020754 | M37: =L37 -> 0.083020754 | N37: =M37 -> 0.083020754 | O37: =N37 -> 0.083020754 | P37: =O37 -> 0.083020754 | Q37: =P37 -> 0.083020754
B39: SG&A | H39: ='Data Given (Recalculated)'!G25 -> 21973 | I39: ='Data Given (Recalculated)'!H25 -> 25094 | J39: ='Data Given (Recalculated)'!I25 -> 24932 | K39: ='Data Given (Recalculated)'!J25 -> 26097 | L39: ='Data Given (Recalculated)'!K25 -> 27601 | M39: =M20*M40 -> 28506.313 | N39: =N20*N40 -> 29441.32 | O39: =O20*O40 -> 30406.995 | P39: =P20*P40 -> 31304.61 | Q39: =Q20*Q40 -> 32126.043 | S39: =IFERROR((I39/H39)^(1/(COLUMNS(H39:I39)-1))-1,"") -> 0.14203796 | T39: =IFERROR((Q39/J39)^(1/(COLUMNS(J39:Q39)-1))-1,"") -> 0.036880215
B40: % of revenue | H40: =IFERROR(H39/H20,0) -> 0.060065552 | I40: =IFERROR(I39/I20,0) -> 0.063637378 | J40: =IFERROR(J39/J20,0) -> 0.065048202 | K40: =IFERROR(K39/K20,0) -> 0.066738272 | L40: =IFERROR(L39/L20,0) -> 0.066322889 | M40: =L40 -> 0.066322889 | N40: =M40 -> 0.066322889 | O40: =N40 -> 0.066322889 | P40: =O40 -> 0.066322889 | Q40: =P40 -> 0.066322889
B42: D&A (included in Operating) | H42: ='Data Given (Recalculated)'!G26 -> 11284 | I42: ='Data Given (Recalculated)'!H26 -> 11104 | J42: ='Data Given (Recalculated)'!I26 -> 11519 | K42: ='Data Given (Recalculated)'!J26 -> 11445 | L42: ='Data Given (Recalculated)'!K26 -> 11698 | M42: =M20*$F$13 -> 12526.292 | N42: =N20*$F$13 -> 12937.154 | O42: =O20*$F$13 -> 13361.493 | P42: =P20*$F$13 -> 13755.924 | Q42: =Q20*$F$13 -> 14116.88 | S42: =IFERROR((I42/H42)^(1/(COLUMNS(H42:I42)-1))-1,"") -> -0.01595179 | T42: =IFERROR((Q42/J42)^(1/(COLUMNS(J42:Q42)-1))-1,"") -> 0.029479506
B43: % of revenue | H43: =IFERROR(H42/H20,0) -> 0.030846024 | I43: =IFERROR(I42/I20,0) -> 0.028159299 | J43: =IFERROR(J42/J20,0) -> 0.030053355 | K43: =IFERROR(K42/K20,0) -> 0.02926848 | L43: =IFERROR(L42/L20,0) -> 0.028109313 | M43: =L43 -> 0.028109313 | N43: =M43 -> 0.028109313 | O43: =N43 -> 0.028109313 | P43: =O43 -> 0.028109313 | Q43: =P43 -> 0.028109313
B45: Other OpEx / (Income) | H45: ='Data Given (Recalculated)'!G27 -> 0 | I45: ='Data Given (Recalculated)'!H27 -> 0 | J45: ='Data Given (Recalculated)'!I27 -> 0 | K45: ='Data Given (Recalculated)'!J27 -> 0 | L45: ='Data Given (Recalculated)'!K27 -> 0 | M45: =M32-M36-M39-M20*M53 -> -4227.7019 | N45: =N32-N36-N39-N20*N53 -> -3593.9796 | O45: =O32-O36-O39-O20*O53 -> -2914.1368 | P45: =P32-P36-P39-P20*P53 -> -2178.888 | Q45: =Q32-Q36-Q39-Q20*Q53 -> -1393.2376 | S45: =IFERROR((I45/H45)^(1/(COLUMNS(H45:I45)-1))-1,"") | T45: =IFERROR((Q45/J45)^(1/(COLUMNS(J45:Q45)-1))-1,"")
B46: % of revenue | H46: =IFERROR(H45/H20,0) -> 0 | I46: =IFERROR(I45/I20,0) -> 0 | J46: =IFERROR(J45/J20,0) -> 0 | K46: =IFERROR(K45/K20,0) -> 0 | L46: =IFERROR(L45/L20,0) -> 0 | M46: =IFERROR(M45/M20,0) -> -0.0098361865 | N46: =IFERROR(N45/N20,0) -> -0.0080962102 | O46: =IFERROR(O45/O20,0) -> -0.006356234 | ... Q46: =IFERROR(Q45/Q20,0) -> -0.0028762814
B48: Total Operating Expenses | H48: =-(H36+H39+H45) -> -43887 | I48: =-(I36+I39+I45) -> -51345 | J48: =-(J36+J39+J45) -> -54847 | K48: =-(K36+K39+K45) -> -57467 | L48: =-(L36+L39+L45) -> -62151 | M48: =-(M36+M39+M45) -> -59961.851 | N48: =-(N36+N39+N45) -> -62700.99 | O48: =-(O36+O39+O45) -> -65555.308 | ... Q48: =-(Q36+Q39+Q45) -> -70947.101 | S48: =IFERROR((I48/H48)^(1/(COLUMNS(H48:I48)-1))-1,"") -> 0.16993643 | T48: =IFERROR((Q48/J48)^(1/(COLUMNS(J48:Q48)-1))-1,"") -> 0.037453941
B49: % of revenue | H49: =IFERROR(-H48/H20,0) -> 0.11996982 | I49: =IFERROR(-I48/I20,0) -> 0.13020886 | J49: =IFERROR(-J48/J20,0) -> 0.14309717 | K49: =IFERROR(-K48/K20,0) -> 0.14696127 | L49: =IFERROR(-L48/L20,0) -> 0.14934364 | M49: =IFERROR(-M48/M20,0) -> 0.13950746 | N49: =IFERROR(-N48/N20,0) -> 0.14124743 | O49: =IFERROR(-O48/O20,0) -> 0.14298741 | ... Q49: =IFERROR(-Q48/Q20,0) -> 0.14646736
B51: EBIT | H51: =H32+H48 -> 108949 | I51: =I32+I48 -> 119437 | J51: =J32+J48 -> 114301 | K51: =K32+K48 -> 123216 | L51: =L32+L48 -> 133050 | M51: =M32+M48 -> 136666.18 | N51: =N32+N48 -> 140376.44 | O51: =O32+O48 -> 144183.06 | ... Q51: =Q32+Q48 -> 150648.74 | S51: =IFERROR((I51/H51)^(1/(COLUMNS(H51:I51)-1))-1,"") -> 0.096265225 | T51: =IFERROR((Q51/J51)^(1/(COLUMNS(J51:Q51)-1))-1,"") -> 0.040233375
B52: % margin | H52: =IFERROR(H51/H20,0) -> 0.29782378 | I52: =IFERROR(I51/I20,0) -> 0.30288744 | J52: =IFERROR(J51/J20,0) -> 0.29821412 | K52: =IFERROR(K51/K20,0) -> 0.31510223 | L52: =IFERROR(L51/L20,0) -> 0.319708 | M52: =IFERROR(M51/M20,0) -> 0.31796802 | N52: =IFERROR(N51/N20,0) -> 0.31622805 | O52: =IFERROR(O51/O20,0) -> 0.31448807 | ... Q52: =IFERROR(Q51/Q20,0) -> 0.31100812
B53: Forecast EBIT Margin Driver | M53: =IF(M$83<$I$13,$F$15+($F$17-$F$15)*M$83/$I$13,$F$17) -> 0.31796802 | N53: =IF(N$83<$I$13,$F$15+($F$17-$F$15)*N$83/$I$13,$F$17) -> 0.31622805 | O53: =IF(O$83<$I$13,$F$15+($F$17-$F$15)*O$83/$I$13,$F$17) -> 0.31448807 | P53: =IF(P$83<$I$13,$F$15+($F$17-$F$15)*P$83/$I$13,$F$17) -> 0.31274809 | Q53: =IF(Q$83<$I$13,$F$15+($F$17-$F$15)*Q$83/$I$13,$F$17) -> 0.31100812
B54: EBITDA | H54: =H51+H68 -> 120233 | I54: =I51+I68 -> 130541 | J54: =J51+J68 -> 125820 | K54: =K51+K68 -> 134661 | L54: =L51+L68 -> 144748 | M54: =M51+M68 -> 149192.47 | N54: =N51+N68 -> 153313.59 | O54: =O51+O68 -> 157544.55 | ... Q54: =Q51+Q68 -> 164765.62 | S54: =IFERROR((I54/H54)^(1/(COLUMNS(H54:I54)-1))-1,"") -> 0.085733534 | T54: =IFERROR((Q54/J54)^(1/(COLUMNS(J54:Q54)-1))-1,"") -> 0.039276218
B55: % margin | H55: =IFERROR(H54/H20,0) -> 0.3286698 | I55: =IFERROR(I54/I20,0) -> 0.33104674 | J55: =IFERROR(J54/J20,0) -> 0.32826748 | K55: =IFERROR(K54/K20,0) -> 0.34437071 | L55: =IFERROR(L54/L20,0) -> 0.34781731 | M55: =IFERROR(M54/M20,0) -> 0.34711174 | N55: =IFERROR(N54/N20,0) -> 0.34537176 | O55: =IFERROR(O54/O20,0) -> 0.34363178 | ... Q55: =IFERROR(Q54/Q20,0) -> 0.34015183
B57: Income Taxes | H57: =-H51*H58 -> -17006.941 | I57: =-I51*I58 -> -18644.118 | J57: =-J51*J58 -> -17842.389 | K57: =-K51*K58 -> -19234.02 | L57: =-L51*L58 -> -20769.108 | M57: =-M51*M58 -> -21333.594 | N57: =-N51*N58 -> -21912.765 | O57: =-O51*O58 -> -22506.979 | ... Q57: =-Q51*Q58 -> -23516.272
B58: % tax rate | H58: =$F$11 -> 0.15610002 | I58: =$F$11 -> 0.15610002 | J58: =$F$11 -> 0.15610002 | K58: =$F$11 -> 0.15610002 | L58: =$F$11 -> 0.15610002 | M58: =$F$11 -> 0.15610002 | N58: =$F$11 -> 0.15610002 | O58: =$F$11 -> 0.15610002 | ... Q58: =$F$11 -> 0.15610002
B60: NOPAT | H60: =H51+H57 -> 91942.059 | I60: =I51+I57 -> 100792.88 | J60: =J51+J57 -> 96458.611 | K60: =K51+K57 -> 103981.98 | L60: =L51+L57 -> 112280.89 | M60: =M51+M57 -> 115332.59 | N60: =N51+N57 -> 118463.67 | O60: =O51+O57 -> 121676.08 | ... Q60: =Q51+Q57 -> 127132.47 | S60: =IFERROR((I60/H60)^(1/(COLUMNS(H60:I60)-1))-1,"") -> 0.096265225 | T60: =IFERROR((Q60/J60)^(1/(COLUMNS(J60:Q60)-1))-1,"") -> 0.040233375
B61: % revenue | H61: =IFERROR(H60/H20,0) -> 0.25133348 | I61: =IFERROR(I60/I20,0) -> 0.25560671 | J61: =IFERROR(J60/J20,0) -> 0.25166289 | K61: =IFERROR(K60/K20,0) -> 0.26591476 | L61: =IFERROR(L60/L20,0) -> 0.26980157 | M61: =IFERROR(M60/M20,0) -> 0.26833321 | N61: =IFERROR(N60/N20,0) -> 0.26686484 | O61: =IFERROR(O60/O20,0) -> 0.26539647 | ... Q61: =IFERROR(Q60/Q20,0) -> 0.26245974
B63: PP&E Schedule | H63: FY2021A | I63: FY2022A | J63: FY2023A | K63: FY2024A | L63: FY2025A | M63: FY2026E | N63: FY2027E | O63: FY2028E | P63: FY2029E | Q63: FY2030E
B65: CapEx | H65: =IF('Data Given (Recalculated)'!G35="","",-'Data Given (Recalculated)'!G35) -> -11085 | I65: =IF('Data Given (Recalculated)'!H35="","",-'Data Given (Recalculated)'!H35) -> -10708 | J65: =IF('Data Given (Recalculated)'!I35="","",-'Data Given (Recalculated)'!I35) -> -10959 | K65: =IF('Data Given (Recalculated)'!J35="","",-'Data Given (Recalculated)'!J35) -> -9447 | L65: =IF('Data Given (Recalculated)'!K35="","",-'Data Given (Recalculated)'!K35) -> -12715 | M65: =-M20*$F$9 -> -11935.043 | N65: =-N20*$F$9 -> -12326.513 | O65: =-O20*$F$9 -> -12730.822 | P65: =-P20*$F$9 -> -13106.636 | Q65: =-Q20*$F$9 -> -13450.554
B66: % sales | H66: =IFERROR(-H65/H20,0) -> 0.030302036 | I66: =IFERROR(-I65/I20,0) -> 0.027155059 | J66: =IFERROR(-J65/J20,0) -> 0.028592301 | K66: =IFERROR(-K65/K20,0) -> 0.024158963 | L66: =IFERROR(-L65/L20,0) -> 0.030553079 | M66: =IFERROR(-M65/M20,0) -> 0.027768114 | N66: =IFERROR(-N65/N20,0) -> 0.027768114 | O66: =IFERROR(-O65/O20,0) -> 0.027768114 | ... Q66: =IFERROR(-Q65/Q20,0) -> 0.027768114
B68: Depreciation & Amortization | H68: =IF('Data Given (Recalculated)'!G36="","",'Data Given (Recalculated)'!G36) -> 11284 | I68: =IF('Data Given (Recalculated)'!H36="","",'Data Given (Recalculated)'!H36) -> 11104 | J68: =IF('Data Given (Recalculated)'!I36="","",'Data Given (Recalculated)'!I36) -> 11519 | K68: =IF('Data Given (Recalculated)'!J36="","",'Data Given (Recalculated)'!J36) -> 11445 | L68: =IF('Data Given (Recalculated)'!K36="","",'Data Given (Recalculated)'!K36) -> 11698 | M68: =M20*$F$13 -> 12526.292 | N68: =N20*$F$13 -> 12937.154 | O68: =O20*$F$13 -> 13361.493 | P68: =P20*$F$13 -> 13755.924 | Q68: =Q20*$F$13 -> 14116.88
B69: % revenue (assumed) | H69: =IFERROR(H68/H20,0) -> 0.030846024 | I69: =IFERROR(I68/I20,0) -> 0.028159299 | J69: =IFERROR(J68/J20,0) -> 0.030053355 | K69: =IFERROR(K68/K20,0) -> 0.02926848 | L69: =IFERROR(L68/L20,0) -> 0.028109313 | M69: =$F$13 -> 0.029143716 | N69: =$F$13 -> 0.029143716 | O69: =$F$13 -> 0.029143716 | P69: =$F$13 -> 0.029143716 | Q69: =$F$13 -> 0.029143716
B70: % of CapEx | H70: =IFERROR(-H68/H65,0) -> 1.0179522 | I70: =IFERROR(-I68/I65,0) -> 1.0369817 | J70: =IFERROR(-J68/J65,0) -> 1.0510996 | K70: =IFERROR(-K68/K65,0) -> 1.2114957 | L70: =IFERROR(-L68/L65,0) -> 0.92001573 | M70: =IFERROR(-M68/M65,0) -> 1.0495389 | N70: =IFERROR(-N68/N65,0) -> 1.0495389 | O70: =IFERROR(-O68/O65,0) -> 1.0495389 | ... Q70: =IFERROR(-Q68/Q65,0) -> 1.0495389
B71: Unlevered Free Cash Flow Waterfall
B72: Unlevered Free Cash Flow Waterfall | H72: FY2021A | I72: FY2022A | J72: FY2023A | K72: FY2024A | L72: FY2025A | M72: FY2026E | N72: FY2027E | O72: FY2028E | P72: FY2029E | Q72: FY2030E
B74: NOPAT | H74: =H60 -> 91942.059 | I74: =I60 -> 100792.88 | J74: =J60 -> 96458.611 | K74: =K60 -> 103981.98 | L74: =L60 -> 112280.89 | M74: =M60 -> 115332.59 | N74: =N60 -> 118463.67 | O74: =O60 -> 121676.08 | ... Q74: =Q60 -> 127132.47
B75: (+) Depreciation | H75: =H68 -> 11284 | I75: =I68 -> 11104 | J75: =J68 -> 11519 | K75: =K68 -> 11445 | L75: =L68 -> 11698 | M75: =M68 -> 12526.292 | N75: =N68 -> 12937.154 | O75: =O68 -> 13361.493 | ... Q75: =Q68 -> 14116.88
B76: (-) Capital Expenditures | H76: =H65 -> -11085 | I76: =I65 -> -10708 | J76: =J65 -> -10959 | K76: =K65 -> -9447 | L76: =L65 -> -12715 | M76: =M65 -> -11935.043 | N76: =N65 -> -12326.513 | O76: =O65 -> -12730.822 | ... Q76: =Q65 -> -13450.554
B77: (-) Change in NWC | H77: ="" | I77: =IF('Data Given (Recalculated)'!H41="","",-'Data Given (Recalculated)'!H41) -> 9080 | J77: =IF('Data Given (Recalculated)'!I41="","",-'Data Given (Recalculated)'!I41) -> -4213 | K77: =IF('Data Given (Recalculated)'!J41="","",-'Data Given (Recalculated)'!J41) -> 1492 | L77: =IF('Data Given (Recalculated)'!K41="","",-'Data Given (Recalculated)'!K41) -> -3899 | M77: =IFERROR(-((M20*'Data Given (Recalculated)'!$C$50/365+M30*'Data Given (Recalculated)'!$C$51/365-M30*'Data Given (Recalculated)'!$C$52/365+M20*$F$10)-'Data Given (Recalculated)'!K40),"") -> 2243.5174 | N77: =IFERROR(-((N20*'Data Given (Recalculated)'!$C$50/365+N30*'Data Given (Recalculated)'!$C$51/365-N30*'Data Given (Recalculated)'!$C$52/365+N20*$F$10)-(M20*'Data Given (Recalculated)'!$C$50/365+M30*'Data Given (Recalculated)'!$C$51/365-M30*'Data Given (Recalculated)'!$C$52/365+M20*$F$10)),"") -> 872.75937 | O77: =IFERROR(-((O20*'Data Given (Recalculated)'!$C$50/365+O30*'Data Given (Recalculated)'!$C$51/365-O30*'Data Given (Recalculated)'!$C$52/365+O20*$F$10)-(N20*'Data Given (Recalculated)'!$C$50/365+N30*'Data Given (Recalculated)'!$C$51/365-N30*'Data Given (Recalculated)'!$C$52/365+N20*$F$10)),"") -> 901.38588 | P77: =IFERROR(-((P20*'Data Given (Recalculated)'!$C$50/365+P30*'Data Given (Recalculated)'!$C$51/365-P30*'Data Given (Recalculated)'!$C$52/365+P20*$F$10)-(O20*'Data Given (Recalculated)'!$C$50/365+O30*'Data Given (Recalculated)'!$C$51/365-O30*'Data Given (Recalculated)'!$C$52/365+O20*$F$10)),"") -> 837.8562 | Q77: =IFERROR(-((Q20*'Data Given (Recalculated)'!$C$50/365+Q30*'Data Given (Recalculated)'!$C$51/365-Q30*'Data Given (Recalculated)'!$C$52/365+Q20*$F$10)-(P20*'Data Given (Recalculated)'!$C$50/365+P30*'Data Given (Recalculated)'!$C$51/365-P30*'Data Given (Recalculated)'!$C$52/365+P20*$F$10)),"") -> 766.74642
B78: Unlevered Free Cash Flow | H78: =SUM(H74:H77) -> 92141.059 | I78: =SUM(I74:I77) -> 110268.88 | J78: =SUM(J74:J77) -> 92805.611 | K78: =SUM(K74:K77) -> 107471.98 | L78: =SUM(L74:L77) -> 107364.89 | M78: =SUM(M74:M77) -> 118167.35 | N78: =SUM(N74:N77) -> 119947.07 | O78: =SUM(O74:O77) -> 123208.14 | ... Q78: =SUM(Q74:Q77) -> 128565.54 | T78: =IFERROR((Q78/J78)^(1/(COLUMNS(J78:Q78)-1))-1,"") -> 0.047662693
B79: % of revenue | H79: =IFERROR(H78/H20,0) -> 0.25187746 | I79: =IFERROR(I78/I20,0) -> 0.27963746 | J79: =IFERROR(J78/J20,0) -> 0.24213212 | K79: =IFERROR(K78/K20,0) -> 0.2748398 | L79: =IFERROR(L78/L20,0) -> 0.25798884 | M79: =IFERROR(M78/M20,0) -> 0.27492858 | N79: =IFERROR(N78/N20,0) -> 0.27020652 | O79: =IFERROR(O78/O20,0) -> 0.26873815 | ... Q79: =IFERROR(Q78/Q20,0) -> 0.26541826
B81: Date for Valuation | E81: =I9 -> 46298
B82: Date For Discounting Cash Flows | M82: =EOMONTH(I11,12) -> 46660 | N82: =EOMONTH(M82,12) -> 47026 | O82: =EOMONTH(N82,12) -> 47391 | P82: =EOMONTH(O82,12) -> 47756 | Q82: =EOMONTH(P82,12) -> 48121
B83: Period, Stub Adjusted | M83: =1 -> 1 | N83: =M83+1 -> 2 | O83: =N83+1 -> 3 | P83: =O83+1 -> 4 | Q83: =P83+1 -> 5
B84: Discount Period, Stub and Mid-Year Adjusted | M84: =M83/2 -> 0.5 | N84: =N83-0.5 -> 1.5 | O84: =O83-0.5 -> 2.5 | P84: =P83-0.5 -> 3.5 | Q84: =Q83-0.5 -> 4.5
B85: Discount Rate | M85: =$F$12 -> 0.14162494 | N85: =$F$12 -> 0.14162494 | O85: =$F$12 -> 0.14162494 | P85: =$F$12 -> 0.14162494 | Q85: =$F$12 -> 0.14162494
B86: Present Value of Cash Flows
B87: Present Value of Unlevered Free Cash Flow | M87: =M78/(1+M85)^M84 -> 110595.07 | N87: =N78/(1+N85)^N84 -> 98334.177 | O87: =O78/(1+O85)^O84 -> 88477.079 | P87: =P78/(1+P85)^P84 -> 79296.173 | Q87: =Q78/(1+Q85)^Q84 -> 70838.454
B89: Output | H89: FY2021A | I89: FY2022A | J89: FY2023A | K89: FY2024A | L89: FY2025A | M89: FY2026E | N89: FY2027E | O89: FY2028E | P89: FY2029E | Q89: FY2030E
B91: Multiples Method
B92: Terminal Value | Q92: =Q54*$C$16 -> 1762851.6
B93: PV of Terminal Value | Q93: =Q92/(1+Q85)^Q83 -> 909072.5
B94: Enterprise Value | Q94: =Q93+SUM(M87:Q87) -> 1356613.5
B95: (-) Outstanding Debt | Q95: =-$AA$18 -> -98657
B96: (-) Minority Interest and Preferred Equity | Q96: =-$F$20-$F$21 -> 0
B97: (+) Cash and Non-Operating Assets | Q97: =$AA$17+$AA$19 -> 132420
B98: Implied Equity Value | Q98: =SUM(Q94:Q97) -> 1390376.5
B99: Current Equity Value | Q99: =C11 -> 4869931.9
B100: Implied Upside | Q100: =IFERROR(Q98/Q99 - 1,0) -> -0.71449776
B102: Gordon Growth Method
B103: Long Term Growth Rate | Q103: 0.025
B104: Final Year UFCF × (1 + g) | Q104: =Q78*(1+Q103) -> 131779.68
B105: Terminal Value | Q105: =IFERROR(IF(Q85>Q103,Q104/(Q85-Q103),0),0) -> 1129944.3
B106: PV of Terminal Value | Q106: =Q105/(1+Q85)^Q83 -> 582692.97
B107: Enterprise Value | Q107: =Q106+SUM(M87:Q87) -> 1030233.9
B108: (-) Outstanding Debt | Q108: =-$AA$18 -> -98657
B109: (-) Minority Interest and Preferred Equity | Q109: =-$F$20-$F$21 -> 0
B110: (+) Cash and Non-Operating Assets | Q110: =$AA$17+$AA$19 -> 132420
B111: Implied Equity Value | Q111: =SUM(Q107:Q110) -> 1063996.9
B112: Current Equity Value | Q112: =C11 -> 4869931.9
B113: Implied Upside | Q113: =IFERROR(Q111/Q112 - 1,0) -> -0.78151708
B115: Sensitivity Analysis
C117: Enterprise Value - WACC x Terminal Growth | I117: Enterprise Value - Revenue Growth x EBIT Margin
D118: WACC | J118: Revenue Growth
C119: ='Outputs - Base'!$D$35 -> 1356613.5 | D119: =E119-0.01 -> 0.12162494 | E119: =F119-0.01 -> 0.13162494 | F119: =$F$12 -> 0.14162494 | G119: =F119+0.01 -> 0.15162494 | H119: =G119+0.01 -> 0.16162494 | J119: =K119-0.01 -> 0.0128 | K119: =L119-0.01 -> 0.0228 | L119: =$F$14 -> 0.0328 | M119: =L119+0.01 -> 0.0428 | N119: =M119+0.01 -> 0.0528
C120: =C121-0.005 -> 0.015 | D120: =IFERROR(IF($D$119>$C$120,M78/(1+$D$119)^M84+N78/(1+$D$119)^N84+O78/(1+$D$119)^O84+P78/(1+$D$119)^P84+Q78/(1+$D$119)^Q84+Q78*(1+$C$120)/($D$119-$C$120)/(1+$D$119)^Q83,""),"") -> 1155521.1 | E120: =IFERROR(IF($E$119>$C$120,M78/(1+$E$119)^M84+N78/(1+$E$119)^N84+O78/(1+$E$119)^O84+P78/(1+$E$119)^P84+Q78/(1+$E$119)^Q84+Q78*(1+$C$120)/($E$119-$C$120)/(1+$E$119)^Q83,""),"") -> 1059600.5 | F120: =IFERROR(IF($F$119>$C$120,M78/(1+$F$119)^M84+N78/(1+$F$119)^N84+O78/(1+$F$119)^O84+P78/(1+$F$119)^P84+Q78/(1+$F$119)^Q84+Q78*(1+$C$120)/($F$119-$C$120)/(1+$F$119)^Q83,""),"") -> 978980.83 | G120: =IFERROR(IF($G$119>$C$120,M78/(1+$G$119)^M84+N78/(1+$G$119)^N84+O78/(1+$G$119)^O84+P78/(1+$G$119)^P84+Q78/(1+$G$119)^Q84+Q78*(1+$C$120)/($G$119-$C$120)/(1+$G$119)^Q83,""),"") -> 910288.99 | H120: =IFERROR(IF($H$119>$C$120,M78/(1+$H$119)^M84+N78/(1+$H$119)^N84+O78/(1+$H$119)^O84+P78/(1+$H$119)^P84+Q78/(1+$H$119)^Q84+Q78*(1+$C$120)/($H$119-$C$120)/(1+$H$119)^Q83,""),"") -> 851073.11 | I120: =I121-0.01 -> 0.29796802 | J120: =IFERROR((L20*(1+J$119)^1*$I$120*(1-$F$11)+L20*(1+J$119)^1*$F$13-$F$9-$F$10)/(1+$F$12)^M84+(L20*(1+J$119)^2*$I$120*(1-$F$11)+L20*(1+J$119)^2*$F$13-$F$9-$F$10)/(1+$F$12)^N84+(L20*(1+J$119)^3*$I$120*(1-$F$11)+L20*(1+J$119)^3*$F$13-$F$9-$F$10)/(1+$F$12)^O84+(L20*(1+J$119)^4*$I$120*(1-$F$11)+L20*(1+J$119)^4*$F$13-$F$9-$F$10)/(1+$F$12)^P84+(L20*(1+J$119)^5*$I$120*(1-$F$11)+L20*(1+J$119)^5*$F$13-$F$9-$F$10)/(1+$F$12)^Q84+(L20*(1+J$119)^5*$I$120+L20*(1+J$119)^5*$F$13)*$C$16/(1+$F$12)^Q83,"") -> 1242263.5 | K120: =IFERROR((L20*(1+K$119)^1*$I$120*(1-$F$11)+L20*(1+K$119)^1*$F$13-$F$9-$F$10)/(1+$F$12)^M84+(L20*(1+K$119)^2*$I$120*(1-$F$11)+L20*(1+K$119)^2*$F$13-$F$9-$F$10)/(1+$F$12)^N84+(L20*(1+K$119)^3*$I$120*(1-$F$11)+L20*(1+K$119)^3*$F$13-$F$9-$F$10)/(1+$F$12)^O84+(L20*(1+K$119)^4*$I$120*(1-$F$11)+L20*(1+K$119)^4*$F$13-$F$9-$F$10)/(1+$F$12)^P84+(L20*(1+K$119)^5*$I$120*(1-$F$11)+L20*(1+K$119)^5*$F$13-$F$9-$F$10)/(1+$F$12)^Q84+(L20*(1+K$119)^5*$I$120+L20*(1+K$119)^5*$F$13)*$C$16/(1+$F$12)^Q83,"") -> 1294764 | L120: =IFERROR((L20*(1+L$119)^1*$I$120*(1-$F$11)+L20*(1+L$119)^1*$F$13-$F$9-$F$10)/(1+$F$12)^M84+(L20*(1+L$119)^2*$I$120*(1-$F$11)+L20*(1+L$119)^2*$F$13-$F$9-$F$10)/(1+$F$12)^N84+(L20*(1+L$119)^3*$I$120*(1-$F$11)+L20*(1+L$119)^3*$F$13-$F$9-$F$10)/(1+$F$12)^O84+(L20*(1+L$119)^4*$I$120*(1-$F$11)+L20*(1+L$119)^4*$F$13-$F$9-$F$10)/(1+$F$12)^P84+(L20*(1+L$119)^5*$I$120*(1-$F$11)+L20*(1+L$119)^5*$F$13-$F$9-$F$10)/(1+$F$12)^Q84+(L20*(1+L$119)^5*$I$120+L20*(1+L$119)^5*$F$13)*$C$16/(1+$F$12)^Q83,"") -> 1349172.3 | M120: =IFERROR((L20*(1+M$119)^1*$I$120*(1-$F$11)+L20*(1+M$119)^1*$F$13-$F$9-$F$10)/(1+$F$12)^M84+(L20*(1+M$119)^2*$I$120*(1-$F$11)+L20*(1+M$119)^2*$F$13-$F$9-$F$10)/(1+$F$12)^N84+(L20*(1+M$119)^3*$I$120*(1-$F$11)+L20*(1+M$119)^3*$F$13-$F$9-$F$10)/(1+$F$12)^O84+(L20*(1+M$119)^4*$I$120*(1-$F$11)+L20*(1+M$119)^4*$F$13-$F$9-$F$10)/(1+$F$12)^P84+(L20*(1+M$119)^5*$I$120*(1-$F$11)+L20*(1+M$119)^5*$F$13-$F$9-$F$10)/(1+$F$12)^Q84+(L20*(1+M$119)^5*$I$120+L20*(1+M$119)^5*$F$13)*$C$16/(1+$F$12)^Q83,"") -> 1405542.6 | N120: =IFERROR((L20*(1+N$119)^1*$I$120*(1-$F$11)+L20*(1+N$119)^1*$F$13-$F$9-$F$10)/(1+$F$12)^M84+(L20*(1+N$119)^2*$I$120*(1-$F$11)+L20*(1+N$119)^2*$F$13-$F$9-$F$10)/(1+$F$12)^N84+(L20*(1+N$119)^3*$I$120*(1-$F$11)+L20*(1+N$119)^3*$F$13-$F$9-$F$10)/(1+$F$12)^O84+(L20*(1+N$119)^4*$I$120*(1-$F$11)+L20*(1+N$119)^4*$F$13-$F$9-$F$10)/(1+$F$12)^P84+(L20*(1+N$119)^5*$I$120*(1-$F$11)+L20*(1+N$119)^5*$F$13-$F$9-$F$10)/(1+$F$12)^Q84+(L20*(1+N$119)^5*$I$120+L20*(1+N$119)^5*$F$13)*$C$16/(1+$F$12)^Q83,"") -> 1463929.7
B121: Terminal Growth | C121: =C122-0.005 -> 0.02 | D121: =IFERROR(IF($D$119>$C$121,M78/(1+$D$119)^M84+N78/(1+$D$119)^N84+O78/(1+$D$119)^O84+P78/(1+$D$119)^P84+Q78/(1+$D$119)^Q84+Q78*(1+$C$121)/($D$119-$C$121)/(1+$D$119)^Q83,""),"") -> 1193005 | E121: =IFERROR(IF($E$119>$C$121,M78/(1+$E$119)^M84+N78/(1+$E$119)^N84+O78/(1+$E$119)^O84+P78/(1+$E$119)^P84+Q78/(1+$E$119)^Q84+Q78*(1+$C$121)/($E$119-$C$121)/(1+$E$119)^Q83,""),"") -> 1089712 | F121: =IFERROR(IF($F$119>$C$121,M78/(1+$F$119)^M84+N78/(1+$F$119)^N84+O78/(1+$F$119)^O84+P78/(1+$F$119)^P84+Q78/(1+$F$119)^Q84+Q78*(1+$C$121)/($F$119-$C$121)/(1+$F$119)^Q83,""),"") -> 1003553.9 | G121: =IFERROR(IF($G$119>$C$121,M78/(1+$G$119)^M84+N78/(1+$G$119)^N84+O78/(1+$G$119)^O84+P78/(1+$G$119)^P84+Q78/(1+$G$119)^Q84+Q78*(1+$C$121)/($G$119-$C$121)/(1+$G$119)^Q83,""),"") -> 930611.72 | H121: =IFERROR(IF($H$119>$C$121,M78/(1+$H$119)^M84+N78/(1+$H$119)^N84+O78/(1+$H$119)^O84+P78/(1+$H$119)^P84+Q78/(1+$H$119)^Q84+Q78*(1+$C$121)/($H$119-$C$121)/(1+$H$119)^Q83,""),"") -> 868074.45 | I121: =I122-0.01 -> 0.30796802 | J121: =IFERROR((L20*(1+J$119)^1*$I$121*(1-$F$11)+L20*(1+J$119)^1*$F$13-$F$9-$F$10)/(1+$F$12)^M84+(L20*(1+J$119)^2*$I$121*(1-$F$11)+L20*(1+J$119)^2*$F$13-$F$9-$F$10)/(1+$F$12)^N84+(L20*(1+J$119)^3*$I$121*(1-$F$11)+L20*(1+J$119)^3*$F$13-$F$9-$F$10)/(1+$F$12)^O84+(L20*(1+J$119)^4*$I$121*(1-$F$11)+L20*(1+J$119)^4*$F$13-$F$9-$F$10)/(1+$F$12)^P84+(L20*(1+J$119)^5*$I$121*(1-$F$11)+L20*(1+J$119)^5*$F$13-$F$9-$F$10)/(1+$F$12)^Q84+(L20*(1+J$119)^5*$I$121+L20*(1+J$119)^5*$F$13)*$C$16/(1+$F$12)^Q83,"") -> 1280021.2 | K121: =IFERROR((L20*(1+K$119)^1*$I$121*(1-$F$11)+L20*(1+K$119)^1*$F$13-$F$9-$F$10)/(1+$F$12)^M84+(L20*(1+K$119)^2*$I$121*(1-$F$11)+L20*(1+K$119)^2*$F$13-$F$9-$F$10)/(1+$F$12)^N84+(L20*(1+K$119)^3*$I$121*(1-$F$11)+L20*(1+K$119)^3*$F$13-$F$9-$F$10)/(1+$F$12)^O84+(L20*(1+K$119)^4*$I$121*(1-$F$11)+L20*(1+K$119)^4*$F$13-$F$9-$F$10)/(1+$F$12)^P84+(L20*(1+K$119)^5*$I$121*(1-$F$11)+L20*(1+K$119)^5*$F$13-$F$9-$F$10)/(1+$F$12)^Q84+(L20*(1+K$119)^5*$I$121+L20*(1+K$119)^5*$F$13)*$C$16/(1+$F$12)^Q83,"") -> 1334120.6 | L121: =IFERROR((L20*(1+L$119)^1*$I$121*(1-$F$11)+L20*(1+L$119)^1*$F$13-$F$9-$F$10)/(1+$F$12)^M84+(L20*(1+L$119)^2*$I$121*(1-$F$11)+L20*(1+L$119)^2*$F$13-$F$9-$F$10)/(1+$F$12)^N84+(L20*(1+L$119)^3*$I$121*(1-$F$11)+L20*(1+L$119)^3*$F$13-$F$9-$F$10)/(1+$F$12)^O84+(L20*(1+L$119)^4*$I$121*(1-$F$11)+L20*(1+L$119)^4*$F$13-$F$9-$F$10)/(1+$F$12)^P84+(L20*(1+L$119)^5*$I$121*(1-$F$11)+L20*(1+L$119)^5*$F$13-$F$9-$F$10)/(1+$F$12)^Q84+(L20*(1+L$119)^5*$I$121+L20*(1+L$119)^5*$F$13)*$C$16/(1+$F$12)^Q83,"") -> 1390186.1 | M121: =IFERROR((L20*(1+M$119)^1*$I$121*(1-$F$11)+L20*(1+M$119)^1*$F$13-$F$9-$F$10)/(1+$F$12)^M84+(L20*(1+M$119)^2*$I$121*(1-$F$11)+L20*(1+M$119)^2*$F$13-$F$9-$F$10)/(1+$F$12)^N84+(L20*(1+M$119)^3*$I$121*(1-$F$11)+L20*(1+M$119)^3*$F$13-$F$9-$F$10)/(1+$F$12)^O84+(L20*(1+M$119)^4*$I$121*(1-$F$11)+L20*(1+M$119)^4*$F$13-$F$9-$F$10)/(1+$F$12)^P84+(L20*(1+M$119)^5*$I$121*(1-$F$11)+L20*(1+M$119)^5*$F$13-$F$9-$F$10)/(1+$F$12)^Q84+(L20*(1+M$119)^5*$I$121+L20*(1+M$119)^5*$F$13)*$C$16/(1+$F$12)^Q83,"") -> 1448273.3 | N121: =IFERROR((L20*(1+N$119)^1*$I$121*(1-$F$11)+L20*(1+N$119)^1*$F$13-$F$9-$F$10)/(1+$F$12)^M84+(L20*(1+N$119)^2*$I$121*(1-$F$11)+L20*(1+N$119)^2*$F$13-$F$9-$F$10)/(1+$F$12)^N84+(L20*(1+N$119)^3*$I$121*(1-$F$11)+L20*(1+N$119)^3*$F$13-$F$9-$F$10)/(1+$F$12)^O84+(L20*(1+N$119)^4*$I$121*(1-$F$11)+L20*(1+N$119)^4*$F$13-$F$9-$F$10)/(1+$F$12)^P84+(L20*(1+N$119)^5*$I$121*(1-$F$11)+L20*(1+N$119)^5*$F$13-$F$9-$F$10)/(1+$F$12)^Q84+(L20*(1+N$119)^5*$I$121+L20*(1+N$119)^5*$F$13)*$C$16/(1+$F$12)^Q83,"") -> 1508438.8
B122: Rate | C122: =$Q$103 -> 0.025 | D122: =IFERROR(IF($D$119>$C$122,M78/(1+$D$119)^M84+N78/(1+$D$119)^N84+O78/(1+$D$119)^O84+P78/(1+$D$119)^P84+Q78/(1+$D$119)^Q84+Q78*(1+$C$122)/($D$119-$C$122)/(1+$D$119)^Q83,""),"") -> 1234368.2 | E122: =IFERROR(IF($E$119>$C$122,M78/(1+$E$119)^M84+N78/(1+$E$119)^N84+O78/(1+$E$119)^O84+P78/(1+$E$119)^P84+Q78/(1+$E$119)^Q84+Q78*(1+$C$122)/($E$119-$C$122)/(1+$E$119)^Q83,""),"") -> 1122647.5 | F122: =IFERROR(IF($F$119>$C$122,M78/(1+$F$119)^M84+N78/(1+$F$119)^N84+O78/(1+$F$119)^O84+P78/(1+$F$119)^P84+Q78/(1+$F$119)^Q84+Q78*(1+$C$122)/($F$119-$C$122)/(1+$F$119)^Q83,""),"") -> 1030233.9 | G122: =IFERROR(IF($G$119>$C$122,M78/(1+$G$119)^M84+N78/(1+$G$119)^N84+O78/(1+$G$119)^O84+P78/(1+$G$119)^P84+Q78/(1+$G$119)^Q84+Q78*(1+$C$122)/($G$119-$C$122)/(1+$G$119)^Q83,""),"") -> 952539.41 | H122: =IFERROR(IF($H$119>$C$122,M78/(1+$H$119)^M84+N78/(1+$H$119)^N84+O78/(1+$H$119)^O84+P78/(1+$H$119)^P84+Q78/(1+$H$119)^Q84+Q78*(1+$C$122)/($H$119-$C$122)/(1+$H$119)^Q83,""),"") -> 886320.18 | I122: =M52 -> 0.31796802 | J122: =IFERROR((L20*(1+J$119)^1*$I$122*(1-$F$11)+L20*(1+J$119)^1*$F$13-$F$9-$F$10)/(1+$F$12)^M84+(L20*(1+J$119)^2*$I$122*(1-$F$11)+L20*(1+J$119)^2*$F$13-$F$9-$F$10)/(1+$F$12)^N84+(L20*(1+J$119)^3*$I$122*(1-$F$11)+L20*(1+J$119)^3*$F$13-$F$9-$F$10)/(1+$F$12)^O84+(L20*(1+J$119)^4*$I$122*(1-$F$11)+L20*(1+J$119)^4*$F$13-$F$9-$F$10)/(1+$F$12)^P84+(L20*(1+J$119)^5*$I$122*(1-$F$11)+L20*(1+J$119)^5*$F$13-$F$9-$F$10)/(1+$F$12)^Q84+(L20*(1+J$119)^5*$I$122+L20*(1+J$119)^5*$F$13)*$C$16/(1+$F$12)^Q83,"") -> 1317778.9 | K122: =IFERROR((L20*(1+K$119)^1*$I$122*(1-$F$11)+L20*(1+K$119)^1*$F$13-$F$9-$F$10)/(1+$F$12)^M84+(L20*(1+K$119)^2*$I$122*(1-$F$11)+L20*(1+K$119)^2*$F$13-$F$9-$F$10)/(1+$F$12)^N84+(L20*(1+K$119)^3*$I$122*(1-$F$11)+L20*(1+K$119)^3*$F$13-$F$9-$F$10)/(1+$F$12)^O84+(L20*(1+K$119)^4*$I$122*(1-$F$11)+L20*(1+K$119)^4*$F$13-$F$9-$F$10)/(1+$F$12)^P84+(L20*(1+K$119)^5*$I$122*(1-$F$11)+L20*(1+K$119)^5*$F$13-$F$9-$F$10)/(1+$F$12)^Q84+(L20*(1+K$119)^5*$I$122+L20*(1+K$119)^5*$F$13)*$C$16/(1+$F$12)^Q83,"") -> 1373477.3 | L122: =IFERROR((L20*(1+L$119)^1*$I$122*(1-$F$11)+L20*(1+L$119)^1*$F$13-$F$9-$F$10)/(1+$F$12)^M84+(L20*(1+L$119)^2*$I$122*(1-$F$11)+L20*(1+L$119)^2*$F$13-$F$9-$F$10)/(1+$F$12)^N84+(L20*(1+L$119)^3*$I$122*(1-$F$11)+L20*(1+L$119)^3*$F$13-$F$9-$F$10)/(1+$F$12)^O84+(L20*(1+L$119)^4*$I$122*(1-$F$11)+L20*(1+L$119)^4*$F$13-$F$9-$F$10)/(1+$F$12)^P84+(L20*(1+L$119)^5*$I$122*(1-$F$11)+L20*(1+L$119)^5*$F$13-$F$9-$F$10)/(1+$F$12)^Q84+(L20*(1+L$119)^5*$I$122+L20*(1+L$119)^5*$F$13)*$C$16/(1+$F$12)^Q83,"") -> 1431199.9 | M122: =IFERROR((L20*(1+M$119)^1*$I$122*(1-$F$11)+L20*(1+M$119)^1*$F$13-$F$9-$F$10)/(1+$F$12)^M84+(L20*(1+M$119)^2*$I$122*(1-$F$11)+L20*(1+M$119)^2*$F$13-$F$9-$F$10)/(1+$F$12)^N84+(L20*(1+M$119)^3*$I$122*(1-$F$11)+L20*(1+M$119)^3*$F$13-$F$9-$F$10)/(1+$F$12)^O84+(L20*(1+M$119)^4*$I$122*(1-$F$11)+L20*(1+M$119)^4*$F$13-$F$9-$F$10)/(1+$F$12)^P84+(L20*(1+M$119)^5*$I$122*(1-$F$11)+L20*(1+M$119)^5*$F$13-$F$9-$F$10)/(1+$F$12)^Q84+(L20*(1+M$119)^5*$I$122+L20*(1+M$119)^5*$F$13)*$C$16/(1+$F$12)^Q83,"") -> 1491004 | N122: =IFERROR((L20*(1+N$119)^1*$I$122*(1-$F$11)+L20*(1+N$119)^1*$F$13-$F$9-$F$10)/(1+$F$12)^M84+(L20*(1+N$119)^2*$I$122*(1-$F$11)+L20*(1+N$119)^2*$F$13-$F$9-$F$10)/(1+$F$12)^N84+(L20*(1+N$119)^3*$I$122*(1-$F$11)+L20*(1+N$119)^3*$F$13-$F$9-$F$10)/(1+$F$12)^O84+(L20*(1+N$119)^4*$I$122*(1-$F$11)+L20*(1+N$119)^4*$F$13-$F$9-$F$10)/(1+$F$12)^P84+(L20*(1+N$119)^5*$I$122*(1-$F$11)+L20*(1+N$119)^5*$F$13-$F$9-$F$10)/(1+$F$12)^Q84+(L20*(1+N$119)^5*$I$122+L20*(1+N$119)^5*$F$13)*$C$16/(1+$F$12)^Q83,"") -> 1552948
C123: =C122+0.005 -> 0.03 | D123: =IFERROR(IF($D$119>$C$123,M78/(1+$D$119)^M84+N78/(1+$D$119)^N84+O78/(1+$D$119)^O84+P78/(1+$D$119)^P84+Q78/(1+$D$119)^Q84+Q78*(1+$C$123)/($D$119-$C$123)/(1+$D$119)^Q83,""),"") -> 1280245.9 | E123: =IFERROR(IF($E$119>$C$123,M78/(1+$E$119)^M84+N78/(1+$E$119)^N84+O78/(1+$E$119)^O84+P78/(1+$E$119)^P84+Q78/(1+$E$119)^Q84+Q78*(1+$C$123)/($E$119-$C$123)/(1+$E$119)^Q83,""),"") -> 1158823.9 | F123: =IFERROR(IF($F$119>$C$123,M78/(1+$F$119)^M84+N78/(1+$F$119)^N84+O78/(1+$F$119)^O84+P78/(1+$F$119)^P84+Q78/(1+$F$119)^Q84+Q78*(1+$C$123)/($F$119-$C$123)/(1+$F$119)^Q83,""),"") -> 1059304.1 | G123: =IFERROR(IF($G$119>$C$123,M78/(1+$G$119)^M84+N78/(1+$G$119)^N84+O78/(1+$G$119)^O84+P78/(1+$G$119)^P84+Q78/(1+$G$119)^Q84+Q78*(1+$C$123)/($G$119-$C$123)/(1+$G$119)^Q83,""),"") -> 976270 | H123: =IFERROR(IF($H$119>$C$123,M78/(1+$H$119)^M84+N78/(1+$H$119)^N84+O78/(1+$H$119)^O84+P78/(1+$H$119)^P84+Q78/(1+$H$119)^Q84+Q78*(1+$C$123)/($H$119-$C$123)/(1+$H$119)^Q83,""),"") -> 905952.09 | I123: =I122+0.01 -> 0.32796802 | J123: =IFERROR((L20*(1+J$119)^1*$I$123*(1-$F$11)+L20*(1+J$119)^1*$F$13-$F$9-$F$10)/(1+$F$12)^M84+(L20*(1+J$119)^2*$I$123*(1-$F$11)+L20*(1+J$119)^2*$F$13-$F$9-$F$10)/(1+$F$12)^N84+(L20*(1+J$119)^3*$I$123*(1-$F$11)+L20*(1+J$119)^3*$F$13-$F$9-$F$10)/(1+$F$12)^O84+(L20*(1+J$119)^4*$I$123*(1-$F$11)+L20*(1+J$119)^4*$F$13-$F$9-$F$10)/(1+$F$12)^P84+(L20*(1+J$119)^5*$I$123*(1-$F$11)+L20*(1+J$119)^5*$F$13-$F$9-$F$10)/(1+$F$12)^Q84+(L20*(1+J$119)^5*$I$123+L20*(1+J$119)^5*$F$13)*$C$16/(1+$F$12)^Q83,"") -> 1355536.7 | K123: =IFERROR((L20*(1+K$119)^1*$I$123*(1-$F$11)+L20*(1+K$119)^1*$F$13-$F$9-$F$10)/(1+$F$12)^M84+(L20*(1+K$119)^2*$I$123*(1-$F$11)+L20*(1+K$119)^2*$F$13-$F$9-$F$10)/(1+$F$12)^N84+(L20*(1+K$119)^3*$I$123*(1-$F$11)+L20*(1+K$119)^3*$F$13-$F$9-$F$10)/(1+$F$12)^O84+(L20*(1+K$119)^4*$I$123*(1-$F$11)+L20*(1+K$119)^4*$F$13-$F$9-$F$10)/(1+$F$12)^P84+(L20*(1+K$119)^5*$I$123*(1-$F$11)+L20*(1+K$119)^5*$F$13-$F$9-$F$10)/(1+$F$12)^Q84+(L20*(1+K$119)^5*$I$123+L20*(1+K$119)^5*$F$13)*$C$16/(1+$F$12)^Q83,"") -> 1412833.9 | L123: =IFERROR((L20*(1+L$119)^1*$I$123*(1-$F$11)+L20*(1+L$119)^1*$F$13-$F$9-$F$10)/(1+$F$12)^M84+(L20*(1+L$119)^2*$I$123*(1-$F$11)+L20*(1+L$119)^2*$F$13-$F$9-$F$10)/(1+$F$12)^N84+(L20*(1+L$119)^3*$I$123*(1-$F$11)+L20*(1+L$119)^3*$F$13-$F$9-$F$10)/(1+$F$12)^O84+(L20*(1+L$119)^4*$I$123*(1-$F$11)+L20*(1+L$119)^4*$F$13-$F$9-$F$10)/(1+$F$12)^P84+(L20*(1+L$119)^5*$I$123*(1-$F$11)+L20*(1+L$119)^5*$F$13-$F$9-$F$10)/(1+$F$12)^Q84+(L20*(1+L$119)^5*$I$123+L20*(1+L$119)^5*$F$13)*$C$16/(1+$F$12)^Q83,"") -> 1472213.6 | M123: =IFERROR((L20*(1+M$119)^1*$I$123*(1-$F$11)+L20*(1+M$119)^1*$F$13-$F$9-$F$10)/(1+$F$12)^M84+(L20*(1+M$119)^2*$I$123*(1-$F$11)+L20*(1+M$119)^2*$F$13-$F$9-$F$10)/(1+$F$12)^N84+(L20*(1+M$119)^3*$I$123*(1-$F$11)+L20*(1+M$119)^3*$F$13-$F$9-$F$10)/(1+$F$12)^O84+(L20*(1+M$119)^4*$I$123*(1-$F$11)+L20*(1+M$119)^4*$F$13-$F$9-$F$10)/(1+$F$12)^P84+(L20*(1+M$119)^5*$I$123*(1-$F$11)+L20*(1+M$119)^5*$F$13-$F$9-$F$10)/(1+$F$12)^Q84+(L20*(1+M$119)^5*$I$123+L20*(1+M$119)^5*$F$13)*$C$16/(1+$F$12)^Q83,"") -> 1533734.6 | N123: =IFERROR((L20*(1+N$119)^1*$I$123*(1-$F$11)+L20*(1+N$119)^1*$F$13-$F$9-$F$10)/(1+$F$12)^M84+(L20*(1+N$119)^2*$I$123*(1-$F$11)+L20*(1+N$119)^2*$F$13-$F$9-$F$10)/(1+$F$12)^N84+(L20*(1+N$119)^3*$I$123*(1-$F$11)+L20*(1+N$119)^3*$F$13-$F$9-$F$10)/(1+$F$12)^O84+(L20*(1+N$119)^4*$I$123*(1-$F$11)+L20*(1+N$119)^4*$F$13-$F$9-$F$10)/(1+$F$12)^P84+(L20*(1+N$119)^5*$I$123*(1-$F$11)+L20*(1+N$119)^5*$F$13-$F$9-$F$10)/(1+$F$12)^Q84+(L20*(1+N$119)^5*$I$123+L20*(1+N$119)^5*$F$13)*$C$16/(1+$F$12)^Q83,"") -> 1597457.1
C124: =C123+0.005 -> 0.035 | D124: =IFERROR(IF($D$119>$C$124,M78/(1+$D$119)^M84+N78/(1+$D$119)^N84+O78/(1+$D$119)^O84+P78/(1+$D$119)^P84+Q78/(1+$D$119)^Q84+Q78*(1+$C$124)/($D$119-$C$124)/(1+$D$119)^Q83,""),"") -> 1331419.6 | E124: =IFERROR(IF($E$119>$C$124,M78/(1+$E$119)^M84+N78/(1+$E$119)^N84+O78/(1+$E$119)^O84+P78/(1+$E$119)^P84+Q78/(1+$E$119)^Q84+Q78*(1+$C$124)/($E$119-$C$124)/(1+$E$119)^Q83,""),"") -> 1198744.3 | F124: =IFERROR(IF($F$119>$C$124,M78/(1+$F$119)^M84+N78/(1+$F$119)^N84+O78/(1+$F$119)^O84+P78/(1+$F$119)^P84+Q78/(1+$F$119)^Q84+Q78*(1+$C$124)/($F$119-$C$124)/(1+$F$119)^Q83,""),"") -> 1091100.7 | G124: =IFERROR(IF($G$119>$C$124,M78/(1+$G$119)^M84+N78/(1+$G$119)^N84+O78/(1+$G$119)^O84+P78/(1+$G$119)^P84+Q78/(1+$G$119)^Q84+Q78*(1+$C$124)/($G$119-$C$124)/(1+$G$119)^Q83,""),"") -> 1002035.4 | H124: =IFERROR(IF($H$119>$C$124,M78/(1+$H$119)^M84+N78/(1+$H$119)^N84+O78/(1+$H$119)^O84+P78/(1+$H$119)^P84+Q78/(1+$H$119)^Q84+Q78*(1+$C$124)/($H$119-$C$124)/(1+$H$119)^Q83,""),"") -> 927134.41 | I124: =I123+0.01 -> 0.33796802 | J124: =IFERROR((L20*(1+J$119)^1*$I$124*(1-$F$11)+L20*(1+J$119)^1*$F$13-$F$9-$F$10)/(1+$F$12)^M84+(L20*(1+J$119)^2*$I$124*(1-$F$11)+L20*(1+J$119)^2*$F$13-$F$9-$F$10)/(1+$F$12)^N84+(L20*(1+J$119)^3*$I$124*(1-$F$11)+L20*(1+J$119)^3*$F$13-$F$9-$F$10)/(1+$F$12)^O84+(L20*(1+J$119)^4*$I$124*(1-$F$11)+L20*(1+J$119)^4*$F$13-$F$9-$F$10)/(1+$F$12)^P84+(L20*(1+J$119)^5*$I$124*(1-$F$11)+L20*(1+J$119)^5*$F$13-$F$9-$F$10)/(1+$F$12)^Q84+(L20*(1+J$119)^5*$I$124+L20*(1+J$119)^5*$F$13)*$C$16/(1+$F$12)^Q83,"") -> 1393294.4 | K124: =IFERROR((L20*(1+K$119)^1*$I$124*(1-$F$11)+L20*(1+K$119)^1*$F$13-$F$9-$F$10)/(1+$F$12)^M84+(L20*(1+K$119)^2*$I$124*(1-$F$11)+L20*(1+K$119)^2*$F$13-$F$9-$F$10)/(1+$F$12)^N84+(L20*(1+K$119)^3*$I$124*(1-$F$11)+L20*(1+K$119)^3*$F$13-$F$9-$F$10)/(1+$F$12)^O84+(L20*(1+K$119)^4*$I$124*(1-$F$11)+L20*(1+K$119)^4*$F$13-$F$9-$F$10)/(1+$F$12)^P84+(L20*(1+K$119)^5*$I$124*(1-$F$11)+L20*(1+K$119)^5*$F$13-$F$9-$F$10)/(1+$F$12)^Q84+(L20*(1+K$119)^5*$I$124+L20*(1+K$119)^5*$F$13)*$C$16/(1+$F$12)^Q83,"") -> 1452190.6 | L124: =IFERROR((L20*(1+L$119)^1*$I$124*(1-$F$11)+L20*(1+L$119)^1*$F$13-$F$9-$F$10)/(1+$F$12)^M84+(L20*(1+L$119)^2*$I$124*(1-$F$11)+L20*(1+L$119)^2*$F$13-$F$9-$F$10)/(1+$F$12)^N84+(L20*(1+L$119)^3*$I$124*(1-$F$11)+L20*(1+L$119)^3*$F$13-$F$9-$F$10)/(1+$F$12)^O84+(L20*(1+L$119)^4*$I$124*(1-$F$11)+L20*(1+L$119)^4*$F$13-$F$9-$F$10)/(1+$F$12)^P84+(L20*(1+L$119)^5*$I$124*(1-$F$11)+L20*(1+L$119)^5*$F$13-$F$9-$F$10)/(1+$F$12)^Q84+(L20*(1+L$119)^5*$I$124+L20*(1+L$119)^5*$F$13)*$C$16/(1+$F$12)^Q83,"") -> 1513227.4 | M124: =IFERROR((L20*(1+M$119)^1*$I$124*(1-$F$11)+L20*(1+M$119)^1*$F$13-$F$9-$F$10)/(1+$F$12)^M84+(L20*(1+M$119)^2*$I$124*(1-$F$11)+L20*(1+M$119)^2*$F$13-$F$9-$F$10)/(1+$F$12)^N84+(L20*(1+M$119)^3*$I$124*(1-$F$11)+L20*(1+M$119)^3*$F$13-$F$9-$F$10)/(1+$F$12)^O84+(L20*(1+M$119)^4*$I$124*(1-$F$11)+L20*(1+M$119)^4*$F$13-$F$9-$F$10)/(1+$F$12)^P84+(L20*(1+M$119)^5*$I$124*(1-$F$11)+L20*(1+M$119)^5*$F$13-$F$9-$F$10)/(1+$F$12)^Q84+(L20*(1+M$119)^5*$I$124+L20*(1+M$119)^5*$F$13)*$C$16/(1+$F$12)^Q83,"") -> 1576465.3 | N124: =IFERROR((L20*(1+N$119)^1*$I$124*(1-$F$11)+L20*(1+N$119)^1*$F$13-$F$9-$F$10)/(1+$F$12)^M84+(L20*(1+N$119)^2*$I$124*(1-$F$11)+L20*(1+N$119)^2*$F$13-$F$9-$F$10)/(1+$F$12)^N84+(L20*(1+N$119)^3*$I$124*(1-$F$11)+L20*(1+N$119)^3*$F$13-$F$9-$F$10)/(1+$F$12)^O84+(L20*(1+N$119)^4*$I$124*(1-$F$11)+L20*(1+N$119)^4*$F$13-$F$9-$F$10)/(1+$F$12)^P84+(L20*(1+N$119)^5*$I$124*(1-$F$11)+L20*(1+N$119)^5*$F$13-$F$9-$F$10)/(1+$F$12)^Q84+(L20*(1+N$119)^5*$I$124+L20*(1+N$119)^5*$F$13)*$C$16/(1+$F$12)^Q83,"") -> 1641966.2
B126: Min | C126: =MIN(D120:H124) -> 851073.11 | I126: Min | J126: =MIN(J120:N124) -> 1242263.5
...

Sheet DCF Model - Bull (2)
B2: Discounted Cash Flow Model
B3: Company Apple Inc.
B4: All $ in USD millions unless otherwise stated
B6: Assumptions
B8: Valuation Summary | E8: Operating Assumptions | H8: Other Inputs
B9: Implied Enterprise Value | C9: =Q94 -> 1601928.3 | E9: CapEx | F9: 0.025268114 | H9: Valuation Date | I9: 46298
B10: Implied EV / EBITDA | C10: =IFERROR(C9/L54,0) -> 11.067015 | E10: Change in NWC | F10: -0.0025 | H10: Closing Date
B11: Current Equity Value | C11: 4869931.9 | E11: Tax Rate | F11: 0.15610002 | H11: Fiscal Year End | I11: 46291
B12: Implied Equity Value | C12: =C9-AA18+AA17+AA19-F20-F21 -> 1635691.3 | E12: WACC | F12: =WACC!D35 -> 0.1334077
B13: Implied Share Price (Gordon Growth) | C13: =Q111/$I$16 -> 84.79197 | E13: D&A % revenue | F13: 0.029143716 | H13: EBIT Margin Convergence (Years) | I13: 5
B14: Implied Share Price (Exit Multiple) | C14: =C12/$I$16 -> 109.01195 | E14: Stage 1 Revenue Growth | F14: 0.0428 | H14: Revenue Growth Stage 1 (Years) | I14: 3
B15: Terminal Assumptions | E15: Starting EBIT Margin | F15: 0.329708 | H15: Revenue Growth Fade (Years) | I15: 4
B16: Exit EBITDA Multiple | C16: 11.699147 | E16: Forecast Gross Margin | F16: 0.45747548 | H16: Diluted Shares (millions) | I16: 15004.697
B17: Cash and Cash Equivalents | C17: 35934 | E17: Steady-State EBIT Margin | F17: 0.32100812 | H17: Current Share Price | I17: 333.69 | AA17: =C17 -> 35934
B18: Income Statement | H18: FY2021A | I18: FY2022A | J18: FY2023A | K18: FY2024A | L18: FY2025A | M18: FY2026E | N18: FY2027E | O18: FY2028E | P18: FY2029E | Q18: FY2030E | S18: FY'21-22A | T18: FY'23-30E | AA18: 98657
E19: Stage 2 Revenue Growth | F19: 0.02968 | AA19: 96486
B20: Total Revenue | F20: 0 | H20: ='Data Given (Recalculated)'!G12 -> 365817 | I20: ='Data Given (Recalculated)'!H12 -> 394328 | J20: ='Data Given (Recalculated)'!I12 -> 383285 | K20: ='Data Given (Recalculated)'!J12 -> 391035 | L20: ='Data Given (Recalculated)'!K12 -> 416161 | M20: =L20*(1+M21) -> 433972.69 | N20: =M20*(1+N21) -> 452546.72 | O20: =N20*(1+O21) -> 471915.72 | P20: =O20*(1+P21) -> 490565.83 | Q20: =P20*(1+Q21) -> 508343.94 | S20: =IFERROR((I20/H20)^(1/(COLUMNS(H20:I20)-1))-1,"") -> 0.077937876 | T20: =IFERROR((Q20/J20)^(1/(COLUMNS(J20:Q20)-1))-1,"") -> 0.041164624
B21: % growth | F21: 0 | H21: ="" | I21: =IFERROR(I20/H20-1,0) -> 0.077937876 | J21: =IFERROR(J20/I20-1,0) -> -0.028004605 | K21: =IFERROR(K20/J20-1,0) -> 0.020219941 | L21: =IFERROR(L20/K20-1,0) -> 0.064255118 | M21: =$F$14+($F$19-$F$14)*MAX(0,MIN(1,(M$83-$I$14)/$I$15)) -> 0.0428 | N21: =$F$14+($F$19-$F$14)*MAX(0,MIN(1,(N$83-$I$14)/$I$15)) -> 0.0428 | O21: =$F$14+($F$19-$F$14)*MAX(0,MIN(1,(O$83-$I$14)/$I$15)) -> 0.0428 | P21: =$F$14+($F$19-$F$14)*MAX(0,MIN(1,(P$83-$I$14)/$I$15)) -> 0.03952 | Q21: =$F$14+($F$19-$F$14)*MAX(0,MIN(1,(Q$83-$I$14)/$I$15)) -> 0.03624
B23: Cost of Revenue
B24: Cost of Revenue | H24: ='Data Given (Recalculated)'!G16 -> 212981 | I24: ='Data Given (Recalculated)'!H16 -> 223546 | J24: ='Data Given (Recalculated)'!I16 -> 214137 | K24: ='Data Given (Recalculated)'!J16 -> 210352 | L24: ='Data Given (Recalculated)'!K16 -> 201436 | M24: =M20*(1-$F$16)-M27 -> 215081.2 | N24: =N20*(1-$F$16)-N27 -> 224286.67 | O24: =O20*(1-$F$16)-O27 -> 233886.14 | P24: =P20*(1-$F$16)-P27 -> 243129.32 | Q24: =Q20*(1-$F$16)-Q27 -> 251940.33 | S24: =IFERROR((I24/H24)^(1/(COLUMNS(H24:I24)-1))-1,"") -> 0.049605364 | T24: =IFERROR((Q24/J24)^(1/(COLUMNS(J24:Q24)-1))-1,"") -> 0.023496988
B25: % of revenue | H25: =IFERROR(H24/H20,0) -> 0.5822064 | I25: =IFERROR(I24/I20,0) -> 0.56690369 | J25: =IFERROR(J24/J20,0) -> 0.5586887 | K25: =IFERROR(K24/K20,0) -> 0.5379365 | L25: =IFERROR(L24/L20,0) -> 0.48403382 | M25: =IFERROR(M24/M20,0) -> 0.49560999 | N25: =IFERROR(N24/N20,0) -> 0.49560999 | O25: =IFERROR(O24/O20,0) -> 0.49560999 | ... Q25: =IFERROR(Q24/Q20,0) -> 0.49560999
B27: Other Cost of Revenue | H27: ='Data Given (Recalculated)'!G17 -> 0 | I27: ='Data Given (Recalculated)'!H17 -> 0 | J27: ='Data Given (Recalculated)'!I17 -> 0 | K27: ='Data Given (Recalculated)'!J17 -> 0 | L27: ='Data Given (Recalculated)'!K17 -> 19524 | M27: =M20*L28 -> 20359.627 | N27: =N20*M28 -> 21231.019 | O27: =O20*N28 -> 22139.707 | P27: =P20*O28 -> 23014.668 | Q27: =Q20*P28 -> 23848.72 | S27: =IFERROR((I27/H27)^(1/(COLUMNS(H27:I27)-1))-1,"") | T27: =IFERROR((Q27/J27)^(1/(COLUMNS(J27:Q27)-1))-1,"")
B28: % of revenue | H28: =IFERROR(H27/H20,0) -> 0 | I28: =IFERROR(I27/I20,0) -> 0 | J28: =IFERROR(J27/J20,0) -> 0 | K28: =IFERROR(K27/K20,0) -> 0 | L28: =IFERROR(L27/L20,0) -> 0.046914535 | M28: =IFERROR(M27/M20,0) -> 0.046914535 | N28: =IFERROR(N27/N20,0) -> 0.046914535 | O28: =IFERROR(O27/O20,0) -> 0.046914535 | ... Q28: =IFERROR(Q27/Q20,0) -> 0.046914535
B30: Total Cost of Sales | H30: =H24+H27 -> 212981 | I30: =I24+I27 -> 223546 | J30: =J24+J27 -> 214137 | K30: =K24+K27 -> 210352 | L30: =L24+L27 -> 220960 | M30: =M24+M27 -> 235440.83 | N30: =N24+N27 -> 245517.69 | O30: =O24+O27 -> 256025.85 | ... Q30: =Q24+Q27 -> 275789.05
B32: Gross Profit | H32: =H20-H30 -> 152836 | I32: =I20-I30 -> 170782 | J32: =J20-J30 -> 169148 | K32: =K20-K30 -> 180683 | L32: =L20-L30 -> 195201 | M32: =M20-M30 -> 198531.86 | N32: =N20-N30 -> 207029.03 | O32: =O20-O30 -> 215889.87 | ... Q32: =Q20-Q30 -> 232554.89 | S32: =IFERROR((I32/H32)^(1/(COLUMNS(H32:I32)-1))-1,"") -> 0.11741998 | T32: =IFERROR((Q32/J32)^(1/(COLUMNS(J32:Q32)-1))-1,"") -> 0.046528907
B33: % margin | H33: =IFERROR(H32/H20,0) -> 0.4177936 | I33: =IFERROR(I32/I20,0) -> 0.43309631 | J33: =IFERROR(J32/J20,0) -> 0.4413113 | K33: =IFERROR(K32/K20,0) -> 0.4620635 | L33: =IFERROR(L32/L20,0) -> 0.46905164 | M33: =IFERROR(M32/M20,0) -> 0.45747548 | N33: =IFERROR(N32/N20,0) -> 0.45747548 | O33: =IFERROR(O32/O20,0) -> 0.45747548 | ... Q33: =IFERROR(Q32/Q20,0) -> 0.45747548
B35: Operating Expenses
B36: Research & Development | H36: ='Data Given (Recalculated)'!G24 -> 21914 | I36: ='Data Given (Recalculated)'!H24 -> 26251 | J36: ='Data Given (Recalculated)'!I24 -> 29915 | K36: ='Data Given (Recalculated)'!J24 -> 31370 | L36: ='Data Given (Recalculated)'!K24 -> 34550 | M36: =M20*M37 -> 36028.74 | N36: =N20*N37 -> 37570.77 | O36: =O20*O37 -> 39178.799 | P36: =P20*P37 -> 40727.145 | Q36: =Q20*Q37 -> 42203.097 | S36: =IFERROR((I36/H36)^(1/(COLUMNS(H36:I36)-1))-1,"") -> 0.19791001 | T36: =IFERROR((Q36/J36)^(1/(COLUMNS(J36:Q36)-1))-1,"") -> 0.050390437
B37: % of revenue | H37: =IFERROR(H36/H20,0) -> 0.059904269 | I37: =IFERROR(I36/I20,0) -> 0.066571484 | J37: =IFERROR(J36/J20,0) -> 0.078048971 | K37: =IFERROR(K36/K20,0) -> 0.080222998 | L37: =IFERROR(L36/L20,0) -> 0.083020754 | M37: =L37 -> 0.083020754 | N37: =M37 -> 0.083020754 | O37: =N37 -> 0.083020754 | P37: =O37 -> 0.083020754 | Q37: =P37 -> 0.083020754
B39: SG&A | H39: ='Data Given (Recalculated)'!G25 -> 21973 | I39: ='Data Given (Recalculated)'!H25 -> 25094 | J39: ='Data Given (Recalculated)'!I25 -> 24932 | K39: ='Data Given (Recalculated)'!J25 -> 26097 | L39: ='Data Given (Recalculated)'!K25 -> 27601 | M39: =M20*M40 -> 28782.323 | N39: =N20*N40 -> 30014.206 | O39: =O20*O40 -> 31298.814 | P39: =P20*P40 -> 32535.743 | Q39: =Q20*Q40 -> 33714.839 | S39: =IFERROR((I39/H39)^(1/(COLUMNS(H39:I39)-1))-1,"") -> 0.14203796 | T39: =IFERROR((Q39/J39)^(1/(COLUMNS(J39:Q39)-1))-1,"") -> 0.044055112
B40: % of revenue | H40: =IFERROR(H39/H20,0) -> 0.060065552 | I40: =IFERROR(I39/I20,0) -> 0.063637378 | J40: =IFERROR(J39/J20,0) -> 0.065048202 | K40: =IFERROR(K39/K20,0) -> 0.066738272 | L40: =IFERROR(L39/L20,0) -> 0.066322889 | M40: =L40 -> 0.066322889 | N40: =M40 -> 0.066322889 | O40: =N40 -> 0.066322889 | P40: =O40 -> 0.066322889 | Q40: =P40 -> 0.066322889
B42: D&A (included in Operating) | H42: ='Data Given (Recalculated)'!G26 -> 11284 | I42: ='Data Given (Recalculated)'!H26 -> 11104 | J42: ='Data Given (Recalculated)'!I26 -> 11519 | K42: ='Data Given (Recalculated)'!J26 -> 11445 | L42: ='Data Given (Recalculated)'!K26 -> 11698 | M42: =M20*$F$13 -> 12647.577 | N42: =N20*$F$13 -> 13188.893 | O42: =O20*$F$13 -> 13753.378 | P42: =P20*$F$13 -> 14296.911 | Q42: =Q20*$F$13 -> 14815.031 | S42: =IFERROR((I42/H42)^(1/(COLUMNS(H42:I42)-1))-1,"") -> -0.01595179 | T42: =IFERROR((Q42/J42)^(1/(COLUMNS(J42:Q42)-1))-1,"") -> 0.036603193
B43: % of revenue | H43: =IFERROR(H42/H20,0) -> 0.030846024 | I43: =IFERROR(I42/I20,0) -> 0.028159299 | J43: =IFERROR(J42/J20,0) -> 0.030053355 | K43: =IFERROR(K42/K20,0) -> 0.02926848 | L43: =IFERROR(L42/L20,0) -> 0.028109313 | M43: =L43 -> 0.028109313 | N43: =M43 -> 0.028109313 | O43: =N43 -> 0.028109313 | P43: =O43 -> 0.028109313 | Q43: =P43 -> 0.028109313
B45: Other OpEx / (Income) | H45: ='Data Given (Recalculated)'!G27 -> 0 | I45: ='Data Given (Recalculated)'!H27 -> 0 | J45: ='Data Given (Recalculated)'!I27 -> 0 | K45: ='Data Given (Recalculated)'!J27 -> 0 | L45: ='Data Given (Recalculated)'!K27 -> 0 | M45: =M32-M36-M39-M20*M53 -> -8608.3632 | N45: =N32-N36-N39-N20*N53 -> -8189.3806 | O45: =O32-O36-O39-O20*O53 -> -7718.764 | P45: =P32-P36-P39-P20*P53 -> -7170.2366 | Q45: =Q32-Q36-Q39-Q20*Q53 -> -6545.5796 | S45: =IFERROR((I45/H45)^(1/(COLUMNS(H45:I45)-1))-1,"") | T45: =IFERROR((Q45/J45)^(1/(COLUMNS(J45:Q45)-1))-1,"")
B46: % of revenue | H46: =IFERROR(H45/H20,0) -> 0 | I46: =IFERROR(I45/I20,0) -> 0 | J46: =IFERROR(J45/J20,0) -> 0 | K46: =IFERROR(K45/K20,0) -> 0 | L46: =IFERROR(L45/L20,0) -> 0 | M46: =IFERROR(M45/M20,0) -> -0.019836186 | N46: =IFERROR(N45/N20,0) -> -0.01809621 | O46: =IFERROR(O45/O20,0) -> -0.016356234 | ... Q46: =IFERROR(Q45/Q20,0) -> -0.012876281
B48: Total Operating Expenses | H48: =-(H36+H39+H45) -> -43887 | I48: =-(I36+I39+I45) -> -51345 | J48: =-(J36+J39+J45) -> -54847 | K48: =-(K36+K39+K45) -> -57467 | L48: =-(L36+L39+L45) -> -62151 | M48: =-(M36+M39+M45) -> -56202.7 | N48: =-(N36+N39+N45) -> -59395.596 | O48: =-(O36+O39+O45) -> -62758.849 | ... Q48: =-(Q36+Q39+Q45) -> -69372.356 | S48: =IFERROR((I48/H48)^(1/(COLUMNS(H48:I48)-1))-1,"") -> 0.16993643 | T48: =IFERROR((Q48/J48)^(1/(COLUMNS(J48:Q48)-1))-1,"") -> 0.034132588
B49: % of revenue | H49: =IFERROR(-H48/H20,0) -> 0.11996982 | I49: =IFERROR(-I48/I20,0) -> 0.13020886 | J49: =IFERROR(-J48/J20,0) -> 0.14309717 | K49: =IFERROR(-K48/K20,0) -> 0.14696127 | L49: =IFERROR(-L48/L20,0) -> 0.14934364 | M49: =IFERROR(-M48/M20,0) -> 0.12950746 | N49: =IFERROR(-N48/N20,0) -> 0.13124743 | O49: =IFERROR(-O48/O20,0) -> 0.13298741 | ... Q49: =IFERROR(-Q48/Q20,0) -> 0.13646736
B51: EBIT | H51: =H32+H48 -> 108949 | I51: =I32+I48 -> 119437 | J51: =J32+J48 -> 114301 | K51: =K32+K48 -> 123216 | L51: =L32+L48 -> 133050 | M51: =M32+M48 -> 142329.16 | N51: =N32+N48 -> 147633.43 | O51: =O32+O48 -> 153131.02 | ... Q51: =Q32+Q48 -> 163182.53 | S51: =IFERROR((I51/H51)^(1/(COLUMNS(H51:I51)-1))-1,"") -> 0.096265225 | T51: =IFERROR((Q51/J51)^(1/(COLUMNS(J51:Q51)-1))-1,"") -> 0.052177693
B52: % margin | H52: =IFERROR(H51/H20,0) -> 0.29782378 | I52: =IFERROR(I51/I20,0) -> 0.30288744 | J52: =IFERROR(J51/J20,0) -> 0.29821412 | K52: =IFERROR(K51/K20,0) -> 0.31510223 | L52: =IFERROR(L51/L20,0) -> 0.319708 | M52: =IFERROR(M51/M20,0) -> 0.32796802 | N52: =IFERROR(N51/N20,0) -> 0.32622805 | O52: =IFERROR(O51/O20,0) -> 0.32448807 | ... Q52: =IFERROR(Q51/Q20,0) -> 0.32100812
B53: Forecast EBIT Margin Driver | M53: =IF(M$83<$I$13,$F$15+($F$17-$F$15)*M$83/$I$13,$F$17) -> 0.32796802 | N53: =IF(N$83<$I$13,$F$15+($F$17-$F$15)*N$83/$I$13,$F$17) -> 0.32622805 | O53: =IF(O$83<$I$13,$F$15+($F$17-$F$15)*O$83/$I$13,$F$17) -> 0.32448807 | P53: =IF(P$83<$I$13,$F$15+($F$17-$F$15)*P$83/$I$13,$F$17) -> 0.32274809 | Q53: =IF(Q$83<$I$13,$F$15+($F$17-$F$15)*Q$83/$I$13,$F$17) -> 0.32100812
B54: EBITDA | H54: =H51+H68 -> 120233 | I54: =I51+I68 -> 130541 | J54: =J51+J68 -> 125820 | K54: =K51+K68 -> 134661 | L54: =L51+L68 -> 144748 | M54: =M51+M68 -> 154976.74 | N54: =N51+N68 -> 160822.33 | O54: =O51+O68 -> 166884.4 | ... Q54: =Q51+Q68 -> 177997.56 | S54: =IFERROR((I54/H54)^(1/(COLUMNS(H54:I54)-1))-1,"") -> 0.085733534 | T54: =IFERROR((Q54/J54)^(1/(COLUMNS(J54:Q54)-1))-1,"") -> 0.050808269
B55: % margin | H55: =IFERROR(H54/H20,0) -> 0.3286698 | I55: =IFERROR(I54/I20,0) -> 0.33104674 | J55: =IFERROR(J54/J20,0) -> 0.32826748 | K55: =IFERROR(K54/K20,0) -> 0.34437071 | L55: =IFERROR(L54/L20,0) -> 0.34781731 | M55: =IFERROR(M54/M20,0) -> 0.35711174 | N55: =IFERROR(N54/N20,0) -> 0.35537176 | O55: =IFERROR(O54/O20,0) -> 0.35363178 | ... Q55: =IFERROR(Q54/Q20,0) -> 0.35015183
B57: Income Taxes | H57: =-H51*H58 -> -17006.941 | I57: =-I51*I58 -> -18644.118 | J57: =-J51*J58 -> -17842.389 | K57: =-K51*K58 -> -19234.02 | L57: =-L51*L58 -> -20769.108 | M57: =-M51*M58 -> -22217.586 | N57: =-N51*N58 -> -23045.582 | O57: =-O51*O58 -> -23903.756 | ... Q57: =-Q51*Q58 -> -25472.797
B58: % tax rate | H58: =$F$11 -> 0.15610002 | I58: =$F$11 -> 0.15610002 | J58: =$F$11 -> 0.15610002 | K58: =$F$11 -> 0.15610002 | L58: =$F$11 -> 0.15610002 | M58: =$F$11 -> 0.15610002 | N58: =$F$11 -> 0.15610002 | O58: =$F$11 -> 0.15610002 | ... Q58: =$F$11 -> 0.15610002
B60: NOPAT | H60: =H51+H57 -> 91942.059 | I60: =I51+I57 -> 100792.88 | J60: =J51+J57 -> 96458.611 | K60: =K51+K57 -> 103981.98 | L60: =L51+L57 -> 112280.89 | M60: =M51+M57 -> 120111.58 | N60: =N51+N57 -> 124587.85 | O60: =O51+O57 -> 129227.27 | ... Q60: =Q51+Q57 -> 137709.73 | S60: =IFERROR((I60/H60)^(1/(COLUMNS(H60:I60)-1))-1,"") -> 0.096265225 | T60: =IFERROR((Q60/J60)^(1/(COLUMNS(J60:Q60)-1))-1,"") -> 0.052177693
B61: % revenue | H61: =IFERROR(H60/H20,0) -> 0.25133348 | I61: =IFERROR(I60/I20,0) -> 0.25560671 | J61: =IFERROR(J60/J20,0) -> 0.25166289 | K61: =IFERROR(K60/K20,0) -> 0.26591476 | L61: =IFERROR(L60/L20,0) -> 0.26980157 | M61: =IFERROR(M60/M20,0) -> 0.27677221 | N61: =IFERROR(N60/N20,0) -> 0.27530384 | O61: =IFERROR(O60/O20,0) -> 0.27383547 | ... Q61: =IFERROR(Q60/Q20,0) -> 0.27089874
B63: PP&E Schedule | H63: FY2021A | I63: FY2022A | J63: FY2023A | K63: FY2024A | L63: FY2025A | M63: FY2026E | N63: FY2027E | O63: FY2028E | P63: FY2029E | Q63: FY2030E
B65: CapEx | H65: =IF('Data Given (Recalculated)'!G35="","",-'Data Given (Recalculated)'!G35) -> -11085 | I65: =IF('Data Given (Recalculated)'!H35="","",-'Data Given (Recalculated)'!H35) -> -10708 | J65: =IF('Data Given (Recalculated)'!I35="","",-'Data Given (Recalculated)'!I35) -> -10959 | K65: =IF('Data Given (Recalculated)'!J35="","",-'Data Given (Recalculated)'!J35) -> -9447 | L65: =IF('Data Given (Recalculated)'!K35="","",-'Data Given (Recalculated)'!K35) -> -12715 | M65: =-M20*$F$9 -> -10965.672 | N65: =-N20*$F$9 -> -11435.002 | O65: =-O20*$F$9 -> -11924.42 | P65: =-P20*$F$9 -> -12395.673 | Q65: =-Q20*$F$9 -> -12844.893
B66: % sales | H66: =IFERROR(-H65/H20,0) -> 0.030302036 | I66: =IFERROR(-I65/I20,0) -> 0.027155059 | J66: =IFERROR(-J65/J20,0) -> 0.028592301 | K66: =IFERROR(-K65/K20,0) -> 0.024158963 | L66: =IFERROR(-L65/L20,0) -> 0.030553079 | M66: =IFERROR(-M65/M20,0) -> 0.025268114 | N66: =IFERROR(-N65/N20,0) -> 0.025268114 | O66: =IFERROR(-O65/O20,0) -> 0.025268114 | ... Q66: =IFERROR(-Q65/Q20,0) -> 0.025268114
B68: Depreciation & Amortization | H68: =IF('Data Given (Recalculated)'!G36="","",'Data Given (Recalculated)'!G36) -> 11284 | I68: =IF('Data Given (Recalculated)'!H36="","",'Data Given (Recalculated)'!H36) -> 11104 | J68: =IF('Data Given (Recalculated)'!I36="","",'Data Given (Recalculated)'!I36) -> 11519 | K68: =IF('Data Given (Recalculated)'!J36="","",'Data Given (Recalculated)'!J36) -> 11445 | L68: =IF('Data Given (Recalculated)'!K36="","",'Data Given (Recalculated)'!K36) -> 11698 | M68: =M20*$F$13 -> 12647.577 | N68: =N20*$F$13 -> 13188.893 | O68: =O20*$F$13 -> 13753.378 | P68: =P20*$F$13 -> 14296.911 | Q68: =Q20*$F$13 -> 14815.031
B69: % revenue (assumed) | H69: =IFERROR(H68/H20,0) -> 0.030846024 | I69: =IFERROR(I68/I20,0) -> 0.028159299 | J69: =IFERROR(J68/J20,0) -> 0.030053355 | K69: =IFERROR(K68/K20,0) -> 0.02926848 | L69: =IFERROR(L68/L20,0) -> 0.028109313 | M69: =$F$13 -> 0.029143716 | N69: =$F$13 -> 0.029143716 | O69: =$F$13 -> 0.029143716 | P69: =$F$13 -> 0.029143716 | Q69: =$F$13 -> 0.029143716
B70: % of CapEx | H70: =IFERROR(-H68/H65,0) -> 1.0179522 | I70: =IFERROR(-I68/I65,0) -> 1.0369817 | J70: =IFERROR(-J68/J65,0) -> 1.0510996 | K70: =IFERROR(-K68/K65,0) -> 1.2114957 | L70: =IFERROR(-L68/L65,0) -> 0.92001573 | M70: =IFERROR(-M68/M65,0) -> 1.1533791 | N70: =IFERROR(-N68/N65,0) -> 1.1533791 | O70: =IFERROR(-O68/O65,0) -> 1.1533791 | ... Q70: =IFERROR(-Q68/Q65,0) -> 1.1533791
B71: Unlevered Free Cash Flow Waterfall
B72: Unlevered Free Cash Flow Waterfall | H72: FY2021A | I72: FY2022A | J72: FY2023A | K72: FY2024A | L72: FY2025A | M72: FY2026E | N72: FY2027E | O72: FY2028E | P72: FY2029E | Q72: FY2030E
B74: NOPAT | H74: =H60 -> 91942.059 | I74: =I60 -> 100792.88 | J74: =J60 -> 96458.611 | K74: =K60 -> 103981.98 | L74: =L60 -> 112280.89 | M74: =M60 -> 120111.58 | N74: =N60 -> 124587.85 | O74: =O60 -> 129227.27 | ... Q74: =Q60 -> 137709.73
B75: (+) Depreciation | H75: =H68 -> 11284 | I75: =I68 -> 11104 | J75: =J68 -> 11519 | K75: =K68 -> 11445 | L75: =L68 -> 11698 | M75: =M68 -> 12647.577 | N75: =N68 -> 13188.893 | O75: =O68 -> 13753.378 | ... Q75: =Q68 -> 14815.031
B76: (-) Capital Expenditures | H76: =H65 -> -11085 | I76: =I65 -> -10708 | J76: =J65 -> -10959 | K76: =K65 -> -9447 | L76: =L65 -> -12715 | M76: =M65 -> -10965.672 | N76: =N65 -> -11435.002 | O76: =O65 -> -11924.42 | ... Q76: =Q65 -> -12844.893
B77: (-) Change in NWC | H77: ="" | I77: =IF('Data Given (Recalculated)'!H41="","",-'Data Given (Recalculated)'!H41) -> 9080 | J77: =IF('Data Given (Recalculated)'!I41="","",-'Data Given (Recalculated)'!I41) -> -4213 | K77: =IF('Data Given (Recalculated)'!J41="","",-'Data Given (Recalculated)'!J41) -> 1492 | L77: =IF('Data Given (Recalculated)'!K41="","",-'Data Given (Recalculated)'!K41) -> -3899 | M77: =IFERROR(-((M20*'Data Given (Recalculated)'!$C$50/365+M30*'Data Given (Recalculated)'!$C$51/365-M30*'Data Given (Recalculated)'!$C$52/365+M20*$F$10)-'Data Given (Recalculated)'!K40),"") -> 3586.0839 | N77: =IFERROR(-((N20*'Data Given (Recalculated)'!$C$50/365+N30*'Data Given (Recalculated)'!$C$51/365-N30*'Data Given (Recalculated)'!$C$52/365+N20*$F$10)-(M20*'Data Given (Recalculated)'!$C$50/365+M30*'Data Given (Recalculated)'!$C$51/365-M30*'Data Given (Recalculated)'!$C$52/365+M20*$F$10)),"") -> 1196.3064 | O77: =IFERROR(-((O20*'Data Given (Recalculated)'!$C$50/365+O30*'Data Given (Recalculated)'!$C$51/365-O30*'Data Given (Recalculated)'!$C$52/365+O20*$F$10)-(N20*'Data Given (Recalculated)'!$C$50/365+N30*'Data Given (Recalculated)'!$C$51/365-N30*'Data Given (Recalculated)'!$C$52/365+N20*$F$10)),"") -> 1247.5083 | P77: =IFERROR(-((P20*'Data Given (Recalculated)'!$C$50/365+P30*'Data Given (Recalculated)'!$C$51/365-P30*'Data Given (Recalculated)'!$C$52/365+P20*$F$10)-(O20*'Data Given (Recalculated)'!$C$50/365+O30*'Data Given (Recalculated)'!$C$51/365-O30*'Data Given (Recalculated)'!$C$52/365+O20*$F$10)),"") -> 1201.2064 | Q77: =IFERROR(-((Q20*'Data Given (Recalculated)'!$C$50/365+Q30*'Data Given (Recalculated)'!$C$51/365-Q30*'Data Given (Recalculated)'!$C$52/365+Q20*$F$10)-(P20*'Data Given (Recalculated)'!$C$50/365+P30*'Data Given (Recalculated)'!$C$51/365-P30*'Data Given (Recalculated)'!$C$52/365+P20*$F$10)),"") -> 1145.0428
B78: Unlevered Free Cash Flow | H78: =SUM(H74:H77) -> 92141.059 | I78: =SUM(I74:I77) -> 110268.88 | J78: =SUM(J74:J77) -> 92805.611 | K78: =SUM(K74:K77) -> 107471.98 | L78: =SUM(L74:L77) -> 107364.89 | M78: =SUM(M74:M77) -> 125379.57 | N78: =SUM(N74:N77) -> 127538.05 | O78: =SUM(O74:O77) -> 132303.73 | ... Q78: =SUM(Q74:Q77) -> 140824.91 | T78: =IFERROR((Q78/J78)^(1/(COLUMNS(J78:Q78)-1))-1,"") -> 0.061383129
B79: % of revenue | H79: =IFERROR(H78/H20,0) -> 0.25187746 | I79: =IFERROR(I78/I20,0) -> 0.27963746 | J79: =IFERROR(J78/J20,0) -> 0.24213212 | K79: =IFERROR(K78/K20,0) -> 0.2748398 | L79: =IFERROR(L78/L20,0) -> 0.25798884 | M79: =IFERROR(M78/M20,0) -> 0.28891119 | N79: =IFERROR(N78/N20,0) -> 0.28182294 | O79: =IFERROR(O78/O20,0) -> 0.28035457 | ... Q79: =IFERROR(Q78/Q20,0) -> 0.27702684
B81: Date for Valuation | E81: =I9 -> 46298
B82: Date For Discounting Cash Flows | M82: =EOMONTH(I11,12) -> 46660 | N82: =EOMONTH(M82,12) -> 47026 | O82: =EOMONTH(N82,12) -> 47391 | P82: =EOMONTH(O82,12) -> 47756 | Q82: =EOMONTH(P82,12) -> 48121
B83: Period, Stub Adjusted | M83: =1 -> 1 | N83: =M83+1 -> 2 | O83: =N83+1 -> 3 | P83: =O83+1 -> 4 | Q83: =P83+1 -> 5
B84: Discount Period, Stub and Mid-Year Adjusted | M84: =M83/2 -> 0.5 | N84: =N83-0.5 -> 1.5 | O84: =O83-0.5 -> 2.5 | P84: =P83-0.5 -> 3.5 | Q84: =Q83-0.5 -> 4.5
B85: Discount Rate | M85: =$F$12 -> 0.1334077 | N85: =$F$12 -> 0.1334077 | O85: =$F$12 -> 0.1334077 | P85: =$F$12 -> 0.1334077 | Q85: =$F$12 -> 0.1334077
B86: Present Value of Cash Flows
B87: Present Value of Unlevered Free Cash Flow | M87: =M78/(1+M85)^M84 -> 117769.73 | N87: =N78/(1+N85)^N84 -> 105696.48 | O87: =O78/(1+O85)^O84 -> 96740.136 | P87: =P78/(1+P85)^P84 -> 88200.123 | Q87: =Q78/(1+Q85)^Q84 -> 80157.061
B89: Output | H89: FY2021A | I89: FY2022A | J89: FY2023A | K89: FY2024A | L89: FY2025A | M89: FY2026E | N89: FY2027E | O89: FY2028E | P89: FY2029E | Q89: FY2030E
B91: Multiples Method
B92: Terminal Value | Q92: =Q54*$C$16 -> 2082419.6
B93: PV of Terminal Value | Q93: =Q92/(1+Q85)^Q83 -> 1113364.7
B94: Enterprise Value | Q94: =Q93+SUM(M87:Q87) -> 1601928.3
B95: (-) Outstanding Debt | Q95: =-$AA$18 -> -98657
B96: (-) Minority Interest and Preferred Equity | Q96: =-$F$20-$F$21 -> 0
B97: (+) Cash and Non-Operating Assets | Q97: =$AA$17+$AA$19 -> 132420
B98: Implied Equity Value | Q98: =SUM(Q94:Q97) -> 1635691.3
B99: Current Equity Value | Q99: =C11 -> 4869931.9
B100: Implied Upside | Q100: =IFERROR(Q98/Q99 - 1,0) -> -0.66412441
B102: Gordon Growth Method
B103: Long Term Growth Rate | Q103: 0.03
B104: Final Year UFCF × (1 + g) | Q104: =Q78*(1+Q103) -> 145049.66
B105: Terminal Value | Q105: =IFERROR(IF(Q85>Q103,Q104/(Q85-Q103),0),0) -> 1402696.9
B106: PV of Terminal Value | Q106: =Q105/(1+Q85)^Q83 -> 749951.29
B107: Enterprise Value | Q107: =Q106+SUM(M87:Q87) -> 1238514.8
B108: (-) Outstanding Debt | Q108: =-$AA$18 -> -98657
B109: (-) Minority Interest and Preferred Equity | Q109: =-$F$20-$F$21 -> 0
B110: (+) Cash and Non-Operating Assets | Q110: =$AA$17+$AA$19 -> 132420
B111: Implied Equity Value | Q111: =SUM(Q107:Q110) -> 1272277.8
B112: Current Equity Value | Q112: =C11 -> 4869931.9
B113: Implied Upside | Q113: =IFERROR(Q111/Q112 - 1,0) -> -0.73874834

Sheet DCF Model - Bear (3)
B2: Discounted Cash Flow Model
B3: Company Apple Inc.
B4: All $ in USD millions unless otherwise stated
B6: Assumptions
B8: Valuation Summary | E8: Operating Assumptions | H8: Other Inputs
B9: Implied Enterprise Value | C9: =Q94 -> 1144283.6 | E9: CapEx | F9: 0.030268114 | H9: Valuation Date | I9: 46298
B10: Implied EV / EBITDA | C10: =IFERROR(C9/L54,0) -> 7.9053501 | E10: Change in NWC | F10: 0.0025 | H10: Closing Date
B11: Current Equity Value | C11: 4869931.9 | E11: Tax Rate | F11: 0.15610002 | H11: Fiscal Year End | I11: 46291
B12: Implied Equity Value | C12: =C9-AA18+AA17+AA19-F20-F21 -> 1178046.6 | E12: WACC | F12: =WACC!D36 -> 0.14984218
B13: Implied Share Price (Gordon Growth) | C13: =Q111/$I$16 -> 60.032157 | E13: D&A % revenue | F13: 0.029143716 | H13: EBIT Margin Convergence (Years) | I13: 5
B14: Implied Share Price (Exit Multiple) | C14: =C12/$I$16 -> 78.511856 | E14: Stage 1 Revenue Growth | F14: 0.0228 | H14: Revenue Growth Stage 1 (Years) | I14: 3
B15: Terminal Assumptions | E15: Starting EBIT Margin | F15: 0.309708 | H15: Revenue Growth Fade (Years) | I15: 4
B16: Exit EBITDA Multiple | C16: 9.699147 | E16: Forecast Gross Margin | F16: 0.45747548 | H16: Diluted Shares (millions) | I16: 15004.697
B17: Cash and Cash Equivalents | C17: 35934 | E17: Steady-State EBIT Margin | F17: 0.30100812 | H17: Current Share Price | I17: 333.69 | AA17: =C17 -> 35934
B18: Income Statement | H18: FY2021A | I18: FY2022A | J18: FY2023A | K18: FY2024A | L18: FY2025A | M18: FY2026E | N18: FY2027E | O18: FY2028E | P18: FY2029E | Q18: FY2030E | S18: FY'21-22A | T18: FY'23-30E | AA18: 98657
E19: Stage 2 Revenue Growth | F19: 0.00968 | AA19: 96486
B20: Total Revenue | F20: 0 | H20: ='Data Given (Recalculated)'!G12 -> 365817 | I20: ='Data Given (Recalculated)'!H12 -> 394328 | J20: ='Data Given (Recalculated)'!I12 -> 383285 | K20: ='Data Given (Recalculated)'!J12 -> 391035 | L20: ='Data Given (Recalculated)'!K12 -> 416161 | M20: =L20*(1+M21) -> 425649.47 | N20: =M20*(1+N21) -> 435354.28 | O20: =N20*(1+O21) -> 445280.36 | P20: =O20*(1+P21) -> 453972.23 | Q20: =P20*(1+Q21) -> 461344.74 | S20: =IFERROR((I20/H20)^(1/(COLUMNS(H20:I20)-1))-1,"") -> 0.077937876 | T20: =IFERROR((Q20/J20)^(1/(COLUMNS(J20:Q20)-1))-1,"") -> 0.026834698
B21: % growth | F21: 0 | H21: ="" | I21: =IFERROR(I20/H20-1,0) -> 0.077937876 | J21: =IFERROR(J20/I20-1,0) -> -0.028004605 | K21: =IFERROR(K20/J20-1,0) -> 0.020219941 | L21: =IFERROR(L20/K20-1,0) -> 0.064255118 | M21: =$F$14+($F$19-$F$14)*MAX(0,MIN(1,(M$83-$I$14)/$I$15)) -> 0.0228 | N21: =$F$14+($F$19-$F$14)*MAX(0,MIN(1,(N$83-$I$14)/$I$15)) -> 0.0228 | O21: =$F$14+($F$19-$F$14)*MAX(0,MIN(1,(O$83-$I$14)/$I$15)) -> 0.0228 | P21: =$F$14+($F$19-$F$14)*MAX(0,MIN(1,(P$83-$I$14)/$I$15)) -> 0.01952 | Q21: =$F$14+($F$19-$F$14)*MAX(0,MIN(1,(Q$83-$I$14)/$I$15)) -> 0.01624
B23: Cost of Revenue
B24: Cost of Revenue | H24: ='Data Given (Recalculated)'!G16 -> 212981 | I24: ='Data Given (Recalculated)'!H16 -> 223546 | J24: ='Data Given (Recalculated)'!I16 -> 214137 | K24: ='Data Given (Recalculated)'!J16 -> 210352 | L24: ='Data Given (Recalculated)'!K16 -> 201436 | M24: =M20*(1-$F$16)-M27 -> 210956.13 | N24: =N20*(1-$F$16)-N27 -> 215765.93 | O24: =O20*(1-$F$16)-O27 -> 220685.39 | P24: =P20*(1-$F$16)-P27 -> 224993.17 | Q24: =Q20*(1-$F$16)-Q27 -> 228647.06 | S24: =IFERROR((I24/H24)^(1/(COLUMNS(H24:I24)-1))-1,"") -> 0.049605364 | T24: =IFERROR((Q24/J24)^(1/(COLUMNS(J24:Q24)-1))-1,"") -> 0.0094102277
B25: % of revenue | H25: =IFERROR(H24/H20,0) -> 0.5822064 | I25: =IFERROR(I24/I20,0) -> 0.56690369 | J25: =IFERROR(J24/J20,0) -> 0.5586887 | K25: =IFERROR(K24/K20,0) -> 0.5379365 | L25: =IFERROR(L24/L20,0) -> 0.48403382 | M25: =IFERROR(M24/M20,0) -> 0.49560999 | N25: =IFERROR(N24/N20,0) -> 0.49560999 | O25: =IFERROR(O24/O20,0) -> 0.49560999 | ... Q25: =IFERROR(Q24/Q20,0) -> 0.49560999
B27: Other Cost of Revenue | H27: ='Data Given (Recalculated)'!G17 -> 0 | I27: ='Data Given (Recalculated)'!H17 -> 0 | J27: ='Data Given (Recalculated)'!I17 -> 0 | K27: ='Data Given (Recalculated)'!J17 -> 0 | L27: ='Data Given (Recalculated)'!K17 -> 19524 | M27: =M20*L28 -> 19969.147 | N27: =N20*M28 -> 20424.444 | O27: =O20*N28 -> 20890.121 | P27: =P20*O28 -> 21297.896 | Q27: =Q20*P28 -> 21643.774 | S27: =IFERROR((I27/H27)^(1/(COLUMNS(H27:I27)-1))-1,"") | T27: =IFERROR((Q27/J27)^(1/(COLUMNS(J27:Q27)-1))-1,"")
B28: % of revenue | H28: =IFERROR(H27/H20,0) -> 0 | I28: =IFERROR(I27/I20,0) -> 0 | J28: =IFERROR(J27/J20,0) -> 0 | K28: =IFERROR(K27/K20,0) -> 0 | L28: =IFERROR(L27/L20,0) -> 0.046914535 | M28: =IFERROR(M27/M20,0) -> 0.046914535 | N28: =IFERROR(N27/N20,0) -> 0.046914535 | O28: =IFERROR(O27/O20,0) -> 0.046914535 | ... Q28: =IFERROR(Q27/Q20,0) -> 0.046914535
B30: Total Cost of Sales | H30: =H24+H27 -> 212981 | I30: =I24+I27 -> 223546 | J30: =J24+J27 -> 214137 | K30: =K24+K27 -> 210352 | L30: =L24+L27 -> 220960 | M30: =M24+M27 -> 230925.28 | N30: =N24+N27 -> 236190.37 | O30: =O24+O27 -> 241575.51 | ... Q30: =Q24+Q27 -> 250290.83
B32: Gross Profit | H32: =H20-H30 -> 152836 | I32: =I20-I30 -> 170782 | J32: =J20-J30 -> 169148 | K32: =K20-K30 -> 180683 | L32: =L20-L30 -> 195201 | M32: =M20-M30 -> 194724.2 | N32: =N20-N30 -> 199163.91 | O32: =O20-O30 -> 203704.84 | ... Q32: =Q20-Q30 -> 211053.9 | S32: =IFERROR((I32/H32)^(1/(COLUMNS(H32:I32)-1))-1,"") -> 0.11741998 | T32: =IFERROR((Q32/J32)^(1/(COLUMNS(J32:Q32)-1))-1,"") -> 0.03212515
B33: % margin | H33: =IFERROR(H32/H20,0) -> 0.4177936 | I33: =IFERROR(I32/I20,0) -> 0.43309631 | J33: =IFERROR(J32/J20,0) -> 0.4413113 | K33: =IFERROR(K32/K20,0) -> 0.4620635 | L33: =IFERROR(L32/L20,0) -> 0.46905164 | M33: =IFERROR(M32/M20,0) -> 0.45747548 | N33: =IFERROR(N32/N20,0) -> 0.45747548 | O33: =IFERROR(O32/O20,0) -> 0.45747548 | ... Q33: =IFERROR(Q32/Q20,0) -> 0.45747548
B35: Operating Expenses
B36: Research & Development | H36: ='Data Given (Recalculated)'!G24 -> 21914 | I36: ='Data Given (Recalculated)'!H24 -> 26251 | J36: ='Data Given (Recalculated)'!I24 -> 29915 | K36: ='Data Given (Recalculated)'!J24 -> 31370 | L36: ='Data Given (Recalculated)'!K24 -> 34550 | M36: =M20*M37 -> 35337.74 | N36: =N20*N37 -> 36143.44 | O36: =O20*O37 -> 36967.511 | P36: =P20*P37 -> 37689.117 | Q36: =Q20*Q37 -> 38301.188 | S36: =IFERROR((I36/H36)^(1/(COLUMNS(H36:I36)-1))-1,"") -> 0.19791001 | T36: =IFERROR((Q36/J36)^(1/(COLUMNS(J36:Q36)-1))-1,"") -> 0.035933532
B37: % of revenue | H37: =IFERROR(H36/H20,0) -> 0.059904269 | I37: =IFERROR(I36/I20,0) -> 0.066571484 | J37: =IFERROR(J36/J20,0) -> 0.078048971 | K37: =IFERROR(K36/K20,0) -> 0.080222998 | L37: =IFERROR(L36/L20,0) -> 0.083020754 | M37: =L37 -> 0.083020754 | N37: =M37 -> 0.083020754 | O37: =N37 -> 0.083020754 | P37: =O37 -> 0.083020754 | Q37: =P37 -> 0.083020754
B39: SG&A | H39: ='Data Given (Recalculated)'!G25 -> 21973 | I39: ='Data Given (Recalculated)'!H25 -> 25094 | J39: ='Data Given (Recalculated)'!I25 -> 24932 | K39: ='Data Given (Recalculated)'!J25 -> 26097 | L39: ='Data Given (Recalculated)'!K25 -> 27601 | M39: =M20*M40 -> 28230.303 | N39: =N20*N40 -> 28873.954 | O39: =O20*O40 -> 29532.28 | P39: =P20*P40 -> 30108.75 | Q39: =Q20*Q40 -> 30597.716 | S39: =IFERROR((I39/H39)^(1/(COLUMNS(H39:I39)-1))-1,"") -> 0.14203796 | T39: =IFERROR((Q39/J39)^(1/(COLUMNS(J39:Q39)-1))-1,"") -> 0.029685403
B40: % of revenue | H40: =IFERROR(H39/H20,0) -> 0.060065552 | I40: =IFERROR(I39/I20,0) -> 0.063637378 | J40: =IFERROR(J39/J20,0) -> 0.065048202 | K40: =IFERROR(K39/K20,0) -> 0.066738272 | L40: =IFERROR(L39/L20,0) -> 0.066322889 | M40: =L40 -> 0.066322889 | N40: =M40 -> 0.066322889 | O40: =N40 -> 0.066322889 | P40: =O40 -> 0.066322889 | Q40: =P40 -> 0.066322889
B42: D&A (included in Operating) | H42: ='Data Given (Recalculated)'!G26 -> 11284 | I42: ='Data Given (Recalculated)'!H26 -> 11104 | J42: ='Data Given (Recalculated)'!I26 -> 11519 | K42: ='Data Given (Recalculated)'!J26 -> 11445 | L42: ='Data Given (Recalculated)'!K26 -> 11698 | M42: =M20*$F$13 -> 12405.007 | N42: =N20*$F$13 -> 12687.841 | O42: =O20*$F$13 -> 12977.124 | P42: =P20*$F$13 -> 13230.438 | Q42: =Q20*$F$13 -> 13445.3 | S42: =IFERROR((I42/H42)^(1/(COLUMNS(H42:I42)-1))-1,"") -> -0.01595179 | T42: =IFERROR((Q42/J42)^(1/(COLUMNS(J42:Q42)-1))-1,"") -> 0.022336047
B43: % of revenue | H43: =IFERROR(H42/H20,0) -> 0.030846024 | I43: =IFERROR(I42/I20,0) -> 0.028159299 | J43: =IFERROR(J42/J20,0) -> 0.030053355 | K43: =IFERROR(K42/K20,0) -> 0.02926848 | L43: =IFERROR(L42/L20,0) -> 0.028109313 | M43: =L43 -> 0.028109313 | N43: =M43 -> 0.028109313 | O43: =N43 -> 0.028109313 | P43: =O43 -> 0.028109313 | Q43: =P43 -> 0.028109313
B45: Other OpEx / (Income) | H45: ='Data Given (Recalculated)'!G27 -> 0 | I45: ='Data Given (Recalculated)'!H27 -> 0 | J45: ='Data Given (Recalculated)'!I27 -> 0 | K45: ='Data Given (Recalculated)'!J27 -> 0 | L45: ='Data Given (Recalculated)'!K27 -> 0 | M45: =M32-M36-M39-M20*M53 -> 69.727138 | N45: =N32-N36-N39-N20*N53 -> 828.82303 | O45: =O32-O36-O39-O20*O53 -> 1622.4974 | P45: =P32-P36-P39-P20*P53 -> 2444.0695 | Q45: =Q32-Q36-Q39-Q20*Q53 -> 3286.4901 | S45: =IFERROR((I45/H45)^(1/(COLUMNS(H45:I45)-1))-1,"") | T45: =IFERROR((Q45/J45)^(1/(COLUMNS(J45:Q45)-1))-1,"")
B46: % of revenue | H46: =IFERROR(H45/H20,0) -> 0 | I46: =IFERROR(I45/I20,0) -> 0 | J46: =IFERROR(J45/J20,0) -> 0 | K46: =IFERROR(K45/K20,0) -> 0 | L46: =IFERROR(L45/L20,0) -> 0 | M46: =IFERROR(M45/M20,0) -> 0.00016381352 | N46: =IFERROR(N45/N20,0) -> 0.0019037898 | O46: =IFERROR(O45/O20,0) -> 0.003643766 | ... Q46: =IFERROR(Q45/Q20,0) -> 0.0071237186
B48: Total Operating Expenses | H48: =-(H36+H39+H45) -> -43887 | I48: =-(I36+I39+I45) -> -51345 | J48: =-(J36+J39+J45) -> -54847 | K48: =-(K36+K39+K45) -> -57467 | L48: =-(L36+L39+L45) -> -62151 | M48: =-(M36+M39+M45) -> -63637.77 | N48: =-(N36+N39+N45) -> -65846.217 | O48: =-(O36+O39+O45) -> -68122.288 | ... Q48: =-(Q36+Q39+Q45) -> -72185.394 | S48: =IFERROR((I48/H48)^(1/(COLUMNS(H48:I48)-1))-1,"") -> 0.16993643 | T48: =IFERROR((Q48/J48)^(1/(COLUMNS(J48:Q48)-1))-1,"") -> 0.040021579
B49: % of revenue | H49: =IFERROR(-H48/H20,0) -> 0.11996982 | I49: =IFERROR(-I48/I20,0) -> 0.13020886 | J49: =IFERROR(-J48/J20,0) -> 0.14309717 | K49: =IFERROR(-K48/K20,0) -> 0.14696127 | L49: =IFERROR(-L48/L20,0) -> 0.14934364 | M49: =IFERROR(-M48/M20,0) -> 0.14950746 | N49: =IFERROR(-N48/N20,0) -> 0.15124743 | O49: =IFERROR(-O48/O20,0) -> 0.15298741 | ... Q49: =IFERROR(-Q48/Q20,0) -> 0.15646736
B51: EBIT | H51: =H32+H48 -> 108949 | I51: =I32+I48 -> 119437 | J51: =J32+J48 -> 114301 | K51: =K32+K48 -> 123216 | L51: =L32+L48 -> 133050 | M51: =M32+M48 -> 131086.43 | N51: =N32+N48 -> 133317.69 | O51: =O32+O48 -> 135582.56 | ... Q51: =Q32+Q48 -> 138868.51 | S51: =IFERROR((I51/H51)^(1/(COLUMNS(H51:I51)-1))-1,"") -> 0.096265225 | T51: =IFERROR((Q51/J51)^(1/(COLUMNS(J51:Q51)-1))-1,"") -> 0.028203568
B52: % margin | H52: =IFERROR(H51/H20,0) -> 0.29782378 | I52: =IFERROR(I51/I20,0) -> 0.30288744 | J52: =IFERROR(J51/J20,0) -> 0.29821412 | K52: =IFERROR(K51/K20,0) -> 0.31510223 | L52: =IFERROR(L51/L20,0) -> 0.319708 | M52: =IFERROR(M51/M20,0) -> 0.30796802 | N52: =IFERROR(N51/N20,0) -> 0.30622805 | O52: =IFERROR(O51/O20,0) -> 0.30448807 | ... Q52: =IFERROR(Q51/Q20,0) -> 0.30100812
B53: Forecast EBIT Margin Driver | M53: =IF(M$83<$I$13,$F$15+($F$17-$F$15)*M$83/$I$13,$F$17) -> 0.30796802 | N53: =IF(N$83<$I$13,$F$15+($F$17-$F$15)*N$83/$I$13,$F$17) -> 0.30622805 | O53: =IF(O$83<$I$13,$F$15+($F$17-$F$15)*O$83/$I$13,$F$17) -> 0.30448807 | P53: =IF(P$83<$I$13,$F$15+($F$17-$F$15)*P$83/$I$13,$F$17) -> 0.30274809 | Q53: =IF(Q$83<$I$13,$F$15+($F$17-$F$15)*Q$83/$I$13,$F$17) -> 0.30100812
B54: EBITDA | H54: =H51+H68 -> 120233 | I54: =I51+I68 -> 130541 | J54: =J51+J68 -> 125820 | K54: =K51+K68 -> 134661 | L54: =L51+L68 -> 144748 | M54: =M51+M68 -> 143491.43 | N54: =N51+N68 -> 146005.53 | O54: =O51+O68 -> 148559.68 | ... Q54: =Q51+Q68 -> 152313.81 | S54: =IFERROR((I54/H54)^(1/(COLUMNS(H54:I54)-1))-1,"") -> 0.085733534 | T54: =IFERROR((Q54/J54)^(1/(COLUMNS(J54:Q54)-1))-1,"") -> 0.027674682
B55: % margin | H55: =IFERROR(H54/H20,0) -> 0.3286698 | I55: =IFERROR(I54/I20,0) -> 0.33104674 | J55: =IFERROR(J54/J20,0) -> 0.32826748 | K55: =IFERROR(K54/K20,0) -> 0.34437071 | L55: =IFERROR(L54/L20,0) -> 0.34781731 | M55: =IFERROR(M54/M20,0) -> 0.33711174 | N55: =IFERROR(N54/N20,0) -> 0.33537176 | O55: =IFERROR(O54/O20,0) -> 0.33363178 | ... Q55: =IFERROR(Q54/Q20,0) -> 0.33015183
B57: Income Taxes | H57: =-H51*H58 -> -17006.941 | I57: =-I51*I58 -> -18644.118 | J57: =-J51*J58 -> -17842.389 | K57: =-K51*K58 -> -19234.02 | L57: =-L51*L58 -> -20769.108 | M57: =-M51*M58 -> -20462.594 | N57: =-N51*N58 -> -20810.894 | O57: =-O51*O58 -> -21164.44 | ... Q57: =-Q51*Q58 -> -21677.378
B58: % tax rate | H58: =$F$11 -> 0.15610002 | I58: =$F$11 -> 0.15610002 | J58: =$F$11 -> 0.15610002 | K58: =$F$11 -> 0.15610002 | L58: =$F$11 -> 0.15610002 | M58: =$F$11 -> 0.15610002 | N58: =$F$11 -> 0.15610002 | O58: =$F$11 -> 0.15610002 | ... Q58: =$F$11 -> 0.15610002
B60: NOPAT | H60: =H51+H57 -> 91942.059 | I60: =I51+I57 -> 100792.88 | J60: =J51+J57 -> 96458.611 | K60: =K51+K57 -> 103981.98 | L60: =L51+L57 -> 112280.89 | M60: =M51+M57 -> 110623.83 | N60: =N51+N57 -> 112506.8 | O60: =O51+O57 -> 114418.12 | ... Q60: =Q51+Q57 -> 117191.13 | S60: =IFERROR((I60/H60)^(1/(COLUMNS(H60:I60)-1))-1,"") -> 0.096265225 | T60: =IFERROR((Q60/J60)^(1/(COLUMNS(J60:Q60)-1))-1,"") -> 0.028203568
B61: % revenue | H61: =IFERROR(H60/H20,0) -> 0.25133348 | I61: =IFERROR(I60/I20,0) -> 0.25560671 | J61: =IFERROR(J60/J20,0) -> 0.25166289 | K61: =IFERROR(K60/K20,0) -> 0.26591476 | L61: =IFERROR(L60/L20,0) -> 0.26980157 | M61: =IFERROR(M60/M20,0) -> 0.25989421 | N61: =IFERROR(N60/N20,0) -> 0.25842584 | O61: =IFERROR(O60/O20,0) -> 0.25695747 | ... Q61: =IFERROR(Q60/Q20,0) -> 0.25402074
B63: PP&E Schedule | H63: FY2021A | I63: FY2022A | J63: FY2023A | K63: FY2024A | L63: FY2025A | M63: FY2026E | N63: FY2027E | O63: FY2028E | P63: FY2029E | Q63: FY2030E
B65: CapEx | H65: =IF('Data Given (Recalculated)'!G35="","",-'Data Given (Recalculated)'!G35) -> -11085 | I65: =IF('Data Given (Recalculated)'!H35="","",-'Data Given (Recalculated)'!H35) -> -10708 | J65: =IF('Data Given (Recalculated)'!I35="","",-'Data Given (Recalculated)'!I35) -> -10959 | K65: =IF('Data Given (Recalculated)'!J35="","",-'Data Given (Recalculated)'!J35) -> -9447 | L65: =IF('Data Given (Recalculated)'!K35="","",-'Data Given (Recalculated)'!K35) -> -12715 | M65: =-M20*$F$9 -> -12883.607 | N65: =-N20*$F$9 -> -13177.353 | O65: =-O20*$F$9 -> -13477.797 | P65: =-P20*$F$9 -> -13740.883 | Q65: =-Q20*$F$9 -> -13964.035
B66: % sales | H66: =IFERROR(-H65/H20,0) -> 0.030302036 | I66: =IFERROR(-I65/I20,0) -> 0.027155059 | J66: =IFERROR(-J65/J20,0) -> 0.028592301 | K66: =IFERROR(-K65/K20,0) -> 0.024158963 | L66: =IFERROR(-L65/L20,0) -> 0.030553079 | M66: =IFERROR(-M65/M20,0) -> 0.030268114 | N66: =IFERROR(-N65/N20,0) -> 0.030268114 | O66: =IFERROR(-O65/O20,0) -> 0.030268114 | ... Q66: =IFERROR(-Q65/Q20,0) -> 0.030268114
B68: Depreciation & Amortization | H68: =IF('Data Given (Recalculated)'!G36="","",'Data Given (Recalculated)'!G36) -> 11284 | I68: =IF('Data Given (Recalculated)'!H36="","",'Data Given (Recalculated)'!H36) -> 11104 | J68: =IF('Data Given (Recalculated)'!I36="","",'Data Given (Recalculated)'!I36) -> 11519 | K68: =IF('Data Given (Recalculated)'!J36="","",'Data Given (Recalculated)'!J36) -> 11445 | L68: =IF('Data Given (Recalculated)'!K36="","",'Data Given (Recalculated)'!K36) -> 11698 | M68: =M20*$F$13 -> 12405.007 | N68: =N20*$F$13 -> 12687.841 | O68: =O20*$F$13 -> 12977.124 | P68: =P20*$F$13 -> 13230.438 | Q68: =Q20*$F$13 -> 13445.3
B69: % revenue (assumed) | H69: =IFERROR(H68/H20,0) -> 0.030846024 | I69: =IFERROR(I68/I20,0) -> 0.028159299 | J69: =IFERROR(J68/J20,0) -> 0.030053355 | K69: =IFERROR(K68/K20,0) -> 0.02926848 | L69: =IFERROR(L68/L20,0) -> 0.028109313 | M69: =$F$13 -> 0.029143716 | N69: =$F$13 -> 0.029143716 | O69: =$F$13 -> 0.029143716 | P69: =$F$13 -> 0.029143716 | Q69: =$F$13 -> 0.029143716
B70: % of CapEx | H70: =IFERROR(-H68/H65,0) -> 1.0179522 | I70: =IFERROR(-I68/I65,0) -> 1.0369817 | J70: =IFERROR(-J68/J65,0) -> 1.0510996 | K70: =IFERROR(-K68/K65,0) -> 1.2114957 | L70: =IFERROR(-L68/L65,0) -> 0.92001573 | M70: =IFERROR(-M68/M65,0) -> 0.96285205 | N70: =IFERROR(-N68/N65,0) -> 0.96285205 | O70: =IFERROR(-O68/O65,0) -> 0.96285205 | ... Q70: =IFERROR(-Q68/Q65,0) -> 0.96285205
B71: Unlevered Free Cash Flow Waterfall
B72: Unlevered Free Cash Flow Waterfall | H72: FY2021A | I72: FY2022A | J72: FY2023A | K72: FY2024A | L72: FY2025A | M72: FY2026E | N72: FY2027E | O72: FY2028E | P72: FY2029E | Q72: FY2030E
B74: NOPAT | H74: =H60 -> 91942.059 | I74: =I60 -> 100792.88 | J74: =J60 -> 96458.611 | K74: =K60 -> 103981.98 | L74: =L60 -> 112280.89 | M74: =M60 -> 110623.83 | N74: =N60 -> 112506.8 | O74: =O60 -> 114418.12 | ... Q74: =Q60 -> 117191.13
B75: (+) Depreciation | H75: =H68 -> 11284 | I75: =I68 -> 11104 | J75: =J68 -> 11519 | K75: =K68 -> 11445 | L75: =L68 -> 11698 | M75: =M68 -> 12405.007 | N75: =N68 -> 12687.841 | O75: =O68 -> 12977.124 | ... Q75: =Q68 -> 13445.3
B76: (-) Capital Expenditures | H76: =H65 -> -11085 | I76: =I65 -> -10708 | J76: =J65 -> -10959 | K76: =K65 -> -9447 | L76: =L65 -> -12715 | M76: =M65 -> -12883.607 | N76: =N65 -> -13177.353 | O76: =O65 -> -13477.797 | ... Q76: =Q65 -> -13964.035
B77: (-) Change in NWC | H77: ="" | I77: =IF('Data Given (Recalculated)'!H41="","",-'Data Given (Recalculated)'!H41) -> 9080 | J77: =IF('Data Given (Recalculated)'!I41="","",-'Data Given (Recalculated)'!I41) -> -4213 | K77: =IF('Data Given (Recalculated)'!J41="","",-'Data Given (Recalculated)'!J41) -> 1492 | L77: =IF('Data Given (Recalculated)'!K41="","",-'Data Given (Recalculated)'!K41) -> -3899 | M77: =IFERROR(-((M20*'Data Given (Recalculated)'!$C$50/365+M30*'Data Given (Recalculated)'!$C$51/365-M30*'Data Given (Recalculated)'!$C$52/365+M20*$F$10)-'Data Given (Recalculated)'!K40),"") -> 921.75898 | N77: =IFERROR(-((N20*'Data Given (Recalculated)'!$C$50/365+N30*'Data Given (Recalculated)'!$C$51/365-N30*'Data Given (Recalculated)'!$C$52/365+N20*$F$10)-(M20*'Data Given (Recalculated)'!$C$50/365+M30*'Data Given (Recalculated)'!$C$51/365-M30*'Data Given (Recalculated)'!$C$52/365+M20*$F$10)),"") -> 576.5381 | O77: =IFERROR(-((O20*'Data Given (Recalculated)'!$C$50/365+O30*'Data Given (Recalculated)'!$C$51/365-O30*'Data Given (Recalculated)'!$C$52/365+O20*$F$10)-(N20*'Data Given (Recalculated)'!$C$50/365+N30*'Data Given (Recalculated)'!$C$51/365-N30*'Data Given (Recalculated)'!$C$52/365+N20*$F$10)),"") -> 589.68317 | P77: =IFERROR(-((P20*'Data Given (Recalculated)'!$C$50/365+P30*'Data Given (Recalculated)'!$C$51/365-P30*'Data Given (Recalculated)'!$C$52/365+P20*$F$10)-(O20*'Data Given (Recalculated)'!$C$50/365+O30*'Data Given (Recalculated)'!$C$51/365-O30*'Data Given (Recalculated)'!$C$52/365+O20*$F$10)),"") -> 516.36217 | Q77: =IFERROR(-((Q20*'Data Given (Recalculated)'!$C$50/365+Q30*'Data Given (Recalculated)'!$C$51/365-Q30*'Data Given (Recalculated)'!$C$52/365+Q20*$F$10)-(P20*'Data Given (Recalculated)'!$C$50/365+P30*'Data Given (Recalculated)'!$C$51/365-P30*'Data Given (Recalculated)'!$C$52/365+P20*$F$10)),"") -> 437.98212
B78: Unlevered Free Cash Flow | H78: =SUM(H74:H77) -> 92141.059 | I78: =SUM(I74:I77) -> 110268.88 | J78: =SUM(J74:J77) -> 92805.611 | K78: =SUM(K74:K77) -> 107471.98 | L78: =SUM(L74:L77) -> 107364.89 | M78: =SUM(M74:M77) -> 111066.99 | N78: =SUM(N74:N77) -> 112593.82 | O78: =SUM(O74:O77) -> 114507.13 | ... Q78: =SUM(Q74:Q77) -> 117110.38 | T78: =IFERROR((Q78/J78)^(1/(COLUMNS(J78:Q78)-1))-1,"") -> 0.033788254
B79: % of revenue | H79: =IFERROR(H78/H20,0) -> 0.25187746 | I79: =IFERROR(I78/I20,0) -> 0.27963746 | J79: =IFERROR(J78/J20,0) -> 0.24213212 | K79: =IFERROR(K78/K20,0) -> 0.2748398 | L79: =IFERROR(L78/L20,0) -> 0.25798884 | M79: =IFERROR(M78/M20,0) -> 0.26093534 | N79: =IFERROR(N78/N20,0) -> 0.25862574 | O79: =IFERROR(O78/O20,0) -> 0.25715737 | ... Q79: =IFERROR(Q78/Q20,0) -> 0.2538457
B81: Date for Valuation | E81: =I9 -> 46298
B82: Date For Discounting Cash Flows | M82: =EOMONTH(I11,12) -> 46660 | N82: =EOMONTH(M82,12) -> 47026 | O82: =EOMONTH(N82,12) -> 47391 | P82: =EOMONTH(O82,12) -> 47756 | Q82: =EOMONTH(P82,12) -> 48121
B83: Period, Stub Adjusted | M83: =1 -> 1 | N83: =M83+1 -> 2 | O83: =N83+1 -> 3 | P83: =O83+1 -> 4 | Q83: =P83+1 -> 5
B84: Discount Period, Stub and Mid-Year Adjusted | M84: =M83/2 -> 0.5 | N84: =N83-0.5 -> 1.5 | O84: =O83-0.5 -> 2.5 | P84: =P83-0.5 -> 3.5 | Q84: =Q83-0.5 -> 4.5
B85: Discount Rate | M85: =$F$12 -> 0.14984218 | N85: =$F$12 -> 0.14984218 | O85: =$F$12 -> 0.14984218 | P85: =$F$12 -> 0.14984218 | Q85: =$F$12 -> 0.14984218
B86: Present Value of Cash Flows
B87: Present Value of Unlevered Free Cash Flow | M87: =M78/(1+M85)^M84 -> 103577.61 | N87: =N78/(1+N85)^N84 -> 91318.171 | O87: =O78/(1+O85)^O84 -> 80767.552 | P87: =P78/(1+P85)^P84 -> 71152.473 | Q87: =Q78/(1+Q85)^Q84 -> 62477.454
B89: Output | H89: FY2021A | I89: FY2022A | J89: FY2023A | K89: FY2024A | L89: FY2025A | M89: FY2026E | N89: FY2027E | O89: FY2028E | P89: FY2029E | Q89: FY2030E
B91: Multiples Method
B92: Terminal Value | Q92: =Q54*$C$16 -> 1477314
B93: PV of Terminal Value | Q93: =Q92/(1+Q85)^Q83 -> 734990.35
B94: Enterprise Value | Q94: =Q93+SUM(M87:Q87) -> 1144283.6
B95: (-) Outstanding Debt | Q95: =-$AA$18 -> -98657
B96: (-) Minority Interest and Preferred Equity | Q96: =-$F$20-$F$21 -> 0
B97: (+) Cash and Non-Operating Assets | Q97: =$AA$17+$AA$19 -> 132420
B98: Implied Equity Value | Q98: =SUM(Q94:Q97) -> 1178046.6
B99: Current Equity Value | Q99: =C11 -> 4869931.9
B100: Implied Upside | Q100: =IFERROR(Q98/Q99 - 1,0) -> -0.75809793
B102: Gordon Growth Method
B103: Long Term Growth Rate | Q103: 0.02
B104: Final Year UFCF × (1 + g) | Q104: =Q78*(1+Q103) -> 119452.59
B105: Terminal Value | Q105: =IFERROR(IF(Q85>Q103,Q104/(Q85-Q103),0),0) -> 919982.89
B106: PV of Terminal Value | Q106: =Q105/(1+Q85)^Q83 -> 457708.06
B107: Enterprise Value | Q107: =Q106+SUM(M87:Q87) -> 867001.32
B108: (-) Outstanding Debt | Q108: =-$AA$18 -> -98657
B109: (-) Minority Interest and Preferred Equity | Q109: =-$F$20-$F$21 -> 0
B110: (+) Cash and Non-Operating Assets | Q110: =$AA$17+$AA$19 -> 132420
B111: Implied Equity Value | Q111: =SUM(Q107:Q110) -> 900764.32
B112: Current Equity Value | Q112: =C11 -> 4869931.9
B113: Implied Upside | Q113: =IFERROR(Q111/Q112 - 1,0) -> -0.81503554

Sheet WACC
B2: WACC Calculation
B3: Company Apple Inc.
B4: All $ in USD millions unless otherwise stated
B6: WACC Calculation | F6: Beta Calculation
F7: Company | H7: Levered Beta | I7: Debt ($B) | J7: Equity Value | K7: D/E | L7: Tax Rate | M7: Unlevered Beta | N7: Correlation
B8: Cost of Equity | F8: 1 | G8: =IF(Comps!B8="","",Comps!B8) -> Sony Group Corporation (SONY) | H8: =IF(G8="","",Comps!E8) -> 0.763 | I8: 417.3 | J8: =IF(G8="","",Comps!F8) -> 139235.84 | K8: =IFERROR(IF(J8>0,(I8*1000)/J8,""),"") -> 2.9970733 | L8: 0.265 | M8: =IF(G8="","",IFERROR(H8/(1+(1-L8)*K8),"")) -> 0.23822542 | N8: 0.114
B9: Risk Free Rate (10 Year Treasury Yield) | D9: 0.05277 | F9: 2 | G9: =IF(Comps!B9="","",Comps!B9) -> Dell Technologies Inc. (DELL) | H9: =IF(G9="","",Comps!E9) -> 1.409 | I9: 23 | J9: =IF(G9="","",Comps!F9) -> 357657.38 | K9: =IFERROR(IF(J9>0,(I9*1000)/J9,""),"") -> 0.064307355 | L9: 0.265 | M9: =IF(G9="","",IFERROR(H9/(1+(1-L9)*K9),"")) -> 1.3454081 | N9: 0.469
B10: Equity Risk Premium | D10: 0.083837107 | F10: 3 | G10: =IF(Comps!B10="","",Comps!B10) -> HP Inc. (HPQ) | H10: =IF(G10="","",Comps!E10) -> 1.205 | I10: 2400.6 | J10: =IF(G10="","",Comps!F10) -> 28965.526 | K10: =IFERROR(IF(J10>0,(I10*1000)/J10,""),"") -> 82.877834 | L10: 0.265 | M10: =IF(G10="","",IFERROR(H10/(1+(1-L10)*K10),"")) -> 0.019462101 | N10: 0.277
B11: Levered Beta | D11: 1.085 | F11: 4 | G11: =IF(Comps!B11="","",Comps!B11) -> Logitech International S.A. - R (LOGI) | H11: =IF(G11="","",Comps!E11) -> 0.649 | I11: 14.6 | J11: =IF(G11="","",Comps!F11) -> 14937.407 | K11: =IFERROR(IF(J11>0,(I11*1000)/J11,""),"") -> 0.97741191 | L11: 0.265 | M11: =IF(G11="","",IFERROR(H11/(1+(1-L11)*K11),"")) -> 0.3776774 | N11: 0.258
B12: Average Correlation | D12: =N23 -> 0.2795 | F12: 5 | G12: =IF(Comps!B12="","",Comps!B12) | H12: =IF(G12="","",Comps!E12) | J12: =IF(G12="","",Comps!F12) | K12: =IFERROR(IF(J12>0,(I12*1000)/J12,""),"") | M12: =IF(G12="","",IFERROR(H12/(1+(1-L12)*K12),""))
B13: Total Beta | D13: =D11/D12 -> 3.881932 | F13: 6 | G13: =IF(Comps!B13="","",Comps!B13) | H13: =IF(G13="","",Comps!E13) | J13: =IF(G13="","",Comps!F13) | K13: =IFERROR(IF(J13>0,(I13*1000)/J13,""),"") | M13: =IF(G13="","",IFERROR(H13/(1+(1-L13)*K13),""))
B14: Illiquidity Discount | D14: 0 | F14: Min | H14: =IFERROR(IF(COUNT(H8:H11)>0,MIN(H8:H11),""),"") -> 0.649 | I14: =IFERROR(IF(COUNT(I8:I11)>0,MIN(I8:I11),""),"") -> 14.6 | J14: =IFERROR(IF(COUNT(J8:J11)>0,MIN(J8:J11),""),"") -> 14937.407 | K14: =IFERROR(IF(COUNT(K8:K11)>0,MIN(K8:K11),""),"") -> 0.064307355 | L14: =IFERROR(IF(COUNT(L8:L11)>0,MIN(L8:L11),""),"") -> 0.265 | M14: =IFERROR(IF(COUNT(M8:M11)>0,MIN(M8:M11),""),"") -> 0.019462101 | N14: =IFERROR(IF(COUNT(N8:N11)>0,MIN(N8:N11),""),"") -> 0.114
B15: Size Premium | D15: 0 | F15: 0.25 | H15: =IFERROR(IF(COUNT(H8:H11)>0,SMALL(H8:H11,INT((COUNT(H8:H11)-1)*0.25+1))+((COUNT(H8:H11)-1)*0.25+1-INT((COUNT(H8:H11)-1)*0.25+1))*(SMALL(H8:H11,MIN(COUNT(H8:H11),INT((COUNT(H8:H11)-1)*0.25+1)+1))-SMALL(H8:H11,INT((COUNT(H8:H11)-1)*0.25+1))),""),"") -> 0.7345 | I15: =IFERROR(IF(COUNT(I8:I11)>0,SMALL(I8:I11,INT((COUNT(I8:I11)-1)*0.25+1))+((COUNT(I8:I11)-1)*0.25+1-INT((COUNT(I8:I11)-1)*0.25+1))*(SMALL(I8:I11,MIN(COUNT(I8:I11),INT((COUNT(I8:I11)-1)*0.25+1)+1))-SMALL(I8:I11,INT((COUNT(I8:I11)-1)*0.25+1))),""),"") -> 20.9 | J15: =IFERROR(IF(COUNT(J8:J11)>0,SMALL(J8:J11,INT((COUNT(J8:J11)-1)*0.25+1))+((COUNT(J8:J11)-1)*0.25+1-INT((COUNT(J8:J11)-1)*0.25+1))*(SMALL(J8:J11,MIN(COUNT(J8:J11),INT((COUNT(J8:J11)-1)*0.25+1)+1))-SMALL(J8:J11,INT((COUNT(J8:J11)-1)*0.25+1))),""),"") -> 25458.496 | K15: =IFERROR(IF(COUNT(K8:K11)>0,SMALL(K8:K11,INT((COUNT(K8:K11)-1)*0.25+1))+((COUNT(K8:K11)-1)*0.25+1-INT((COUNT(K8:K11)-1)*0.25+1))*(SMALL(K8:K11,MIN(COUNT(K8:K11),INT((COUNT(K8:K11)-1)*0.25+1)+1))-SMALL(K8:K11,INT((COUNT(K8:K11)-1)*0.25+1))),""),"") -> 0.74913577 | L15: =IFERROR(IF(COUNT(L8:L11)>0,SMALL(L8:L11,INT((COUNT(L8:L11)-1)*0.25+1))+((COUNT(L8:L11)-1)*0.25+1-INT((COUNT(L8:L11)-1)*0.25+1))*(SMALL(L8:L11,MIN(COUNT(L8:L11),INT((COUNT(L8:L11)-1)*0.25+1)+1))-SMALL(L8:L11,INT((COUNT(L8:L11)-1)*0.25+1))),""),"") -> 0.265 | M15: =IFERROR(IF(COUNT(M8:M11)>0,SMALL(M8:M11,INT((COUNT(M8:M11)-1)*0.25+1))+((COUNT(M8:M11)-1)*0.25+1-INT((COUNT(M8:M11)-1)*0.25+1))*(SMALL(M8:M11,MIN(COUNT(M8:M11),INT((COUNT(M8:M11)-1)*0.25+1)+1))-SMALL(M8:M11,INT((COUNT(M8:M11)-1)*0.25+1))),""),"") -> 0.18353459 | N15: =IFERROR(IF(COUNT(N8:N11)>0,SMALL(N8:N11,INT((COUNT(N8:N11)-1)*0.25+1))+((COUNT(N8:N11)-1)*0.25+1-INT((COUNT(N8:N11)-1)*0.25+1))*(SMALL(N8:N11,MIN(COUNT(N8:N11),INT((COUNT(N8:N11)-1)*0.25+1)+1))-SMALL(N8:N11,INT((COUNT(N8:N11)-1)*0.25+1))),""),"") -> 0.222
B16: CAPM/Cost of Equity | D16: =D9+D11*(D10)+D14+D15 -> 0.14373326 | F16: Mean | H16: =IFERROR(IF(COUNT(H8:H11)>0,AVERAGE(H8:H11),1),1) -> 1.0065 | I16: =IFERROR(IF(COUNT(I8:I11)>0,AVERAGE(I8:I11),0),0) -> 713.875 | J16: =IFERROR(IF(COUNT(J8:J11)>0,AVERAGE(J8:J11),0),0) -> 135199.04 | K16: =IFERROR(IF(COUNT(K8:K11)>0,AVERAGE(K8:K11),0),0) -> 21.729157 | L16: =IFERROR(IF(COUNT(L8:L11)>0,AVERAGE(L8:L11),0.25),0.25) -> 0.265 | M16: =IFERROR(IF(COUNT(M8:M11)>0,AVERAGE(M8:M11),1),1) -> 0.49519325 | N16: =IFERROR(IF(COUNT(N8:N11)>0,AVERAGE(N8:N11),1),1) -> 0.2795
F17: Median | H17: =IFERROR(IF(COUNT(H8:H11)>0,MEDIAN(H8:H11),1),1) -> 0.984 | I17: =IFERROR(IF(COUNT(I8:I11)>0,MEDIAN(I8:I11),0),0) -> 220.15 | J17: =IFERROR(IF(COUNT(J8:J11)>0,MEDIAN(J8:J11),0),0) -> 84100.681 | K17: =IFERROR(IF(COUNT(K8:K11)>0,MEDIAN(K8:K11),0),0) -> 1.9872426 | L17: =IFERROR(IF(COUNT(L8:L11)>0,MEDIAN(L8:L11),0.25),0.25) -> 0.265 | M17: =IFERROR(IF(COUNT(M8:M11)>0,MEDIAN(M8:M11),1),1) -> 0.30795141 | N17: =IFERROR(IF(COUNT(N8:N11)>0,MEDIAN(N8:N11),1),1) -> 0.2675
B18: Cost of Debt | F18: 0.75 | H18: =IFERROR(IF(COUNT(H8:H11)>0,SMALL(H8:H11,INT((COUNT(H8:H11)-1)*0.75+1))+((COUNT(H8:H11)-1)*0.75+1-INT((COUNT(H8:H11)-1)*0.75+1))*(SMALL(H8:H11,MIN(COUNT(H8:H11),INT((COUNT(H8:H11)-1)*0.75+1)+1))-SMALL(H8:H11,INT((COUNT(H8:H11)-1)*0.75+1))),""),"") -> 1.256 | I18: =IFERROR(IF(COUNT(I8:I11)>0,SMALL(I8:I11,INT((COUNT(I8:I11)-1)*0.75+1))+((COUNT(I8:I11)-1)*0.75+1-INT((COUNT(I8:I11)-1)*0.75+1))*(SMALL(I8:I11,MIN(COUNT(I8:I11),INT((COUNT(I8:I11)-1)*0.75+1)+1))-SMALL(I8:I11,INT((COUNT(I8:I11)-1)*0.75+1))),""),"") -> 913.125 | J18: =IFERROR(IF(COUNT(J8:J11)>0,SMALL(J8:J11,INT((COUNT(J8:J11)-1)*0.75+1))+((COUNT(J8:J11)-1)*0.75+1-INT((COUNT(J8:J11)-1)*0.75+1))*(SMALL(J8:J11,MIN(COUNT(J8:J11),INT((COUNT(J8:J11)-1)*0.75+1)+1))-SMALL(J8:J11,INT((COUNT(J8:J11)-1)*0.75+1))),""),"") -> 193841.22 | K18: =IFERROR(IF(COUNT(K8:K11)>0,SMALL(K8:K11,INT((COUNT(K8:K11)-1)*0.75+1))+((COUNT(K8:K11)-1)*0.75+1-INT((COUNT(K8:K11)-1)*0.75+1))*(SMALL(K8:K11,MIN(COUNT(K8:K11),INT((COUNT(K8:K11)-1)*0.75+1)+1))-SMALL(K8:K11,INT((COUNT(K8:K11)-1)*0.75+1))),""),"") -> 22.967263 | L18: =IFERROR(IF(COUNT(L8:L11)>0,SMALL(L8:L11,INT((COUNT(L8:L11)-1)*0.75+1))+((COUNT(L8:L11)-1)*0.75+1-INT((COUNT(L8:L11)-1)*0.75+1))*(SMALL(L8:L11,MIN(COUNT(L8:L11),INT((COUNT(L8:L11)-1)*0.75+1)+1))-SMALL(L8:L11,INT((COUNT(L8:L11)-1)*0.75+1))),""),"") -> 0.265 | M18: =IFERROR(IF(COUNT(M8:M11)>0,SMALL(M8:M11,INT((COUNT(M8:M11)-1)*0.75+1))+((COUNT(M8:M11)-1)*0.75+1-INT((COUNT(M8:M11)-1)*0.75+1))*(SMALL(M8:M11,MIN(COUNT(M8:M11),INT((COUNT(M8:M11)-1)*0.75+1)+1))-SMALL(M8:M11,INT((COUNT(M8:M11)-1)*0.75+1))),""),"") -> 0.61961007 | N18: =IFERROR(IF(COUNT(N8:N11)>0,SMALL(N8:N11,INT((COUNT(N8:N11)-1)*0.75+1))+((COUNT(N8:N11)-1)*0.75+1-INT((COUNT(N8:N11)-1)*0.75+1))*(SMALL(N8:N11,MIN(COUNT(N8:N11),INT((COUNT(N8:N11)-1)*0.75+1)+1))-SMALL(N8:N11,INT((COUNT(N8:N11)-1)*0.75+1))),""),"") -> 0.325
B19: Interest Rate on Debt | D19: 0.0445 | F19: Max | H19: =IFERROR(IF(COUNT(H8:H11)>0,MAX(H8:H11),""),"") -> 1.409 | I19: =IFERROR(IF(COUNT(I8:I11)>0,MAX(I8:I11),""),"") -> 2400.6 | J19: =IFERROR(IF(COUNT(J8:J11)>0,MAX(J8:J11),""),"") -> 357657.38 | K19: =IFERROR(IF(COUNT(K8:K11)>0,MAX(K8:K11),""),"") -> 82.877834 | L19: =IFERROR(IF(COUNT(L8:L11)>0,MAX(L8:L11),""),"") -> 0.265 | M19: =IFERROR(IF(COUNT(M8:M11)>0,MAX(M8:M11),""),"") -> 1.3454081 | N19: =IFERROR(IF(COUNT(N8:N11)>0,MAX(N8:N11),""),"") -> 0.469
B20: Tax Rate | D20: =IFERROR('DCF Model - Base (1)'!$F$11,0.21) -> 0.15610002
B21: Cost of Debt Post-Tax | D21: =IFERROR(D19*(1-D20),D19*0.79) -> 0.037553549 | F21: Relevered Beta
F22: Company | H22: Levered Beta | I22: Debt Units | J22: Equity Values Units | K22: Optimal D/E | L22: Tax Rate | M22: Unlevered Beta | N22: Correlation
B23: Total Equity | D23: ='DCF Model - Base (1)'!C11 -> 4869931.9 | F23: ABC Corp. | H23: =M23*(1+(1-L23)*K23) -> 0.75775241 | I23: =IFERROR(D23+D24-J23,D24) -> 3305319.6 | J23: =IFERROR((D23+D24)/(1+K23),D23) -> 1663269.3 | K23: =IFERROR(IF(K17>0,K17,IF(D23>0,D24/D23,0.15)),0.15) -> 1.9872426 | L23: =L16 -> 0.265 | M23: =M17 -> 0.30795141 | N23: =N16 -> 0.2795
B24: Total Debt | D24: ='DCF Model - Base (1)'!AA18 -> 98657
B26: Current Debt/Equity Ratio | D26: =D28/D27 -> 0.020258394
B27: Current Equity/Capital | D27: =IFERROR(D23/(D23+D24),0.85) -> 0.98014386
B28: Current Debt/Capital | D28: =IFERROR(D24/(D23+D24),0.15) -> 0.019856141
B30: Optimal Debt/Equity Ratio | D30: =D32/D31 -> 1.9872426
B31: Optimal Equity/Capital | D31: =IFERROR(J23/(I23+J23),0.85) -> 0.33475688
B32: Optimal Debt/Capital | D32: =IFERROR(I23/(I23+J23),0.15) -> 0.66524312
B34: Base WACC | D34: =(D27*D16)+(D28*D21) -> 0.14162494
B35: Bull WACC | D35: =(D27*D39)+(D28*D21) -> 0.1334077
B36: Bear WACC | D36: =(D27*D40)+(D28*D21) -> 0.14984218
B37: Bull Beta | D37: 0.985
B38: Bear Beta | D38: 1.185
B39: Bull Cost of Equity | D39: =D9+D37*(D10)+D14+D15 -> 0.13534955
B40: Bear Cost of Equity | D40: =D9+D38*(D10)+D14+D15 -> 0.15211697

Sheet Comps
B2: Comparable Companies Analysis
B3: Company Apple Inc.
B4: All $ in USD millions unless otherwise stated
C6: Share | D6: Shares | E6: Levered | F6: Market | G6: Enterprise | H6: EBITDA Margin | I6: EV/EBITDA | K6: EV/Sales | M6: Debt/Equity | P6: EBITDA | R6: Sales
B7: Company | C7: Price | D7: Outstanding | E7: Beta | F7: Cap | G7: Value | H7: LTM | I7: LTM | J7: NTM | K7: LTM | M7: Ratio | O7: Ticker | P7: LTM | Q7: NTM | R7: LTM | S7: NTM
B8: Sony Group Corporation (SONY) | C8: 23.82 | D8: 5845.3332 | E8: 0.763 | F8: =IFERROR(IF(AND(C8>0,D8>0),C8*D8,""),"") -> 139235.84 | G8: 246140.04 | H8: =IFERROR(P8/R8,"") -> 0.1637737 | I8: =IFERROR($G8/P8,"") -> 0.11838015 | J8: =IFERROR($G8/Q8,"") -> 0.1146206 | K8: =IFERROR($G8/R8,"") -> 0.019387555 | L8: =IFERROR($G8/S8,"") -> 0.018771839 | M8: 13.434745 | O8: SONY | P8: 2079234.1 | Q8: 2147432.9 | R8: 12695775 | S8: 13112197
B9: Dell Technologies Inc. (DELL) | C9: 562.52 | D9: 635.81273 | E9: 1.409 | F9: =IFERROR(IF(AND(C9>0,D9>0),C9*D9,""),"") -> 357657.38 | G9: 381371.38 | H9: =IFERROR(P9/R9,"") -> 0.11723776 | I9: =IFERROR($G9/P9,"") -> 21.514803 | J9: =IFERROR($G9/Q9,"") -> 20.831529 | K9: =IFERROR($G9/R9,"") -> 2.5223474 | L9: =IFERROR($G9/S9,"") -> 2.4422419 | M9: 0.098653077 | O9: DELL | P9: 17725.999 | Q9: 18307.412 | R9: 151197.01 | S9: 156156.27
B10: HP Inc. (HPQ) | C10: 32.12 | D10: 901.79096 | E10: 1.205 | F10: =IFERROR(IF(AND(C10>0,D10>0),C10*D10,""),"") -> 28965.526 | G10: 35135.525 | H10: =IFERROR(P10/R10,"") -> 0.078361113 | I10: =IFERROR($G10/P10,"") -> 7.5788445 | J10: =IFERROR($G10/Q10,"") -> 7.338153 | K10: =IFERROR($G10/R10,"") -> 0.59388668 | L10: =IFERROR($G10/S10,"") -> 0.57502584 | M10: 0.35694158 | O10: HPQ | P10: 4636.0003 | Q10: 4788.0611 | R10: 59162.001 | S10: 61102.515
B11: Logitech International S.A. - R (LOGI) | C11: 104.32 | D11: 143.18834 | E11: 0.649 | F11: =IFERROR(IF(AND(C11>0,D11>0),C11*D11,""),"") -> 14937.407 | G11: 13272.116 | H11: =IFERROR(P11/R11,"") -> 0.19519045 | I11: =IFERROR($G11/P11,"") -> 13.81945 | J11: =IFERROR($G11/Q11,"") -> 13.380567 | K11: =IFERROR($G11/R11,"") -> 2.6974246 | L11: =IFERROR($G11/S11,"") -> 2.6117589 | M11: 0.0056494408 | O11: LOGI | P11: 960.39398 | Q11: 991.89491 | R11: 4920.2918 | S11: 5081.6774
F12: =IFERROR(IF(AND(C12>0,D12>0),C12*D12,""),"") | H12: =IFERROR(P12/R12,"") | I12: =IFERROR($G12/P12,"") | J12: =IFERROR($G12/Q12,"") | K12: =IFERROR($G12/R12,"") | L12: =IFERROR($G12/S12,"")
F13: =IFERROR(IF(AND(C13>0,D13>0),C13*D13,""),"") | H13: =IFERROR(P13/R13,"") | I13: =IFERROR($G13/P13,"") | J13: =IFERROR($G13/Q13,"") | K13: =IFERROR($G13/R13,"") | L13: =IFERROR($G13/S13,"")
B15: Minimum | F15: =IFERROR(IF(COUNT(F8:F11)>0,MIN(F8:F11),""),"") -> 14937.407 | G15: =IFERROR(IF(COUNT(G8:G11)>0,MIN(G8:G11),""),"") -> 13272.116 | H15: =IFERROR(IF(COUNT(H8:H11)>0,MIN(H8:H11),""),"") -> 0.078361113 | I15: =IFERROR(IF(COUNT(I8:I11)>0,MIN(I8:I11),""),"") -> 0.11838015 | J15: =IFERROR(IF(COUNT(J8:J11)>0,MIN(J8:J11),""),"") -> 0.1146206 | K15: =IFERROR(IF(COUNT(K8:K11)>0,MIN(K8:K11),""),"") -> 0.019387555 | L15: =IFERROR(IF(COUNT(L8:L11)>0,MIN(L8:L11),""),"") -> 0.018771839 | M15: =IFERROR(IF(COUNT(M8:M11)>0,MIN(M8:M11),""),"") -> 0.0056494408
B16: 0.25 | F16: =IFERROR(IF(COUNT(F8:F11)>0,SMALL(F8:F11,INT((COUNT(F8:F11)-1)*0.25+1))+((COUNT(F8:F11)-1)*0.25+1-INT((COUNT(F8:F11)-1)*0.25+1))*(SMALL(F8:F11,MIN(COUNT(F8:F11),INT((COUNT(F8:F11)-1)*0.25+1)+1))-SMALL(F8:F11,INT((COUNT(F8:F11)-1)*0.25+1))),""),"") -> 25458.496 | G16: =IFERROR(IF(COUNT(G8:G11)>0,SMALL(G8:G11,INT((COUNT(G8:G11)-1)*0.25+1))+((COUNT(G8:G11)-1)*0.25+1-INT((COUNT(G8:G11)-1)*0.25+1))*(SMALL(G8:G11,MIN(COUNT(G8:G11),INT((COUNT(G8:G11)-1)*0.25+1)+1))-SMALL(G8:G11,INT((COUNT(G8:G11)-1)*0.25+1))),""),"") -> 29669.673 | H16: =IFERROR(IF(COUNT(H8:H11)>0,SMALL(H8:H11,INT((COUNT(H8:H11)-1)*0.25+1))+((COUNT(H8:H11)-1)*0.25+1-INT((COUNT(H8:H11)-1)*0.25+1))*(SMALL(H8:H11,MIN(COUNT(H8:H11),INT((COUNT(H8:H11)-1)*0.25+1)+1))-SMALL(H8:H11,INT((COUNT(H8:H11)-1)*0.25+1))),""),"") -> 0.1075186 | I16: =IFERROR(IF(COUNT(I8:I11)>0,SMALL(I8:I11,INT((COUNT(I8:I11)-1)*0.25+1))+((COUNT(I8:I11)-1)*0.25+1-INT((COUNT(I8:I11)-1)*0.25+1))*(SMALL(I8:I11,MIN(COUNT(I8:I11),INT((COUNT(I8:I11)-1)*0.25+1)+1))-SMALL(I8:I11,INT((COUNT(I8:I11)-1)*0.25+1))),""),"") -> 5.7137284 | J16: =IFERROR(IF(COUNT(J8:J11)>0,SMALL(J8:J11,INT((COUNT(J8:J11)-1)*0.25+1))+((COUNT(J8:J11)-1)*0.25+1-INT((COUNT(J8:J11)-1)*0.25+1))*(SMALL(J8:J11,MIN(COUNT(J8:J11),INT((COUNT(J8:J11)-1)*0.25+1)+1))-SMALL(J8:J11,INT((COUNT(J8:J11)-1)*0.25+1))),""),"") -> 5.5322699 | K16: =IFERROR(IF(COUNT(K8:K11)>0,SMALL(K8:K11,INT((COUNT(K8:K11)-1)*0.25+1))+((COUNT(K8:K11)-1)*0.25+1-INT((COUNT(K8:K11)-1)*0.25+1))*(SMALL(K8:K11,MIN(COUNT(K8:K11),INT((COUNT(K8:K11)-1)*0.25+1)+1))-SMALL(K8:K11,INT((COUNT(K8:K11)-1)*0.25+1))),""),"") -> 0.4502619 | L16: =IFERROR(IF(COUNT(L8:L11)>0,SMALL(L8:L11,INT((COUNT(L8:L11)-1)*0.25+1))+((COUNT(L8:L11)-1)*0.25+1-INT((COUNT(L8:L11)-1)*0.25+1))*(SMALL(L8:L11,MIN(COUNT(L8:L11),INT((COUNT(L8:L11)-1)*0.25+1)+1))-SMALL(L8:L11,INT((COUNT(L8:L11)-1)*0.25+1))),""),"") -> 0.43596234 | M16: =IFERROR(IF(COUNT(M8:M11)>0,SMALL(M8:M11,INT((COUNT(M8:M11)-1)*0.25+1))+((COUNT(M8:M11)-1)*0.25+1-INT((COUNT(M8:M11)-1)*0.25+1))*(SMALL(M8:M11,MIN(COUNT(M8:M11),INT((COUNT(M8:M11)-1)*0.25+1)+1))-SMALL(M8:M11,INT((COUNT(M8:M11)-1)*0.25+1))),""),"") -> 0.075402168
B17: Average | F17: =IFERROR(IF(COUNT(F8:F11)>0,AVERAGE(F8:F11),""),"") -> 135199.04 | G17: =IFERROR(IF(COUNT(G8:G11)>0,AVERAGE(G8:G11),""),"") -> 168979.77 | H17: =IFERROR(IF(COUNT(H8:H11)>0,AVERAGE(H8:H11),""),"") -> 0.13864076 | I17: =IFERROR(IF(COUNT(I8:I11)>0,AVERAGE(I8:I11),""),"") -> 10.757869 | J17: =IFERROR(IF(COUNT(J8:J11)>0,AVERAGE(J8:J11),""),"") -> 10.416217 | K17: =IFERROR(IF(COUNT(K8:K11)>0,AVERAGE(K8:K11),""),"") -> 1.4582616 | L17: =IFERROR(IF(COUNT(L8:L11)>0,AVERAGE(L8:L11),""),"") -> 1.4119496 | M17: =IFERROR(IF(COUNT(M8:M11)>0,AVERAGE(M8:M11),""),"") -> 3.4739973
B18: Median | F18: =IFERROR(IF(COUNT(F8:F11)>0,MEDIAN(F8:F11),""),"") -> 84100.681 | G18: =IFERROR(IF(COUNT(G8:G11)>0,MEDIAN(G8:G11),""),"") -> 140637.78 | H18: =IFERROR(IF(COUNT(H8:H11)>0,MEDIAN(H8:H11),""),"") -> 0.14050573 | I18: =IFERROR(IF(COUNT(I8:I11)>0,MEDIAN(I8:I11),""),"") -> 10.699147 | J18: =IFERROR(IF(COUNT(J8:J11)>0,MEDIAN(J8:J11),""),"") -> 10.35936 | K18: =IFERROR(IF(COUNT(K8:K11)>0,MEDIAN(K8:K11),""),"") -> 1.5581171 | L18: =IFERROR(IF(COUNT(L8:L11)>0,MEDIAN(L8:L11),""),"") -> 1.5086339 | M18: =IFERROR(IF(COUNT(M8:M11)>0,MEDIAN(M8:M11),""),"") -> 0.22779733
B19: 0.75 | F19: =IFERROR(IF(COUNT(F8:F11)>0,SMALL(F8:F11,INT((COUNT(F8:F11)-1)*0.75+1))+((COUNT(F8:F11)-1)*0.75+1-INT((COUNT(F8:F11)-1)*0.75+1))*(SMALL(F8:F11,MIN(COUNT(F8:F11),INT((COUNT(F8:F11)-1)*0.75+1)+1))-SMALL(F8:F11,INT((COUNT(F8:F11)-1)*0.75+1))),""),"") -> 193841.22 | G19: =IFERROR(IF(COUNT(G8:G11)>0,SMALL(G8:G11,INT((COUNT(G8:G11)-1)*0.75+1))+((COUNT(G8:G11)-1)*0.75+1-INT((COUNT(G8:G11)-1)*0.75+1))*(SMALL(G8:G11,MIN(COUNT(G8:G11),INT((COUNT(G8:G11)-1)*0.75+1)+1))-SMALL(G8:G11,INT((COUNT(G8:G11)-1)*0.75+1))),""),"") -> 279947.88 | H19: =IFERROR(IF(COUNT(H8:H11)>0,SMALL(H8:H11,INT((COUNT(H8:H11)-1)*0.75+1))+((COUNT(H8:H11)-1)*0.75+1-INT((COUNT(H8:H11)-1)*0.75+1))*(SMALL(H8:H11,MIN(COUNT(H8:H11),INT((COUNT(H8:H11)-1)*0.75+1)+1))-SMALL(H8:H11,INT((COUNT(H8:H11)-1)*0.75+1))),""),"") -> 0.17162788 | I19: =IFERROR(IF(COUNT(I8:I11)>0,SMALL(I8:I11,INT((COUNT(I8:I11)-1)*0.75+1))+((COUNT(I8:I11)-1)*0.75+1-INT((COUNT(I8:I11)-1)*0.75+1))*(SMALL(I8:I11,MIN(COUNT(I8:I11),INT((COUNT(I8:I11)-1)*0.75+1)+1))-SMALL(I8:I11,INT((COUNT(I8:I11)-1)*0.75+1))),""),"") -> 15.743288 | J19: =IFERROR(IF(COUNT(J8:J11)>0,SMALL(J8:J11,INT((COUNT(J8:J11)-1)*0.75+1))+((COUNT(J8:J11)-1)*0.75+1-INT((COUNT(J8:J11)-1)*0.75+1))*(SMALL(J8:J11,MIN(COUNT(J8:J11),INT((COUNT(J8:J11)-1)*0.75+1)+1))-SMALL(J8:J11,INT((COUNT(J8:J11)-1)*0.75+1))),""),"") -> 15.243308 | K19: =IFERROR(IF(COUNT(K8:K11)>0,SMALL(K8:K11,INT((COUNT(K8:K11)-1)*0.75+1))+((COUNT(K8:K11)-1)*0.75+1-INT((COUNT(K8:K11)-1)*0.75+1))*(SMALL(K8:K11,MIN(COUNT(K8:K11),INT((COUNT(K8:K11)-1)*0.75+1)+1))-SMALL(K8:K11,INT((COUNT(K8:K11)-1)*0.75+1))),""),"") -> 2.5661167 | L19: =IFERROR(IF(COUNT(L8:L11)>0,SMALL(L8:L11,INT((COUNT(L8:L11)-1)*0.75+1))+((COUNT(L8:L11)-1)*0.75+1-INT((COUNT(L8:L11)-1)*0.75+1))*(SMALL(L8:L11,MIN(COUNT(L8:L11),INT((COUNT(L8:L11)-1)*0.75+1)+1))-SMALL(L8:L11,INT((COUNT(L8:L11)-1)*0.75+1))),""),"") -> 2.4846211 | M19: =IFERROR(IF(COUNT(M8:M11)>0,SMALL(M8:M11,INT((COUNT(M8:M11)-1)*0.75+1))+((COUNT(M8:M11)-1)*0.75+1-INT((COUNT(M8:M11)-1)*0.75+1))*(SMALL(M8:M11,MIN(COUNT(M8:M11),INT((COUNT(M8:M11)-1)*0.75+1)+1))-SMALL(M8:M11,INT((COUNT(M8:M11)-1)*0.75+1))),""),"") -> 3.6263925
B20: Max | F20: =IFERROR(IF(COUNT(F8:F11)>0,MAX(F8:F11),""),"") -> 357657.38 | G20: =IFERROR(IF(COUNT(G8:G11)>0,MAX(G8:G11),""),"") -> 381371.38 | H20: =IFERROR(IF(COUNT(H8:H11)>0,MAX(H8:H11),""),"") -> 0.19519045 | I20: =IFERROR(IF(COUNT(I8:I11)>0,MAX(I8:I11),""),"") -> 21.514803 | J20: =IFERROR(IF(COUNT(J8:J11)>0,MAX(J8:J11),""),"") -> 20.831529 | K20: =IFERROR(IF(COUNT(K8:K11)>0,MAX(K8:K11),""),"") -> 2.6974246 | L20: =IFERROR(IF(COUNT(L8:L11)>0,MAX(L8:L11),""),"") -> 2.6117589 | M20: =IFERROR(IF(COUNT(M8:M11)>0,MAX(M8:M11),""),"") -> 13.434745

Sheet Data Given (Recalculated)
B1: AAPL
B2: Preliminary Base Case
G3: Actual | I3: Actual
B4: Period Start | E4: 43101 | F4: 42736 | G4: 44197 | H4: 44562 | I4: 44927 | J4: 45292 | K4: 45658 | L4: 46023 | M4: 46388 | N4: 46753 | O4: 47119 | P4: 47484
B5: Period End | C5: Unit | E5: 42735 | F5: 43100 | G5: 44465 | H5: 44830 | I5: 45195 | J5: 45561 | K5: 45926 | L5: 46291 | M5: 46656 | N5: 47022 | O5: 47387 | P5: 47752
B6: Fiscal Year | E6: =YEAR(E5) -> 2016 | F6: =YEAR(F5) -> 2017 | G6: FY2021A | H6: FY2022A | I6: FY2023A | J6: FY2024A | K6: FY2025A | L6: FY2026E | M6: FY2027E | N6: FY2028E | O6: FY2029E | P6: FY2030E
B7: Days in Period | E7: =+E5-E4+1 -> -365 | F7: =+F5-F4+1 -> 365 | G7: =+G5-G4+1 -> 269 | H7: =+H5-H4+1 -> 269 | I7: =+I5-I4+1 -> 269 | J7: =+J5-J4+1 -> 270 | K7: =+K5-K4+1 -> 269 | L7: =+L5-L4+1 -> 269 | ... P7: =+P5-P4+1 -> 269
B8: Days in Year | E8: =+E7 -> -365 | F8: =+F7 -> 365 | G8: =+G7 -> 269 | H8: =+H7 -> 269 | I8: =+I7 -> 269 | J8: =+J7 -> 270 | K8: =+K7 -> 269 | L8: =+L7 -> 269 | ... P8: =+P7 -> 269
A10: Financial Summary
B12: Total Revenue | C12: [$] | E12: 0 | F12: 0 | G12: 365817 | H12: 394328 | I12: 383285 | J12: 391035 | K12: 416161 | L12: ='DCF Model - Base (1)'!M20 -> 429811.08 | M12: ='DCF Model - Base (1)'!N20 -> 443908.88 | N12: ='DCF Model - Base (1)'!O20 -> 458469.1 | O12: ='DCF Model - Base (1)'!P20 -> 472003.1 | P12: ='DCF Model - Base (1)'!Q20 -> 484388.46
B13: Growth | C13: [%] | G13: ="" | H13: =IFERROR(H12/G12-1,"") -> 0.077937876 | I13: =IFERROR(I12/H12-1,"") -> -0.028004605 | J13: =IFERROR(J12/I12-1,"") -> 0.020219941 | K13: =IFERROR(K12/J12-1,"") -> 0.064255118 | L13: =IFERROR(L12/K12-1,"") -> 0.0328 | M13: =IFERROR(M12/L12-1,"") -> 0.0328 | N13: =IFERROR(N12/M12-1,"") -> 0.0328 | O13: =IFERROR(O12/N12-1,"") -> 0.02952 | P13: =IFERROR(P12/O12-1,"") -> 0.02624
B15: Cost of Revenue
B16: Cost of Revenue | C16: [$] | E16: 0 | F16: 0 | G16: 212981 | H16: 223546 | I16: 214137 | J16: 210352 | K16: 201436 | L16: ='DCF Model - Base (1)'!M24 -> 213018.66 | M16: ='DCF Model - Base (1)'!N24 -> 220005.68 | N16: ='DCF Model - Base (1)'!O24 -> 227221.86 | O16: ='DCF Model - Base (1)'!P24 -> 233929.45 | P16: ='DCF Model - Base (1)'!Q24 -> 240067.76
B17: Other Cost of Revenue | C17: [$] | E17: 0 | F17: 0 | G17: 0 | H17: 0 | I17: 0 | J17: 0 | K17: 19524 | L17: ='DCF Model - Base (1)'!M27 -> 20164.387 | M17: ='DCF Model - Base (1)'!N27 -> 20825.779 | N17: ='DCF Model - Base (1)'!O27 -> 21508.865 | O17: ='DCF Model - Base (1)'!P27 -> 22143.806 | P17: ='DCF Model - Base (1)'!Q27 -> 22724.86
B18: Total Cost of Sales | E18: =+SUM(E16:E17) -> 0 | F18: =+SUM(F16:F17) -> 0 | G18: =G16+G17 -> 212981 | H18: =H16+H17 -> 223546 | I18: =I16+I17 -> 214137 | J18: =J16+J17 -> 210352 | K18: =K16+K17 -> 220960 | L18: =L16+L17 -> 233183.05 | M18: =M16+M17 -> 240831.46 | N18: =N16+N17 -> 248730.73 | ... P18: =P16+P17 -> 262792.62
B20: Gross Profit | C20: [$] | E20: =+E12-E18 -> 0 | F20: =+F12-F18 -> 0 | G20: =G12-G18 -> 152836 | H20: =H12-H18 -> 170782 | I20: =I12-I18 -> 169148 | J20: =J12-J18 -> 180683 | K20: =K12-K18 -> 195201 | L20: =L12-L18 -> 196628.03 | M20: =M12-M18 -> 203077.43 | N20: =N12-N18 -> 209738.37 | ... P20: =P12-P18 -> 221595.84
B21: Margin | C21: [%] | E21: =+IFERROR(E20/E$12,"n.a.") -> n.a. | F21: =+IFERROR(F20/F$12,"n.a.") -> n.a. | G21: =IFERROR(G20/G12,0) -> 0.4177936 | H21: =IFERROR(H20/H12,0) -> 0.43309631 | I21: =IFERROR(I20/I12,0) -> 0.4413113 | J21: =IFERROR(J20/J12,0) -> 0.4620635 | K21: =IFERROR(K20/K12,0) -> 0.46905164 | L21: =IFERROR(L20/L12,0) -> 0.45747548 | M21: =IFERROR(M20/M12,0) -> 0.45747548 | N21: =IFERROR(N20/N12,0) -> 0.45747548 | ... P21: =IFERROR(P20/P12,0) -> 0.45747548
B23: Operating Expenses
B24: Research & Development | C24: [$] | E24: 0 | F24: 0 | G24: 21914 | H24: 26251 | I24: 29915 | J24: 31370 | K24: 34550 | L24: ='DCF Model - Base (1)'!M36 -> 35683.24 | M24: ='DCF Model - Base (1)'!N36 -> 36853.65 | N24: ='DCF Model - Base (1)'!O36 -> 38062.45 | O24: ='DCF Model - Base (1)'!P36 -> 39186.054 | P24: ='DCF Model - Base (1)'!Q36 -> 40214.296
B25: SG&A | C25: [$] | E25: 0 | F25: 0 | G25: 21973 | H25: 25094 | I25: 24932 | J25: 26097 | K25: 27601 | L25: ='DCF Model - Base (1)'!M39 -> 28506.313 | M25: ='DCF Model - Base (1)'!N39 -> 29441.32 | N25: ='DCF Model - Base (1)'!O39 -> 30406.995 | O25: ='DCF Model - Base (1)'!P39 -> 31304.61 | P25: ='DCF Model - Base (1)'!Q39 -> 32126.043
B26: D&A (included in Operating) | C26: [$] | E26: 0 | F26: 0 | G26: 11284 | H26: 11104 | I26: 11519 | J26: 11445 | K26: 11698 | L26: ='DCF Model - Base (1)'!M68 -> 12526.292 | M26: ='DCF Model - Base (1)'!N68 -> 12937.154 | N26: ='DCF Model - Base (1)'!O68 -> 13361.493 | O26: ='DCF Model - Base (1)'!P68 -> 13755.924 | P26: ='DCF Model - Base (1)'!Q68 -> 14116.88
B27: Other Operating Expenses | C27: [$] | E27: 0 | F27: 0 | G27: 0 | H27: 0 | I27: 0 | J27: 0 | K27: 0 | L27: ='DCF Model - Base (1)'!M45 -> -4227.7019 | M27: ='DCF Model - Base (1)'!N45 -> -3593.9796 | N27: ='DCF Model - Base (1)'!O45 -> -2914.1368 | O27: ='DCF Model - Base (1)'!P45 -> -2178.888 | P27: ='DCF Model - Base (1)'!Q45 -> -1393.2376
B28: Total Operating Expenses | C28: [$] | E28: =+SUM(E24:E27) -> 0 | F28: =+SUM(F24:F27) -> 0 | G28: =G24+G25+G27 -> 43887 | H28: =H24+H25+H27 -> 51345 | I28: =I24+I25+I27 -> 54847 | J28: =J24+J25+J27 -> 57467 | K28: =K24+K25+K27 -> 62151 | L28: =L24+L25+L27 -> 59961.851 | M28: =M24+M25+M27 -> 62700.99 | N28: =N24+N25+N27 -> 65555.308 | ... P28: =P24+P25+P27 -> 70947.101
B30: EBIT | C30: [$] | E30: =+E20-E28 -> 0 | F30: =+F20-F28 -> 0 | G30: =G20-G28 -> 108949 | H30: =H20-H28 -> 119437 | I30: =I20-I28 -> 114301 | J30: =J20-J28 -> 123216 | K30: =K20-K28 -> 133050 | L30: =L20-L28 -> 136666.18 | M30: =M20-M28 -> 140376.44 | N30: =N20-N28 -> 144183.06 | ... P30: =P20-P28 -> 150648.74
B31: EBIT Margin | C31: [%] | E31: =+IFERROR(E30/E$12,"n.a.") -> n.a. | F31: =+IFERROR(F30/F$12,"n.a.") -> n.a. | G31: =IFERROR(G30/G12,0) -> 0.29782378 | H31: =IFERROR(H30/H12,0) -> 0.30288744 | I31: =IFERROR(I30/I12,0) -> 0.29821412 | J31: =IFERROR(J30/J12,0) -> 0.31510223 | K31: =IFERROR(K30/K12,0) -> 0.319708 | L31: =IFERROR(L30/L12,0) -> 0.31796802 | M31: =IFERROR(M30/M12,0) -> 0.31622805 | N31: =IFERROR(N30/N12,0) -> 0.31448807 | ... P31: =IFERROR(P30/P12,0) -> 0.31100812
B34: Cash Flow and Working Capital Detail
B35: Capital Expenditures | G35: 11085 | H35: 10708 | I35: 10959 | J35: 9447 | K35: 12715 | L35: =-'DCF Model - Base (1)'!M65 -> 11935.043 | M35: =-'DCF Model - Base (1)'!N65 -> 12326.513 | N35: =-'DCF Model - Base (1)'!O65 -> 12730.822 | O35: =-'DCF Model - Base (1)'!P65 -> 13106.636 | P35: =-'DCF Model - Base (1)'!Q65 -> 13450.554
B36: Depreciation and Amortization | G36: 11284 | H36: 11104 | I36: 11519 | J36: 11445 | K36: 11698 | L36: ='DCF Model - Base (1)'!M68 -> 12526.292 | M36: ='DCF Model - Base (1)'!N68 -> 12937.154 | N36: ='DCF Model - Base (1)'!O68 -> 13361.493 | O36: ='DCF Model - Base (1)'!P68 -> 13755.924 | P36: ='DCF Model - Base (1)'!Q68 -> 14116.88
B37: Accounts Receivable | G37: 26278 | H37: 28184 | I37: 29508 | J37: 33410 | K37: 39777 | L37: ='DCF Model - Base (1)'!M20*$C$50/365 -> 41081.686 | M37: ='DCF Model - Base (1)'!N20*$C$50/365 -> 42429.165 | N37: ='DCF Model - Base (1)'!O20*$C$50/365 -> 43820.841 | O37: ='DCF Model - Base (1)'!P20*$C$50/365 -> 45114.433 | P37: ='DCF Model - Base (1)'!Q20*$C$50/365 -> 46298.235
B38: Inventory | G38: 6580 | H38: 4946 | I38: 6331 | J38: 7286 | K38: 5718 | L38: =('DCF Model - Base (1)'!M24+'DCF Model - Base (1)'!M27)*$C$51/365 -> 6034.308 | M38: =('DCF Model - Base (1)'!N24+'DCF Model - Base (1)'!N27)*$C$51/365 -> 6232.2333 | N38: =('DCF Model - Base (1)'!O24+'DCF Model - Base (1)'!O27)*$C$51/365 -> 6436.6505 | O38: =('DCF Model - Base (1)'!P24+'DCF Model - Base (1)'!P27)*$C$51/365 -> 6626.6604 | P38: =('DCF Model - Base (1)'!Q24+'DCF Model - Base (1)'!Q27)*$C$51/365 -> 6800.544
B39: Accounts Payable | G39: 54763 | H39: 64115 | I39: 62611 | J39: 68960 | K39: 69860 | L39: =('DCF Model - Base (1)'!M24+'DCF Model - Base (1)'!M27)*$C$52/365 -> 73724.511 | M39: =('DCF Model - Base (1)'!N24+'DCF Model - Base (1)'!N27)*$C$52/365 -> 76142.675 | N39: =('DCF Model - Base (1)'!O24+'DCF Model - Base (1)'!O27)*$C$52/365 -> 78640.155 | O39: =('DCF Model - Base (1)'!P24+'DCF Model - Base (1)'!P27)*$C$52/365 -> 80961.612 | P39: =('DCF Model - Base (1)'!Q24+'DCF Model - Base (1)'!Q27)*$C$52/365 -> 83086.045
B40: Net Working Capital | G40: =G37+G38-G39 -> -21905 | H40: =H37+H38-H39 -> -30985 | I40: =I37+I38-I39 -> -26772 | J40: =J37+J38-J39 -> -28264 | K40: =K37+K38-K39 -> -24365 | L40: =L37+L38-L39+L12*$C$53 -> -26608.517 | M40: =M37+M38-M39+M12*$C$53 -> -27481.277 | N40: =N37+N38-N39+N12*$C$53 -> -28382.663 | O40: =O37+O38-O39+O12*$C$53 -> -29220.519 | P40: =P37+P38-P39+P12*$C$53 -> -29987.265
B41: Change in Net Working Capital | H41: =H40-G40 -> -9080 | I41: =I40-H40 -> 4213 | J41: =J40-I40 -> -1492 | K41: =K40-J40 -> 3899 | L41: =L40-K40 -> -2243.5174 | M41: =M40-L40 -> -872.75937 | N41: =N40-M40 -> -901.38588 | O41: =O40-N40 -> -837.8562 | P41: =P40-O40 -> -766.74642
B43: Salaries & Benefits | C43: [$] | E43: 0 | F43: 0 | G43: 3033.3638 | H43: 3430.707 | I43: 3269.7653 | J43: 3269.9513 | K43: 3335.3504 | L43: 3402.0574 | M43: 3470.0985 | N43: 3539.5005 | O43: 3610.2905 | P43: 3682.4963
B49: Editable Working-Capital Assumptions
B50: Days sales outstanding (DSO) | C50: 34.886991
B51: Days inventory outstanding (DIO) | C51: 9.4454652
B52: Days payables outstanding (DPO) | C52: 115.40052
B53: NWC intensity overlay (% Revenue) | C53: ='DCF Model - Base (1)'!$F$10 -> 0

Sheet Data Review
A1: Draft review — Apple Inc. (AAPL)
A2: Editable starting model. Check REVIEW rows, then adjust the input cells and assumptions to fit your view.
A3: Model confidence | B3: High (80%)
A5: Status | B5: Area | C5: Review note
A6: REVIEW | B6: FY 2024 interest_expense | C6: FY 2024 interest_expense: missing SEC mapping; missing.
A7: REVIEW | B7: FY 2025 interest_expense | C7: FY 2025 interest_expense: missing SEC mapping; missing.
A8: REVIEW | B8: FY 2021 marketing | C8: FY 2021 marketing: missing SEC mapping; missing.
A9: REVIEW | B9: FY 2022 marketing | C9: FY 2022 marketing: missing SEC mapping; missing.
A10: REVIEW | B10: FY 2023 marketing | C10: FY 2023 marketing: missing SEC mapping; missing.
A11: REVIEW | B11: FY 2024 marketing | C11: FY 2024 marketing: missing SEC mapping; missing.
A12: REVIEW | B12: FY 2021 rent | C12: FY 2021 rent: missing SEC mapping; missing.
A13: REVIEW | B13: FY 2022 rent | C13: FY 2022 rent: missing SEC mapping; missing.
A14: REVIEW | B14: FY 2023 rent | C14: FY 2023 rent: missing SEC mapping; missing.
A15: REVIEW | B15: FY 2024 rent | C15: FY 2024 rent: missing SEC mapping; missing.
A16: REVIEW | B16: FY 2025 rent | C16: FY 2025 rent: missing SEC mapping; missing.
... A497: INFO | B497: Source | C497: insider_trades: lazy_optional
