Workbook

Sheet Utility Model
A1: Regulated Utility Rate-Base DDM — DUK
A2: Duke Energy CORP
A3: Direct common-equity dividend DCF. Rate-base additions, depreciation, authorized returns, and payout inputs are visible below; no enterprise value or corporate FCFF is calculated.
A4: Model status | B4: ='Input Required'!$B$3 -> INCOMPLETE — fill required inputs | I4: Current Market Inputs | J4: Value | K4: Source / as-of date
I5: Current risk-free rate | J5: 0.05277 | K5: live as of 2026-10-03
A6: FY2025 regulated rate base | B6: =IF('Input Required'!$B$3<>"READY","",'Input Required'!F6/1000000) | I6: Current equity-risk premium | J6: 0.083837107 | K6: live as of 2026-10-03
C7: 2026 | D7: 2027 | E7: 2028 | F7: 2029 | G7: 2030 | I7: Current utility beta | J7: 0.364 | K7: openbb_yfinance as of 2026-10-03
A8: Rate-base roll-forward | K8: openbb_yfinance as of 2026-10-03
A9: Opening regulated rate base | C9: =$B$6 | D9: =C12 | E9: =D12 | F9: =E12 | G9: =F12 | K9: SEC accession 0001326160-26-000014, filed 2026-02-26
A10: Approved additions entering rate base | C10: =IF('Input Required'!$B$3<>"READY","",'Input Required'!F9/1000000) | D10: =IF('Input Required'!$B$3<>"READY","",'Input Required'!F10/1000000) | E10: =IF('Input Required'!$B$3<>"READY","",'Input Required'!F11/1000000) | F10: =IF('Input Required'!$B$3<>"READY","",'Input Required'!F12/1000000) | G10: =IF('Input Required'!$B$3<>"READY","",'Input Required'!F13/1000000)
A11: Rate-base depreciation and retirements | C11: =IF('Input Required'!$B$3<>"READY","",'Input Required'!F14/1000000) | D11: =IF('Input Required'!$B$3<>"READY","",'Input Required'!F15/1000000) | E11: =IF('Input Required'!$B$3<>"READY","",'Input Required'!F16/1000000) | F11: =IF('Input Required'!$B$3<>"READY","",'Input Required'!F17/1000000) | G11: =IF('Input Required'!$B$3<>"READY","",'Input Required'!F18/1000000)
A12: Closing regulated rate base | C12: =IF('Input Required'!$B$3<>"READY","",C9+C10-C11) | D12: =IF('Input Required'!$B$3<>"READY","",D9+D10-D11) | E12: =IF('Input Required'!$B$3<>"READY","",E9+E10-E11) | F12: =IF('Input Required'!$B$3<>"READY","",F9+F10-F11) | G12: =IF('Input Required'!$B$3<>"READY","",G9+G10-G11)
A13: Average regulated rate base | C13: =IF('Input Required'!$B$3<>"READY","",AVERAGE(C9,C12)) | D13: =IF('Input Required'!$B$3<>"READY","",AVERAGE(D9,D12)) | E13: =IF('Input Required'!$B$3<>"READY","",AVERAGE(E9,E12)) | F13: =IF('Input Required'!$B$3<>"READY","",AVERAGE(F9,F12)) | G13: =IF('Input Required'!$B$3<>"READY","",AVERAGE(G9,G12))
A15: Authorized common-equity ratio | C15: =IF('Input Required'!$B$3<>"READY","",'Input Required'!F8/1) | D15: =IF('Input Required'!$B$3<>"READY","",'Input Required'!F8/1) | E15: =IF('Input Required'!$B$3<>"READY","",'Input Required'!F8/1) | F15: =IF('Input Required'!$B$3<>"READY","",'Input Required'!F8/1) | G15: =IF('Input Required'!$B$3<>"READY","",'Input Required'!F8/1)
A16: Allowed return on common equity | C16: =IF('Input Required'!$B$3<>"READY","",'Input Required'!F7/1) | D16: =IF('Input Required'!$B$3<>"READY","",'Input Required'!F7/1) | E16: =IF('Input Required'!$B$3<>"READY","",'Input Required'!F7/1) | F16: =IF('Input Required'!$B$3<>"READY","",'Input Required'!F7/1) | G16: =IF('Input Required'!$B$3<>"READY","",'Input Required'!F7/1)
A17: Allowed equity earnings proxy | C17: =IF('Input Required'!$B$3<>"READY","",C13*C15*C16) | D17: =IF('Input Required'!$B$3<>"READY","",D13*D15*D16) | E17: =IF('Input Required'!$B$3<>"READY","",E13*E15*E16) | F17: =IF('Input Required'!$B$3<>"READY","",F13*F15*F16) | G17: =IF('Input Required'!$B$3<>"READY","",G13*G15*G16)
A18: Common dividend payout ratio | C18: =IF('Input Required'!$B$3<>"READY","",'Input Required'!F19/1) | D18: =IF('Input Required'!$B$3<>"READY","",'Input Required'!F19/1) | E18: =IF('Input Required'!$B$3<>"READY","",'Input Required'!F19/1) | F18: =IF('Input Required'!$B$3<>"READY","",'Input Required'!F19/1) | G18: =IF('Input Required'!$B$3<>"READY","",'Input Required'!F19/1)
A19: Forecast common dividends | C19: =IF('Input Required'!$B$3<>"READY","",C17*C18) | D19: =IF('Input Required'!$B$3<>"READY","",D17*D18) | E19: =IF('Input Required'!$B$3<>"READY","",E17*E18) | F19: =IF('Input Required'!$B$3<>"READY","",F17*F18) | G19: =IF('Input Required'!$B$3<>"READY","",G17*G18)
A20: Dividend discount factor | C20: =IF('Input Required'!$B$3<>"READY","",1/(1+$B$24)^1) | D20: =IF('Input Required'!$B$3<>"READY","",1/(1+$B$24)^2) | E20: =IF('Input Required'!$B$3<>"READY","",1/(1+$B$24)^3) | F20: =IF('Input Required'!$B$3<>"READY","",1/(1+$B$24)^4) | G20: =IF('Input Required'!$B$3<>"READY","",1/(1+$B$24)^5)
A21: Present value of common dividends | C21: =IF('Input Required'!$B$3<>"READY","",C19*C20) | D21: =IF('Input Required'!$B$3<>"READY","",D19*D20) | E21: =IF('Input Required'!$B$3<>"READY","",E19*E20) | F21: =IF('Input Required'!$B$3<>"READY","",F19*F20) | G21: =IF('Input Required'!$B$3<>"READY","",G19*G20)
A23: Common-equity dividend DCF
A24: Cost of equity (CAPM) | B24: =IF('Input Required'!$B$3<>"READY","",J5+J7*J6)
A25: Terminal dividend growth | B25: =IF('Input Required'!$B$3<>"READY","",'Input Required'!F20/1)
A26: Terminal value | B26: =IF('Input Required'!$B$3<>"READY","",IF(B24<=B25,"",G19*(1+B25)/(B24-B25)))
A27: Present value of terminal value | B27: =IF('Input Required'!$B$3<>"READY","",IF(B24<=B25,"",B26/(1+B24)^5))
A28: Present value of forecast dividends | B28: =IF('Input Required'!$B$3<>"READY","",SUM(C21:G21))
A29: Common-equity value | B29: =IF('Input Required'!$B$3<>"READY","",IF(B24<=B25,"",B27+B28))
A30: Diluted shares (millions) | B30: 777
A31: Implied value per share | B31: =IF('Input Required'!$B$3<>"READY","",IF(B24<=B25,"",IFERROR(B29/B30,0)))
A32: Current share price | B32: 114.13
A33: Implied upside / (downside) | B33: =IF('Input Required'!$B$3<>"READY","",IF(B24<=B25,"",IFERROR(B31/B32-1,0)))
A35: Per-share sensitivity — cost of equity vs. terminal growth
B36: Cost of equity / terminal growth | C36: -0.02 | D36: -0.01 | E36: 0 | F36: 0.01 | G36: 0.02
B37: -0.02 | C37: =IF('Input Required'!$B$3<>"READY","",IF($B$24+$B37<=($B$25+C$36),"",IFERROR((C19/(1+$B$24+$B37)^1+D19/(1+$B$24+$B37)^2+E19/(1+$B$24+$B37)^3+F19/(1+$B$24+$B37)^4+G19/(1+$B$24+$B37)^5+($G$19*(1+($B$25+C$36))/($B$24+$B37-($B$25+C$36)))/(1+$B$24+$B37)^5)/$B$30,""))) | D37: =IF('Input Required'!$B$3<>"READY","",IF($B$24+$B37<=($B$25+D$36),"",IFERROR((C19/(1+$B$24+$B37)^1+D19/(1+$B$24+$B37)^2+E19/(1+$B$24+$B37)^3+F19/(1+$B$24+$B37)^4+G19/(1+$B$24+$B37)^5+($G$19*(1+($B$25+D$36))/($B$24+$B37-($B$25+D$36)))/(1+$B$24+$B37)^5)/$B$30,""))) | E37: =IF('Input Required'!$B$3<>"READY","",IF($B$24+$B37<=($B$25+E$36),"",IFERROR((C19/(1+$B$24+$B37)^1+D19/(1+$B$24+$B37)^2+E19/(1+$B$24+$B37)^3+F19/(1+$B$24+$B37)^4+G19/(1+$B$24+$B37)^5+($G$19*(1+($B$25+E$36))/($B$24+$B37-($B$25+E$36)))/(1+$B$24+$B37)^5)/$B$30,""))) | F37: =IF('Input Required'!$B$3<>"READY","",IF($B$24+$B37<=($B$25+F$36),"",IFERROR((C19/(1+$B$24+$B37)^1+D19/(1+$B$24+$B37)^2+E19/(1+$B$24+$B37)^3+F19/(1+$B$24+$B37)^4+G19/(1+$B$24+$B37)^5+($G$19*(1+($B$25+F$36))/($B$24+$B37-($B$25+F$36)))/(1+$B$24+$B37)^5)/$B$30,""))) | G37: =IF('Input Required'!$B$3<>"READY","",IF($B$24+$B37<=($B$25+G$36),"",IFERROR((C19/(1+$B$24+$B37)^1+D19/(1+$B$24+$B37)^2+E19/(1+$B$24+$B37)^3+F19/(1+$B$24+$B37)^4+G19/(1+$B$24+$B37)^5+($G$19*(1+($B$25+G$36))/($B$24+$B37-($B$25+G$36)))/(1+$B$24+$B37)^5)/$B$30,"")))
B38: -0.01 | C38: =IF('Input Required'!$B$3<>"READY","",IF($B$24+$B38<=($B$25+C$36),"",IFERROR((C19/(1+$B$24+$B38)^1+D19/(1+$B$24+$B38)^2+E19/(1+$B$24+$B38)^3+F19/(1+$B$24+$B38)^4+G19/(1+$B$24+$B38)^5+($G$19*(1+($B$25+C$36))/($B$24+$B38-($B$25+C$36)))/(1+$B$24+$B38)^5)/$B$30,""))) | D38: =IF('Input Required'!$B$3<>"READY","",IF($B$24+$B38<=($B$25+D$36),"",IFERROR((C19/(1+$B$24+$B38)^1+D19/(1+$B$24+$B38)^2+E19/(1+$B$24+$B38)^3+F19/(1+$B$24+$B38)^4+G19/(1+$B$24+$B38)^5+($G$19*(1+($B$25+D$36))/($B$24+$B38-($B$25+D$36)))/(1+$B$24+$B38)^5)/$B$30,""))) | E38: =IF('Input Required'!$B$3<>"READY","",IF($B$24+$B38<=($B$25+E$36),"",IFERROR((C19/(1+$B$24+$B38)^1+D19/(1+$B$24+$B38)^2+E19/(1+$B$24+$B38)^3+F19/(1+$B$24+$B38)^4+G19/(1+$B$24+$B38)^5+($G$19*(1+($B$25+E$36))/($B$24+$B38-($B$25+E$36)))/(1+$B$24+$B38)^5)/$B$30,""))) | F38: =IF('Input Required'!$B$3<>"READY","",IF($B$24+$B38<=($B$25+F$36),"",IFERROR((C19/(1+$B$24+$B38)^1+D19/(1+$B$24+$B38)^2+E19/(1+$B$24+$B38)^3+F19/(1+$B$24+$B38)^4+G19/(1+$B$24+$B38)^5+($G$19*(1+($B$25+F$36))/($B$24+$B38-($B$25+F$36)))/(1+$B$24+$B38)^5)/$B$30,""))) | G38: =IF('Input Required'!$B$3<>"READY","",IF($B$24+$B38<=($B$25+G$36),"",IFERROR((C19/(1+$B$24+$B38)^1+D19/(1+$B$24+$B38)^2+E19/(1+$B$24+$B38)^3+F19/(1+$B$24+$B38)^4+G19/(1+$B$24+$B38)^5+($G$19*(1+($B$25+G$36))/($B$24+$B38-($B$25+G$36)))/(1+$B$24+$B38)^5)/$B$30,"")))
B39: 0 | C39: =IF('Input Required'!$B$3<>"READY","",IF($B$24+$B39<=($B$25+C$36),"",IFERROR((C19/(1+$B$24+$B39)^1+D19/(1+$B$24+$B39)^2+E19/(1+$B$24+$B39)^3+F19/(1+$B$24+$B39)^4+G19/(1+$B$24+$B39)^5+($G$19*(1+($B$25+C$36))/($B$24+$B39-($B$25+C$36)))/(1+$B$24+$B39)^5)/$B$30,""))) | D39: =IF('Input Required'!$B$3<>"READY","",IF($B$24+$B39<=($B$25+D$36),"",IFERROR((C19/(1+$B$24+$B39)^1+D19/(1+$B$24+$B39)^2+E19/(1+$B$24+$B39)^3+F19/(1+$B$24+$B39)^4+G19/(1+$B$24+$B39)^5+($G$19*(1+($B$25+D$36))/($B$24+$B39-($B$25+D$36)))/(1+$B$24+$B39)^5)/$B$30,""))) | E39: =IF('Input Required'!$B$3<>"READY","",IF($B$24+$B39<=($B$25+E$36),"",IFERROR((C19/(1+$B$24+$B39)^1+D19/(1+$B$24+$B39)^2+E19/(1+$B$24+$B39)^3+F19/(1+$B$24+$B39)^4+G19/(1+$B$24+$B39)^5+($G$19*(1+($B$25+E$36))/($B$24+$B39-($B$25+E$36)))/(1+$B$24+$B39)^5)/$B$30,""))) | F39: =IF('Input Required'!$B$3<>"READY","",IF($B$24+$B39<=($B$25+F$36),"",IFERROR((C19/(1+$B$24+$B39)^1+D19/(1+$B$24+$B39)^2+E19/(1+$B$24+$B39)^3+F19/(1+$B$24+$B39)^4+G19/(1+$B$24+$B39)^5+($G$19*(1+($B$25+F$36))/($B$24+$B39-($B$25+F$36)))/(1+$B$24+$B39)^5)/$B$30,""))) | G39: =IF('Input Required'!$B$3<>"READY","",IF($B$24+$B39<=($B$25+G$36),"",IFERROR((C19/(1+$B$24+$B39)^1+D19/(1+$B$24+$B39)^2+E19/(1+$B$24+$B39)^3+F19/(1+$B$24+$B39)^4+G19/(1+$B$24+$B39)^5+($G$19*(1+($B$25+G$36))/($B$24+$B39-($B$25+G$36)))/(1+$B$24+$B39)^5)/$B$30,"")))
B40: 0.01 | C40: =IF('Input Required'!$B$3<>"READY","",IF($B$24+$B40<=($B$25+C$36),"",IFERROR((C19/(1+$B$24+$B40)^1+D19/(1+$B$24+$B40)^2+E19/(1+$B$24+$B40)^3+F19/(1+$B$24+$B40)^4+G19/(1+$B$24+$B40)^5+($G$19*(1+($B$25+C$36))/($B$24+$B40-($B$25+C$36)))/(1+$B$24+$B40)^5)/$B$30,""))) | D40: =IF('Input Required'!$B$3<>"READY","",IF($B$24+$B40<=($B$25+D$36),"",IFERROR((C19/(1+$B$24+$B40)^1+D19/(1+$B$24+$B40)^2+E19/(1+$B$24+$B40)^3+F19/(1+$B$24+$B40)^4+G19/(1+$B$24+$B40)^5+($G$19*(1+($B$25+D$36))/($B$24+$B40-($B$25+D$36)))/(1+$B$24+$B40)^5)/$B$30,""))) | E40: =IF('Input Required'!$B$3<>"READY","",IF($B$24+$B40<=($B$25+E$36),"",IFERROR((C19/(1+$B$24+$B40)^1+D19/(1+$B$24+$B40)^2+E19/(1+$B$24+$B40)^3+F19/(1+$B$24+$B40)^4+G19/(1+$B$24+$B40)^5+($G$19*(1+($B$25+E$36))/($B$24+$B40-($B$25+E$36)))/(1+$B$24+$B40)^5)/$B$30,""))) | F40: =IF('Input Required'!$B$3<>"READY","",IF($B$24+$B40<=($B$25+F$36),"",IFERROR((C19/(1+$B$24+$B40)^1+D19/(1+$B$24+$B40)^2+E19/(1+$B$24+$B40)^3+F19/(1+$B$24+$B40)^4+G19/(1+$B$24+$B40)^5+($G$19*(1+($B$25+F$36))/($B$24+$B40-($B$25+F$36)))/(1+$B$24+$B40)^5)/$B$30,""))) | G40: =IF('Input Required'!$B$3<>"READY","",IF($B$24+$B40<=($B$25+G$36),"",IFERROR((C19/(1+$B$24+$B40)^1+D19/(1+$B$24+$B40)^2+E19/(1+$B$24+$B40)^3+F19/(1+$B$24+$B40)^4+G19/(1+$B$24+$B40)^5+($G$19*(1+($B$25+G$36))/($B$24+$B40-($B$25+G$36)))/(1+$B$24+$B40)^5)/$B$30,"")))
B41: 0.02 | C41: =IF('Input Required'!$B$3<>"READY","",IF($B$24+$B41<=($B$25+C$36),"",IFERROR((C19/(1+$B$24+$B41)^1+D19/(1+$B$24+$B41)^2+E19/(1+$B$24+$B41)^3+F19/(1+$B$24+$B41)^4+G19/(1+$B$24+$B41)^5+($G$19*(1+($B$25+C$36))/($B$24+$B41-($B$25+C$36)))/(1+$B$24+$B41)^5)/$B$30,""))) | D41: =IF('Input Required'!$B$3<>"READY","",IF($B$24+$B41<=($B$25+D$36),"",IFERROR((C19/(1+$B$24+$B41)^1+D19/(1+$B$24+$B41)^2+E19/(1+$B$24+$B41)^3+F19/(1+$B$24+$B41)^4+G19/(1+$B$24+$B41)^5+($G$19*(1+($B$25+D$36))/($B$24+$B41-($B$25+D$36)))/(1+$B$24+$B41)^5)/$B$30,""))) | E41: =IF('Input Required'!$B$3<>"READY","",IF($B$24+$B41<=($B$25+E$36),"",IFERROR((C19/(1+$B$24+$B41)^1+D19/(1+$B$24+$B41)^2+E19/(1+$B$24+$B41)^3+F19/(1+$B$24+$B41)^4+G19/(1+$B$24+$B41)^5+($G$19*(1+($B$25+E$36))/($B$24+$B41-($B$25+E$36)))/(1+$B$24+$B41)^5)/$B$30,""))) | F41: =IF('Input Required'!$B$3<>"READY","",IF($B$24+$B41<=($B$25+F$36),"",IFERROR((C19/(1+$B$24+$B41)^1+D19/(1+$B$24+$B41)^2+E19/(1+$B$24+$B41)^3+F19/(1+$B$24+$B41)^4+G19/(1+$B$24+$B41)^5+($G$19*(1+($B$25+F$36))/($B$24+$B41-($B$25+F$36)))/(1+$B$24+$B41)^5)/$B$30,""))) | G41: =IF('Input Required'!$B$3<>"READY","",IF($B$24+$B41<=($B$25+G$36),"",IFERROR((C19/(1+$B$24+$B41)^1+D19/(1+$B$24+$B41)^2+E19/(1+$B$24+$B41)^3+F19/(1+$B$24+$B41)^4+G19/(1+$B$24+$B41)^5+($G$19*(1+($B$25+G$36))/($B$24+$B41-($B$25+G$36)))/(1+$B$24+$B41)^5)/$B$30,"")))

Sheet Input Required
A1: INCOMPLETE MODEL — Duke Energy CORP (DUK)
A2: Model family: utility_dcf. No valuation has been calculated because required inputs are missing.
A3: Model status | B3: =IF(COUNTIF('Data Review'!$C$5:$C$19,"INPUT ERROR")>0,"INPUT ERROR — check required inputs",IF(COUNTIF('Data Review'!$C$5:$C$19,"INPUT REQUIRED")+COUNTIF('Data Review'!$C$5:$C$19,"SOURCE REQUIRED")>0,"INCOMPLETE — fill required inputs","READY")) -> INCOMPLETE — fill required inputs
A5: Input key | B5: Required input | C5: Period | D5: Unit | E5: Why required | F5: Enter value | G5: Source / reference | H5: Source required
A6: jurisdictional_rate_base | B6: Latest regulated jurisdictional rate base | C6: FY2025 | D6: USD actual | E6: Regulated utility valuation needs source-backed jurisdictional rate base, allowed ROE, authorized equity ratio, and approved rate-base additions. Enter the missing regulatory facts and forecast inputs in the utility workbook. Fiscal year 2025. Use the regulated operating-company scope stated in the source reference. | H6: Yes
A7: allowed_roe | B7: Current authorized return on common equity | C7: FY2025 | D7: ratio | E7: Regulated utility valuation needs source-backed jurisdictional rate base, allowed ROE, authorized equity ratio, and approved rate-base additions. Enter the missing regulatory facts and forecast inputs in the utility workbook. | H7: Yes
A8: authorized_equity_ratio | B8: Authorized common-equity share of capital structure | C8: FY2025 | D8: ratio | E8: Regulated utility valuation needs source-backed jurisdictional rate base, allowed ROE, authorized equity ratio, and approved rate-base additions. Enter the missing regulatory facts and forecast inputs in the utility workbook. | H8: Yes
A9: rate_base_additions | B9: Approved additions entering rate base | C9: FY2026 | D9: USD actual | E9: Regulated utility valuation needs source-backed jurisdictional rate base, allowed ROE, authorized equity ratio, and approved rate-base additions. Enter the missing regulatory facts and forecast inputs in the utility workbook. Enter each forecast-year value and its source or forecast basis. Fiscal year 2026. | H9: Yes
A10: rate_base_additions | B10: Approved additions entering rate base | C10: FY2027 | D10: USD actual | E10: Regulated utility valuation needs source-backed jurisdictional rate base, allowed ROE, authorized equity ratio, and approved rate-base additions. Enter the missing regulatory facts and forecast inputs in the utility workbook. Enter each forecast-year value and its source or forecast basis. Fiscal year 2027. | H10: Yes
A11: rate_base_additions | B11: Approved additions entering rate base | C11: FY2028 | D11: USD actual | E11: Regulated utility valuation needs source-backed jurisdictional rate base, allowed ROE, authorized equity ratio, and approved rate-base additions. Enter the missing regulatory facts and forecast inputs in the utility workbook. Enter each forecast-year value and its source or forecast basis. Fiscal year 2028. | H11: Yes
A12: rate_base_additions | B12: Approved additions entering rate base | C12: FY2029 | D12: USD actual | E12: Regulated utility valuation needs source-backed jurisdictional rate base, allowed ROE, authorized equity ratio, and approved rate-base additions. Enter the missing regulatory facts and forecast inputs in the utility workbook. Enter each forecast-year value and its source or forecast basis. Fiscal year 2029. | H12: Yes
A13: rate_base_additions | B13: Approved additions entering rate base | C13: FY2030 | D13: USD actual | E13: Regulated utility valuation needs source-backed jurisdictional rate base, allowed ROE, authorized equity ratio, and approved rate-base additions. Enter the missing regulatory facts and forecast inputs in the utility workbook. Enter each forecast-year value and its source or forecast basis. Fiscal year 2030. | H13: Yes
A14: rate_base_depreciation | B14: Rate-base depreciation and retirements | C14: FY2026 | D14: USD actual | E14: Regulated utility valuation needs source-backed jurisdictional rate base, allowed ROE, authorized equity ratio, and approved rate-base additions. Enter the missing regulatory facts and forecast inputs in the utility workbook. Enter each forecast-year value and its source or forecast basis. Fiscal year 2026; label the forecast basis in the workbook. | H14: No
A15: rate_base_depreciation | B15: Rate-base depreciation and retirements | C15: FY2027 | D15: USD actual | E15: Regulated utility valuation needs source-backed jurisdictional rate base, allowed ROE, authorized equity ratio, and approved rate-base additions. Enter the missing regulatory facts and forecast inputs in the utility workbook. Enter each forecast-year value and its source or forecast basis. Fiscal year 2027; label the forecast basis in the workbook. | H15: No
A16: rate_base_depreciation | B16: Rate-base depreciation and retirements | C16: FY2028 | D16: USD actual | E16: Regulated utility valuation needs source-backed jurisdictional rate base, allowed ROE, authorized equity ratio, and approved rate-base additions. Enter the missing regulatory facts and forecast inputs in the utility workbook. Enter each forecast-year value and its source or forecast basis. Fiscal year 2028; label the forecast basis in the workbook. | H16: No
A17: rate_base_depreciation | B17: Rate-base depreciation and retirements | C17: FY2029 | D17: USD actual | E17: Regulated utility valuation needs source-backed jurisdictional rate base, allowed ROE, authorized equity ratio, and approved rate-base additions. Enter the missing regulatory facts and forecast inputs in the utility workbook. Enter each forecast-year value and its source or forecast basis. Fiscal year 2029; label the forecast basis in the workbook. | H17: No
... A19: dividend_payout_ratio | B19: Forecast common-dividend payout ratio | C19: FY2025 | D19: ratio | E19: Regulated utility valuation needs source-backed jurisdictional rate base, allowed ROE, authorized equity ratio, and approved rate-base additions. Enter the missing regulatory facts and forecast inputs in the utility workbook. State the intended payout policy or attach the source basis. | H19: No
A20: terminal_growth_rate | B20: Long-run regulated dividend growth | D20: ratio | E20: Regulated utility valuation needs source-backed jurisdictional rate base, allowed ROE, authorized equity ratio, and approved rate-base additions. Enter the missing regulatory facts and forecast inputs in the utility workbook. Keep terminal growth below cost of equity (8.33%). | H20: No

Sheet Data Review
A1: Required input review
A2: Fill blue input cells on Input Required. Reported facts require a source reference; missing values are not zero.
A4: Input key | B4: Required input | C4: Status | D4: Source status | E4: Period | F4: Unit | G4: Reason | H4: Workbook cell | I4: Source / reference
A5: jurisdictional_rate_base | B5: Latest regulated jurisdictional rate base | C5: =IF('Input Required'!F6="","INPUT REQUIRED",IF(AND('Input Required'!H6="Yes",'Input Required'!G6=""),"SOURCE REQUIRED",IF(OR(AND('Input Required'!F6<>"",NOT(ISNUMBER('Input Required'!F6))),AND(ISNUMBER('Input Required'!F6),'Input Required'!F6<1)),"INPUT ERROR","READY"))) -> INPUT REQUIRED | D5: missing | E5: FY2025 | F5: USD actual | G5: Regulated utility valuation needs source-backed jurisdictional rate base, allowed ROE, authorized equity ratio, and approved rate-base additions. Enter the missing regulatory facts and forecast inputs in the utility workbook. Fiscal year 2025. Use the regulated operating-company scope stated in the source reference. | H5: Input Required!F6 | I5: ='Input Required'!G6 -> 0
A6: allowed_roe | B6: Current authorized return on common equity | C6: =IF('Input Required'!F7="","INPUT REQUIRED",IF(AND('Input Required'!H7="Yes",'Input Required'!G7=""),"SOURCE REQUIRED",IF(OR(AND('Input Required'!F7<>"",NOT(ISNUMBER('Input Required'!F7))),AND(ISNUMBER('Input Required'!F7),'Input Required'!F7<0.001),AND(ISNUMBER('Input Required'!F7),'Input Required'!F7>0.5)),"INPUT ERROR","READY"))) -> INPUT REQUIRED | D6: missing | E6: FY2025 | F6: ratio | G6: Regulated utility valuation needs source-backed jurisdictional rate base, allowed ROE, authorized equity ratio, and approved rate-base additions. Enter the missing regulatory facts and forecast inputs in the utility workbook. | H6: Input Required!F7 | I6: ='Input Required'!G7 -> 0
A7: authorized_equity_ratio | B7: Authorized common-equity share of capital structure | C7: =IF('Input Required'!F8="","INPUT REQUIRED",IF(AND('Input Required'!H8="Yes",'Input Required'!G8=""),"SOURCE REQUIRED",IF(OR(AND('Input Required'!F8<>"",NOT(ISNUMBER('Input Required'!F8))),AND(ISNUMBER('Input Required'!F8),'Input Required'!F8<0.01),AND(ISNUMBER('Input Required'!F8),'Input Required'!F8>0.99)),"INPUT ERROR","READY"))) -> INPUT REQUIRED | D7: missing | E7: FY2025 | F7: ratio | G7: Regulated utility valuation needs source-backed jurisdictional rate base, allowed ROE, authorized equity ratio, and approved rate-base additions. Enter the missing regulatory facts and forecast inputs in the utility workbook. | H7: Input Required!F8 | I7: ='Input Required'!G8 -> 0
A8: rate_base_additions | B8: Approved additions entering rate base | C8: =IF('Input Required'!F9="","INPUT REQUIRED",IF(AND('Input Required'!H9="Yes",'Input Required'!G9=""),"SOURCE REQUIRED",IF(OR(AND('Input Required'!F9<>"",NOT(ISNUMBER('Input Required'!F9))),AND(ISNUMBER('Input Required'!F9),'Input Required'!F9<0)),"INPUT ERROR","READY"))) -> INPUT REQUIRED | D8: missing | E8: FY2026 | F8: USD actual | G8: Regulated utility valuation needs source-backed jurisdictional rate base, allowed ROE, authorized equity ratio, and approved rate-base additions. Enter the missing regulatory facts and forecast inputs in the utility workbook. Enter each forecast-year value and its source or forecast basis. Fiscal year 2026. | H8: Input Required!F9 | I8: ='Input Required'!G9 -> 0
A9: rate_base_additions | B9: Approved additions entering rate base | C9: =IF('Input Required'!F10="","INPUT REQUIRED",IF(AND('Input Required'!H10="Yes",'Input Required'!G10=""),"SOURCE REQUIRED",IF(OR(AND('Input Required'!F10<>"",NOT(ISNUMBER('Input Required'!F10))),AND(ISNUMBER('Input Required'!F10),'Input Required'!F10<0)),"INPUT ERROR","READY"))) -> INPUT REQUIRED | D9: missing | E9: FY2027 | F9: USD actual | G9: Regulated utility valuation needs source-backed jurisdictional rate base, allowed ROE, authorized equity ratio, and approved rate-base additions. Enter the missing regulatory facts and forecast inputs in the utility workbook. Enter each forecast-year value and its source or forecast basis. Fiscal year 2027. | H9: Input Required!F10 | I9: ='Input Required'!G10 -> 0
A10: rate_base_additions | B10: Approved additions entering rate base | C10: =IF('Input Required'!F11="","INPUT REQUIRED",IF(AND('Input Required'!H11="Yes",'Input Required'!G11=""),"SOURCE REQUIRED",IF(OR(AND('Input Required'!F11<>"",NOT(ISNUMBER('Input Required'!F11))),AND(ISNUMBER('Input Required'!F11),'Input Required'!F11<0)),"INPUT ERROR","READY"))) -> INPUT REQUIRED | D10: missing | E10: FY2028 | F10: USD actual | G10: Regulated utility valuation needs source-backed jurisdictional rate base, allowed ROE, authorized equity ratio, and approved rate-base additions. Enter the missing regulatory facts and forecast inputs in the utility workbook. Enter each forecast-year value and its source or forecast basis. Fiscal year 2028. | H10: Input Required!F11 | I10: ='Input Required'!G11 -> 0
A11: rate_base_additions | B11: Approved additions entering rate base | C11: =IF('Input Required'!F12="","INPUT REQUIRED",IF(AND('Input Required'!H12="Yes",'Input Required'!G12=""),"SOURCE REQUIRED",IF(OR(AND('Input Required'!F12<>"",NOT(ISNUMBER('Input Required'!F12))),AND(ISNUMBER('Input Required'!F12),'Input Required'!F12<0)),"INPUT ERROR","READY"))) -> INPUT REQUIRED | D11: missing | E11: FY2029 | F11: USD actual | G11: Regulated utility valuation needs source-backed jurisdictional rate base, allowed ROE, authorized equity ratio, and approved rate-base additions. Enter the missing regulatory facts and forecast inputs in the utility workbook. Enter each forecast-year value and its source or forecast basis. Fiscal year 2029. | H11: Input Required!F12 | I11: ='Input Required'!G12 -> 0
A12: rate_base_additions | B12: Approved additions entering rate base | C12: =IF('Input Required'!F13="","INPUT REQUIRED",IF(AND('Input Required'!H13="Yes",'Input Required'!G13=""),"SOURCE REQUIRED",IF(OR(AND('Input Required'!F13<>"",NOT(ISNUMBER('Input Required'!F13))),AND(ISNUMBER('Input Required'!F13),'Input Required'!F13<0)),"INPUT ERROR","READY"))) -> INPUT REQUIRED | D12: missing | E12: FY2030 | F12: USD actual | G12: Regulated utility valuation needs source-backed jurisdictional rate base, allowed ROE, authorized equity ratio, and approved rate-base additions. Enter the missing regulatory facts and forecast inputs in the utility workbook. Enter each forecast-year value and its source or forecast basis. Fiscal year 2030. | H12: Input Required!F13 | I12: ='Input Required'!G13 -> 0
A13: rate_base_depreciation | B13: Rate-base depreciation and retirements | C13: =IF('Input Required'!F14="","INPUT REQUIRED",IF(AND('Input Required'!H14="Yes",'Input Required'!G14=""),"SOURCE REQUIRED",IF(OR(AND('Input Required'!F14<>"",NOT(ISNUMBER('Input Required'!F14))),AND(ISNUMBER('Input Required'!F14),'Input Required'!F14<0)),"INPUT ERROR","READY"))) -> INPUT REQUIRED | D13: missing | E13: FY2026 | F13: USD actual | G13: Regulated utility valuation needs source-backed jurisdictional rate base, allowed ROE, authorized equity ratio, and approved rate-base additions. Enter the missing regulatory facts and forecast inputs in the utility workbook. Enter each forecast-year value and its source or forecast basis. Fiscal year 2026; label the forecast basis in the workbook. | H13: Input Required!F14 | I13: ='Input Required'!G14 -> 0
A14: rate_base_depreciation | B14: Rate-base depreciation and retirements | C14: =IF('Input Required'!F15="","INPUT REQUIRED",IF(AND('Input Required'!H15="Yes",'Input Required'!G15=""),"SOURCE REQUIRED",IF(OR(AND('Input Required'!F15<>"",NOT(ISNUMBER('Input Required'!F15))),AND(ISNUMBER('Input Required'!F15),'Input Required'!F15<0)),"INPUT ERROR","READY"))) -> INPUT REQUIRED | D14: missing | E14: FY2027 | F14: USD actual | G14: Regulated utility valuation needs source-backed jurisdictional rate base, allowed ROE, authorized equity ratio, and approved rate-base additions. Enter the missing regulatory facts and forecast inputs in the utility workbook. Enter each forecast-year value and its source or forecast basis. Fiscal year 2027; label the forecast basis in the workbook. | H14: Input Required!F15 | I14: ='Input Required'!G15 -> 0
A15: rate_base_depreciation | B15: Rate-base depreciation and retirements | C15: =IF('Input Required'!F16="","INPUT REQUIRED",IF(AND('Input Required'!H16="Yes",'Input Required'!G16=""),"SOURCE REQUIRED",IF(OR(AND('Input Required'!F16<>"",NOT(ISNUMBER('Input Required'!F16))),AND(ISNUMBER('Input Required'!F16),'Input Required'!F16<0)),"INPUT ERROR","READY"))) -> INPUT REQUIRED | D15: missing | E15: FY2028 | F15: USD actual | G15: Regulated utility valuation needs source-backed jurisdictional rate base, allowed ROE, authorized equity ratio, and approved rate-base additions. Enter the missing regulatory facts and forecast inputs in the utility workbook. Enter each forecast-year value and its source or forecast basis. Fiscal year 2028; label the forecast basis in the workbook. | H15: Input Required!F16 | I15: ='Input Required'!G16 -> 0
A16: rate_base_depreciation | B16: Rate-base depreciation and retirements | C16: =IF('Input Required'!F17="","INPUT REQUIRED",IF(AND('Input Required'!H17="Yes",'Input Required'!G17=""),"SOURCE REQUIRED",IF(OR(AND('Input Required'!F17<>"",NOT(ISNUMBER('Input Required'!F17))),AND(ISNUMBER('Input Required'!F17),'Input Required'!F17<0)),"INPUT ERROR","READY"))) -> INPUT REQUIRED | D16: missing | E16: FY2029 | F16: USD actual | G16: Regulated utility valuation needs source-backed jurisdictional rate base, allowed ROE, authorized equity ratio, and approved rate-base additions. Enter the missing regulatory facts and forecast inputs in the utility workbook. Enter each forecast-year value and its source or forecast basis. Fiscal year 2029; label the forecast basis in the workbook. | H16: Input Required!F17 | I16: ='Input Required'!G17 -> 0
A17: rate_base_depreciation | B17: Rate-base depreciation and retirements | C17: =IF('Input Required'!F18="","INPUT REQUIRED",IF(AND('Input Required'!H18="Yes",'Input Required'!G18=""),"SOURCE REQUIRED",IF(OR(AND('Input Required'!F18<>"",NOT(ISNUMBER('Input Required'!F18))),AND(ISNUMBER('Input Required'!F18),'Input Required'!F18<0)),"INPUT ERROR","READY"))) -> INPUT REQUIRED | D17: missing | E17: FY2030 | F17: USD actual | G17: Regulated utility valuation needs source-backed jurisdictional rate base, allowed ROE, authorized equity ratio, and approved rate-base additions. Enter the missing regulatory facts and forecast inputs in the utility workbook. Enter each forecast-year value and its source or forecast basis. Fiscal year 2030; label the forecast basis in the workbook. | H17: Input Required!F18 | I17: ='Input Required'!G18 -> 0
A18: dividend_payout_ratio | B18: Forecast common-dividend payout ratio | C18: =IF('Input Required'!F19="","INPUT REQUIRED",IF(AND('Input Required'!H19="Yes",'Input Required'!G19=""),"SOURCE REQUIRED",IF(OR(AND('Input Required'!F19<>"",NOT(ISNUMBER('Input Required'!F19))),AND(ISNUMBER('Input Required'!F19),'Input Required'!F19<0),AND(ISNUMBER('Input Required'!F19),'Input Required'!F19>1)),"INPUT ERROR","READY"))) -> INPUT REQUIRED | D18: missing | E18: FY2025 | F18: ratio | G18: Regulated utility valuation needs source-backed jurisdictional rate base, allowed ROE, authorized equity ratio, and approved rate-base additions. Enter the missing regulatory facts and forecast inputs in the utility workbook. State the intended payout policy or attach the source basis. | H18: Input Required!F19 | I18: ='Input Required'!G19 -> 0
A19: terminal_growth_rate | B19: Long-run regulated dividend growth | C19: =IF('Input Required'!F20="","INPUT REQUIRED",IF(AND('Input Required'!H20="Yes",'Input Required'!G20=""),"SOURCE REQUIRED",IF(OR(AND('Input Required'!F20<>"",NOT(ISNUMBER('Input Required'!F20))),AND(ISNUMBER('Input Required'!F20),'Input Required'!F20<0),AND(ISNUMBER('Input Required'!F20),'Input Required'!F20>0.0782867063840063)),"INPUT ERROR","READY"))) -> INPUT REQUIRED | D19: missing | F19: ratio | G19: Regulated utility valuation needs source-backed jurisdictional rate base, allowed ROE, authorized equity ratio, and approved rate-base additions. Enter the missing regulatory facts and forecast inputs in the utility workbook. Keep terminal growth below cost of equity (8.33%). | H19: Input Required!F20 | I19: ='Input Required'!G20 -> 0
