Workbook

Sheet Biotech Model
A1: Commercial DCF and Pipeline rNPV — MRNA
A2: Moderna, Inc.
A3: Commercial revenue starts from reported consolidated revenue (which can include collaboration and milestone revenue). Pipeline assumptions are blank and analyst-owned.
A4: Model status | B4: =IF('Input Required'!$B$3<>"READY",'Input Required'!$B$3,IF(OR($M$15<2%,$M$15>50%),"INPUT ERROR — WACC outside supported range",IF(OR($M$16>10%,$M$16>$M$15-0.5%),"INPUT ERROR — terminal growth must be at least 0.5% below WACC","READY"))) -> INCOMPLETE — fill required inputs | L4: WACC and market inputs | M4: Value | N4: Source / as-of date
A5: Units: USD millions; diluted shares in millions; per-share value in USD. | L5: Risk-free rate | M5: 0.05277 | N5: live as of 2026-10-03
A6: FY2025 reported consolidated revenue base | B6: 1944 | L6: Equity-risk premium | M6: 0.083837107 | N6: live as of 2026-10-03
L7: Beta | M7: 1.106 | N7: openbb_yfinance as of 2026-10-03
A8: Commercial franchise DCF | L8: Cost of equity | M8: =M5+M7*M6 -> 0.14549384
B9: 2026 | C9: 2027 | D9: 2028 | E9: 2029 | F9: 2030 | G9: 2031 | H9: 2032 | I9: 2033 | J9: 2034 | K9: 2035 | L9: Cost of debt | M9: =IF('Input Required'!$B$3<>"READY","",'Input Required'!F194/1)
A10: Commercial revenue growth | B10: =IF('Input Required'!$B$3<>"READY","",'Input Required'!F6/1) | C10: =IF('Input Required'!$B$3<>"READY","",'Input Required'!F7/1) | D10: =IF('Input Required'!$B$3<>"READY","",'Input Required'!F8/1) | E10: =IF('Input Required'!$B$3<>"READY","",'Input Required'!F9/1) | F10: =IF('Input Required'!$B$3<>"READY","",'Input Required'!F10/1) | G10: =IF('Input Required'!$B$3<>"READY","",'Input Required'!F11/1) | H10: =IF('Input Required'!$B$3<>"READY","",'Input Required'!F12/1) | I10: =IF('Input Required'!$B$3<>"READY","",'Input Required'!F13/1) | J10: =IF('Input Required'!$B$3<>"READY","",'Input Required'!F14/1) | K10: =IF('Input Required'!$B$3<>"READY","",'Input Required'!F15/1) | L10: Normalized tax rate | M10: =IF('Input Required'!$B$3<>"READY","",'Input Required'!F195/1)
A11: Commercial revenue | B11: =IF('Biotech Model'!$B$4<>"READY","",$B$6*(1+B10)) | C11: =IF('Biotech Model'!$B$4<>"READY","",B11*(1+C10)) | D11: =IF('Biotech Model'!$B$4<>"READY","",C11*(1+D10)) | E11: =IF('Biotech Model'!$B$4<>"READY","",D11*(1+E10)) | F11: =IF('Biotech Model'!$B$4<>"READY","",E11*(1+F10)) | G11: =IF('Biotech Model'!$B$4<>"READY","",F11*(1+G10)) | H11: =IF('Biotech Model'!$B$4<>"READY","",G11*(1+H10)) | I11: =IF('Biotech Model'!$B$4<>"READY","",H11*(1+I10)) | J11: =IF('Biotech Model'!$B$4<>"READY","",I11*(1+J10)) | K11: =IF('Biotech Model'!$B$4<>"READY","",J11*(1+K10)) | L11: Market capitalization | M11: 75858.813
A12: Post-tax commercial FCFF margin | B12: =IF('Input Required'!$B$3<>"READY","",'Input Required'!F16/1) | C12: =IF('Input Required'!$B$3<>"READY","",'Input Required'!F16/1) | D12: =IF('Input Required'!$B$3<>"READY","",'Input Required'!F16/1) | E12: =IF('Input Required'!$B$3<>"READY","",'Input Required'!F16/1) | F12: =IF('Input Required'!$B$3<>"READY","",'Input Required'!F16/1) | G12: =IF('Input Required'!$B$3<>"READY","",'Input Required'!F16/1) | H12: =IF('Input Required'!$B$3<>"READY","",'Input Required'!F16/1) | I12: =IF('Input Required'!$B$3<>"READY","",'Input Required'!F16/1) | J12: =IF('Input Required'!$B$3<>"READY","",'Input Required'!F16/1) | K12: =IF('Input Required'!$B$3<>"READY","",'Input Required'!F16/1) | L12: Interest-bearing debt | M12: 590
A13: Commercial FCFF | B13: =IF('Biotech Model'!$B$4<>"READY","",B11*B12) | C13: =IF('Biotech Model'!$B$4<>"READY","",C11*C12) | D13: =IF('Biotech Model'!$B$4<>"READY","",D11*D12) | E13: =IF('Biotech Model'!$B$4<>"READY","",E11*E12) | F13: =IF('Biotech Model'!$B$4<>"READY","",F11*F12) | G13: =IF('Biotech Model'!$B$4<>"READY","",G11*G12) | H13: =IF('Biotech Model'!$B$4<>"READY","",H11*H12) | I13: =IF('Biotech Model'!$B$4<>"READY","",I11*I12) | ... K13: =IF('Biotech Model'!$B$4<>"READY","",K11*K12) | L13: Equity weight | M13: =IFERROR(M11/(M11+M12),1) -> 0.99228242
A14: Discount factor | B14: =IF('Biotech Model'!$B$4<>"READY","",1/(1+$M$15)^1) | C14: =IF('Biotech Model'!$B$4<>"READY","",1/(1+$M$15)^2) | D14: =IF('Biotech Model'!$B$4<>"READY","",1/(1+$M$15)^3) | E14: =IF('Biotech Model'!$B$4<>"READY","",1/(1+$M$15)^4) | F14: =IF('Biotech Model'!$B$4<>"READY","",1/(1+$M$15)^5) | G14: =IF('Biotech Model'!$B$4<>"READY","",1/(1+$M$15)^6) | H14: =IF('Biotech Model'!$B$4<>"READY","",1/(1+$M$15)^7) | I14: =IF('Biotech Model'!$B$4<>"READY","",1/(1+$M$15)^8) | J14: =IF('Biotech Model'!$B$4<>"READY","",1/(1+$M$15)^9) | K14: =IF('Biotech Model'!$B$4<>"READY","",1/(1+$M$15)^10) | L14: Debt weight | M14: =IFERROR(M12/(M11+M12),0) -> 0.0077175822
A15: PV of commercial FCFF | B15: =IF('Biotech Model'!$B$4<>"READY","",B13*B14) | C15: =IF('Biotech Model'!$B$4<>"READY","",C13*C14) | D15: =IF('Biotech Model'!$B$4<>"READY","",D13*D14) | E15: =IF('Biotech Model'!$B$4<>"READY","",E13*E14) | F15: =IF('Biotech Model'!$B$4<>"READY","",F13*F14) | G15: =IF('Biotech Model'!$B$4<>"READY","",G13*G14) | H15: =IF('Biotech Model'!$B$4<>"READY","",H13*H14) | I15: =IF('Biotech Model'!$B$4<>"READY","",I13*I14) | ... K15: =IF('Biotech Model'!$B$4<>"READY","",K13*K14) | L15: WACC | M15: =IF('Input Required'!$B$3<>"READY","",M8*M13+M9*(1-M10)*M14)
L16: Terminal growth | M16: =IF('Input Required'!$B$3<>"READY","",'Input Required'!F196/1)
L18: Commercial franchise terminal value | M18: =IF('Biotech Model'!$B$4<>"READY","",IF($M$15<=$M$16,"",$K$13*(1+$M$16)/($M$15-$M$16)))
L19: PV of commercial terminal value | M19: =IF('Biotech Model'!$B$4<>"READY","",IF($M$15<=$M$16,"",$M$18/(1+$M$15)^10))
L20: PV of commercial forecast | M20: =IF('Biotech Model'!$B$4<>"READY","",SUM($B$15:$K$15))
L21: Commercial franchise enterprise value | M21: =IF('Biotech Model'!$B$4<>"READY","",IF($M$15<=$M$16,"",$M$19+$M$20))
L22: Individually forecast late-stage asset rNPV | M22: ='Pipeline Valuation'!$B$3
L23: Other SEC-listed pipeline asset rNPV | M23: ='Pipeline Valuation'!$B$4
L24: Pipeline rNPV outside the SEC-mapped asset inventory | M24: =IF('Input Required'!$B$3<>"READY","",'Input Required'!F193/1000000)
L25: Enterprise value | M25: =IF('Biotech Model'!$B$4<>"READY","",IF($M$15<=$M$16,"",SUM(M21:M24)))
L26: Add cash and cash equivalents | M26: 2595
L27: Add marketable securities / nonoperating assets | M27: 0
L28: Less interest-bearing debt | M28: 590
L29: Less noncontrolling interest | M29: 0
L30: Less preferred equity | M30: 0
L31: Common-equity value | M31: =IF('Biotech Model'!$B$4<>"READY","",IF($M$15<=$M$16,"",M25+M26+M27-M28-M29-M30))
L32: Diluted shares (millions) | M32: 389
L33: Implied value per share | M33: =IF('Biotech Model'!$B$4<>"READY","",IF($M$15<=$M$16,"",IFERROR(M31/M32,0)))
L34: Current share price | M34: 190.01
L35: Implied upside / (downside) | M35: =IF('Biotech Model'!$B$4<>"READY","",IF($M$15<=$M$16,"",IFERROR(M33/M34-1,0)))
A37: Formula guide: Commercial revenue = prior year × (1 + growth). Late-stage asset FCFF = sales × PoS × retained share × post-tax margin. Asset rNPV = discounted FCFF − included development-cost PV. Early, paused, and other SEC-listed programs use explicit include controls and analyst-entered PVs; those PVs stay fixed in sensitivity. Unmapped pipeline is separate.
A39: Sensitivity: implied value per share
A40: WACC / terminal growth | B40: =IF('Biotech Model'!$B$4<>"READY","",MAX(0,$M$16+(-0.01))) | C40: =IF('Biotech Model'!$B$4<>"READY","",MAX(0,$M$16+(-0.005))) | D40: =IF('Biotech Model'!$B$4<>"READY","",MAX(0,$M$16+(0))) | E40: =IF('Biotech Model'!$B$4<>"READY","",MAX(0,$M$16+(0.005))) | F40: =IF('Biotech Model'!$B$4<>"READY","",MAX(0,$M$16+(0.01)))
A41: =IF('Biotech Model'!$B$4<>"READY","",$M$15+(-0.02)) | B41: =IF('Biotech Model'!$B$4<>"READY","",IF(OR($A41<2%,$A41>50%,B$40>10%,$A41<=B$40+0.5%),"",($B$13/(1+$A$41)^1+$C$13/(1+$A$41)^2+$D$13/(1+$A$41)^3+$E$13/(1+$A$41)^4+$F$13/(1+$A$41)^5+$G$13/(1+$A$41)^6+$H$13/(1+$A$41)^7+$I$13/(1+$A$41)^8+$J$13/(1+$A$41)^9+$K$13/(1+$A$41)^10+$K$13*(1+B$40)/($A41-B$40)/(1+$A41)^10+'Pipeline Valuation'!$P$4/(1+$A$41)^1+'Pipeline Valuation'!$Q$4/(1+$A$41)^2+'Pipeline Valuation'!$R$4/(1+$A$41)^3+'Pipeline Valuation'!$S$4/(1+$A$41)^4+'Pipeline Valuation'!$T$4/(1+$A$41)^5+'Pipeline Valuation'!$U$4/(1+$A$41)^6+'Pipeline Valuation'!$V$4/(1+$A$41)^7+'Pipeline Valuation'!$W$4/(1+$A$41)^8+'Pipeline Valuation'!$X$4/(1+$A$41)^9+'Pipeline Valuation'!$Y$4/(1+$A$41)^10+'Pipeline Valuation'!$Z$4/(1+$A$41)^11+'Pipeline Valuation'!$AA$4/(1+$A$41)^12+'Pipeline Valuation'!$AB$4/(1+$A$41)^13+'Pipeline Valuation'!$AC$4/(1+$A$41)^14+'Pipeline Valuation'!$AD$4/(1+$A$41)^15+'Pipeline Valuation'!$AE$4/(1+$A$41)^16+'Pipeline Valuation'!$AF$4/(1+$A$41)^17+'Pipeline Valuation'!$AG$4/(1+$A$41)^18+'Pipeline Valuation'!$AH$4/(1+$A$41)^19+'Pipeline Valuation'!$AI$4/(1+$A$41)^20+'Pipeline Valuation'!$AJ$4/(1+$A$41)^21+'Pipeline Valuation'!$AK$4/(1+$A$41)^22+'Pipeline Valuation'!$AL$4/(1+$A$41)^23+'Pipeline Valuation'!$AM$4/(1+$A$41)^24+'Pipeline Valuation'!$AN$4/(1+$A$41)^25+'Pipeline Valuation'!$AO$4/(1+$A$41)^26+'Pipeline Valuation'!$AP$4/(1+$A$41)^27+'Pipeline Valuation'!$AQ$4/(1+$A$41)^28+'Pipeline Valuation'!$AR$4/(1+$A$41)^29+'Pipeline Valuation'!$AS$4/(1+$A$41)^30+'Pipeline Valuation'!$AT$4/(1+$A$41)^31+'Pipeline Valuation'!$AU$4/(1+$A$41)^32+'Pipeline Valuation'!$AV$4/(1+$A$41)^33+'Pipeline Valuation'!$AW$4/(1+$A$41)^34+'Pipeline Valuation'!$AX$4/(1+$A$41)^35-SUMPRODUCT('Pipeline Valuation'!$E$6:$E$19,'Pipeline Valuation'!$N$6:$N$19)+'Pipeline Valuation'!$B$4+$M$24+$M$26+$M$27-$M$28-$M$29-$M$30)/$M$32)) | C41: =IF('Biotech Model'!$B$4<>"READY","",IF(OR($A41<2%,$A41>50%,C$40>10%,$A41<=C$40+0.5%),"",($B$13/(1+$A$41)^1+$C$13/(1+$A$41)^2+$D$13/(1+$A$41)^3+$E$13/(1+$A$41)^4+$F$13/(1+$A$41)^5+$G$13/(1+$A$41)^6+$H$13/(1+$A$41)^7+$I$13/(1+$A$41)^8+$J$13/(1+$A$41)^9+$K$13/(1+$A$41)^10+$K$13*(1+C$40)/($A41-C$40)/(1+$A41)^10+'Pipeline Valuation'!$P$4/(1+$A$41)^1+'Pipeline Valuation'!$Q$4/(1+$A$41)^2+'Pipeline Valuation'!$R$4/(1+$A$41)^3+'Pipeline Valuation'!$S$4/(1+$A$41)^4+'Pipeline Valuation'!$T$4/(1+$A$41)^5+'Pipeline Valuation'!$U$4/(1+$A$41)^6+'Pipeline Valuation'!$V$4/(1+$A$41)^7+'Pipeline Valuation'!$W$4/(1+$A$41)^8+'Pipeline Valuation'!$X$4/(1+$A$41)^9+'Pipeline Valuation'!$Y$4/(1+$A$41)^10+'Pipeline Valuation'!$Z$4/(1+$A$41)^11+'Pipeline Valuation'!$AA$4/(1+$A$41)^12+'Pipeline Valuation'!$AB$4/(1+$A$41)^13+'Pipeline Valuation'!$AC$4/(1+$A$41)^14+'Pipeline Valuation'!$AD$4/(1+$A$41)^15+'Pipeline Valuation'!$AE$4/(1+$A$41)^16+'Pipeline Valuation'!$AF$4/(1+$A$41)^17+'Pipeline Valuation'!$AG$4/(1+$A$41)^18+'Pipeline Valuation'!$AH$4/(1+$A$41)^19+'Pipeline Valuation'!$AI$4/(1+$A$41)^20+'Pipeline Valuation'!$AJ$4/(1+$A$41)^21+'Pipeline Valuation'!$AK$4/(1+$A$41)^22+'Pipeline Valuation'!$AL$4/(1+$A$41)^23+'Pipeline Valuation'!$AM$4/(1+$A$41)^24+'Pipeline Valuation'!$AN$4/(1+$A$41)^25+'Pipeline Valuation'!$AO$4/(1+$A$41)^26+'Pipeline Valuation'!$AP$4/(1+$A$41)^27+'Pipeline Valuation'!$AQ$4/(1+$A$41)^28+'Pipeline Valuation'!$AR$4/(1+$A$41)^29+'Pipeline Valuation'!$AS$4/(1+$A$41)^30+'Pipeline Valuation'!$AT$4/(1+$A$41)^31+'Pipeline Valuation'!$AU$4/(1+$A$41)^32+'Pipeline Valuation'!$AV$4/(1+$A$41)^33+'Pipeline Valuation'!$AW$4/(1+$A$41)^34+'Pipeline Valuation'!$AX$4/(1+$A$41)^35-SUMPRODUCT('Pipeline Valuation'!$E$6:$E$19,'Pipeline Valuation'!$N$6:$N$19)+'Pipeline Valuation'!$B$4+$M$24+$M$26+$M$27-$M$28-$M$29-$M$30)/$M$32)) | D41: =IF('Biotech Model'!$B$4<>"READY","",IF(OR($A41<2%,$A41>50%,D$40>10%,$A41<=D$40+0.5%),"",($B$13/(1+$A$41)^1+$C$13/(1+$A$41)^2+$D$13/(1+$A$41)^3+$E$13/(1+$A$41)^4+$F$13/(1+$A$41)^5+$G$13/(1+$A$41)^6+$H$13/(1+$A$41)^7+$I$13/(1+$A$41)^8+$J$13/(1+$A$41)^9+$K$13/(1+$A$41)^10+$K$13*(1+D$40)/($A41-D$40)/(1+$A41)^10+'Pipeline Valuation'!$P$4/(1+$A$41)^1+'Pipeline Valuation'!$Q$4/(1+$A$41)^2+'Pipeline Valuation'!$R$4/(1+$A$41)^3+'Pipeline Valuation'!$S$4/(1+$A$41)^4+'Pipeline Valuation'!$T$4/(1+$A$41)^5+'Pipeline Valuation'!$U$4/(1+$A$41)^6+'Pipeline Valuation'!$V$4/(1+$A$41)^7+'Pipeline Valuation'!$W$4/(1+$A$41)^8+'Pipeline Valuation'!$X$4/(1+$A$41)^9+'Pipeline Valuation'!$Y$4/(1+$A$41)^10+'Pipeline Valuation'!$Z$4/(1+$A$41)^11+'Pipeline Valuation'!$AA$4/(1+$A$41)^12+'Pipeline Valuation'!$AB$4/(1+$A$41)^13+'Pipeline Valuation'!$AC$4/(1+$A$41)^14+'Pipeline Valuation'!$AD$4/(1+$A$41)^15+'Pipeline Valuation'!$AE$4/(1+$A$41)^16+'Pipeline Valuation'!$AF$4/(1+$A$41)^17+'Pipeline Valuation'!$AG$4/(1+$A$41)^18+'Pipeline Valuation'!$AH$4/(1+$A$41)^19+'Pipeline Valuation'!$AI$4/(1+$A$41)^20+'Pipeline Valuation'!$AJ$4/(1+$A$41)^21+'Pipeline Valuation'!$AK$4/(1+$A$41)^22+'Pipeline Valuation'!$AL$4/(1+$A$41)^23+'Pipeline Valuation'!$AM$4/(1+$A$41)^24+'Pipeline Valuation'!$AN$4/(1+$A$41)^25+'Pipeline Valuation'!$AO$4/(1+$A$41)^26+'Pipeline Valuation'!$AP$4/(1+$A$41)^27+'Pipeline Valuation'!$AQ$4/(1+$A$41)^28+'Pipeline Valuation'!$AR$4/(1+$A$41)^29+'Pipeline Valuation'!$AS$4/(1+$A$41)^30+'Pipeline Valuation'!$AT$4/(1+$A$41)^31+'Pipeline Valuation'!$AU$4/(1+$A$41)^32+'Pipeline Valuation'!$AV$4/(1+$A$41)^33+'Pipeline Valuation'!$AW$4/(1+$A$41)^34+'Pipeline Valuation'!$AX$4/(1+$A$41)^35-SUMPRODUCT('Pipeline Valuation'!$E$6:$E$19,'Pipeline Valuation'!$N$6:$N$19)+'Pipeline Valuation'!$B$4+$M$24+$M$26+$M$27-$M$28-$M$29-$M$30)/$M$32)) | E41: =IF('Biotech Model'!$B$4<>"READY","",IF(OR($A41<2%,$A41>50%,E$40>10%,$A41<=E$40+0.5%),"",($B$13/(1+$A$41)^1+$C$13/(1+$A$41)^2+$D$13/(1+$A$41)^3+$E$13/(1+$A$41)^4+$F$13/(1+$A$41)^5+$G$13/(1+$A$41)^6+$H$13/(1+$A$41)^7+$I$13/(1+$A$41)^8+$J$13/(1+$A$41)^9+$K$13/(1+$A$41)^10+$K$13*(1+E$40)/($A41-E$40)/(1+$A41)^10+'Pipeline Valuation'!$P$4/(1+$A$41)^1+'Pipeline Valuation'!$Q$4/(1+$A$41)^2+'Pipeline Valuation'!$R$4/(1+$A$41)^3+'Pipeline Valuation'!$S$4/(1+$A$41)^4+'Pipeline Valuation'!$T$4/(1+$A$41)^5+'Pipeline Valuation'!$U$4/(1+$A$41)^6+'Pipeline Valuation'!$V$4/(1+$A$41)^7+'Pipeline Valuation'!$W$4/(1+$A$41)^8+'Pipeline Valuation'!$X$4/(1+$A$41)^9+'Pipeline Valuation'!$Y$4/(1+$A$41)^10+'Pipeline Valuation'!$Z$4/(1+$A$41)^11+'Pipeline Valuation'!$AA$4/(1+$A$41)^12+'Pipeline Valuation'!$AB$4/(1+$A$41)^13+'Pipeline Valuation'!$AC$4/(1+$A$41)^14+'Pipeline Valuation'!$AD$4/(1+$A$41)^15+'Pipeline Valuation'!$AE$4/(1+$A$41)^16+'Pipeline Valuation'!$AF$4/(1+$A$41)^17+'Pipeline Valuation'!$AG$4/(1+$A$41)^18+'Pipeline Valuation'!$AH$4/(1+$A$41)^19+'Pipeline Valuation'!$AI$4/(1+$A$41)^20+'Pipeline Valuation'!$AJ$4/(1+$A$41)^21+'Pipeline Valuation'!$AK$4/(1+$A$41)^22+'Pipeline Valuation'!$AL$4/(1+$A$41)^23+'Pipeline Valuation'!$AM$4/(1+$A$41)^24+'Pipeline Valuation'!$AN$4/(1+$A$41)^25+'Pipeline Valuation'!$AO$4/(1+$A$41)^26+'Pipeline Valuation'!$AP$4/(1+$A$41)^27+'Pipeline Valuation'!$AQ$4/(1+$A$41)^28+'Pipeline Valuation'!$AR$4/(1+$A$41)^29+'Pipeline Valuation'!$AS$4/(1+$A$41)^30+'Pipeline Valuation'!$AT$4/(1+$A$41)^31+'Pipeline Valuation'!$AU$4/(1+$A$41)^32+'Pipeline Valuation'!$AV$4/(1+$A$41)^33+'Pipeline Valuation'!$AW$4/(1+$A$41)^34+'Pipeline Valuation'!$AX$4/(1+$A$41)^35-SUMPRODUCT('Pipeline Valuation'!$E$6:$E$19,'Pipeline Valuation'!$N$6:$N$19)+'Pipeline Valuation'!$B$4+$M$24+$M$26+$M$27-$M$28-$M$29-$M$30)/$M$32)) | F41: =IF('Biotech Model'!$B$4<>"READY","",IF(OR($A41<2%,$A41>50%,F$40>10%,$A41<=F$40+0.5%),"",($B$13/(1+$A$41)^1+$C$13/(1+$A$41)^2+$D$13/(1+$A$41)^3+$E$13/(1+$A$41)^4+$F$13/(1+$A$41)^5+$G$13/(1+$A$41)^6+$H$13/(1+$A$41)^7+$I$13/(1+$A$41)^8+$J$13/(1+$A$41)^9+$K$13/(1+$A$41)^10+$K$13*(1+F$40)/($A41-F$40)/(1+$A41)^10+'Pipeline Valuation'!$P$4/(1+$A$41)^1+'Pipeline Valuation'!$Q$4/(1+$A$41)^2+'Pipeline Valuation'!$R$4/(1+$A$41)^3+'Pipeline Valuation'!$S$4/(1+$A$41)^4+'Pipeline Valuation'!$T$4/(1+$A$41)^5+'Pipeline Valuation'!$U$4/(1+$A$41)^6+'Pipeline Valuation'!$V$4/(1+$A$41)^7+'Pipeline Valuation'!$W$4/(1+$A$41)^8+'Pipeline Valuation'!$X$4/(1+$A$41)^9+'Pipeline Valuation'!$Y$4/(1+$A$41)^10+'Pipeline Valuation'!$Z$4/(1+$A$41)^11+'Pipeline Valuation'!$AA$4/(1+$A$41)^12+'Pipeline Valuation'!$AB$4/(1+$A$41)^13+'Pipeline Valuation'!$AC$4/(1+$A$41)^14+'Pipeline Valuation'!$AD$4/(1+$A$41)^15+'Pipeline Valuation'!$AE$4/(1+$A$41)^16+'Pipeline Valuation'!$AF$4/(1+$A$41)^17+'Pipeline Valuation'!$AG$4/(1+$A$41)^18+'Pipeline Valuation'!$AH$4/(1+$A$41)^19+'Pipeline Valuation'!$AI$4/(1+$A$41)^20+'Pipeline Valuation'!$AJ$4/(1+$A$41)^21+'Pipeline Valuation'!$AK$4/(1+$A$41)^22+'Pipeline Valuation'!$AL$4/(1+$A$41)^23+'Pipeline Valuation'!$AM$4/(1+$A$41)^24+'Pipeline Valuation'!$AN$4/(1+$A$41)^25+'Pipeline Valuation'!$AO$4/(1+$A$41)^26+'Pipeline Valuation'!$AP$4/(1+$A$41)^27+'Pipeline Valuation'!$AQ$4/(1+$A$41)^28+'Pipeline Valuation'!$AR$4/(1+$A$41)^29+'Pipeline Valuation'!$AS$4/(1+$A$41)^30+'Pipeline Valuation'!$AT$4/(1+$A$41)^31+'Pipeline Valuation'!$AU$4/(1+$A$41)^32+'Pipeline Valuation'!$AV$4/(1+$A$41)^33+'Pipeline Valuation'!$AW$4/(1+$A$41)^34+'Pipeline Valuation'!$AX$4/(1+$A$41)^35-SUMPRODUCT('Pipeline Valuation'!$E$6:$E$19,'Pipeline Valuation'!$N$6:$N$19)+'Pipeline Valuation'!$B$4+$M$24+$M$26+$M$27-$M$28-$M$29-$M$30)/$M$32))
A42: =IF('Biotech Model'!$B$4<>"READY","",$M$15+(-0.01)) | B42: =IF('Biotech Model'!$B$4<>"READY","",IF(OR($A42<2%,$A42>50%,B$40>10%,$A42<=B$40+0.5%),"",($B$13/(1+$A$42)^1+$C$13/(1+$A$42)^2+$D$13/(1+$A$42)^3+$E$13/(1+$A$42)^4+$F$13/(1+$A$42)^5+$G$13/(1+$A$42)^6+$H$13/(1+$A$42)^7+$I$13/(1+$A$42)^8+$J$13/(1+$A$42)^9+$K$13/(1+$A$42)^10+$K$13*(1+B$40)/($A42-B$40)/(1+$A42)^10+'Pipeline Valuation'!$P$4/(1+$A$42)^1+'Pipeline Valuation'!$Q$4/(1+$A$42)^2+'Pipeline Valuation'!$R$4/(1+$A$42)^3+'Pipeline Valuation'!$S$4/(1+$A$42)^4+'Pipeline Valuation'!$T$4/(1+$A$42)^5+'Pipeline Valuation'!$U$4/(1+$A$42)^6+'Pipeline Valuation'!$V$4/(1+$A$42)^7+'Pipeline Valuation'!$W$4/(1+$A$42)^8+'Pipeline Valuation'!$X$4/(1+$A$42)^9+'Pipeline Valuation'!$Y$4/(1+$A$42)^10+'Pipeline Valuation'!$Z$4/(1+$A$42)^11+'Pipeline Valuation'!$AA$4/(1+$A$42)^12+'Pipeline Valuation'!$AB$4/(1+$A$42)^13+'Pipeline Valuation'!$AC$4/(1+$A$42)^14+'Pipeline Valuation'!$AD$4/(1+$A$42)^15+'Pipeline Valuation'!$AE$4/(1+$A$42)^16+'Pipeline Valuation'!$AF$4/(1+$A$42)^17+'Pipeline Valuation'!$AG$4/(1+$A$42)^18+'Pipeline Valuation'!$AH$4/(1+$A$42)^19+'Pipeline Valuation'!$AI$4/(1+$A$42)^20+'Pipeline Valuation'!$AJ$4/(1+$A$42)^21+'Pipeline Valuation'!$AK$4/(1+$A$42)^22+'Pipeline Valuation'!$AL$4/(1+$A$42)^23+'Pipeline Valuation'!$AM$4/(1+$A$42)^24+'Pipeline Valuation'!$AN$4/(1+$A$42)^25+'Pipeline Valuation'!$AO$4/(1+$A$42)^26+'Pipeline Valuation'!$AP$4/(1+$A$42)^27+'Pipeline Valuation'!$AQ$4/(1+$A$42)^28+'Pipeline Valuation'!$AR$4/(1+$A$42)^29+'Pipeline Valuation'!$AS$4/(1+$A$42)^30+'Pipeline Valuation'!$AT$4/(1+$A$42)^31+'Pipeline Valuation'!$AU$4/(1+$A$42)^32+'Pipeline Valuation'!$AV$4/(1+$A$42)^33+'Pipeline Valuation'!$AW$4/(1+$A$42)^34+'Pipeline Valuation'!$AX$4/(1+$A$42)^35-SUMPRODUCT('Pipeline Valuation'!$E$6:$E$19,'Pipeline Valuation'!$N$6:$N$19)+'Pipeline Valuation'!$B$4+$M$24+$M$26+$M$27-$M$28-$M$29-$M$30)/$M$32)) | C42: =IF('Biotech Model'!$B$4<>"READY","",IF(OR($A42<2%,$A42>50%,C$40>10%,$A42<=C$40+0.5%),"",($B$13/(1+$A$42)^1+$C$13/(1+$A$42)^2+$D$13/(1+$A$42)^3+$E$13/(1+$A$42)^4+$F$13/(1+$A$42)^5+$G$13/(1+$A$42)^6+$H$13/(1+$A$42)^7+$I$13/(1+$A$42)^8+$J$13/(1+$A$42)^9+$K$13/(1+$A$42)^10+$K$13*(1+C$40)/($A42-C$40)/(1+$A42)^10+'Pipeline Valuation'!$P$4/(1+$A$42)^1+'Pipeline Valuation'!$Q$4/(1+$A$42)^2+'Pipeline Valuation'!$R$4/(1+$A$42)^3+'Pipeline Valuation'!$S$4/(1+$A$42)^4+'Pipeline Valuation'!$T$4/(1+$A$42)^5+'Pipeline Valuation'!$U$4/(1+$A$42)^6+'Pipeline Valuation'!$V$4/(1+$A$42)^7+'Pipeline Valuation'!$W$4/(1+$A$42)^8+'Pipeline Valuation'!$X$4/(1+$A$42)^9+'Pipeline Valuation'!$Y$4/(1+$A$42)^10+'Pipeline Valuation'!$Z$4/(1+$A$42)^11+'Pipeline Valuation'!$AA$4/(1+$A$42)^12+'Pipeline Valuation'!$AB$4/(1+$A$42)^13+'Pipeline Valuation'!$AC$4/(1+$A$42)^14+'Pipeline Valuation'!$AD$4/(1+$A$42)^15+'Pipeline Valuation'!$AE$4/(1+$A$42)^16+'Pipeline Valuation'!$AF$4/(1+$A$42)^17+'Pipeline Valuation'!$AG$4/(1+$A$42)^18+'Pipeline Valuation'!$AH$4/(1+$A$42)^19+'Pipeline Valuation'!$AI$4/(1+$A$42)^20+'Pipeline Valuation'!$AJ$4/(1+$A$42)^21+'Pipeline Valuation'!$AK$4/(1+$A$42)^22+'Pipeline Valuation'!$AL$4/(1+$A$42)^23+'Pipeline Valuation'!$AM$4/(1+$A$42)^24+'Pipeline Valuation'!$AN$4/(1+$A$42)^25+'Pipeline Valuation'!$AO$4/(1+$A$42)^26+'Pipeline Valuation'!$AP$4/(1+$A$42)^27+'Pipeline Valuation'!$AQ$4/(1+$A$42)^28+'Pipeline Valuation'!$AR$4/(1+$A$42)^29+'Pipeline Valuation'!$AS$4/(1+$A$42)^30+'Pipeline Valuation'!$AT$4/(1+$A$42)^31+'Pipeline Valuation'!$AU$4/(1+$A$42)^32+'Pipeline Valuation'!$AV$4/(1+$A$42)^33+'Pipeline Valuation'!$AW$4/(1+$A$42)^34+'Pipeline Valuation'!$AX$4/(1+$A$42)^35-SUMPRODUCT('Pipeline Valuation'!$E$6:$E$19,'Pipeline Valuation'!$N$6:$N$19)+'Pipeline Valuation'!$B$4+$M$24+$M$26+$M$27-$M$28-$M$29-$M$30)/$M$32)) | D42: =IF('Biotech Model'!$B$4<>"READY","",IF(OR($A42<2%,$A42>50%,D$40>10%,$A42<=D$40+0.5%),"",($B$13/(1+$A$42)^1+$C$13/(1+$A$42)^2+$D$13/(1+$A$42)^3+$E$13/(1+$A$42)^4+$F$13/(1+$A$42)^5+$G$13/(1+$A$42)^6+$H$13/(1+$A$42)^7+$I$13/(1+$A$42)^8+$J$13/(1+$A$42)^9+$K$13/(1+$A$42)^10+$K$13*(1+D$40)/($A42-D$40)/(1+$A42)^10+'Pipeline Valuation'!$P$4/(1+$A$42)^1+'Pipeline Valuation'!$Q$4/(1+$A$42)^2+'Pipeline Valuation'!$R$4/(1+$A$42)^3+'Pipeline Valuation'!$S$4/(1+$A$42)^4+'Pipeline Valuation'!$T$4/(1+$A$42)^5+'Pipeline Valuation'!$U$4/(1+$A$42)^6+'Pipeline Valuation'!$V$4/(1+$A$42)^7+'Pipeline Valuation'!$W$4/(1+$A$42)^8+'Pipeline Valuation'!$X$4/(1+$A$42)^9+'Pipeline Valuation'!$Y$4/(1+$A$42)^10+'Pipeline Valuation'!$Z$4/(1+$A$42)^11+'Pipeline Valuation'!$AA$4/(1+$A$42)^12+'Pipeline Valuation'!$AB$4/(1+$A$42)^13+'Pipeline Valuation'!$AC$4/(1+$A$42)^14+'Pipeline Valuation'!$AD$4/(1+$A$42)^15+'Pipeline Valuation'!$AE$4/(1+$A$42)^16+'Pipeline Valuation'!$AF$4/(1+$A$42)^17+'Pipeline Valuation'!$AG$4/(1+$A$42)^18+'Pipeline Valuation'!$AH$4/(1+$A$42)^19+'Pipeline Valuation'!$AI$4/(1+$A$42)^20+'Pipeline Valuation'!$AJ$4/(1+$A$42)^21+'Pipeline Valuation'!$AK$4/(1+$A$42)^22+'Pipeline Valuation'!$AL$4/(1+$A$42)^23+'Pipeline Valuation'!$AM$4/(1+$A$42)^24+'Pipeline Valuation'!$AN$4/(1+$A$42)^25+'Pipeline Valuation'!$AO$4/(1+$A$42)^26+'Pipeline Valuation'!$AP$4/(1+$A$42)^27+'Pipeline Valuation'!$AQ$4/(1+$A$42)^28+'Pipeline Valuation'!$AR$4/(1+$A$42)^29+'Pipeline Valuation'!$AS$4/(1+$A$42)^30+'Pipeline Valuation'!$AT$4/(1+$A$42)^31+'Pipeline Valuation'!$AU$4/(1+$A$42)^32+'Pipeline Valuation'!$AV$4/(1+$A$42)^33+'Pipeline Valuation'!$AW$4/(1+$A$42)^34+'Pipeline Valuation'!$AX$4/(1+$A$42)^35-SUMPRODUCT('Pipeline Valuation'!$E$6:$E$19,'Pipeline Valuation'!$N$6:$N$19)+'Pipeline Valuation'!$B$4+$M$24+$M$26+$M$27-$M$28-$M$29-$M$30)/$M$32)) | E42: =IF('Biotech Model'!$B$4<>"READY","",IF(OR($A42<2%,$A42>50%,E$40>10%,$A42<=E$40+0.5%),"",($B$13/(1+$A$42)^1+$C$13/(1+$A$42)^2+$D$13/(1+$A$42)^3+$E$13/(1+$A$42)^4+$F$13/(1+$A$42)^5+$G$13/(1+$A$42)^6+$H$13/(1+$A$42)^7+$I$13/(1+$A$42)^8+$J$13/(1+$A$42)^9+$K$13/(1+$A$42)^10+$K$13*(1+E$40)/($A42-E$40)/(1+$A42)^10+'Pipeline Valuation'!$P$4/(1+$A$42)^1+'Pipeline Valuation'!$Q$4/(1+$A$42)^2+'Pipeline Valuation'!$R$4/(1+$A$42)^3+'Pipeline Valuation'!$S$4/(1+$A$42)^4+'Pipeline Valuation'!$T$4/(1+$A$42)^5+'Pipeline Valuation'!$U$4/(1+$A$42)^6+'Pipeline Valuation'!$V$4/(1+$A$42)^7+'Pipeline Valuation'!$W$4/(1+$A$42)^8+'Pipeline Valuation'!$X$4/(1+$A$42)^9+'Pipeline Valuation'!$Y$4/(1+$A$42)^10+'Pipeline Valuation'!$Z$4/(1+$A$42)^11+'Pipeline Valuation'!$AA$4/(1+$A$42)^12+'Pipeline Valuation'!$AB$4/(1+$A$42)^13+'Pipeline Valuation'!$AC$4/(1+$A$42)^14+'Pipeline Valuation'!$AD$4/(1+$A$42)^15+'Pipeline Valuation'!$AE$4/(1+$A$42)^16+'Pipeline Valuation'!$AF$4/(1+$A$42)^17+'Pipeline Valuation'!$AG$4/(1+$A$42)^18+'Pipeline Valuation'!$AH$4/(1+$A$42)^19+'Pipeline Valuation'!$AI$4/(1+$A$42)^20+'Pipeline Valuation'!$AJ$4/(1+$A$42)^21+'Pipeline Valuation'!$AK$4/(1+$A$42)^22+'Pipeline Valuation'!$AL$4/(1+$A$42)^23+'Pipeline Valuation'!$AM$4/(1+$A$42)^24+'Pipeline Valuation'!$AN$4/(1+$A$42)^25+'Pipeline Valuation'!$AO$4/(1+$A$42)^26+'Pipeline Valuation'!$AP$4/(1+$A$42)^27+'Pipeline Valuation'!$AQ$4/(1+$A$42)^28+'Pipeline Valuation'!$AR$4/(1+$A$42)^29+'Pipeline Valuation'!$AS$4/(1+$A$42)^30+'Pipeline Valuation'!$AT$4/(1+$A$42)^31+'Pipeline Valuation'!$AU$4/(1+$A$42)^32+'Pipeline Valuation'!$AV$4/(1+$A$42)^33+'Pipeline Valuation'!$AW$4/(1+$A$42)^34+'Pipeline Valuation'!$AX$4/(1+$A$42)^35-SUMPRODUCT('Pipeline Valuation'!$E$6:$E$19,'Pipeline Valuation'!$N$6:$N$19)+'Pipeline Valuation'!$B$4+$M$24+$M$26+$M$27-$M$28-$M$29-$M$30)/$M$32)) | F42: =IF('Biotech Model'!$B$4<>"READY","",IF(OR($A42<2%,$A42>50%,F$40>10%,$A42<=F$40+0.5%),"",($B$13/(1+$A$42)^1+$C$13/(1+$A$42)^2+$D$13/(1+$A$42)^3+$E$13/(1+$A$42)^4+$F$13/(1+$A$42)^5+$G$13/(1+$A$42)^6+$H$13/(1+$A$42)^7+$I$13/(1+$A$42)^8+$J$13/(1+$A$42)^9+$K$13/(1+$A$42)^10+$K$13*(1+F$40)/($A42-F$40)/(1+$A42)^10+'Pipeline Valuation'!$P$4/(1+$A$42)^1+'Pipeline Valuation'!$Q$4/(1+$A$42)^2+'Pipeline Valuation'!$R$4/(1+$A$42)^3+'Pipeline Valuation'!$S$4/(1+$A$42)^4+'Pipeline Valuation'!$T$4/(1+$A$42)^5+'Pipeline Valuation'!$U$4/(1+$A$42)^6+'Pipeline Valuation'!$V$4/(1+$A$42)^7+'Pipeline Valuation'!$W$4/(1+$A$42)^8+'Pipeline Valuation'!$X$4/(1+$A$42)^9+'Pipeline Valuation'!$Y$4/(1+$A$42)^10+'Pipeline Valuation'!$Z$4/(1+$A$42)^11+'Pipeline Valuation'!$AA$4/(1+$A$42)^12+'Pipeline Valuation'!$AB$4/(1+$A$42)^13+'Pipeline Valuation'!$AC$4/(1+$A$42)^14+'Pipeline Valuation'!$AD$4/(1+$A$42)^15+'Pipeline Valuation'!$AE$4/(1+$A$42)^16+'Pipeline Valuation'!$AF$4/(1+$A$42)^17+'Pipeline Valuation'!$AG$4/(1+$A$42)^18+'Pipeline Valuation'!$AH$4/(1+$A$42)^19+'Pipeline Valuation'!$AI$4/(1+$A$42)^20+'Pipeline Valuation'!$AJ$4/(1+$A$42)^21+'Pipeline Valuation'!$AK$4/(1+$A$42)^22+'Pipeline Valuation'!$AL$4/(1+$A$42)^23+'Pipeline Valuation'!$AM$4/(1+$A$42)^24+'Pipeline Valuation'!$AN$4/(1+$A$42)^25+'Pipeline Valuation'!$AO$4/(1+$A$42)^26+'Pipeline Valuation'!$AP$4/(1+$A$42)^27+'Pipeline Valuation'!$AQ$4/(1+$A$42)^28+'Pipeline Valuation'!$AR$4/(1+$A$42)^29+'Pipeline Valuation'!$AS$4/(1+$A$42)^30+'Pipeline Valuation'!$AT$4/(1+$A$42)^31+'Pipeline Valuation'!$AU$4/(1+$A$42)^32+'Pipeline Valuation'!$AV$4/(1+$A$42)^33+'Pipeline Valuation'!$AW$4/(1+$A$42)^34+'Pipeline Valuation'!$AX$4/(1+$A$42)^35-SUMPRODUCT('Pipeline Valuation'!$E$6:$E$19,'Pipeline Valuation'!$N$6:$N$19)+'Pipeline Valuation'!$B$4+$M$24+$M$26+$M$27-$M$28-$M$29-$M$30)/$M$32))
A43: =IF('Biotech Model'!$B$4<>"READY","",$M$15+(0)) | B43: =IF('Biotech Model'!$B$4<>"READY","",IF(OR($A43<2%,$A43>50%,B$40>10%,$A43<=B$40+0.5%),"",($B$13/(1+$A$43)^1+$C$13/(1+$A$43)^2+$D$13/(1+$A$43)^3+$E$13/(1+$A$43)^4+$F$13/(1+$A$43)^5+$G$13/(1+$A$43)^6+$H$13/(1+$A$43)^7+$I$13/(1+$A$43)^8+$J$13/(1+$A$43)^9+$K$13/(1+$A$43)^10+$K$13*(1+B$40)/($A43-B$40)/(1+$A43)^10+'Pipeline Valuation'!$P$4/(1+$A$43)^1+'Pipeline Valuation'!$Q$4/(1+$A$43)^2+'Pipeline Valuation'!$R$4/(1+$A$43)^3+'Pipeline Valuation'!$S$4/(1+$A$43)^4+'Pipeline Valuation'!$T$4/(1+$A$43)^5+'Pipeline Valuation'!$U$4/(1+$A$43)^6+'Pipeline Valuation'!$V$4/(1+$A$43)^7+'Pipeline Valuation'!$W$4/(1+$A$43)^8+'Pipeline Valuation'!$X$4/(1+$A$43)^9+'Pipeline Valuation'!$Y$4/(1+$A$43)^10+'Pipeline Valuation'!$Z$4/(1+$A$43)^11+'Pipeline Valuation'!$AA$4/(1+$A$43)^12+'Pipeline Valuation'!$AB$4/(1+$A$43)^13+'Pipeline Valuation'!$AC$4/(1+$A$43)^14+'Pipeline Valuation'!$AD$4/(1+$A$43)^15+'Pipeline Valuation'!$AE$4/(1+$A$43)^16+'Pipeline Valuation'!$AF$4/(1+$A$43)^17+'Pipeline Valuation'!$AG$4/(1+$A$43)^18+'Pipeline Valuation'!$AH$4/(1+$A$43)^19+'Pipeline Valuation'!$AI$4/(1+$A$43)^20+'Pipeline Valuation'!$AJ$4/(1+$A$43)^21+'Pipeline Valuation'!$AK$4/(1+$A$43)^22+'Pipeline Valuation'!$AL$4/(1+$A$43)^23+'Pipeline Valuation'!$AM$4/(1+$A$43)^24+'Pipeline Valuation'!$AN$4/(1+$A$43)^25+'Pipeline Valuation'!$AO$4/(1+$A$43)^26+'Pipeline Valuation'!$AP$4/(1+$A$43)^27+'Pipeline Valuation'!$AQ$4/(1+$A$43)^28+'Pipeline Valuation'!$AR$4/(1+$A$43)^29+'Pipeline Valuation'!$AS$4/(1+$A$43)^30+'Pipeline Valuation'!$AT$4/(1+$A$43)^31+'Pipeline Valuation'!$AU$4/(1+$A$43)^32+'Pipeline Valuation'!$AV$4/(1+$A$43)^33+'Pipeline Valuation'!$AW$4/(1+$A$43)^34+'Pipeline Valuation'!$AX$4/(1+$A$43)^35-SUMPRODUCT('Pipeline Valuation'!$E$6:$E$19,'Pipeline Valuation'!$N$6:$N$19)+'Pipeline Valuation'!$B$4+$M$24+$M$26+$M$27-$M$28-$M$29-$M$30)/$M$32)) | C43: =IF('Biotech Model'!$B$4<>"READY","",IF(OR($A43<2%,$A43>50%,C$40>10%,$A43<=C$40+0.5%),"",($B$13/(1+$A$43)^1+$C$13/(1+$A$43)^2+$D$13/(1+$A$43)^3+$E$13/(1+$A$43)^4+$F$13/(1+$A$43)^5+$G$13/(1+$A$43)^6+$H$13/(1+$A$43)^7+$I$13/(1+$A$43)^8+$J$13/(1+$A$43)^9+$K$13/(1+$A$43)^10+$K$13*(1+C$40)/($A43-C$40)/(1+$A43)^10+'Pipeline Valuation'!$P$4/(1+$A$43)^1+'Pipeline Valuation'!$Q$4/(1+$A$43)^2+'Pipeline Valuation'!$R$4/(1+$A$43)^3+'Pipeline Valuation'!$S$4/(1+$A$43)^4+'Pipeline Valuation'!$T$4/(1+$A$43)^5+'Pipeline Valuation'!$U$4/(1+$A$43)^6+'Pipeline Valuation'!$V$4/(1+$A$43)^7+'Pipeline Valuation'!$W$4/(1+$A$43)^8+'Pipeline Valuation'!$X$4/(1+$A$43)^9+'Pipeline Valuation'!$Y$4/(1+$A$43)^10+'Pipeline Valuation'!$Z$4/(1+$A$43)^11+'Pipeline Valuation'!$AA$4/(1+$A$43)^12+'Pipeline Valuation'!$AB$4/(1+$A$43)^13+'Pipeline Valuation'!$AC$4/(1+$A$43)^14+'Pipeline Valuation'!$AD$4/(1+$A$43)^15+'Pipeline Valuation'!$AE$4/(1+$A$43)^16+'Pipeline Valuation'!$AF$4/(1+$A$43)^17+'Pipeline Valuation'!$AG$4/(1+$A$43)^18+'Pipeline Valuation'!$AH$4/(1+$A$43)^19+'Pipeline Valuation'!$AI$4/(1+$A$43)^20+'Pipeline Valuation'!$AJ$4/(1+$A$43)^21+'Pipeline Valuation'!$AK$4/(1+$A$43)^22+'Pipeline Valuation'!$AL$4/(1+$A$43)^23+'Pipeline Valuation'!$AM$4/(1+$A$43)^24+'Pipeline Valuation'!$AN$4/(1+$A$43)^25+'Pipeline Valuation'!$AO$4/(1+$A$43)^26+'Pipeline Valuation'!$AP$4/(1+$A$43)^27+'Pipeline Valuation'!$AQ$4/(1+$A$43)^28+'Pipeline Valuation'!$AR$4/(1+$A$43)^29+'Pipeline Valuation'!$AS$4/(1+$A$43)^30+'Pipeline Valuation'!$AT$4/(1+$A$43)^31+'Pipeline Valuation'!$AU$4/(1+$A$43)^32+'Pipeline Valuation'!$AV$4/(1+$A$43)^33+'Pipeline Valuation'!$AW$4/(1+$A$43)^34+'Pipeline Valuation'!$AX$4/(1+$A$43)^35-SUMPRODUCT('Pipeline Valuation'!$E$6:$E$19,'Pipeline Valuation'!$N$6:$N$19)+'Pipeline Valuation'!$B$4+$M$24+$M$26+$M$27-$M$28-$M$29-$M$30)/$M$32)) | D43: =IF('Biotech Model'!$B$4<>"READY","",IF(OR($A43<2%,$A43>50%,D$40>10%,$A43<=D$40+0.5%),"",($B$13/(1+$A$43)^1+$C$13/(1+$A$43)^2+$D$13/(1+$A$43)^3+$E$13/(1+$A$43)^4+$F$13/(1+$A$43)^5+$G$13/(1+$A$43)^6+$H$13/(1+$A$43)^7+$I$13/(1+$A$43)^8+$J$13/(1+$A$43)^9+$K$13/(1+$A$43)^10+$K$13*(1+D$40)/($A43-D$40)/(1+$A43)^10+'Pipeline Valuation'!$P$4/(1+$A$43)^1+'Pipeline Valuation'!$Q$4/(1+$A$43)^2+'Pipeline Valuation'!$R$4/(1+$A$43)^3+'Pipeline Valuation'!$S$4/(1+$A$43)^4+'Pipeline Valuation'!$T$4/(1+$A$43)^5+'Pipeline Valuation'!$U$4/(1+$A$43)^6+'Pipeline Valuation'!$V$4/(1+$A$43)^7+'Pipeline Valuation'!$W$4/(1+$A$43)^8+'Pipeline Valuation'!$X$4/(1+$A$43)^9+'Pipeline Valuation'!$Y$4/(1+$A$43)^10+'Pipeline Valuation'!$Z$4/(1+$A$43)^11+'Pipeline Valuation'!$AA$4/(1+$A$43)^12+'Pipeline Valuation'!$AB$4/(1+$A$43)^13+'Pipeline Valuation'!$AC$4/(1+$A$43)^14+'Pipeline Valuation'!$AD$4/(1+$A$43)^15+'Pipeline Valuation'!$AE$4/(1+$A$43)^16+'Pipeline Valuation'!$AF$4/(1+$A$43)^17+'Pipeline Valuation'!$AG$4/(1+$A$43)^18+'Pipeline Valuation'!$AH$4/(1+$A$43)^19+'Pipeline Valuation'!$AI$4/(1+$A$43)^20+'Pipeline Valuation'!$AJ$4/(1+$A$43)^21+'Pipeline Valuation'!$AK$4/(1+$A$43)^22+'Pipeline Valuation'!$AL$4/(1+$A$43)^23+'Pipeline Valuation'!$AM$4/(1+$A$43)^24+'Pipeline Valuation'!$AN$4/(1+$A$43)^25+'Pipeline Valuation'!$AO$4/(1+$A$43)^26+'Pipeline Valuation'!$AP$4/(1+$A$43)^27+'Pipeline Valuation'!$AQ$4/(1+$A$43)^28+'Pipeline Valuation'!$AR$4/(1+$A$43)^29+'Pipeline Valuation'!$AS$4/(1+$A$43)^30+'Pipeline Valuation'!$AT$4/(1+$A$43)^31+'Pipeline Valuation'!$AU$4/(1+$A$43)^32+'Pipeline Valuation'!$AV$4/(1+$A$43)^33+'Pipeline Valuation'!$AW$4/(1+$A$43)^34+'Pipeline Valuation'!$AX$4/(1+$A$43)^35-SUMPRODUCT('Pipeline Valuation'!$E$6:$E$19,'Pipeline Valuation'!$N$6:$N$19)+'Pipeline Valuation'!$B$4+$M$24+$M$26+$M$27-$M$28-$M$29-$M$30)/$M$32)) | E43: =IF('Biotech Model'!$B$4<>"READY","",IF(OR($A43<2%,$A43>50%,E$40>10%,$A43<=E$40+0.5%),"",($B$13/(1+$A$43)^1+$C$13/(1+$A$43)^2+$D$13/(1+$A$43)^3+$E$13/(1+$A$43)^4+$F$13/(1+$A$43)^5+$G$13/(1+$A$43)^6+$H$13/(1+$A$43)^7+$I$13/(1+$A$43)^8+$J$13/(1+$A$43)^9+$K$13/(1+$A$43)^10+$K$13*(1+E$40)/($A43-E$40)/(1+$A43)^10+'Pipeline Valuation'!$P$4/(1+$A$43)^1+'Pipeline Valuation'!$Q$4/(1+$A$43)^2+'Pipeline Valuation'!$R$4/(1+$A$43)^3+'Pipeline Valuation'!$S$4/(1+$A$43)^4+'Pipeline Valuation'!$T$4/(1+$A$43)^5+'Pipeline Valuation'!$U$4/(1+$A$43)^6+'Pipeline Valuation'!$V$4/(1+$A$43)^7+'Pipeline Valuation'!$W$4/(1+$A$43)^8+'Pipeline Valuation'!$X$4/(1+$A$43)^9+'Pipeline Valuation'!$Y$4/(1+$A$43)^10+'Pipeline Valuation'!$Z$4/(1+$A$43)^11+'Pipeline Valuation'!$AA$4/(1+$A$43)^12+'Pipeline Valuation'!$AB$4/(1+$A$43)^13+'Pipeline Valuation'!$AC$4/(1+$A$43)^14+'Pipeline Valuation'!$AD$4/(1+$A$43)^15+'Pipeline Valuation'!$AE$4/(1+$A$43)^16+'Pipeline Valuation'!$AF$4/(1+$A$43)^17+'Pipeline Valuation'!$AG$4/(1+$A$43)^18+'Pipeline Valuation'!$AH$4/(1+$A$43)^19+'Pipeline Valuation'!$AI$4/(1+$A$43)^20+'Pipeline Valuation'!$AJ$4/(1+$A$43)^21+'Pipeline Valuation'!$AK$4/(1+$A$43)^22+'Pipeline Valuation'!$AL$4/(1+$A$43)^23+'Pipeline Valuation'!$AM$4/(1+$A$43)^24+'Pipeline Valuation'!$AN$4/(1+$A$43)^25+'Pipeline Valuation'!$AO$4/(1+$A$43)^26+'Pipeline Valuation'!$AP$4/(1+$A$43)^27+'Pipeline Valuation'!$AQ$4/(1+$A$43)^28+'Pipeline Valuation'!$AR$4/(1+$A$43)^29+'Pipeline Valuation'!$AS$4/(1+$A$43)^30+'Pipeline Valuation'!$AT$4/(1+$A$43)^31+'Pipeline Valuation'!$AU$4/(1+$A$43)^32+'Pipeline Valuation'!$AV$4/(1+$A$43)^33+'Pipeline Valuation'!$AW$4/(1+$A$43)^34+'Pipeline Valuation'!$AX$4/(1+$A$43)^35-SUMPRODUCT('Pipeline Valuation'!$E$6:$E$19,'Pipeline Valuation'!$N$6:$N$19)+'Pipeline Valuation'!$B$4+$M$24+$M$26+$M$27-$M$28-$M$29-$M$30)/$M$32)) | F43: =IF('Biotech Model'!$B$4<>"READY","",IF(OR($A43<2%,$A43>50%,F$40>10%,$A43<=F$40+0.5%),"",($B$13/(1+$A$43)^1+$C$13/(1+$A$43)^2+$D$13/(1+$A$43)^3+$E$13/(1+$A$43)^4+$F$13/(1+$A$43)^5+$G$13/(1+$A$43)^6+$H$13/(1+$A$43)^7+$I$13/(1+$A$43)^8+$J$13/(1+$A$43)^9+$K$13/(1+$A$43)^10+$K$13*(1+F$40)/($A43-F$40)/(1+$A43)^10+'Pipeline Valuation'!$P$4/(1+$A$43)^1+'Pipeline Valuation'!$Q$4/(1+$A$43)^2+'Pipeline Valuation'!$R$4/(1+$A$43)^3+'Pipeline Valuation'!$S$4/(1+$A$43)^4+'Pipeline Valuation'!$T$4/(1+$A$43)^5+'Pipeline Valuation'!$U$4/(1+$A$43)^6+'Pipeline Valuation'!$V$4/(1+$A$43)^7+'Pipeline Valuation'!$W$4/(1+$A$43)^8+'Pipeline Valuation'!$X$4/(1+$A$43)^9+'Pipeline Valuation'!$Y$4/(1+$A$43)^10+'Pipeline Valuation'!$Z$4/(1+$A$43)^11+'Pipeline Valuation'!$AA$4/(1+$A$43)^12+'Pipeline Valuation'!$AB$4/(1+$A$43)^13+'Pipeline Valuation'!$AC$4/(1+$A$43)^14+'Pipeline Valuation'!$AD$4/(1+$A$43)^15+'Pipeline Valuation'!$AE$4/(1+$A$43)^16+'Pipeline Valuation'!$AF$4/(1+$A$43)^17+'Pipeline Valuation'!$AG$4/(1+$A$43)^18+'Pipeline Valuation'!$AH$4/(1+$A$43)^19+'Pipeline Valuation'!$AI$4/(1+$A$43)^20+'Pipeline Valuation'!$AJ$4/(1+$A$43)^21+'Pipeline Valuation'!$AK$4/(1+$A$43)^22+'Pipeline Valuation'!$AL$4/(1+$A$43)^23+'Pipeline Valuation'!$AM$4/(1+$A$43)^24+'Pipeline Valuation'!$AN$4/(1+$A$43)^25+'Pipeline Valuation'!$AO$4/(1+$A$43)^26+'Pipeline Valuation'!$AP$4/(1+$A$43)^27+'Pipeline Valuation'!$AQ$4/(1+$A$43)^28+'Pipeline Valuation'!$AR$4/(1+$A$43)^29+'Pipeline Valuation'!$AS$4/(1+$A$43)^30+'Pipeline Valuation'!$AT$4/(1+$A$43)^31+'Pipeline Valuation'!$AU$4/(1+$A$43)^32+'Pipeline Valuation'!$AV$4/(1+$A$43)^33+'Pipeline Valuation'!$AW$4/(1+$A$43)^34+'Pipeline Valuation'!$AX$4/(1+$A$43)^35-SUMPRODUCT('Pipeline Valuation'!$E$6:$E$19,'Pipeline Valuation'!$N$6:$N$19)+'Pipeline Valuation'!$B$4+$M$24+$M$26+$M$27-$M$28-$M$29-$M$30)/$M$32))
A44: =IF('Biotech Model'!$B$4<>"READY","",$M$15+(0.01)) | B44: =IF('Biotech Model'!$B$4<>"READY","",IF(OR($A44<2%,$A44>50%,B$40>10%,$A44<=B$40+0.5%),"",($B$13/(1+$A$44)^1+$C$13/(1+$A$44)^2+$D$13/(1+$A$44)^3+$E$13/(1+$A$44)^4+$F$13/(1+$A$44)^5+$G$13/(1+$A$44)^6+$H$13/(1+$A$44)^7+$I$13/(1+$A$44)^8+$J$13/(1+$A$44)^9+$K$13/(1+$A$44)^10+$K$13*(1+B$40)/($A44-B$40)/(1+$A44)^10+'Pipeline Valuation'!$P$4/(1+$A$44)^1+'Pipeline Valuation'!$Q$4/(1+$A$44)^2+'Pipeline Valuation'!$R$4/(1+$A$44)^3+'Pipeline Valuation'!$S$4/(1+$A$44)^4+'Pipeline Valuation'!$T$4/(1+$A$44)^5+'Pipeline Valuation'!$U$4/(1+$A$44)^6+'Pipeline Valuation'!$V$4/(1+$A$44)^7+'Pipeline Valuation'!$W$4/(1+$A$44)^8+'Pipeline Valuation'!$X$4/(1+$A$44)^9+'Pipeline Valuation'!$Y$4/(1+$A$44)^10+'Pipeline Valuation'!$Z$4/(1+$A$44)^11+'Pipeline Valuation'!$AA$4/(1+$A$44)^12+'Pipeline Valuation'!$AB$4/(1+$A$44)^13+'Pipeline Valuation'!$AC$4/(1+$A$44)^14+'Pipeline Valuation'!$AD$4/(1+$A$44)^15+'Pipeline Valuation'!$AE$4/(1+$A$44)^16+'Pipeline Valuation'!$AF$4/(1+$A$44)^17+'Pipeline Valuation'!$AG$4/(1+$A$44)^18+'Pipeline Valuation'!$AH$4/(1+$A$44)^19+'Pipeline Valuation'!$AI$4/(1+$A$44)^20+'Pipeline Valuation'!$AJ$4/(1+$A$44)^21+'Pipeline Valuation'!$AK$4/(1+$A$44)^22+'Pipeline Valuation'!$AL$4/(1+$A$44)^23+'Pipeline Valuation'!$AM$4/(1+$A$44)^24+'Pipeline Valuation'!$AN$4/(1+$A$44)^25+'Pipeline Valuation'!$AO$4/(1+$A$44)^26+'Pipeline Valuation'!$AP$4/(1+$A$44)^27+'Pipeline Valuation'!$AQ$4/(1+$A$44)^28+'Pipeline Valuation'!$AR$4/(1+$A$44)^29+'Pipeline Valuation'!$AS$4/(1+$A$44)^30+'Pipeline Valuation'!$AT$4/(1+$A$44)^31+'Pipeline Valuation'!$AU$4/(1+$A$44)^32+'Pipeline Valuation'!$AV$4/(1+$A$44)^33+'Pipeline Valuation'!$AW$4/(1+$A$44)^34+'Pipeline Valuation'!$AX$4/(1+$A$44)^35-SUMPRODUCT('Pipeline Valuation'!$E$6:$E$19,'Pipeline Valuation'!$N$6:$N$19)+'Pipeline Valuation'!$B$4+$M$24+$M$26+$M$27-$M$28-$M$29-$M$30)/$M$32)) | C44: =IF('Biotech Model'!$B$4<>"READY","",IF(OR($A44<2%,$A44>50%,C$40>10%,$A44<=C$40+0.5%),"",($B$13/(1+$A$44)^1+$C$13/(1+$A$44)^2+$D$13/(1+$A$44)^3+$E$13/(1+$A$44)^4+$F$13/(1+$A$44)^5+$G$13/(1+$A$44)^6+$H$13/(1+$A$44)^7+$I$13/(1+$A$44)^8+$J$13/(1+$A$44)^9+$K$13/(1+$A$44)^10+$K$13*(1+C$40)/($A44-C$40)/(1+$A44)^10+'Pipeline Valuation'!$P$4/(1+$A$44)^1+'Pipeline Valuation'!$Q$4/(1+$A$44)^2+'Pipeline Valuation'!$R$4/(1+$A$44)^3+'Pipeline Valuation'!$S$4/(1+$A$44)^4+'Pipeline Valuation'!$T$4/(1+$A$44)^5+'Pipeline Valuation'!$U$4/(1+$A$44)^6+'Pipeline Valuation'!$V$4/(1+$A$44)^7+'Pipeline Valuation'!$W$4/(1+$A$44)^8+'Pipeline Valuation'!$X$4/(1+$A$44)^9+'Pipeline Valuation'!$Y$4/(1+$A$44)^10+'Pipeline Valuation'!$Z$4/(1+$A$44)^11+'Pipeline Valuation'!$AA$4/(1+$A$44)^12+'Pipeline Valuation'!$AB$4/(1+$A$44)^13+'Pipeline Valuation'!$AC$4/(1+$A$44)^14+'Pipeline Valuation'!$AD$4/(1+$A$44)^15+'Pipeline Valuation'!$AE$4/(1+$A$44)^16+'Pipeline Valuation'!$AF$4/(1+$A$44)^17+'Pipeline Valuation'!$AG$4/(1+$A$44)^18+'Pipeline Valuation'!$AH$4/(1+$A$44)^19+'Pipeline Valuation'!$AI$4/(1+$A$44)^20+'Pipeline Valuation'!$AJ$4/(1+$A$44)^21+'Pipeline Valuation'!$AK$4/(1+$A$44)^22+'Pipeline Valuation'!$AL$4/(1+$A$44)^23+'Pipeline Valuation'!$AM$4/(1+$A$44)^24+'Pipeline Valuation'!$AN$4/(1+$A$44)^25+'Pipeline Valuation'!$AO$4/(1+$A$44)^26+'Pipeline Valuation'!$AP$4/(1+$A$44)^27+'Pipeline Valuation'!$AQ$4/(1+$A$44)^28+'Pipeline Valuation'!$AR$4/(1+$A$44)^29+'Pipeline Valuation'!$AS$4/(1+$A$44)^30+'Pipeline Valuation'!$AT$4/(1+$A$44)^31+'Pipeline Valuation'!$AU$4/(1+$A$44)^32+'Pipeline Valuation'!$AV$4/(1+$A$44)^33+'Pipeline Valuation'!$AW$4/(1+$A$44)^34+'Pipeline Valuation'!$AX$4/(1+$A$44)^35-SUMPRODUCT('Pipeline Valuation'!$E$6:$E$19,'Pipeline Valuation'!$N$6:$N$19)+'Pipeline Valuation'!$B$4+$M$24+$M$26+$M$27-$M$28-$M$29-$M$30)/$M$32)) | D44: =IF('Biotech Model'!$B$4<>"READY","",IF(OR($A44<2%,$A44>50%,D$40>10%,$A44<=D$40+0.5%),"",($B$13/(1+$A$44)^1+$C$13/(1+$A$44)^2+$D$13/(1+$A$44)^3+$E$13/(1+$A$44)^4+$F$13/(1+$A$44)^5+$G$13/(1+$A$44)^6+$H$13/(1+$A$44)^7+$I$13/(1+$A$44)^8+$J$13/(1+$A$44)^9+$K$13/(1+$A$44)^10+$K$13*(1+D$40)/($A44-D$40)/(1+$A44)^10+'Pipeline Valuation'!$P$4/(1+$A$44)^1+'Pipeline Valuation'!$Q$4/(1+$A$44)^2+'Pipeline Valuation'!$R$4/(1+$A$44)^3+'Pipeline Valuation'!$S$4/(1+$A$44)^4+'Pipeline Valuation'!$T$4/(1+$A$44)^5+'Pipeline Valuation'!$U$4/(1+$A$44)^6+'Pipeline Valuation'!$V$4/(1+$A$44)^7+'Pipeline Valuation'!$W$4/(1+$A$44)^8+'Pipeline Valuation'!$X$4/(1+$A$44)^9+'Pipeline Valuation'!$Y$4/(1+$A$44)^10+'Pipeline Valuation'!$Z$4/(1+$A$44)^11+'Pipeline Valuation'!$AA$4/(1+$A$44)^12+'Pipeline Valuation'!$AB$4/(1+$A$44)^13+'Pipeline Valuation'!$AC$4/(1+$A$44)^14+'Pipeline Valuation'!$AD$4/(1+$A$44)^15+'Pipeline Valuation'!$AE$4/(1+$A$44)^16+'Pipeline Valuation'!$AF$4/(1+$A$44)^17+'Pipeline Valuation'!$AG$4/(1+$A$44)^18+'Pipeline Valuation'!$AH$4/(1+$A$44)^19+'Pipeline Valuation'!$AI$4/(1+$A$44)^20+'Pipeline Valuation'!$AJ$4/(1+$A$44)^21+'Pipeline Valuation'!$AK$4/(1+$A$44)^22+'Pipeline Valuation'!$AL$4/(1+$A$44)^23+'Pipeline Valuation'!$AM$4/(1+$A$44)^24+'Pipeline Valuation'!$AN$4/(1+$A$44)^25+'Pipeline Valuation'!$AO$4/(1+$A$44)^26+'Pipeline Valuation'!$AP$4/(1+$A$44)^27+'Pipeline Valuation'!$AQ$4/(1+$A$44)^28+'Pipeline Valuation'!$AR$4/(1+$A$44)^29+'Pipeline Valuation'!$AS$4/(1+$A$44)^30+'Pipeline Valuation'!$AT$4/(1+$A$44)^31+'Pipeline Valuation'!$AU$4/(1+$A$44)^32+'Pipeline Valuation'!$AV$4/(1+$A$44)^33+'Pipeline Valuation'!$AW$4/(1+$A$44)^34+'Pipeline Valuation'!$AX$4/(1+$A$44)^35-SUMPRODUCT('Pipeline Valuation'!$E$6:$E$19,'Pipeline Valuation'!$N$6:$N$19)+'Pipeline Valuation'!$B$4+$M$24+$M$26+$M$27-$M$28-$M$29-$M$30)/$M$32)) | E44: =IF('Biotech Model'!$B$4<>"READY","",IF(OR($A44<2%,$A44>50%,E$40>10%,$A44<=E$40+0.5%),"",($B$13/(1+$A$44)^1+$C$13/(1+$A$44)^2+$D$13/(1+$A$44)^3+$E$13/(1+$A$44)^4+$F$13/(1+$A$44)^5+$G$13/(1+$A$44)^6+$H$13/(1+$A$44)^7+$I$13/(1+$A$44)^8+$J$13/(1+$A$44)^9+$K$13/(1+$A$44)^10+$K$13*(1+E$40)/($A44-E$40)/(1+$A44)^10+'Pipeline Valuation'!$P$4/(1+$A$44)^1+'Pipeline Valuation'!$Q$4/(1+$A$44)^2+'Pipeline Valuation'!$R$4/(1+$A$44)^3+'Pipeline Valuation'!$S$4/(1+$A$44)^4+'Pipeline Valuation'!$T$4/(1+$A$44)^5+'Pipeline Valuation'!$U$4/(1+$A$44)^6+'Pipeline Valuation'!$V$4/(1+$A$44)^7+'Pipeline Valuation'!$W$4/(1+$A$44)^8+'Pipeline Valuation'!$X$4/(1+$A$44)^9+'Pipeline Valuation'!$Y$4/(1+$A$44)^10+'Pipeline Valuation'!$Z$4/(1+$A$44)^11+'Pipeline Valuation'!$AA$4/(1+$A$44)^12+'Pipeline Valuation'!$AB$4/(1+$A$44)^13+'Pipeline Valuation'!$AC$4/(1+$A$44)^14+'Pipeline Valuation'!$AD$4/(1+$A$44)^15+'Pipeline Valuation'!$AE$4/(1+$A$44)^16+'Pipeline Valuation'!$AF$4/(1+$A$44)^17+'Pipeline Valuation'!$AG$4/(1+$A$44)^18+'Pipeline Valuation'!$AH$4/(1+$A$44)^19+'Pipeline Valuation'!$AI$4/(1+$A$44)^20+'Pipeline Valuation'!$AJ$4/(1+$A$44)^21+'Pipeline Valuation'!$AK$4/(1+$A$44)^22+'Pipeline Valuation'!$AL$4/(1+$A$44)^23+'Pipeline Valuation'!$AM$4/(1+$A$44)^24+'Pipeline Valuation'!$AN$4/(1+$A$44)^25+'Pipeline Valuation'!$AO$4/(1+$A$44)^26+'Pipeline Valuation'!$AP$4/(1+$A$44)^27+'Pipeline Valuation'!$AQ$4/(1+$A$44)^28+'Pipeline Valuation'!$AR$4/(1+$A$44)^29+'Pipeline Valuation'!$AS$4/(1+$A$44)^30+'Pipeline Valuation'!$AT$4/(1+$A$44)^31+'Pipeline Valuation'!$AU$4/(1+$A$44)^32+'Pipeline Valuation'!$AV$4/(1+$A$44)^33+'Pipeline Valuation'!$AW$4/(1+$A$44)^34+'Pipeline Valuation'!$AX$4/(1+$A$44)^35-SUMPRODUCT('Pipeline Valuation'!$E$6:$E$19,'Pipeline Valuation'!$N$6:$N$19)+'Pipeline Valuation'!$B$4+$M$24+$M$26+$M$27-$M$28-$M$29-$M$30)/$M$32)) | F44: =IF('Biotech Model'!$B$4<>"READY","",IF(OR($A44<2%,$A44>50%,F$40>10%,$A44<=F$40+0.5%),"",($B$13/(1+$A$44)^1+$C$13/(1+$A$44)^2+$D$13/(1+$A$44)^3+$E$13/(1+$A$44)^4+$F$13/(1+$A$44)^5+$G$13/(1+$A$44)^6+$H$13/(1+$A$44)^7+$I$13/(1+$A$44)^8+$J$13/(1+$A$44)^9+$K$13/(1+$A$44)^10+$K$13*(1+F$40)/($A44-F$40)/(1+$A44)^10+'Pipeline Valuation'!$P$4/(1+$A$44)^1+'Pipeline Valuation'!$Q$4/(1+$A$44)^2+'Pipeline Valuation'!$R$4/(1+$A$44)^3+'Pipeline Valuation'!$S$4/(1+$A$44)^4+'Pipeline Valuation'!$T$4/(1+$A$44)^5+'Pipeline Valuation'!$U$4/(1+$A$44)^6+'Pipeline Valuation'!$V$4/(1+$A$44)^7+'Pipeline Valuation'!$W$4/(1+$A$44)^8+'Pipeline Valuation'!$X$4/(1+$A$44)^9+'Pipeline Valuation'!$Y$4/(1+$A$44)^10+'Pipeline Valuation'!$Z$4/(1+$A$44)^11+'Pipeline Valuation'!$AA$4/(1+$A$44)^12+'Pipeline Valuation'!$AB$4/(1+$A$44)^13+'Pipeline Valuation'!$AC$4/(1+$A$44)^14+'Pipeline Valuation'!$AD$4/(1+$A$44)^15+'Pipeline Valuation'!$AE$4/(1+$A$44)^16+'Pipeline Valuation'!$AF$4/(1+$A$44)^17+'Pipeline Valuation'!$AG$4/(1+$A$44)^18+'Pipeline Valuation'!$AH$4/(1+$A$44)^19+'Pipeline Valuation'!$AI$4/(1+$A$44)^20+'Pipeline Valuation'!$AJ$4/(1+$A$44)^21+'Pipeline Valuation'!$AK$4/(1+$A$44)^22+'Pipeline Valuation'!$AL$4/(1+$A$44)^23+'Pipeline Valuation'!$AM$4/(1+$A$44)^24+'Pipeline Valuation'!$AN$4/(1+$A$44)^25+'Pipeline Valuation'!$AO$4/(1+$A$44)^26+'Pipeline Valuation'!$AP$4/(1+$A$44)^27+'Pipeline Valuation'!$AQ$4/(1+$A$44)^28+'Pipeline Valuation'!$AR$4/(1+$A$44)^29+'Pipeline Valuation'!$AS$4/(1+$A$44)^30+'Pipeline Valuation'!$AT$4/(1+$A$44)^31+'Pipeline Valuation'!$AU$4/(1+$A$44)^32+'Pipeline Valuation'!$AV$4/(1+$A$44)^33+'Pipeline Valuation'!$AW$4/(1+$A$44)^34+'Pipeline Valuation'!$AX$4/(1+$A$44)^35-SUMPRODUCT('Pipeline Valuation'!$E$6:$E$19,'Pipeline Valuation'!$N$6:$N$19)+'Pipeline Valuation'!$B$4+$M$24+$M$26+$M$27-$M$28-$M$29-$M$30)/$M$32))
A45: =IF('Biotech Model'!$B$4<>"READY","",$M$15+(0.02)) | B45: =IF('Biotech Model'!$B$4<>"READY","",IF(OR($A45<2%,$A45>50%,B$40>10%,$A45<=B$40+0.5%),"",($B$13/(1+$A$45)^1+$C$13/(1+$A$45)^2+$D$13/(1+$A$45)^3+$E$13/(1+$A$45)^4+$F$13/(1+$A$45)^5+$G$13/(1+$A$45)^6+$H$13/(1+$A$45)^7+$I$13/(1+$A$45)^8+$J$13/(1+$A$45)^9+$K$13/(1+$A$45)^10+$K$13*(1+B$40)/($A45-B$40)/(1+$A45)^10+'Pipeline Valuation'!$P$4/(1+$A$45)^1+'Pipeline Valuation'!$Q$4/(1+$A$45)^2+'Pipeline Valuation'!$R$4/(1+$A$45)^3+'Pipeline Valuation'!$S$4/(1+$A$45)^4+'Pipeline Valuation'!$T$4/(1+$A$45)^5+'Pipeline Valuation'!$U$4/(1+$A$45)^6+'Pipeline Valuation'!$V$4/(1+$A$45)^7+'Pipeline Valuation'!$W$4/(1+$A$45)^8+'Pipeline Valuation'!$X$4/(1+$A$45)^9+'Pipeline Valuation'!$Y$4/(1+$A$45)^10+'Pipeline Valuation'!$Z$4/(1+$A$45)^11+'Pipeline Valuation'!$AA$4/(1+$A$45)^12+'Pipeline Valuation'!$AB$4/(1+$A$45)^13+'Pipeline Valuation'!$AC$4/(1+$A$45)^14+'Pipeline Valuation'!$AD$4/(1+$A$45)^15+'Pipeline Valuation'!$AE$4/(1+$A$45)^16+'Pipeline Valuation'!$AF$4/(1+$A$45)^17+'Pipeline Valuation'!$AG$4/(1+$A$45)^18+'Pipeline Valuation'!$AH$4/(1+$A$45)^19+'Pipeline Valuation'!$AI$4/(1+$A$45)^20+'Pipeline Valuation'!$AJ$4/(1+$A$45)^21+'Pipeline Valuation'!$AK$4/(1+$A$45)^22+'Pipeline Valuation'!$AL$4/(1+$A$45)^23+'Pipeline Valuation'!$AM$4/(1+$A$45)^24+'Pipeline Valuation'!$AN$4/(1+$A$45)^25+'Pipeline Valuation'!$AO$4/(1+$A$45)^26+'Pipeline Valuation'!$AP$4/(1+$A$45)^27+'Pipeline Valuation'!$AQ$4/(1+$A$45)^28+'Pipeline Valuation'!$AR$4/(1+$A$45)^29+'Pipeline Valuation'!$AS$4/(1+$A$45)^30+'Pipeline Valuation'!$AT$4/(1+$A$45)^31+'Pipeline Valuation'!$AU$4/(1+$A$45)^32+'Pipeline Valuation'!$AV$4/(1+$A$45)^33+'Pipeline Valuation'!$AW$4/(1+$A$45)^34+'Pipeline Valuation'!$AX$4/(1+$A$45)^35-SUMPRODUCT('Pipeline Valuation'!$E$6:$E$19,'Pipeline Valuation'!$N$6:$N$19)+'Pipeline Valuation'!$B$4+$M$24+$M$26+$M$27-$M$28-$M$29-$M$30)/$M$32)) | C45: =IF('Biotech Model'!$B$4<>"READY","",IF(OR($A45<2%,$A45>50%,C$40>10%,$A45<=C$40+0.5%),"",($B$13/(1+$A$45)^1+$C$13/(1+$A$45)^2+$D$13/(1+$A$45)^3+$E$13/(1+$A$45)^4+$F$13/(1+$A$45)^5+$G$13/(1+$A$45)^6+$H$13/(1+$A$45)^7+$I$13/(1+$A$45)^8+$J$13/(1+$A$45)^9+$K$13/(1+$A$45)^10+$K$13*(1+C$40)/($A45-C$40)/(1+$A45)^10+'Pipeline Valuation'!$P$4/(1+$A$45)^1+'Pipeline Valuation'!$Q$4/(1+$A$45)^2+'Pipeline Valuation'!$R$4/(1+$A$45)^3+'Pipeline Valuation'!$S$4/(1+$A$45)^4+'Pipeline Valuation'!$T$4/(1+$A$45)^5+'Pipeline Valuation'!$U$4/(1+$A$45)^6+'Pipeline Valuation'!$V$4/(1+$A$45)^7+'Pipeline Valuation'!$W$4/(1+$A$45)^8+'Pipeline Valuation'!$X$4/(1+$A$45)^9+'Pipeline Valuation'!$Y$4/(1+$A$45)^10+'Pipeline Valuation'!$Z$4/(1+$A$45)^11+'Pipeline Valuation'!$AA$4/(1+$A$45)^12+'Pipeline Valuation'!$AB$4/(1+$A$45)^13+'Pipeline Valuation'!$AC$4/(1+$A$45)^14+'Pipeline Valuation'!$AD$4/(1+$A$45)^15+'Pipeline Valuation'!$AE$4/(1+$A$45)^16+'Pipeline Valuation'!$AF$4/(1+$A$45)^17+'Pipeline Valuation'!$AG$4/(1+$A$45)^18+'Pipeline Valuation'!$AH$4/(1+$A$45)^19+'Pipeline Valuation'!$AI$4/(1+$A$45)^20+'Pipeline Valuation'!$AJ$4/(1+$A$45)^21+'Pipeline Valuation'!$AK$4/(1+$A$45)^22+'Pipeline Valuation'!$AL$4/(1+$A$45)^23+'Pipeline Valuation'!$AM$4/(1+$A$45)^24+'Pipeline Valuation'!$AN$4/(1+$A$45)^25+'Pipeline Valuation'!$AO$4/(1+$A$45)^26+'Pipeline Valuation'!$AP$4/(1+$A$45)^27+'Pipeline Valuation'!$AQ$4/(1+$A$45)^28+'Pipeline Valuation'!$AR$4/(1+$A$45)^29+'Pipeline Valuation'!$AS$4/(1+$A$45)^30+'Pipeline Valuation'!$AT$4/(1+$A$45)^31+'Pipeline Valuation'!$AU$4/(1+$A$45)^32+'Pipeline Valuation'!$AV$4/(1+$A$45)^33+'Pipeline Valuation'!$AW$4/(1+$A$45)^34+'Pipeline Valuation'!$AX$4/(1+$A$45)^35-SUMPRODUCT('Pipeline Valuation'!$E$6:$E$19,'Pipeline Valuation'!$N$6:$N$19)+'Pipeline Valuation'!$B$4+$M$24+$M$26+$M$27-$M$28-$M$29-$M$30)/$M$32)) | D45: =IF('Biotech Model'!$B$4<>"READY","",IF(OR($A45<2%,$A45>50%,D$40>10%,$A45<=D$40+0.5%),"",($B$13/(1+$A$45)^1+$C$13/(1+$A$45)^2+$D$13/(1+$A$45)^3+$E$13/(1+$A$45)^4+$F$13/(1+$A$45)^5+$G$13/(1+$A$45)^6+$H$13/(1+$A$45)^7+$I$13/(1+$A$45)^8+$J$13/(1+$A$45)^9+$K$13/(1+$A$45)^10+$K$13*(1+D$40)/($A45-D$40)/(1+$A45)^10+'Pipeline Valuation'!$P$4/(1+$A$45)^1+'Pipeline Valuation'!$Q$4/(1+$A$45)^2+'Pipeline Valuation'!$R$4/(1+$A$45)^3+'Pipeline Valuation'!$S$4/(1+$A$45)^4+'Pipeline Valuation'!$T$4/(1+$A$45)^5+'Pipeline Valuation'!$U$4/(1+$A$45)^6+'Pipeline Valuation'!$V$4/(1+$A$45)^7+'Pipeline Valuation'!$W$4/(1+$A$45)^8+'Pipeline Valuation'!$X$4/(1+$A$45)^9+'Pipeline Valuation'!$Y$4/(1+$A$45)^10+'Pipeline Valuation'!$Z$4/(1+$A$45)^11+'Pipeline Valuation'!$AA$4/(1+$A$45)^12+'Pipeline Valuation'!$AB$4/(1+$A$45)^13+'Pipeline Valuation'!$AC$4/(1+$A$45)^14+'Pipeline Valuation'!$AD$4/(1+$A$45)^15+'Pipeline Valuation'!$AE$4/(1+$A$45)^16+'Pipeline Valuation'!$AF$4/(1+$A$45)^17+'Pipeline Valuation'!$AG$4/(1+$A$45)^18+'Pipeline Valuation'!$AH$4/(1+$A$45)^19+'Pipeline Valuation'!$AI$4/(1+$A$45)^20+'Pipeline Valuation'!$AJ$4/(1+$A$45)^21+'Pipeline Valuation'!$AK$4/(1+$A$45)^22+'Pipeline Valuation'!$AL$4/(1+$A$45)^23+'Pipeline Valuation'!$AM$4/(1+$A$45)^24+'Pipeline Valuation'!$AN$4/(1+$A$45)^25+'Pipeline Valuation'!$AO$4/(1+$A$45)^26+'Pipeline Valuation'!$AP$4/(1+$A$45)^27+'Pipeline Valuation'!$AQ$4/(1+$A$45)^28+'Pipeline Valuation'!$AR$4/(1+$A$45)^29+'Pipeline Valuation'!$AS$4/(1+$A$45)^30+'Pipeline Valuation'!$AT$4/(1+$A$45)^31+'Pipeline Valuation'!$AU$4/(1+$A$45)^32+'Pipeline Valuation'!$AV$4/(1+$A$45)^33+'Pipeline Valuation'!$AW$4/(1+$A$45)^34+'Pipeline Valuation'!$AX$4/(1+$A$45)^35-SUMPRODUCT('Pipeline Valuation'!$E$6:$E$19,'Pipeline Valuation'!$N$6:$N$19)+'Pipeline Valuation'!$B$4+$M$24+$M$26+$M$27-$M$28-$M$29-$M$30)/$M$32)) | E45: =IF('Biotech Model'!$B$4<>"READY","",IF(OR($A45<2%,$A45>50%,E$40>10%,$A45<=E$40+0.5%),"",($B$13/(1+$A$45)^1+$C$13/(1+$A$45)^2+$D$13/(1+$A$45)^3+$E$13/(1+$A$45)^4+$F$13/(1+$A$45)^5+$G$13/(1+$A$45)^6+$H$13/(1+$A$45)^7+$I$13/(1+$A$45)^8+$J$13/(1+$A$45)^9+$K$13/(1+$A$45)^10+$K$13*(1+E$40)/($A45-E$40)/(1+$A45)^10+'Pipeline Valuation'!$P$4/(1+$A$45)^1+'Pipeline Valuation'!$Q$4/(1+$A$45)^2+'Pipeline Valuation'!$R$4/(1+$A$45)^3+'Pipeline Valuation'!$S$4/(1+$A$45)^4+'Pipeline Valuation'!$T$4/(1+$A$45)^5+'Pipeline Valuation'!$U$4/(1+$A$45)^6+'Pipeline Valuation'!$V$4/(1+$A$45)^7+'Pipeline Valuation'!$W$4/(1+$A$45)^8+'Pipeline Valuation'!$X$4/(1+$A$45)^9+'Pipeline Valuation'!$Y$4/(1+$A$45)^10+'Pipeline Valuation'!$Z$4/(1+$A$45)^11+'Pipeline Valuation'!$AA$4/(1+$A$45)^12+'Pipeline Valuation'!$AB$4/(1+$A$45)^13+'Pipeline Valuation'!$AC$4/(1+$A$45)^14+'Pipeline Valuation'!$AD$4/(1+$A$45)^15+'Pipeline Valuation'!$AE$4/(1+$A$45)^16+'Pipeline Valuation'!$AF$4/(1+$A$45)^17+'Pipeline Valuation'!$AG$4/(1+$A$45)^18+'Pipeline Valuation'!$AH$4/(1+$A$45)^19+'Pipeline Valuation'!$AI$4/(1+$A$45)^20+'Pipeline Valuation'!$AJ$4/(1+$A$45)^21+'Pipeline Valuation'!$AK$4/(1+$A$45)^22+'Pipeline Valuation'!$AL$4/(1+$A$45)^23+'Pipeline Valuation'!$AM$4/(1+$A$45)^24+'Pipeline Valuation'!$AN$4/(1+$A$45)^25+'Pipeline Valuation'!$AO$4/(1+$A$45)^26+'Pipeline Valuation'!$AP$4/(1+$A$45)^27+'Pipeline Valuation'!$AQ$4/(1+$A$45)^28+'Pipeline Valuation'!$AR$4/(1+$A$45)^29+'Pipeline Valuation'!$AS$4/(1+$A$45)^30+'Pipeline Valuation'!$AT$4/(1+$A$45)^31+'Pipeline Valuation'!$AU$4/(1+$A$45)^32+'Pipeline Valuation'!$AV$4/(1+$A$45)^33+'Pipeline Valuation'!$AW$4/(1+$A$45)^34+'Pipeline Valuation'!$AX$4/(1+$A$45)^35-SUMPRODUCT('Pipeline Valuation'!$E$6:$E$19,'Pipeline Valuation'!$N$6:$N$19)+'Pipeline Valuation'!$B$4+$M$24+$M$26+$M$27-$M$28-$M$29-$M$30)/$M$32)) | F45: =IF('Biotech Model'!$B$4<>"READY","",IF(OR($A45<2%,$A45>50%,F$40>10%,$A45<=F$40+0.5%),"",($B$13/(1+$A$45)^1+$C$13/(1+$A$45)^2+$D$13/(1+$A$45)^3+$E$13/(1+$A$45)^4+$F$13/(1+$A$45)^5+$G$13/(1+$A$45)^6+$H$13/(1+$A$45)^7+$I$13/(1+$A$45)^8+$J$13/(1+$A$45)^9+$K$13/(1+$A$45)^10+$K$13*(1+F$40)/($A45-F$40)/(1+$A45)^10+'Pipeline Valuation'!$P$4/(1+$A$45)^1+'Pipeline Valuation'!$Q$4/(1+$A$45)^2+'Pipeline Valuation'!$R$4/(1+$A$45)^3+'Pipeline Valuation'!$S$4/(1+$A$45)^4+'Pipeline Valuation'!$T$4/(1+$A$45)^5+'Pipeline Valuation'!$U$4/(1+$A$45)^6+'Pipeline Valuation'!$V$4/(1+$A$45)^7+'Pipeline Valuation'!$W$4/(1+$A$45)^8+'Pipeline Valuation'!$X$4/(1+$A$45)^9+'Pipeline Valuation'!$Y$4/(1+$A$45)^10+'Pipeline Valuation'!$Z$4/(1+$A$45)^11+'Pipeline Valuation'!$AA$4/(1+$A$45)^12+'Pipeline Valuation'!$AB$4/(1+$A$45)^13+'Pipeline Valuation'!$AC$4/(1+$A$45)^14+'Pipeline Valuation'!$AD$4/(1+$A$45)^15+'Pipeline Valuation'!$AE$4/(1+$A$45)^16+'Pipeline Valuation'!$AF$4/(1+$A$45)^17+'Pipeline Valuation'!$AG$4/(1+$A$45)^18+'Pipeline Valuation'!$AH$4/(1+$A$45)^19+'Pipeline Valuation'!$AI$4/(1+$A$45)^20+'Pipeline Valuation'!$AJ$4/(1+$A$45)^21+'Pipeline Valuation'!$AK$4/(1+$A$45)^22+'Pipeline Valuation'!$AL$4/(1+$A$45)^23+'Pipeline Valuation'!$AM$4/(1+$A$45)^24+'Pipeline Valuation'!$AN$4/(1+$A$45)^25+'Pipeline Valuation'!$AO$4/(1+$A$45)^26+'Pipeline Valuation'!$AP$4/(1+$A$45)^27+'Pipeline Valuation'!$AQ$4/(1+$A$45)^28+'Pipeline Valuation'!$AR$4/(1+$A$45)^29+'Pipeline Valuation'!$AS$4/(1+$A$45)^30+'Pipeline Valuation'!$AT$4/(1+$A$45)^31+'Pipeline Valuation'!$AU$4/(1+$A$45)^32+'Pipeline Valuation'!$AV$4/(1+$A$45)^33+'Pipeline Valuation'!$AW$4/(1+$A$45)^34+'Pipeline Valuation'!$AX$4/(1+$A$45)^35-SUMPRODUCT('Pipeline Valuation'!$E$6:$E$19,'Pipeline Valuation'!$N$6:$N$19)+'Pipeline Valuation'!$B$4+$M$24+$M$26+$M$27-$M$28-$M$29-$M$30)/$M$32))

Sheet Pipeline Valuation
A1: Risk-adjusted Pipeline Valuation — MRNA
A2: SEC identity, stage, status, partner, and filing narrative are reported facts. The 35-year schedule captures launch and post-LOE cash flows; sales, probability, economics, and residual rNPV remain analyst inputs.
A3: Total individually forecast late-stage asset rNPV | B3: =IF('Biotech Model'!$B$4<>"READY","",SUM(O6:O19)) | O3: Discount factor | P3: =IF('Biotech Model'!$B$4<>"READY","",1/(1+'Biotech Model'!$M$15)^1) | Q3: =IF('Biotech Model'!$B$4<>"READY","",1/(1+'Biotech Model'!$M$15)^2) | R3: =IF('Biotech Model'!$B$4<>"READY","",1/(1+'Biotech Model'!$M$15)^3) | S3: =IF('Biotech Model'!$B$4<>"READY","",1/(1+'Biotech Model'!$M$15)^4) | T3: =IF('Biotech Model'!$B$4<>"READY","",1/(1+'Biotech Model'!$M$15)^5) | U3: =IF('Biotech Model'!$B$4<>"READY","",1/(1+'Biotech Model'!$M$15)^6) | V3: =IF('Biotech Model'!$B$4<>"READY","",1/(1+'Biotech Model'!$M$15)^7) | W3: =IF('Biotech Model'!$B$4<>"READY","",1/(1+'Biotech Model'!$M$15)^8) | X3: =IF('Biotech Model'!$B$4<>"READY","",1/(1+'Biotech Model'!$M$15)^9) | Y3: =IF('Biotech Model'!$B$4<>"READY","",1/(1+'Biotech Model'!$M$15)^10) | Z3: =IF('Biotech Model'!$B$4<>"READY","",1/(1+'Biotech Model'!$M$15)^11) | AA3: =IF('Biotech Model'!$B$4<>"READY","",1/(1+'Biotech Model'!$M$15)^12) | AB3: =IF('Biotech Model'!$B$4<>"READY","",1/(1+'Biotech Model'!$M$15)^13) | AC3: =IF('Biotech Model'!$B$4<>"READY","",1/(1+'Biotech Model'!$M$15)^14) | AD3: =IF('Biotech Model'!$B$4<>"READY","",1/(1+'Biotech Model'!$M$15)^15) | AE3: =IF('Biotech Model'!$B$4<>"READY","",1/(1+'Biotech Model'!$M$15)^16) | AF3: =IF('Biotech Model'!$B$4<>"READY","",1/(1+'Biotech Model'!$M$15)^17) | AG3: =IF('Biotech Model'!$B$4<>"READY","",1/(1+'Biotech Model'!$M$15)^18) | AH3: =IF('Biotech Model'!$B$4<>"READY","",1/(1+'Biotech Model'!$M$15)^19) | AI3: =IF('Biotech Model'!$B$4<>"READY","",1/(1+'Biotech Model'!$M$15)^20) | AJ3: =IF('Biotech Model'!$B$4<>"READY","",1/(1+'Biotech Model'!$M$15)^21) | AK3: =IF('Biotech Model'!$B$4<>"READY","",1/(1+'Biotech Model'!$M$15)^22) | AL3: =IF('Biotech Model'!$B$4<>"READY","",1/(1+'Biotech Model'!$M$15)^23) | AM3: =IF('Biotech Model'!$B$4<>"READY","",1/(1+'Biotech Model'!$M$15)^24) | AN3: =IF('Biotech Model'!$B$4<>"READY","",1/(1+'Biotech Model'!$M$15)^25) | AO3: =IF('Biotech Model'!$B$4<>"READY","",1/(1+'Biotech Model'!$M$15)^26) | AP3: =IF('Biotech Model'!$B$4<>"READY","",1/(1+'Biotech Model'!$M$15)^27) | AQ3: =IF('Biotech Model'!$B$4<>"READY","",1/(1+'Biotech Model'!$M$15)^28) | AR3: =IF('Biotech Model'!$B$4<>"READY","",1/(1+'Biotech Model'!$M$15)^29) | AS3: =IF('Biotech Model'!$B$4<>"READY","",1/(1+'Biotech Model'!$M$15)^30) | AT3: =IF('Biotech Model'!$B$4<>"READY","",1/(1+'Biotech Model'!$M$15)^31) | AU3: =IF('Biotech Model'!$B$4<>"READY","",1/(1+'Biotech Model'!$M$15)^32) | AV3: =IF('Biotech Model'!$B$4<>"READY","",1/(1+'Biotech Model'!$M$15)^33) | AW3: =IF('Biotech Model'!$B$4<>"READY","",1/(1+'Biotech Model'!$M$15)^34) | AX3: =IF('Biotech Model'!$B$4<>"READY","",1/(1+'Biotech Model'!$M$15)^35)
A4: Other SEC-listed pipeline asset rNPV | B4: =IF('Biotech Model'!$B$4<>"READY","",SUM(G24:G41)) | O4: Risk-adjusted asset FCFF | P4: =IF('Biotech Model'!$B$4<>"READY","",SUM(P6:P19)) | Q4: =IF('Biotech Model'!$B$4<>"READY","",SUM(Q6:Q19)) | R4: =IF('Biotech Model'!$B$4<>"READY","",SUM(R6:R19)) | S4: =IF('Biotech Model'!$B$4<>"READY","",SUM(S6:S19)) | T4: =IF('Biotech Model'!$B$4<>"READY","",SUM(T6:T19)) | U4: =IF('Biotech Model'!$B$4<>"READY","",SUM(U6:U19)) | V4: =IF('Biotech Model'!$B$4<>"READY","",SUM(V6:V19)) | W4: =IF('Biotech Model'!$B$4<>"READY","",SUM(W6:W19)) | ... AX4: =IF('Biotech Model'!$B$4<>"READY","",SUM(AX6:AX19))
A5: Asset ID | B5: SEC asset label | C5: Stage / status / partner | D5: SEC source and filing basis | E5: Include | F5: Launch year | G5: Peak sales | H5: Years to peak | I5: Exclusivity year | J5: Post-LOE erosion | K5: PoS | L5: Retained share | M5: Post-tax FCFF margin | N5: Development-cost PV | O5: Asset rNPV | P5: 2026 | Q5: 2027 | R5: 2028 | S5: 2029 | T5: 2030 | U5: 2031 | V5: 2032 | W5: 2033 | X5: 2034 | Y5: 2035 | Z5: 2036 | AA5: 2037 | AB5: 2038 | AC5: 2039 | AD5: 2040 | AE5: 2041 | AF5: 2042 | AG5: 2043 | AH5: 2044 | AI5: 2045 | AJ5: 2046 | AK5: 2047 | AL5: 2048 | AM5: 2049 | AN5: 2050 | AO5: 2051 | AP5: 2052 | AQ5: 2053 | AR5: 2054 | AS5: 2055 | AT5: 2056 | AU5: 2057 | AV5: 2058 | AW5: 2059 | AX5: 2060
A6: mRNA-4157 | B6: mRNA-4157 | C6: Phase 2; disclosed; Partner: Merck | D6: SEC accession 0001682852-26-000033; filed 2026-02-20; report date 2025-12-31; 10-K; SEC 10-K Item 1, Business: In January 2026, we and Merck announced five-year data from the Phase 2b study of intismeran autogene (mRNA-4157), our mRNA-based individualized neoantigen therapy, in combination with Merck’s pembrolizumab (KEYTRUDA®), which demonstrated sustained improvement in recurrence-free survival in patients with high-risk melanoma (stage III/IV) following complete resection. | ONCOLOGY THERAPEUTICS FRANCHISE Within our oncology therapeutics franchise, we are developing intismeran autogene (mRNA-4157) in collaboration with Merck. | 18 Table of Contents Intismeran autogene (mRNA-4157) As tumors grow, they acquire mutations which may lead to the creation of new protein segments (neoantigens) that can be presented on human leukocyte antigen (HLA) molecules in the tumor and recognized as non-self by T cells. | Intismeran autogene, mRNA-4157, uses next generation sequencing and a machine-learning base | E6: =IF('Input Required'!$B$3<>"READY","",'Input Required'!F17/1) | F6: =IF('Input Required'!$B$3<>"READY","",'Input Required'!F18/1) | G6: =IF('Input Required'!$B$3<>"READY","",'Input Required'!F19/1000000) | H6: =IF('Input Required'!$B$3<>"READY","",'Input Required'!F20/1) | I6: =IF('Input Required'!$B$3<>"READY","",'Input Required'!F21/1) | J6: =IF('Input Required'!$B$3<>"READY","",'Input Required'!F22/1) | K6: =IF('Input Required'!$B$3<>"READY","",'Input Required'!F23/1) | L6: =IF('Input Required'!$B$3<>"READY","",'Input Required'!F24/1) | M6: =IF('Input Required'!$B$3<>"READY","",'Input Required'!F25/1) | N6: =IF('Input Required'!$B$3<>"READY","",'Input Required'!F26/1000000) | O6: =IF('Biotech Model'!$B$4<>"READY","",SUMPRODUCT(P6:AX6,$P$3:$AX$3)-E6*N6) | P6: =IF('Biotech Model'!$B$4<>"READY","",IF(E6=0,0,IF(P$5<F6,0,G6*MIN(1,(P$5-F6+1)/H6)*IF(P$5<=I6,1,(1-J6)^(P$5-I6)))*K6*L6*M6)) | Q6: =IF('Biotech Model'!$B$4<>"READY","",IF(E6=0,0,IF(Q$5<F6,0,G6*MIN(1,(Q$5-F6+1)/H6)*IF(Q$5<=I6,1,(1-J6)^(Q$5-I6)))*K6*L6*M6)) | R6: =IF('Biotech Model'!$B$4<>"READY","",IF(E6=0,0,IF(R$5<F6,0,G6*MIN(1,(R$5-F6+1)/H6)*IF(R$5<=I6,1,(1-J6)^(R$5-I6)))*K6*L6*M6)) | S6: =IF('Biotech Model'!$B$4<>"READY","",IF(E6=0,0,IF(S$5<F6,0,G6*MIN(1,(S$5-F6+1)/H6)*IF(S$5<=I6,1,(1-J6)^(S$5-I6)))*K6*L6*M6)) | T6: =IF('Biotech Model'!$B$4<>"READY","",IF(E6=0,0,IF(T$5<F6,0,G6*MIN(1,(T$5-F6+1)/H6)*IF(T$5<=I6,1,(1-J6)^(T$5-I6)))*K6*L6*M6)) | U6: =IF('Biotech Model'!$B$4<>"READY","",IF(E6=0,0,IF(U$5<F6,0,G6*MIN(1,(U$5-F6+1)/H6)*IF(U$5<=I6,1,(1-J6)^(U$5-I6)))*K6*L6*M6)) | V6: =IF('Biotech Model'!$B$4<>"READY","",IF(E6=0,0,IF(V$5<F6,0,G6*MIN(1,(V$5-F6+1)/H6)*IF(V$5<=I6,1,(1-J6)^(V$5-I6)))*K6*L6*M6)) | W6: =IF('Biotech Model'!$B$4<>"READY","",IF(E6=0,0,IF(W$5<F6,0,G6*MIN(1,(W$5-F6+1)/H6)*IF(W$5<=I6,1,(1-J6)^(W$5-I6)))*K6*L6*M6)) | X6: =IF('Biotech Model'!$B$4<>"READY","",IF(E6=0,0,IF(X$5<F6,0,G6*MIN(1,(X$5-F6+1)/H6)*IF(X$5<=I6,1,(1-J6)^(X$5-I6)))*K6*L6*M6)) | Y6: =IF('Biotech Model'!$B$4<>"READY","",IF(E6=0,0,IF(Y$5<F6,0,G6*MIN(1,(Y$5-F6+1)/H6)*IF(Y$5<=I6,1,(1-J6)^(Y$5-I6)))*K6*L6*M6)) | Z6: =IF('Biotech Model'!$B$4<>"READY","",IF(E6=0,0,IF(Z$5<F6,0,G6*MIN(1,(Z$5-F6+1)/H6)*IF(Z$5<=I6,1,(1-J6)^(Z$5-I6)))*K6*L6*M6)) | AA6: =IF('Biotech Model'!$B$4<>"READY","",IF(E6=0,0,IF(AA$5<F6,0,G6*MIN(1,(AA$5-F6+1)/H6)*IF(AA$5<=I6,1,(1-J6)^(AA$5-I6)))*K6*L6*M6)) | AB6: =IF('Biotech Model'!$B$4<>"READY","",IF(E6=0,0,IF(AB$5<F6,0,G6*MIN(1,(AB$5-F6+1)/H6)*IF(AB$5<=I6,1,(1-J6)^(AB$5-I6)))*K6*L6*M6)) | AC6: =IF('Biotech Model'!$B$4<>"READY","",IF(E6=0,0,IF(AC$5<F6,0,G6*MIN(1,(AC$5-F6+1)/H6)*IF(AC$5<=I6,1,(1-J6)^(AC$5-I6)))*K6*L6*M6)) | AD6: =IF('Biotech Model'!$B$4<>"READY","",IF(E6=0,0,IF(AD$5<F6,0,G6*MIN(1,(AD$5-F6+1)/H6)*IF(AD$5<=I6,1,(1-J6)^(AD$5-I6)))*K6*L6*M6)) | AE6: =IF('Biotech Model'!$B$4<>"READY","",IF(E6=0,0,IF(AE$5<F6,0,G6*MIN(1,(AE$5-F6+1)/H6)*IF(AE$5<=I6,1,(1-J6)^(AE$5-I6)))*K6*L6*M6)) | AF6: =IF('Biotech Model'!$B$4<>"READY","",IF(E6=0,0,IF(AF$5<F6,0,G6*MIN(1,(AF$5-F6+1)/H6)*IF(AF$5<=I6,1,(1-J6)^(AF$5-I6)))*K6*L6*M6)) | AG6: =IF('Biotech Model'!$B$4<>"READY","",IF(E6=0,0,IF(AG$5<F6,0,G6*MIN(1,(AG$5-F6+1)/H6)*IF(AG$5<=I6,1,(1-J6)^(AG$5-I6)))*K6*L6*M6)) | AH6: =IF('Biotech Model'!$B$4<>"READY","",IF(E6=0,0,IF(AH$5<F6,0,G6*MIN(1,(AH$5-F6+1)/H6)*IF(AH$5<=I6,1,(1-J6)^(AH$5-I6)))*K6*L6*M6)) | AI6: =IF('Biotech Model'!$B$4<>"READY","",IF(E6=0,0,IF(AI$5<F6,0,G6*MIN(1,(AI$5-F6+1)/H6)*IF(AI$5<=I6,1,(1-J6)^(AI$5-I6)))*K6*L6*M6)) | AJ6: =IF('Biotech Model'!$B$4<>"READY","",IF(E6=0,0,IF(AJ$5<F6,0,G6*MIN(1,(AJ$5-F6+1)/H6)*IF(AJ$5<=I6,1,(1-J6)^(AJ$5-I6)))*K6*L6*M6)) | AK6: =IF('Biotech Model'!$B$4<>"READY","",IF(E6=0,0,IF(AK$5<F6,0,G6*MIN(1,(AK$5-F6+1)/H6)*IF(AK$5<=I6,1,(1-J6)^(AK$5-I6)))*K6*L6*M6)) | AL6: =IF('Biotech Model'!$B$4<>"READY","",IF(E6=0,0,IF(AL$5<F6,0,G6*MIN(1,(AL$5-F6+1)/H6)*IF(AL$5<=I6,1,(1-J6)^(AL$5-I6)))*K6*L6*M6)) | AM6: =IF('Biotech Model'!$B$4<>"READY","",IF(E6=0,0,IF(AM$5<F6,0,G6*MIN(1,(AM$5-F6+1)/H6)*IF(AM$5<=I6,1,(1-J6)^(AM$5-I6)))*K6*L6*M6)) | AN6: =IF('Biotech Model'!$B$4<>"READY","",IF(E6=0,0,IF(AN$5<F6,0,G6*MIN(1,(AN$5-F6+1)/H6)*IF(AN$5<=I6,1,(1-J6)^(AN$5-I6)))*K6*L6*M6)) | AO6: =IF('Biotech Model'!$B$4<>"READY","",IF(E6=0,0,IF(AO$5<F6,0,G6*MIN(1,(AO$5-F6+1)/H6)*IF(AO$5<=I6,1,(1-J6)^(AO$5-I6)))*K6*L6*M6)) | AP6: =IF('Biotech Model'!$B$4<>"READY","",IF(E6=0,0,IF(AP$5<F6,0,G6*MIN(1,(AP$5-F6+1)/H6)*IF(AP$5<=I6,1,(1-J6)^(AP$5-I6)))*K6*L6*M6)) | AQ6: =IF('Biotech Model'!$B$4<>"READY","",IF(E6=0,0,IF(AQ$5<F6,0,G6*MIN(1,(AQ$5-F6+1)/H6)*IF(AQ$5<=I6,1,(1-J6)^(AQ$5-I6)))*K6*L6*M6)) | AR6: =IF('Biotech Model'!$B$4<>"READY","",IF(E6=0,0,IF(AR$5<F6,0,G6*MIN(1,(AR$5-F6+1)/H6)*IF(AR$5<=I6,1,(1-J6)^(AR$5-I6)))*K6*L6*M6)) | AS6: =IF('Biotech Model'!$B$4<>"READY","",IF(E6=0,0,IF(AS$5<F6,0,G6*MIN(1,(AS$5-F6+1)/H6)*IF(AS$5<=I6,1,(1-J6)^(AS$5-I6)))*K6*L6*M6)) | AT6: =IF('Biotech Model'!$B$4<>"READY","",IF(E6=0,0,IF(AT$5<F6,0,G6*MIN(1,(AT$5-F6+1)/H6)*IF(AT$5<=I6,1,(1-J6)^(AT$5-I6)))*K6*L6*M6)) | AU6: =IF('Biotech Model'!$B$4<>"READY","",IF(E6=0,0,IF(AU$5<F6,0,G6*MIN(1,(AU$5-F6+1)/H6)*IF(AU$5<=I6,1,(1-J6)^(AU$5-I6)))*K6*L6*M6)) | AV6: =IF('Biotech Model'!$B$4<>"READY","",IF(E6=0,0,IF(AV$5<F6,0,G6*MIN(1,(AV$5-F6+1)/H6)*IF(AV$5<=I6,1,(1-J6)^(AV$5-I6)))*K6*L6*M6)) | AW6: =IF('Biotech Model'!$B$4<>"READY","",IF(E6=0,0,IF(AW$5<F6,0,G6*MIN(1,(AW$5-F6+1)/H6)*IF(AW$5<=I6,1,(1-J6)^(AW$5-I6)))*K6*L6*M6)) | AX6: =IF('Biotech Model'!$B$4<>"READY","",IF(E6=0,0,IF(AX$5<F6,0,G6*MIN(1,(AX$5-F6+1)/H6)*IF(AX$5<=I6,1,(1-J6)^(AX$5-I6)))*K6*L6*M6))
A7: mRNA-4359 | B7: mRNA-4359 | C7: Phase 1/2; disclosed | D7: SEC accession 0001682852-26-000033; filed 2026-02-20; report date 2025-12-31; 10-K; SEC 10-K Item 1, Business: In oncology, we are also advancing mRNA-4359, a cancer antigen therapy designed to elicit T-cell immune responses against tumor and immunosuppressive cells. | Separate from the collaboration with Merck, our Phase 1/2 study of mRNA-4359, an investigational wholly-owned cancer antigen therapy, is ongoing. | Cancer antigen therapy (mRNA-4359) We are developing a cancer antigen therapy (mRNA-4359) that encodes Indoleamine 2,3-dioxygenase (IDO) and programmed death-ligand 1 (PD-L1) antigens. | We designed mRNA-4359 with the goal of stimulating effector T cells that target and kill suppressive immune and tumor cells that express the target antigens. | Our initial indications for mRNA-4359 are advanced or metastatic cutaneous melanoma and NSCLC. | 19 Table of Contents We presented data from the Phase 1a study of mRNA-4359 at the European Society for Medical Oncology (ESMO) Congress in 2024, whe | E7: =IF('Input Required'!$B$3<>"READY","",'Input Required'!F27/1) | F7: =IF('Input Required'!$B$3<>"READY","",'Input Required'!F28/1) | G7: =IF('Input Required'!$B$3<>"READY","",'Input Required'!F29/1000000) | H7: =IF('Input Required'!$B$3<>"READY","",'Input Required'!F30/1) | I7: =IF('Input Required'!$B$3<>"READY","",'Input Required'!F31/1) | J7: =IF('Input Required'!$B$3<>"READY","",'Input Required'!F32/1) | K7: =IF('Input Required'!$B$3<>"READY","",'Input Required'!F33/1) | L7: =IF('Input Required'!$B$3<>"READY","",'Input Required'!F34/1) | M7: =IF('Input Required'!$B$3<>"READY","",'Input Required'!F35/1) | N7: =IF('Input Required'!$B$3<>"READY","",'Input Required'!F36/1000000) | O7: =IF('Biotech Model'!$B$4<>"READY","",SUMPRODUCT(P7:AX7,$P$3:$AX$3)-E7*N7) | P7: =IF('Biotech Model'!$B$4<>"READY","",IF(E7=0,0,IF(P$5<F7,0,G7*MIN(1,(P$5-F7+1)/H7)*IF(P$5<=I7,1,(1-J7)^(P$5-I7)))*K7*L7*M7)) | Q7: =IF('Biotech Model'!$B$4<>"READY","",IF(E7=0,0,IF(Q$5<F7,0,G7*MIN(1,(Q$5-F7+1)/H7)*IF(Q$5<=I7,1,(1-J7)^(Q$5-I7)))*K7*L7*M7)) | R7: =IF('Biotech Model'!$B$4<>"READY","",IF(E7=0,0,IF(R$5<F7,0,G7*MIN(1,(R$5-F7+1)/H7)*IF(R$5<=I7,1,(1-J7)^(R$5-I7)))*K7*L7*M7)) | S7: =IF('Biotech Model'!$B$4<>"READY","",IF(E7=0,0,IF(S$5<F7,0,G7*MIN(1,(S$5-F7+1)/H7)*IF(S$5<=I7,1,(1-J7)^(S$5-I7)))*K7*L7*M7)) | T7: =IF('Biotech Model'!$B$4<>"READY","",IF(E7=0,0,IF(T$5<F7,0,G7*MIN(1,(T$5-F7+1)/H7)*IF(T$5<=I7,1,(1-J7)^(T$5-I7)))*K7*L7*M7)) | U7: =IF('Biotech Model'!$B$4<>"READY","",IF(E7=0,0,IF(U$5<F7,0,G7*MIN(1,(U$5-F7+1)/H7)*IF(U$5<=I7,1,(1-J7)^(U$5-I7)))*K7*L7*M7)) | V7: =IF('Biotech Model'!$B$4<>"READY","",IF(E7=0,0,IF(V$5<F7,0,G7*MIN(1,(V$5-F7+1)/H7)*IF(V$5<=I7,1,(1-J7)^(V$5-I7)))*K7*L7*M7)) | W7: =IF('Biotech Model'!$B$4<>"READY","",IF(E7=0,0,IF(W$5<F7,0,G7*MIN(1,(W$5-F7+1)/H7)*IF(W$5<=I7,1,(1-J7)^(W$5-I7)))*K7*L7*M7)) | X7: =IF('Biotech Model'!$B$4<>"READY","",IF(E7=0,0,IF(X$5<F7,0,G7*MIN(1,(X$5-F7+1)/H7)*IF(X$5<=I7,1,(1-J7)^(X$5-I7)))*K7*L7*M7)) | Y7: =IF('Biotech Model'!$B$4<>"READY","",IF(E7=0,0,IF(Y$5<F7,0,G7*MIN(1,(Y$5-F7+1)/H7)*IF(Y$5<=I7,1,(1-J7)^(Y$5-I7)))*K7*L7*M7)) | Z7: =IF('Biotech Model'!$B$4<>"READY","",IF(E7=0,0,IF(Z$5<F7,0,G7*MIN(1,(Z$5-F7+1)/H7)*IF(Z$5<=I7,1,(1-J7)^(Z$5-I7)))*K7*L7*M7)) | AA7: =IF('Biotech Model'!$B$4<>"READY","",IF(E7=0,0,IF(AA$5<F7,0,G7*MIN(1,(AA$5-F7+1)/H7)*IF(AA$5<=I7,1,(1-J7)^(AA$5-I7)))*K7*L7*M7)) | AB7: =IF('Biotech Model'!$B$4<>"READY","",IF(E7=0,0,IF(AB$5<F7,0,G7*MIN(1,(AB$5-F7+1)/H7)*IF(AB$5<=I7,1,(1-J7)^(AB$5-I7)))*K7*L7*M7)) | AC7: =IF('Biotech Model'!$B$4<>"READY","",IF(E7=0,0,IF(AC$5<F7,0,G7*MIN(1,(AC$5-F7+1)/H7)*IF(AC$5<=I7,1,(1-J7)^(AC$5-I7)))*K7*L7*M7)) | AD7: =IF('Biotech Model'!$B$4<>"READY","",IF(E7=0,0,IF(AD$5<F7,0,G7*MIN(1,(AD$5-F7+1)/H7)*IF(AD$5<=I7,1,(1-J7)^(AD$5-I7)))*K7*L7*M7)) | AE7: =IF('Biotech Model'!$B$4<>"READY","",IF(E7=0,0,IF(AE$5<F7,0,G7*MIN(1,(AE$5-F7+1)/H7)*IF(AE$5<=I7,1,(1-J7)^(AE$5-I7)))*K7*L7*M7)) | AF7: =IF('Biotech Model'!$B$4<>"READY","",IF(E7=0,0,IF(AF$5<F7,0,G7*MIN(1,(AF$5-F7+1)/H7)*IF(AF$5<=I7,1,(1-J7)^(AF$5-I7)))*K7*L7*M7)) | AG7: =IF('Biotech Model'!$B$4<>"READY","",IF(E7=0,0,IF(AG$5<F7,0,G7*MIN(1,(AG$5-F7+1)/H7)*IF(AG$5<=I7,1,(1-J7)^(AG$5-I7)))*K7*L7*M7)) | AH7: =IF('Biotech Model'!$B$4<>"READY","",IF(E7=0,0,IF(AH$5<F7,0,G7*MIN(1,(AH$5-F7+1)/H7)*IF(AH$5<=I7,1,(1-J7)^(AH$5-I7)))*K7*L7*M7)) | AI7: =IF('Biotech Model'!$B$4<>"READY","",IF(E7=0,0,IF(AI$5<F7,0,G7*MIN(1,(AI$5-F7+1)/H7)*IF(AI$5<=I7,1,(1-J7)^(AI$5-I7)))*K7*L7*M7)) | AJ7: =IF('Biotech Model'!$B$4<>"READY","",IF(E7=0,0,IF(AJ$5<F7,0,G7*MIN(1,(AJ$5-F7+1)/H7)*IF(AJ$5<=I7,1,(1-J7)^(AJ$5-I7)))*K7*L7*M7)) | AK7: =IF('Biotech Model'!$B$4<>"READY","",IF(E7=0,0,IF(AK$5<F7,0,G7*MIN(1,(AK$5-F7+1)/H7)*IF(AK$5<=I7,1,(1-J7)^(AK$5-I7)))*K7*L7*M7)) | AL7: =IF('Biotech Model'!$B$4<>"READY","",IF(E7=0,0,IF(AL$5<F7,0,G7*MIN(1,(AL$5-F7+1)/H7)*IF(AL$5<=I7,1,(1-J7)^(AL$5-I7)))*K7*L7*M7)) | AM7: =IF('Biotech Model'!$B$4<>"READY","",IF(E7=0,0,IF(AM$5<F7,0,G7*MIN(1,(AM$5-F7+1)/H7)*IF(AM$5<=I7,1,(1-J7)^(AM$5-I7)))*K7*L7*M7)) | AN7: =IF('Biotech Model'!$B$4<>"READY","",IF(E7=0,0,IF(AN$5<F7,0,G7*MIN(1,(AN$5-F7+1)/H7)*IF(AN$5<=I7,1,(1-J7)^(AN$5-I7)))*K7*L7*M7)) | AO7: =IF('Biotech Model'!$B$4<>"READY","",IF(E7=0,0,IF(AO$5<F7,0,G7*MIN(1,(AO$5-F7+1)/H7)*IF(AO$5<=I7,1,(1-J7)^(AO$5-I7)))*K7*L7*M7)) | AP7: =IF('Biotech Model'!$B$4<>"READY","",IF(E7=0,0,IF(AP$5<F7,0,G7*MIN(1,(AP$5-F7+1)/H7)*IF(AP$5<=I7,1,(1-J7)^(AP$5-I7)))*K7*L7*M7)) | AQ7: =IF('Biotech Model'!$B$4<>"READY","",IF(E7=0,0,IF(AQ$5<F7,0,G7*MIN(1,(AQ$5-F7+1)/H7)*IF(AQ$5<=I7,1,(1-J7)^(AQ$5-I7)))*K7*L7*M7)) | AR7: =IF('Biotech Model'!$B$4<>"READY","",IF(E7=0,0,IF(AR$5<F7,0,G7*MIN(1,(AR$5-F7+1)/H7)*IF(AR$5<=I7,1,(1-J7)^(AR$5-I7)))*K7*L7*M7)) | AS7: =IF('Biotech Model'!$B$4<>"READY","",IF(E7=0,0,IF(AS$5<F7,0,G7*MIN(1,(AS$5-F7+1)/H7)*IF(AS$5<=I7,1,(1-J7)^(AS$5-I7)))*K7*L7*M7)) | AT7: =IF('Biotech Model'!$B$4<>"READY","",IF(E7=0,0,IF(AT$5<F7,0,G7*MIN(1,(AT$5-F7+1)/H7)*IF(AT$5<=I7,1,(1-J7)^(AT$5-I7)))*K7*L7*M7)) | AU7: =IF('Biotech Model'!$B$4<>"READY","",IF(E7=0,0,IF(AU$5<F7,0,G7*MIN(1,(AU$5-F7+1)/H7)*IF(AU$5<=I7,1,(1-J7)^(AU$5-I7)))*K7*L7*M7)) | AV7: =IF('Biotech Model'!$B$4<>"READY","",IF(E7=0,0,IF(AV$5<F7,0,G7*MIN(1,(AV$5-F7+1)/H7)*IF(AV$5<=I7,1,(1-J7)^(AV$5-I7)))*K7*L7*M7)) | AW7: =IF('Biotech Model'!$B$4<>"READY","",IF(E7=0,0,IF(AW$5<F7,0,G7*MIN(1,(AW$5-F7+1)/H7)*IF(AW$5<=I7,1,(1-J7)^(AW$5-I7)))*K7*L7*M7)) | AX7: =IF('Biotech Model'!$B$4<>"READY","",IF(E7=0,0,IF(AX$5<F7,0,G7*MIN(1,(AX$5-F7+1)/H7)*IF(AX$5<=I7,1,(1-J7)^(AX$5-I7)))*K7*L7*M7))
A8: mRNA-1083 | B8: mRNA-1083 | C8: Phase 3; disclosed | D8: SEC accession 0001682852-26-000033; filed 2026-02-20; report date 2025-12-31; 10-K; SEC 10-K Item 1, Business: In infectious disease, we have regulatory filings under review for our seasonal flu+COVID combination vaccine candidate (mRNA-1083) in Europe and Canada, and for our seasonal flu vaccine candidate (mRNA-1010) in the United States, Europe, Canada and Australia. | Additionally, we have regulatory filings under review for our seasonal flu+COVID vaccine (mRNA-1083) in Europe and Canada and for our seasonal flu vaccine (mRNA-1010) in the United States, Europe, Canada and Australia. | Combination vaccines (mRNA-1083 and mRNA-1365) We are developing combination vaccine candidates to simplify and facilitate protection against a range of respiratory diseases. | Our COVID and seasonal influenza combination vaccine (mRNA-1083), encodes the same antigens as our seasonal influenza vaccine (mRNA-1010) and mNEXSPIKE. | In June 2024, we announced that our Phase 3 clinical trial of mRNA-1083 met its prim | E8: =IF('Input Required'!$B$3<>"READY","",'Input Required'!F37/1) | F8: =IF('Input Required'!$B$3<>"READY","",'Input Required'!F38/1) | G8: =IF('Input Required'!$B$3<>"READY","",'Input Required'!F39/1000000) | H8: =IF('Input Required'!$B$3<>"READY","",'Input Required'!F40/1) | I8: =IF('Input Required'!$B$3<>"READY","",'Input Required'!F41/1) | J8: =IF('Input Required'!$B$3<>"READY","",'Input Required'!F42/1) | K8: =IF('Input Required'!$B$3<>"READY","",'Input Required'!F43/1) | L8: =IF('Input Required'!$B$3<>"READY","",'Input Required'!F44/1) | M8: =IF('Input Required'!$B$3<>"READY","",'Input Required'!F45/1) | N8: =IF('Input Required'!$B$3<>"READY","",'Input Required'!F46/1000000) | O8: =IF('Biotech Model'!$B$4<>"READY","",SUMPRODUCT(P8:AX8,$P$3:$AX$3)-E8*N8) | P8: =IF('Biotech Model'!$B$4<>"READY","",IF(E8=0,0,IF(P$5<F8,0,G8*MIN(1,(P$5-F8+1)/H8)*IF(P$5<=I8,1,(1-J8)^(P$5-I8)))*K8*L8*M8)) | Q8: =IF('Biotech Model'!$B$4<>"READY","",IF(E8=0,0,IF(Q$5<F8,0,G8*MIN(1,(Q$5-F8+1)/H8)*IF(Q$5<=I8,1,(1-J8)^(Q$5-I8)))*K8*L8*M8)) | R8: =IF('Biotech Model'!$B$4<>"READY","",IF(E8=0,0,IF(R$5<F8,0,G8*MIN(1,(R$5-F8+1)/H8)*IF(R$5<=I8,1,(1-J8)^(R$5-I8)))*K8*L8*M8)) | S8: =IF('Biotech Model'!$B$4<>"READY","",IF(E8=0,0,IF(S$5<F8,0,G8*MIN(1,(S$5-F8+1)/H8)*IF(S$5<=I8,1,(1-J8)^(S$5-I8)))*K8*L8*M8)) | T8: =IF('Biotech Model'!$B$4<>"READY","",IF(E8=0,0,IF(T$5<F8,0,G8*MIN(1,(T$5-F8+1)/H8)*IF(T$5<=I8,1,(1-J8)^(T$5-I8)))*K8*L8*M8)) | U8: =IF('Biotech Model'!$B$4<>"READY","",IF(E8=0,0,IF(U$5<F8,0,G8*MIN(1,(U$5-F8+1)/H8)*IF(U$5<=I8,1,(1-J8)^(U$5-I8)))*K8*L8*M8)) | V8: =IF('Biotech Model'!$B$4<>"READY","",IF(E8=0,0,IF(V$5<F8,0,G8*MIN(1,(V$5-F8+1)/H8)*IF(V$5<=I8,1,(1-J8)^(V$5-I8)))*K8*L8*M8)) | W8: =IF('Biotech Model'!$B$4<>"READY","",IF(E8=0,0,IF(W$5<F8,0,G8*MIN(1,(W$5-F8+1)/H8)*IF(W$5<=I8,1,(1-J8)^(W$5-I8)))*K8*L8*M8)) | X8: =IF('Biotech Model'!$B$4<>"READY","",IF(E8=0,0,IF(X$5<F8,0,G8*MIN(1,(X$5-F8+1)/H8)*IF(X$5<=I8,1,(1-J8)^(X$5-I8)))*K8*L8*M8)) | Y8: =IF('Biotech Model'!$B$4<>"READY","",IF(E8=0,0,IF(Y$5<F8,0,G8*MIN(1,(Y$5-F8+1)/H8)*IF(Y$5<=I8,1,(1-J8)^(Y$5-I8)))*K8*L8*M8)) | Z8: =IF('Biotech Model'!$B$4<>"READY","",IF(E8=0,0,IF(Z$5<F8,0,G8*MIN(1,(Z$5-F8+1)/H8)*IF(Z$5<=I8,1,(1-J8)^(Z$5-I8)))*K8*L8*M8)) | AA8: =IF('Biotech Model'!$B$4<>"READY","",IF(E8=0,0,IF(AA$5<F8,0,G8*MIN(1,(AA$5-F8+1)/H8)*IF(AA$5<=I8,1,(1-J8)^(AA$5-I8)))*K8*L8*M8)) | AB8: =IF('Biotech Model'!$B$4<>"READY","",IF(E8=0,0,IF(AB$5<F8,0,G8*MIN(1,(AB$5-F8+1)/H8)*IF(AB$5<=I8,1,(1-J8)^(AB$5-I8)))*K8*L8*M8)) | AC8: =IF('Biotech Model'!$B$4<>"READY","",IF(E8=0,0,IF(AC$5<F8,0,G8*MIN(1,(AC$5-F8+1)/H8)*IF(AC$5<=I8,1,(1-J8)^(AC$5-I8)))*K8*L8*M8)) | AD8: =IF('Biotech Model'!$B$4<>"READY","",IF(E8=0,0,IF(AD$5<F8,0,G8*MIN(1,(AD$5-F8+1)/H8)*IF(AD$5<=I8,1,(1-J8)^(AD$5-I8)))*K8*L8*M8)) | AE8: =IF('Biotech Model'!$B$4<>"READY","",IF(E8=0,0,IF(AE$5<F8,0,G8*MIN(1,(AE$5-F8+1)/H8)*IF(AE$5<=I8,1,(1-J8)^(AE$5-I8)))*K8*L8*M8)) | AF8: =IF('Biotech Model'!$B$4<>"READY","",IF(E8=0,0,IF(AF$5<F8,0,G8*MIN(1,(AF$5-F8+1)/H8)*IF(AF$5<=I8,1,(1-J8)^(AF$5-I8)))*K8*L8*M8)) | AG8: =IF('Biotech Model'!$B$4<>"READY","",IF(E8=0,0,IF(AG$5<F8,0,G8*MIN(1,(AG$5-F8+1)/H8)*IF(AG$5<=I8,1,(1-J8)^(AG$5-I8)))*K8*L8*M8)) | AH8: =IF('Biotech Model'!$B$4<>"READY","",IF(E8=0,0,IF(AH$5<F8,0,G8*MIN(1,(AH$5-F8+1)/H8)*IF(AH$5<=I8,1,(1-J8)^(AH$5-I8)))*K8*L8*M8)) | AI8: =IF('Biotech Model'!$B$4<>"READY","",IF(E8=0,0,IF(AI$5<F8,0,G8*MIN(1,(AI$5-F8+1)/H8)*IF(AI$5<=I8,1,(1-J8)^(AI$5-I8)))*K8*L8*M8)) | AJ8: =IF('Biotech Model'!$B$4<>"READY","",IF(E8=0,0,IF(AJ$5<F8,0,G8*MIN(1,(AJ$5-F8+1)/H8)*IF(AJ$5<=I8,1,(1-J8)^(AJ$5-I8)))*K8*L8*M8)) | AK8: =IF('Biotech Model'!$B$4<>"READY","",IF(E8=0,0,IF(AK$5<F8,0,G8*MIN(1,(AK$5-F8+1)/H8)*IF(AK$5<=I8,1,(1-J8)^(AK$5-I8)))*K8*L8*M8)) | AL8: =IF('Biotech Model'!$B$4<>"READY","",IF(E8=0,0,IF(AL$5<F8,0,G8*MIN(1,(AL$5-F8+1)/H8)*IF(AL$5<=I8,1,(1-J8)^(AL$5-I8)))*K8*L8*M8)) | AM8: =IF('Biotech Model'!$B$4<>"READY","",IF(E8=0,0,IF(AM$5<F8,0,G8*MIN(1,(AM$5-F8+1)/H8)*IF(AM$5<=I8,1,(1-J8)^(AM$5-I8)))*K8*L8*M8)) | AN8: =IF('Biotech Model'!$B$4<>"READY","",IF(E8=0,0,IF(AN$5<F8,0,G8*MIN(1,(AN$5-F8+1)/H8)*IF(AN$5<=I8,1,(1-J8)^(AN$5-I8)))*K8*L8*M8)) | AO8: =IF('Biotech Model'!$B$4<>"READY","",IF(E8=0,0,IF(AO$5<F8,0,G8*MIN(1,(AO$5-F8+1)/H8)*IF(AO$5<=I8,1,(1-J8)^(AO$5-I8)))*K8*L8*M8)) | AP8: =IF('Biotech Model'!$B$4<>"READY","",IF(E8=0,0,IF(AP$5<F8,0,G8*MIN(1,(AP$5-F8+1)/H8)*IF(AP$5<=I8,1,(1-J8)^(AP$5-I8)))*K8*L8*M8)) | AQ8: =IF('Biotech Model'!$B$4<>"READY","",IF(E8=0,0,IF(AQ$5<F8,0,G8*MIN(1,(AQ$5-F8+1)/H8)*IF(AQ$5<=I8,1,(1-J8)^(AQ$5-I8)))*K8*L8*M8)) | AR8: =IF('Biotech Model'!$B$4<>"READY","",IF(E8=0,0,IF(AR$5<F8,0,G8*MIN(1,(AR$5-F8+1)/H8)*IF(AR$5<=I8,1,(1-J8)^(AR$5-I8)))*K8*L8*M8)) | AS8: =IF('Biotech Model'!$B$4<>"READY","",IF(E8=0,0,IF(AS$5<F8,0,G8*MIN(1,(AS$5-F8+1)/H8)*IF(AS$5<=I8,1,(1-J8)^(AS$5-I8)))*K8*L8*M8)) | AT8: =IF('Biotech Model'!$B$4<>"READY","",IF(E8=0,0,IF(AT$5<F8,0,G8*MIN(1,(AT$5-F8+1)/H8)*IF(AT$5<=I8,1,(1-J8)^(AT$5-I8)))*K8*L8*M8)) | AU8: =IF('Biotech Model'!$B$4<>"READY","",IF(E8=0,0,IF(AU$5<F8,0,G8*MIN(1,(AU$5-F8+1)/H8)*IF(AU$5<=I8,1,(1-J8)^(AU$5-I8)))*K8*L8*M8)) | AV8: =IF('Biotech Model'!$B$4<>"READY","",IF(E8=0,0,IF(AV$5<F8,0,G8*MIN(1,(AV$5-F8+1)/H8)*IF(AV$5<=I8,1,(1-J8)^(AV$5-I8)))*K8*L8*M8)) | AW8: =IF('Biotech Model'!$B$4<>"READY","",IF(E8=0,0,IF(AW$5<F8,0,G8*MIN(1,(AW$5-F8+1)/H8)*IF(AW$5<=I8,1,(1-J8)^(AW$5-I8)))*K8*L8*M8)) | AX8: =IF('Biotech Model'!$B$4<>"READY","",IF(E8=0,0,IF(AX$5<F8,0,G8*MIN(1,(AX$5-F8+1)/H8)*IF(AX$5<=I8,1,(1-J8)^(AX$5-I8)))*K8*L8*M8))
A9: mRNA-1010 | B9: mRNA-1010 | C9: Phase 3; disclosed | D9: SEC accession 0001682852-26-000033; filed 2026-02-20; report date 2025-12-31; 10-K; SEC 10-K Item 1, Business: In infectious disease, we have regulatory filings under review for our seasonal flu+COVID combination vaccine candidate (mRNA-1083) in Europe and Canada, and for our seasonal flu vaccine candidate (mRNA-1010) in the United States, Europe, Canada and Australia. | For mRNA-1010, in response to a prior Refusal-to-File letter, we engaged with the U. | Additionally, we have regulatory filings under review for our seasonal flu+COVID vaccine (mRNA-1083) in Europe and Canada and for our seasonal flu vaccine (mRNA-1010) in the United States, Europe, Canada and Australia. | 13 Table of Contents Seasonal influenza vaccine (mRNA-1010) The WHO estimates that seasonal influenza viruses cause three to five million cases of severe illness and 290,000 to 650,000 deaths each year, resulting in a severe challenge to public health. | Our seasonal influenza vaccine candidate (mRNA-1010) encodes for the hemag | E9: =IF('Input Required'!$B$3<>"READY","",'Input Required'!F47/1) | F9: =IF('Input Required'!$B$3<>"READY","",'Input Required'!F48/1) | G9: =IF('Input Required'!$B$3<>"READY","",'Input Required'!F49/1000000) | H9: =IF('Input Required'!$B$3<>"READY","",'Input Required'!F50/1) | I9: =IF('Input Required'!$B$3<>"READY","",'Input Required'!F51/1) | J9: =IF('Input Required'!$B$3<>"READY","",'Input Required'!F52/1) | K9: =IF('Input Required'!$B$3<>"READY","",'Input Required'!F53/1) | L9: =IF('Input Required'!$B$3<>"READY","",'Input Required'!F54/1) | M9: =IF('Input Required'!$B$3<>"READY","",'Input Required'!F55/1) | N9: =IF('Input Required'!$B$3<>"READY","",'Input Required'!F56/1000000) | O9: =IF('Biotech Model'!$B$4<>"READY","",SUMPRODUCT(P9:AX9,$P$3:$AX$3)-E9*N9) | P9: =IF('Biotech Model'!$B$4<>"READY","",IF(E9=0,0,IF(P$5<F9,0,G9*MIN(1,(P$5-F9+1)/H9)*IF(P$5<=I9,1,(1-J9)^(P$5-I9)))*K9*L9*M9)) | Q9: =IF('Biotech Model'!$B$4<>"READY","",IF(E9=0,0,IF(Q$5<F9,0,G9*MIN(1,(Q$5-F9+1)/H9)*IF(Q$5<=I9,1,(1-J9)^(Q$5-I9)))*K9*L9*M9)) | R9: =IF('Biotech Model'!$B$4<>"READY","",IF(E9=0,0,IF(R$5<F9,0,G9*MIN(1,(R$5-F9+1)/H9)*IF(R$5<=I9,1,(1-J9)^(R$5-I9)))*K9*L9*M9)) | S9: =IF('Biotech Model'!$B$4<>"READY","",IF(E9=0,0,IF(S$5<F9,0,G9*MIN(1,(S$5-F9+1)/H9)*IF(S$5<=I9,1,(1-J9)^(S$5-I9)))*K9*L9*M9)) | T9: =IF('Biotech Model'!$B$4<>"READY","",IF(E9=0,0,IF(T$5<F9,0,G9*MIN(1,(T$5-F9+1)/H9)*IF(T$5<=I9,1,(1-J9)^(T$5-I9)))*K9*L9*M9)) | U9: =IF('Biotech Model'!$B$4<>"READY","",IF(E9=0,0,IF(U$5<F9,0,G9*MIN(1,(U$5-F9+1)/H9)*IF(U$5<=I9,1,(1-J9)^(U$5-I9)))*K9*L9*M9)) | V9: =IF('Biotech Model'!$B$4<>"READY","",IF(E9=0,0,IF(V$5<F9,0,G9*MIN(1,(V$5-F9+1)/H9)*IF(V$5<=I9,1,(1-J9)^(V$5-I9)))*K9*L9*M9)) | W9: =IF('Biotech Model'!$B$4<>"READY","",IF(E9=0,0,IF(W$5<F9,0,G9*MIN(1,(W$5-F9+1)/H9)*IF(W$5<=I9,1,(1-J9)^(W$5-I9)))*K9*L9*M9)) | X9: =IF('Biotech Model'!$B$4<>"READY","",IF(E9=0,0,IF(X$5<F9,0,G9*MIN(1,(X$5-F9+1)/H9)*IF(X$5<=I9,1,(1-J9)^(X$5-I9)))*K9*L9*M9)) | Y9: =IF('Biotech Model'!$B$4<>"READY","",IF(E9=0,0,IF(Y$5<F9,0,G9*MIN(1,(Y$5-F9+1)/H9)*IF(Y$5<=I9,1,(1-J9)^(Y$5-I9)))*K9*L9*M9)) | Z9: =IF('Biotech Model'!$B$4<>"READY","",IF(E9=0,0,IF(Z$5<F9,0,G9*MIN(1,(Z$5-F9+1)/H9)*IF(Z$5<=I9,1,(1-J9)^(Z$5-I9)))*K9*L9*M9)) | AA9: =IF('Biotech Model'!$B$4<>"READY","",IF(E9=0,0,IF(AA$5<F9,0,G9*MIN(1,(AA$5-F9+1)/H9)*IF(AA$5<=I9,1,(1-J9)^(AA$5-I9)))*K9*L9*M9)) | AB9: =IF('Biotech Model'!$B$4<>"READY","",IF(E9=0,0,IF(AB$5<F9,0,G9*MIN(1,(AB$5-F9+1)/H9)*IF(AB$5<=I9,1,(1-J9)^(AB$5-I9)))*K9*L9*M9)) | AC9: =IF('Biotech Model'!$B$4<>"READY","",IF(E9=0,0,IF(AC$5<F9,0,G9*MIN(1,(AC$5-F9+1)/H9)*IF(AC$5<=I9,1,(1-J9)^(AC$5-I9)))*K9*L9*M9)) | AD9: =IF('Biotech Model'!$B$4<>"READY","",IF(E9=0,0,IF(AD$5<F9,0,G9*MIN(1,(AD$5-F9+1)/H9)*IF(AD$5<=I9,1,(1-J9)^(AD$5-I9)))*K9*L9*M9)) | AE9: =IF('Biotech Model'!$B$4<>"READY","",IF(E9=0,0,IF(AE$5<F9,0,G9*MIN(1,(AE$5-F9+1)/H9)*IF(AE$5<=I9,1,(1-J9)^(AE$5-I9)))*K9*L9*M9)) | AF9: =IF('Biotech Model'!$B$4<>"READY","",IF(E9=0,0,IF(AF$5<F9,0,G9*MIN(1,(AF$5-F9+1)/H9)*IF(AF$5<=I9,1,(1-J9)^(AF$5-I9)))*K9*L9*M9)) | AG9: =IF('Biotech Model'!$B$4<>"READY","",IF(E9=0,0,IF(AG$5<F9,0,G9*MIN(1,(AG$5-F9+1)/H9)*IF(AG$5<=I9,1,(1-J9)^(AG$5-I9)))*K9*L9*M9)) | AH9: =IF('Biotech Model'!$B$4<>"READY","",IF(E9=0,0,IF(AH$5<F9,0,G9*MIN(1,(AH$5-F9+1)/H9)*IF(AH$5<=I9,1,(1-J9)^(AH$5-I9)))*K9*L9*M9)) | AI9: =IF('Biotech Model'!$B$4<>"READY","",IF(E9=0,0,IF(AI$5<F9,0,G9*MIN(1,(AI$5-F9+1)/H9)*IF(AI$5<=I9,1,(1-J9)^(AI$5-I9)))*K9*L9*M9)) | AJ9: =IF('Biotech Model'!$B$4<>"READY","",IF(E9=0,0,IF(AJ$5<F9,0,G9*MIN(1,(AJ$5-F9+1)/H9)*IF(AJ$5<=I9,1,(1-J9)^(AJ$5-I9)))*K9*L9*M9)) | AK9: =IF('Biotech Model'!$B$4<>"READY","",IF(E9=0,0,IF(AK$5<F9,0,G9*MIN(1,(AK$5-F9+1)/H9)*IF(AK$5<=I9,1,(1-J9)^(AK$5-I9)))*K9*L9*M9)) | AL9: =IF('Biotech Model'!$B$4<>"READY","",IF(E9=0,0,IF(AL$5<F9,0,G9*MIN(1,(AL$5-F9+1)/H9)*IF(AL$5<=I9,1,(1-J9)^(AL$5-I9)))*K9*L9*M9)) | AM9: =IF('Biotech Model'!$B$4<>"READY","",IF(E9=0,0,IF(AM$5<F9,0,G9*MIN(1,(AM$5-F9+1)/H9)*IF(AM$5<=I9,1,(1-J9)^(AM$5-I9)))*K9*L9*M9)) | AN9: =IF('Biotech Model'!$B$4<>"READY","",IF(E9=0,0,IF(AN$5<F9,0,G9*MIN(1,(AN$5-F9+1)/H9)*IF(AN$5<=I9,1,(1-J9)^(AN$5-I9)))*K9*L9*M9)) | AO9: =IF('Biotech Model'!$B$4<>"READY","",IF(E9=0,0,IF(AO$5<F9,0,G9*MIN(1,(AO$5-F9+1)/H9)*IF(AO$5<=I9,1,(1-J9)^(AO$5-I9)))*K9*L9*M9)) | AP9: =IF('Biotech Model'!$B$4<>"READY","",IF(E9=0,0,IF(AP$5<F9,0,G9*MIN(1,(AP$5-F9+1)/H9)*IF(AP$5<=I9,1,(1-J9)^(AP$5-I9)))*K9*L9*M9)) | AQ9: =IF('Biotech Model'!$B$4<>"READY","",IF(E9=0,0,IF(AQ$5<F9,0,G9*MIN(1,(AQ$5-F9+1)/H9)*IF(AQ$5<=I9,1,(1-J9)^(AQ$5-I9)))*K9*L9*M9)) | AR9: =IF('Biotech Model'!$B$4<>"READY","",IF(E9=0,0,IF(AR$5<F9,0,G9*MIN(1,(AR$5-F9+1)/H9)*IF(AR$5<=I9,1,(1-J9)^(AR$5-I9)))*K9*L9*M9)) | AS9: =IF('Biotech Model'!$B$4<>"READY","",IF(E9=0,0,IF(AS$5<F9,0,G9*MIN(1,(AS$5-F9+1)/H9)*IF(AS$5<=I9,1,(1-J9)^(AS$5-I9)))*K9*L9*M9)) | AT9: =IF('Biotech Model'!$B$4<>"READY","",IF(E9=0,0,IF(AT$5<F9,0,G9*MIN(1,(AT$5-F9+1)/H9)*IF(AT$5<=I9,1,(1-J9)^(AT$5-I9)))*K9*L9*M9)) | AU9: =IF('Biotech Model'!$B$4<>"READY","",IF(E9=0,0,IF(AU$5<F9,0,G9*MIN(1,(AU$5-F9+1)/H9)*IF(AU$5<=I9,1,(1-J9)^(AU$5-I9)))*K9*L9*M9)) | AV9: =IF('Biotech Model'!$B$4<>"READY","",IF(E9=0,0,IF(AV$5<F9,0,G9*MIN(1,(AV$5-F9+1)/H9)*IF(AV$5<=I9,1,(1-J9)^(AV$5-I9)))*K9*L9*M9)) | AW9: =IF('Biotech Model'!$B$4<>"READY","",IF(E9=0,0,IF(AW$5<F9,0,G9*MIN(1,(AW$5-F9+1)/H9)*IF(AW$5<=I9,1,(1-J9)^(AW$5-I9)))*K9*L9*M9)) | AX9: =IF('Biotech Model'!$B$4<>"READY","",IF(E9=0,0,IF(AX$5<F9,0,G9*MIN(1,(AX$5-F9+1)/H9)*IF(AX$5<=I9,1,(1-J9)^(AX$5-I9)))*K9*L9*M9))
A10: mRNA-1403 | B10: mRNA-1403 | C10: Phase 3; disclosed | D10: SEC accession 0001682852-26-000033; filed 2026-02-20; report date 2025-12-31; 10-K; SEC 10-K Item 1, Business: In addition, we recently completed enrollment of a second Northern Hemisphere season (2025-2026) cohort in our ongoing Phase 3 study for our norovirus candidate (mRNA-1403). | Vaccines against enteric viruses Norovirus vaccines (mRNA-1403 and mRNA-1405) Norovirus is a leading cause of acute gastroenteritis (AGE), responsible for approximately 18% of all AGE cases worldwide and imposing a substantial global health care burden. | We are currently developing pentavalent (mRNA-1405) and trivalent (mRNA-1403) vaccine candidates for norovirus. | In March 2024, we presented data demonstrating that a single dose of trivalent vaccine candidate mRNA-1403 was well-tolerated across all dose levels evaluated and elicited robust antibody responses against vaccine-matched norovirus genogroup I & II selected genotypes, including functional histo-blood group antigen (HBGA) blocking antibodies. | In Septe | E10: =IF('Input Required'!$B$3<>"READY","",'Input Required'!F57/1) | F10: =IF('Input Required'!$B$3<>"READY","",'Input Required'!F58/1) | G10: =IF('Input Required'!$B$3<>"READY","",'Input Required'!F59/1000000) | H10: =IF('Input Required'!$B$3<>"READY","",'Input Required'!F60/1) | I10: =IF('Input Required'!$B$3<>"READY","",'Input Required'!F61/1) | J10: =IF('Input Required'!$B$3<>"READY","",'Input Required'!F62/1) | K10: =IF('Input Required'!$B$3<>"READY","",'Input Required'!F63/1) | L10: =IF('Input Required'!$B$3<>"READY","",'Input Required'!F64/1) | M10: =IF('Input Required'!$B$3<>"READY","",'Input Required'!F65/1) | N10: =IF('Input Required'!$B$3<>"READY","",'Input Required'!F66/1000000) | O10: =IF('Biotech Model'!$B$4<>"READY","",SUMPRODUCT(P10:AX10,$P$3:$AX$3)-E10*N10) | P10: =IF('Biotech Model'!$B$4<>"READY","",IF(E10=0,0,IF(P$5<F10,0,G10*MIN(1,(P$5-F10+1)/H10)*IF(P$5<=I10,1,(1-J10)^(P$5-I10)))*K10*L10*M10)) | Q10: =IF('Biotech Model'!$B$4<>"READY","",IF(E10=0,0,IF(Q$5<F10,0,G10*MIN(1,(Q$5-F10+1)/H10)*IF(Q$5<=I10,1,(1-J10)^(Q$5-I10)))*K10*L10*M10)) | R10: =IF('Biotech Model'!$B$4<>"READY","",IF(E10=0,0,IF(R$5<F10,0,G10*MIN(1,(R$5-F10+1)/H10)*IF(R$5<=I10,1,(1-J10)^(R$5-I10)))*K10*L10*M10)) | S10: =IF('Biotech Model'!$B$4<>"READY","",IF(E10=0,0,IF(S$5<F10,0,G10*MIN(1,(S$5-F10+1)/H10)*IF(S$5<=I10,1,(1-J10)^(S$5-I10)))*K10*L10*M10)) | T10: =IF('Biotech Model'!$B$4<>"READY","",IF(E10=0,0,IF(T$5<F10,0,G10*MIN(1,(T$5-F10+1)/H10)*IF(T$5<=I10,1,(1-J10)^(T$5-I10)))*K10*L10*M10)) | U10: =IF('Biotech Model'!$B$4<>"READY","",IF(E10=0,0,IF(U$5<F10,0,G10*MIN(1,(U$5-F10+1)/H10)*IF(U$5<=I10,1,(1-J10)^(U$5-I10)))*K10*L10*M10)) | V10: =IF('Biotech Model'!$B$4<>"READY","",IF(E10=0,0,IF(V$5<F10,0,G10*MIN(1,(V$5-F10+1)/H10)*IF(V$5<=I10,1,(1-J10)^(V$5-I10)))*K10*L10*M10)) | W10: =IF('Biotech Model'!$B$4<>"READY","",IF(E10=0,0,IF(W$5<F10,0,G10*MIN(1,(W$5-F10+1)/H10)*IF(W$5<=I10,1,(1-J10)^(W$5-I10)))*K10*L10*M10)) | X10: =IF('Biotech Model'!$B$4<>"READY","",IF(E10=0,0,IF(X$5<F10,0,G10*MIN(1,(X$5-F10+1)/H10)*IF(X$5<=I10,1,(1-J10)^(X$5-I10)))*K10*L10*M10)) | Y10: =IF('Biotech Model'!$B$4<>"READY","",IF(E10=0,0,IF(Y$5<F10,0,G10*MIN(1,(Y$5-F10+1)/H10)*IF(Y$5<=I10,1,(1-J10)^(Y$5-I10)))*K10*L10*M10)) | Z10: =IF('Biotech Model'!$B$4<>"READY","",IF(E10=0,0,IF(Z$5<F10,0,G10*MIN(1,(Z$5-F10+1)/H10)*IF(Z$5<=I10,1,(1-J10)^(Z$5-I10)))*K10*L10*M10)) | AA10: =IF('Biotech Model'!$B$4<>"READY","",IF(E10=0,0,IF(AA$5<F10,0,G10*MIN(1,(AA$5-F10+1)/H10)*IF(AA$5<=I10,1,(1-J10)^(AA$5-I10)))*K10*L10*M10)) | AB10: =IF('Biotech Model'!$B$4<>"READY","",IF(E10=0,0,IF(AB$5<F10,0,G10*MIN(1,(AB$5-F10+1)/H10)*IF(AB$5<=I10,1,(1-J10)^(AB$5-I10)))*K10*L10*M10)) | AC10: =IF('Biotech Model'!$B$4<>"READY","",IF(E10=0,0,IF(AC$5<F10,0,G10*MIN(1,(AC$5-F10+1)/H10)*IF(AC$5<=I10,1,(1-J10)^(AC$5-I10)))*K10*L10*M10)) | AD10: =IF('Biotech Model'!$B$4<>"READY","",IF(E10=0,0,IF(AD$5<F10,0,G10*MIN(1,(AD$5-F10+1)/H10)*IF(AD$5<=I10,1,(1-J10)^(AD$5-I10)))*K10*L10*M10)) | AE10: =IF('Biotech Model'!$B$4<>"READY","",IF(E10=0,0,IF(AE$5<F10,0,G10*MIN(1,(AE$5-F10+1)/H10)*IF(AE$5<=I10,1,(1-J10)^(AE$5-I10)))*K10*L10*M10)) | AF10: =IF('Biotech Model'!$B$4<>"READY","",IF(E10=0,0,IF(AF$5<F10,0,G10*MIN(1,(AF$5-F10+1)/H10)*IF(AF$5<=I10,1,(1-J10)^(AF$5-I10)))*K10*L10*M10)) | AG10: =IF('Biotech Model'!$B$4<>"READY","",IF(E10=0,0,IF(AG$5<F10,0,G10*MIN(1,(AG$5-F10+1)/H10)*IF(AG$5<=I10,1,(1-J10)^(AG$5-I10)))*K10*L10*M10)) | AH10: =IF('Biotech Model'!$B$4<>"READY","",IF(E10=0,0,IF(AH$5<F10,0,G10*MIN(1,(AH$5-F10+1)/H10)*IF(AH$5<=I10,1,(1-J10)^(AH$5-I10)))*K10*L10*M10)) | AI10: =IF('Biotech Model'!$B$4<>"READY","",IF(E10=0,0,IF(AI$5<F10,0,G10*MIN(1,(AI$5-F10+1)/H10)*IF(AI$5<=I10,1,(1-J10)^(AI$5-I10)))*K10*L10*M10)) | AJ10: =IF('Biotech Model'!$B$4<>"READY","",IF(E10=0,0,IF(AJ$5<F10,0,G10*MIN(1,(AJ$5-F10+1)/H10)*IF(AJ$5<=I10,1,(1-J10)^(AJ$5-I10)))*K10*L10*M10)) | AK10: =IF('Biotech Model'!$B$4<>"READY","",IF(E10=0,0,IF(AK$5<F10,0,G10*MIN(1,(AK$5-F10+1)/H10)*IF(AK$5<=I10,1,(1-J10)^(AK$5-I10)))*K10*L10*M10)) | AL10: =IF('Biotech Model'!$B$4<>"READY","",IF(E10=0,0,IF(AL$5<F10,0,G10*MIN(1,(AL$5-F10+1)/H10)*IF(AL$5<=I10,1,(1-J10)^(AL$5-I10)))*K10*L10*M10)) | AM10: =IF('Biotech Model'!$B$4<>"READY","",IF(E10=0,0,IF(AM$5<F10,0,G10*MIN(1,(AM$5-F10+1)/H10)*IF(AM$5<=I10,1,(1-J10)^(AM$5-I10)))*K10*L10*M10)) | AN10: =IF('Biotech Model'!$B$4<>"READY","",IF(E10=0,0,IF(AN$5<F10,0,G10*MIN(1,(AN$5-F10+1)/H10)*IF(AN$5<=I10,1,(1-J10)^(AN$5-I10)))*K10*L10*M10)) | AO10: =IF('Biotech Model'!$B$4<>"READY","",IF(E10=0,0,IF(AO$5<F10,0,G10*MIN(1,(AO$5-F10+1)/H10)*IF(AO$5<=I10,1,(1-J10)^(AO$5-I10)))*K10*L10*M10)) | AP10: =IF('Biotech Model'!$B$4<>"READY","",IF(E10=0,0,IF(AP$5<F10,0,G10*MIN(1,(AP$5-F10+1)/H10)*IF(AP$5<=I10,1,(1-J10)^(AP$5-I10)))*K10*L10*M10)) | AQ10: =IF('Biotech Model'!$B$4<>"READY","",IF(E10=0,0,IF(AQ$5<F10,0,G10*MIN(1,(AQ$5-F10+1)/H10)*IF(AQ$5<=I10,1,(1-J10)^(AQ$5-I10)))*K10*L10*M10)) | AR10: =IF('Biotech Model'!$B$4<>"READY","",IF(E10=0,0,IF(AR$5<F10,0,G10*MIN(1,(AR$5-F10+1)/H10)*IF(AR$5<=I10,1,(1-J10)^(AR$5-I10)))*K10*L10*M10)) | AS10: =IF('Biotech Model'!$B$4<>"READY","",IF(E10=0,0,IF(AS$5<F10,0,G10*MIN(1,(AS$5-F10+1)/H10)*IF(AS$5<=I10,1,(1-J10)^(AS$5-I10)))*K10*L10*M10)) | AT10: =IF('Biotech Model'!$B$4<>"READY","",IF(E10=0,0,IF(AT$5<F10,0,G10*MIN(1,(AT$5-F10+1)/H10)*IF(AT$5<=I10,1,(1-J10)^(AT$5-I10)))*K10*L10*M10)) | AU10: =IF('Biotech Model'!$B$4<>"READY","",IF(E10=0,0,IF(AU$5<F10,0,G10*MIN(1,(AU$5-F10+1)/H10)*IF(AU$5<=I10,1,(1-J10)^(AU$5-I10)))*K10*L10*M10)) | AV10: =IF('Biotech Model'!$B$4<>"READY","",IF(E10=0,0,IF(AV$5<F10,0,G10*MIN(1,(AV$5-F10+1)/H10)*IF(AV$5<=I10,1,(1-J10)^(AV$5-I10)))*K10*L10*M10)) | AW10: =IF('Biotech Model'!$B$4<>"READY","",IF(E10=0,0,IF(AW$5<F10,0,G10*MIN(1,(AW$5-F10+1)/H10)*IF(AW$5<=I10,1,(1-J10)^(AW$5-I10)))*K10*L10*M10)) | AX10: =IF('Biotech Model'!$B$4<>"READY","",IF(E10=0,0,IF(AX$5<F10,0,G10*MIN(1,(AX$5-F10+1)/H10)*IF(AX$5<=I10,1,(1-J10)^(AX$5-I10)))*K10*L10*M10))
A11: mRNA-3927 | B11: mRNA-3927 | C11: registrational study; disclosed; Partner: Recordati | D11: SEC accession 0001682852-26-000033; filed 2026-02-20; report date 2025-12-31; 10-K; SEC 10-K Item 1, Business: In rare disease, our propionic acidemia therapeutic (mRNA-3927) has reached target enrollment in a registrational study. | In January 2026, we entered into a strategic collaboration with Recordati, an international pharmaceutical group, to advance mRNA-3927 through the final stages of clinical development and, if approved, global commercialization. | Propionic acidemia (mRNA-3927) Propionic acidemia (PA) is a rare, inherited metabolic disorder with significant morbidity and mortality, affecting one in 100,000-150,000 individuals worldwide. | Our PA therapy candidate, mRNA-3927, is a novel, IV-administered, LNP-encapsulated dual mRNA therapy that encodes for PCCA and PCCB subunit proteins to restore functional PCC enzyme activity in the liver. | 20 Table of Contents At the International Congress of Inborn Errors of Metabolism (ICIEM) in September 2025, we reported data from the ongoing gl | E11: =IF('Input Required'!$B$3<>"READY","",'Input Required'!F67/1) | F11: =IF('Input Required'!$B$3<>"READY","",'Input Required'!F68/1) | G11: =IF('Input Required'!$B$3<>"READY","",'Input Required'!F69/1000000) | H11: =IF('Input Required'!$B$3<>"READY","",'Input Required'!F70/1) | I11: =IF('Input Required'!$B$3<>"READY","",'Input Required'!F71/1) | J11: =IF('Input Required'!$B$3<>"READY","",'Input Required'!F72/1) | K11: =IF('Input Required'!$B$3<>"READY","",'Input Required'!F73/1) | L11: =IF('Input Required'!$B$3<>"READY","",'Input Required'!F74/1) | M11: =IF('Input Required'!$B$3<>"READY","",'Input Required'!F75/1) | N11: =IF('Input Required'!$B$3<>"READY","",'Input Required'!F76/1000000) | O11: =IF('Biotech Model'!$B$4<>"READY","",SUMPRODUCT(P11:AX11,$P$3:$AX$3)-E11*N11) | P11: =IF('Biotech Model'!$B$4<>"READY","",IF(E11=0,0,IF(P$5<F11,0,G11*MIN(1,(P$5-F11+1)/H11)*IF(P$5<=I11,1,(1-J11)^(P$5-I11)))*K11*L11*M11)) | Q11: =IF('Biotech Model'!$B$4<>"READY","",IF(E11=0,0,IF(Q$5<F11,0,G11*MIN(1,(Q$5-F11+1)/H11)*IF(Q$5<=I11,1,(1-J11)^(Q$5-I11)))*K11*L11*M11)) | R11: =IF('Biotech Model'!$B$4<>"READY","",IF(E11=0,0,IF(R$5<F11,0,G11*MIN(1,(R$5-F11+1)/H11)*IF(R$5<=I11,1,(1-J11)^(R$5-I11)))*K11*L11*M11)) | S11: =IF('Biotech Model'!$B$4<>"READY","",IF(E11=0,0,IF(S$5<F11,0,G11*MIN(1,(S$5-F11+1)/H11)*IF(S$5<=I11,1,(1-J11)^(S$5-I11)))*K11*L11*M11)) | T11: =IF('Biotech Model'!$B$4<>"READY","",IF(E11=0,0,IF(T$5<F11,0,G11*MIN(1,(T$5-F11+1)/H11)*IF(T$5<=I11,1,(1-J11)^(T$5-I11)))*K11*L11*M11)) | U11: =IF('Biotech Model'!$B$4<>"READY","",IF(E11=0,0,IF(U$5<F11,0,G11*MIN(1,(U$5-F11+1)/H11)*IF(U$5<=I11,1,(1-J11)^(U$5-I11)))*K11*L11*M11)) | V11: =IF('Biotech Model'!$B$4<>"READY","",IF(E11=0,0,IF(V$5<F11,0,G11*MIN(1,(V$5-F11+1)/H11)*IF(V$5<=I11,1,(1-J11)^(V$5-I11)))*K11*L11*M11)) | W11: =IF('Biotech Model'!$B$4<>"READY","",IF(E11=0,0,IF(W$5<F11,0,G11*MIN(1,(W$5-F11+1)/H11)*IF(W$5<=I11,1,(1-J11)^(W$5-I11)))*K11*L11*M11)) | X11: =IF('Biotech Model'!$B$4<>"READY","",IF(E11=0,0,IF(X$5<F11,0,G11*MIN(1,(X$5-F11+1)/H11)*IF(X$5<=I11,1,(1-J11)^(X$5-I11)))*K11*L11*M11)) | Y11: =IF('Biotech Model'!$B$4<>"READY","",IF(E11=0,0,IF(Y$5<F11,0,G11*MIN(1,(Y$5-F11+1)/H11)*IF(Y$5<=I11,1,(1-J11)^(Y$5-I11)))*K11*L11*M11)) | Z11: =IF('Biotech Model'!$B$4<>"READY","",IF(E11=0,0,IF(Z$5<F11,0,G11*MIN(1,(Z$5-F11+1)/H11)*IF(Z$5<=I11,1,(1-J11)^(Z$5-I11)))*K11*L11*M11)) | AA11: =IF('Biotech Model'!$B$4<>"READY","",IF(E11=0,0,IF(AA$5<F11,0,G11*MIN(1,(AA$5-F11+1)/H11)*IF(AA$5<=I11,1,(1-J11)^(AA$5-I11)))*K11*L11*M11)) | AB11: =IF('Biotech Model'!$B$4<>"READY","",IF(E11=0,0,IF(AB$5<F11,0,G11*MIN(1,(AB$5-F11+1)/H11)*IF(AB$5<=I11,1,(1-J11)^(AB$5-I11)))*K11*L11*M11)) | AC11: =IF('Biotech Model'!$B$4<>"READY","",IF(E11=0,0,IF(AC$5<F11,0,G11*MIN(1,(AC$5-F11+1)/H11)*IF(AC$5<=I11,1,(1-J11)^(AC$5-I11)))*K11*L11*M11)) | AD11: =IF('Biotech Model'!$B$4<>"READY","",IF(E11=0,0,IF(AD$5<F11,0,G11*MIN(1,(AD$5-F11+1)/H11)*IF(AD$5<=I11,1,(1-J11)^(AD$5-I11)))*K11*L11*M11)) | AE11: =IF('Biotech Model'!$B$4<>"READY","",IF(E11=0,0,IF(AE$5<F11,0,G11*MIN(1,(AE$5-F11+1)/H11)*IF(AE$5<=I11,1,(1-J11)^(AE$5-I11)))*K11*L11*M11)) | AF11: =IF('Biotech Model'!$B$4<>"READY","",IF(E11=0,0,IF(AF$5<F11,0,G11*MIN(1,(AF$5-F11+1)/H11)*IF(AF$5<=I11,1,(1-J11)^(AF$5-I11)))*K11*L11*M11)) | AG11: =IF('Biotech Model'!$B$4<>"READY","",IF(E11=0,0,IF(AG$5<F11,0,G11*MIN(1,(AG$5-F11+1)/H11)*IF(AG$5<=I11,1,(1-J11)^(AG$5-I11)))*K11*L11*M11)) | AH11: =IF('Biotech Model'!$B$4<>"READY","",IF(E11=0,0,IF(AH$5<F11,0,G11*MIN(1,(AH$5-F11+1)/H11)*IF(AH$5<=I11,1,(1-J11)^(AH$5-I11)))*K11*L11*M11)) | AI11: =IF('Biotech Model'!$B$4<>"READY","",IF(E11=0,0,IF(AI$5<F11,0,G11*MIN(1,(AI$5-F11+1)/H11)*IF(AI$5<=I11,1,(1-J11)^(AI$5-I11)))*K11*L11*M11)) | AJ11: =IF('Biotech Model'!$B$4<>"READY","",IF(E11=0,0,IF(AJ$5<F11,0,G11*MIN(1,(AJ$5-F11+1)/H11)*IF(AJ$5<=I11,1,(1-J11)^(AJ$5-I11)))*K11*L11*M11)) | AK11: =IF('Biotech Model'!$B$4<>"READY","",IF(E11=0,0,IF(AK$5<F11,0,G11*MIN(1,(AK$5-F11+1)/H11)*IF(AK$5<=I11,1,(1-J11)^(AK$5-I11)))*K11*L11*M11)) | AL11: =IF('Biotech Model'!$B$4<>"READY","",IF(E11=0,0,IF(AL$5<F11,0,G11*MIN(1,(AL$5-F11+1)/H11)*IF(AL$5<=I11,1,(1-J11)^(AL$5-I11)))*K11*L11*M11)) | AM11: =IF('Biotech Model'!$B$4<>"READY","",IF(E11=0,0,IF(AM$5<F11,0,G11*MIN(1,(AM$5-F11+1)/H11)*IF(AM$5<=I11,1,(1-J11)^(AM$5-I11)))*K11*L11*M11)) | AN11: =IF('Biotech Model'!$B$4<>"READY","",IF(E11=0,0,IF(AN$5<F11,0,G11*MIN(1,(AN$5-F11+1)/H11)*IF(AN$5<=I11,1,(1-J11)^(AN$5-I11)))*K11*L11*M11)) | AO11: =IF('Biotech Model'!$B$4<>"READY","",IF(E11=0,0,IF(AO$5<F11,0,G11*MIN(1,(AO$5-F11+1)/H11)*IF(AO$5<=I11,1,(1-J11)^(AO$5-I11)))*K11*L11*M11)) | AP11: =IF('Biotech Model'!$B$4<>"READY","",IF(E11=0,0,IF(AP$5<F11,0,G11*MIN(1,(AP$5-F11+1)/H11)*IF(AP$5<=I11,1,(1-J11)^(AP$5-I11)))*K11*L11*M11)) | AQ11: =IF('Biotech Model'!$B$4<>"READY","",IF(E11=0,0,IF(AQ$5<F11,0,G11*MIN(1,(AQ$5-F11+1)/H11)*IF(AQ$5<=I11,1,(1-J11)^(AQ$5-I11)))*K11*L11*M11)) | AR11: =IF('Biotech Model'!$B$4<>"READY","",IF(E11=0,0,IF(AR$5<F11,0,G11*MIN(1,(AR$5-F11+1)/H11)*IF(AR$5<=I11,1,(1-J11)^(AR$5-I11)))*K11*L11*M11)) | AS11: =IF('Biotech Model'!$B$4<>"READY","",IF(E11=0,0,IF(AS$5<F11,0,G11*MIN(1,(AS$5-F11+1)/H11)*IF(AS$5<=I11,1,(1-J11)^(AS$5-I11)))*K11*L11*M11)) | AT11: =IF('Biotech Model'!$B$4<>"READY","",IF(E11=0,0,IF(AT$5<F11,0,G11*MIN(1,(AT$5-F11+1)/H11)*IF(AT$5<=I11,1,(1-J11)^(AT$5-I11)))*K11*L11*M11)) | AU11: =IF('Biotech Model'!$B$4<>"READY","",IF(E11=0,0,IF(AU$5<F11,0,G11*MIN(1,(AU$5-F11+1)/H11)*IF(AU$5<=I11,1,(1-J11)^(AU$5-I11)))*K11*L11*M11)) | AV11: =IF('Biotech Model'!$B$4<>"READY","",IF(E11=0,0,IF(AV$5<F11,0,G11*MIN(1,(AV$5-F11+1)/H11)*IF(AV$5<=I11,1,(1-J11)^(AV$5-I11)))*K11*L11*M11)) | AW11: =IF('Biotech Model'!$B$4<>"READY","",IF(E11=0,0,IF(AW$5<F11,0,G11*MIN(1,(AW$5-F11+1)/H11)*IF(AW$5<=I11,1,(1-J11)^(AW$5-I11)))*K11*L11*M11)) | AX11: =IF('Biotech Model'!$B$4<>"READY","",IF(E11=0,0,IF(AX$5<F11,0,G11*MIN(1,(AX$5-F11+1)/H11)*IF(AX$5<=I11,1,(1-J11)^(AX$5-I11)))*K11*L11*M11))
A12: mRNA-3705 | B12: mRNA-3705 | C12: registrational study; disclosed | D12: SEC accession 0001682852-26-000033; filed 2026-02-20; report date 2025-12-31; 10-K; SEC 10-K Item 1, Business: In addition, we expect the registrational study for our methylmalonic acidemia therapeutic (mRNA-3705) to begin in 2026. | Methylmalonic acidemia (mRNA-3705) Methylmalonic acidemia (MMA) is a rare, inherited metabolic disorder with significant morbidity and mortality caused by a deficiency in an enzyme called methylmalonyl-CoA mutase (MUT). | Our MMA therapy candidate, mRNA-3705, is an investigational, lipid nanoparticle-encapsulated therapy administered intravenously that codes for the human MUT (hMUT) enzyme and is hypothesized to restore normal MUT production. | In 2024, the FDA announced that it had selected our MMA therapy candidate, mRNA-3705, for the Support for Clinical trials Advancing Rare Disease Therapeutics (START) program. | mRNA-3705 was generally well-tolerated. | E12: =IF('Input Required'!$B$3<>"READY","",'Input Required'!F77/1) | F12: =IF('Input Required'!$B$3<>"READY","",'Input Required'!F78/1) | G12: =IF('Input Required'!$B$3<>"READY","",'Input Required'!F79/1000000) | H12: =IF('Input Required'!$B$3<>"READY","",'Input Required'!F80/1) | I12: =IF('Input Required'!$B$3<>"READY","",'Input Required'!F81/1) | J12: =IF('Input Required'!$B$3<>"READY","",'Input Required'!F82/1) | K12: =IF('Input Required'!$B$3<>"READY","",'Input Required'!F83/1) | L12: =IF('Input Required'!$B$3<>"READY","",'Input Required'!F84/1) | M12: =IF('Input Required'!$B$3<>"READY","",'Input Required'!F85/1) | N12: =IF('Input Required'!$B$3<>"READY","",'Input Required'!F86/1000000) | O12: =IF('Biotech Model'!$B$4<>"READY","",SUMPRODUCT(P12:AX12,$P$3:$AX$3)-E12*N12) | P12: =IF('Biotech Model'!$B$4<>"READY","",IF(E12=0,0,IF(P$5<F12,0,G12*MIN(1,(P$5-F12+1)/H12)*IF(P$5<=I12,1,(1-J12)^(P$5-I12)))*K12*L12*M12)) | Q12: =IF('Biotech Model'!$B$4<>"READY","",IF(E12=0,0,IF(Q$5<F12,0,G12*MIN(1,(Q$5-F12+1)/H12)*IF(Q$5<=I12,1,(1-J12)^(Q$5-I12)))*K12*L12*M12)) | R12: =IF('Biotech Model'!$B$4<>"READY","",IF(E12=0,0,IF(R$5<F12,0,G12*MIN(1,(R$5-F12+1)/H12)*IF(R$5<=I12,1,(1-J12)^(R$5-I12)))*K12*L12*M12)) | S12: =IF('Biotech Model'!$B$4<>"READY","",IF(E12=0,0,IF(S$5<F12,0,G12*MIN(1,(S$5-F12+1)/H12)*IF(S$5<=I12,1,(1-J12)^(S$5-I12)))*K12*L12*M12)) | T12: =IF('Biotech Model'!$B$4<>"READY","",IF(E12=0,0,IF(T$5<F12,0,G12*MIN(1,(T$5-F12+1)/H12)*IF(T$5<=I12,1,(1-J12)^(T$5-I12)))*K12*L12*M12)) | U12: =IF('Biotech Model'!$B$4<>"READY","",IF(E12=0,0,IF(U$5<F12,0,G12*MIN(1,(U$5-F12+1)/H12)*IF(U$5<=I12,1,(1-J12)^(U$5-I12)))*K12*L12*M12)) | V12: =IF('Biotech Model'!$B$4<>"READY","",IF(E12=0,0,IF(V$5<F12,0,G12*MIN(1,(V$5-F12+1)/H12)*IF(V$5<=I12,1,(1-J12)^(V$5-I12)))*K12*L12*M12)) | W12: =IF('Biotech Model'!$B$4<>"READY","",IF(E12=0,0,IF(W$5<F12,0,G12*MIN(1,(W$5-F12+1)/H12)*IF(W$5<=I12,1,(1-J12)^(W$5-I12)))*K12*L12*M12)) | X12: =IF('Biotech Model'!$B$4<>"READY","",IF(E12=0,0,IF(X$5<F12,0,G12*MIN(1,(X$5-F12+1)/H12)*IF(X$5<=I12,1,(1-J12)^(X$5-I12)))*K12*L12*M12)) | Y12: =IF('Biotech Model'!$B$4<>"READY","",IF(E12=0,0,IF(Y$5<F12,0,G12*MIN(1,(Y$5-F12+1)/H12)*IF(Y$5<=I12,1,(1-J12)^(Y$5-I12)))*K12*L12*M12)) | Z12: =IF('Biotech Model'!$B$4<>"READY","",IF(E12=0,0,IF(Z$5<F12,0,G12*MIN(1,(Z$5-F12+1)/H12)*IF(Z$5<=I12,1,(1-J12)^(Z$5-I12)))*K12*L12*M12)) | AA12: =IF('Biotech Model'!$B$4<>"READY","",IF(E12=0,0,IF(AA$5<F12,0,G12*MIN(1,(AA$5-F12+1)/H12)*IF(AA$5<=I12,1,(1-J12)^(AA$5-I12)))*K12*L12*M12)) | AB12: =IF('Biotech Model'!$B$4<>"READY","",IF(E12=0,0,IF(AB$5<F12,0,G12*MIN(1,(AB$5-F12+1)/H12)*IF(AB$5<=I12,1,(1-J12)^(AB$5-I12)))*K12*L12*M12)) | AC12: =IF('Biotech Model'!$B$4<>"READY","",IF(E12=0,0,IF(AC$5<F12,0,G12*MIN(1,(AC$5-F12+1)/H12)*IF(AC$5<=I12,1,(1-J12)^(AC$5-I12)))*K12*L12*M12)) | AD12: =IF('Biotech Model'!$B$4<>"READY","",IF(E12=0,0,IF(AD$5<F12,0,G12*MIN(1,(AD$5-F12+1)/H12)*IF(AD$5<=I12,1,(1-J12)^(AD$5-I12)))*K12*L12*M12)) | AE12: =IF('Biotech Model'!$B$4<>"READY","",IF(E12=0,0,IF(AE$5<F12,0,G12*MIN(1,(AE$5-F12+1)/H12)*IF(AE$5<=I12,1,(1-J12)^(AE$5-I12)))*K12*L12*M12)) | AF12: =IF('Biotech Model'!$B$4<>"READY","",IF(E12=0,0,IF(AF$5<F12,0,G12*MIN(1,(AF$5-F12+1)/H12)*IF(AF$5<=I12,1,(1-J12)^(AF$5-I12)))*K12*L12*M12)) | AG12: =IF('Biotech Model'!$B$4<>"READY","",IF(E12=0,0,IF(AG$5<F12,0,G12*MIN(1,(AG$5-F12+1)/H12)*IF(AG$5<=I12,1,(1-J12)^(AG$5-I12)))*K12*L12*M12)) | AH12: =IF('Biotech Model'!$B$4<>"READY","",IF(E12=0,0,IF(AH$5<F12,0,G12*MIN(1,(AH$5-F12+1)/H12)*IF(AH$5<=I12,1,(1-J12)^(AH$5-I12)))*K12*L12*M12)) | AI12: =IF('Biotech Model'!$B$4<>"READY","",IF(E12=0,0,IF(AI$5<F12,0,G12*MIN(1,(AI$5-F12+1)/H12)*IF(AI$5<=I12,1,(1-J12)^(AI$5-I12)))*K12*L12*M12)) | AJ12: =IF('Biotech Model'!$B$4<>"READY","",IF(E12=0,0,IF(AJ$5<F12,0,G12*MIN(1,(AJ$5-F12+1)/H12)*IF(AJ$5<=I12,1,(1-J12)^(AJ$5-I12)))*K12*L12*M12)) | AK12: =IF('Biotech Model'!$B$4<>"READY","",IF(E12=0,0,IF(AK$5<F12,0,G12*MIN(1,(AK$5-F12+1)/H12)*IF(AK$5<=I12,1,(1-J12)^(AK$5-I12)))*K12*L12*M12)) | AL12: =IF('Biotech Model'!$B$4<>"READY","",IF(E12=0,0,IF(AL$5<F12,0,G12*MIN(1,(AL$5-F12+1)/H12)*IF(AL$5<=I12,1,(1-J12)^(AL$5-I12)))*K12*L12*M12)) | AM12: =IF('Biotech Model'!$B$4<>"READY","",IF(E12=0,0,IF(AM$5<F12,0,G12*MIN(1,(AM$5-F12+1)/H12)*IF(AM$5<=I12,1,(1-J12)^(AM$5-I12)))*K12*L12*M12)) | AN12: =IF('Biotech Model'!$B$4<>"READY","",IF(E12=0,0,IF(AN$5<F12,0,G12*MIN(1,(AN$5-F12+1)/H12)*IF(AN$5<=I12,1,(1-J12)^(AN$5-I12)))*K12*L12*M12)) | AO12: =IF('Biotech Model'!$B$4<>"READY","",IF(E12=0,0,IF(AO$5<F12,0,G12*MIN(1,(AO$5-F12+1)/H12)*IF(AO$5<=I12,1,(1-J12)^(AO$5-I12)))*K12*L12*M12)) | AP12: =IF('Biotech Model'!$B$4<>"READY","",IF(E12=0,0,IF(AP$5<F12,0,G12*MIN(1,(AP$5-F12+1)/H12)*IF(AP$5<=I12,1,(1-J12)^(AP$5-I12)))*K12*L12*M12)) | AQ12: =IF('Biotech Model'!$B$4<>"READY","",IF(E12=0,0,IF(AQ$5<F12,0,G12*MIN(1,(AQ$5-F12+1)/H12)*IF(AQ$5<=I12,1,(1-J12)^(AQ$5-I12)))*K12*L12*M12)) | AR12: =IF('Biotech Model'!$B$4<>"READY","",IF(E12=0,0,IF(AR$5<F12,0,G12*MIN(1,(AR$5-F12+1)/H12)*IF(AR$5<=I12,1,(1-J12)^(AR$5-I12)))*K12*L12*M12)) | AS12: =IF('Biotech Model'!$B$4<>"READY","",IF(E12=0,0,IF(AS$5<F12,0,G12*MIN(1,(AS$5-F12+1)/H12)*IF(AS$5<=I12,1,(1-J12)^(AS$5-I12)))*K12*L12*M12)) | AT12: =IF('Biotech Model'!$B$4<>"READY","",IF(E12=0,0,IF(AT$5<F12,0,G12*MIN(1,(AT$5-F12+1)/H12)*IF(AT$5<=I12,1,(1-J12)^(AT$5-I12)))*K12*L12*M12)) | AU12: =IF('Biotech Model'!$B$4<>"READY","",IF(E12=0,0,IF(AU$5<F12,0,G12*MIN(1,(AU$5-F12+1)/H12)*IF(AU$5<=I12,1,(1-J12)^(AU$5-I12)))*K12*L12*M12)) | AV12: =IF('Biotech Model'!$B$4<>"READY","",IF(E12=0,0,IF(AV$5<F12,0,G12*MIN(1,(AV$5-F12+1)/H12)*IF(AV$5<=I12,1,(1-J12)^(AV$5-I12)))*K12*L12*M12)) | AW12: =IF('Biotech Model'!$B$4<>"READY","",IF(E12=0,0,IF(AW$5<F12,0,G12*MIN(1,(AW$5-F12+1)/H12)*IF(AW$5<=I12,1,(1-J12)^(AW$5-I12)))*K12*L12*M12)) | AX12: =IF('Biotech Model'!$B$4<>"READY","",IF(E12=0,0,IF(AX$5<F12,0,G12*MIN(1,(AX$5-F12+1)/H12)*IF(AX$5<=I12,1,(1-J12)^(AX$5-I12)))*K12*L12*M12))
A13: mRNA-1018 | B13: mRNA-1018 | C13: Phase 1/2; disclosed | D13: SEC accession 0001682852-26-000033; filed 2026-02-20; report date 2025-12-31; 10-K; SEC 10-K Item 1, Business: 14 Table of Contents Pandemic influenza vaccine (mRNA-1018) An influenza pandemic is a global outbreak of a new influenza A virus that is very different from recently circulating human seasonal influenza A viruses. | In 2023, we initiated a Phase 1/2 study to generate safety and immunogenicity data of our investigational pandemic influenza vaccine (mRNA-1018) in healthy adults 18 years of age and older. | In October 2025, we presented results of this study showing that mRNA-1018 demonstrated a rapid, potent and durable immune response. | 3 million to support a pivotal Phase 3 clinical trial that aims to help advance our investigational mRNA-based H5 pandemic influenza vaccine candidate, mRNA-1018, to licensure. | E13: =IF('Input Required'!$B$3<>"READY","",'Input Required'!F87/1) | F13: =IF('Input Required'!$B$3<>"READY","",'Input Required'!F88/1) | G13: =IF('Input Required'!$B$3<>"READY","",'Input Required'!F89/1000000) | H13: =IF('Input Required'!$B$3<>"READY","",'Input Required'!F90/1) | I13: =IF('Input Required'!$B$3<>"READY","",'Input Required'!F91/1) | J13: =IF('Input Required'!$B$3<>"READY","",'Input Required'!F92/1) | K13: =IF('Input Required'!$B$3<>"READY","",'Input Required'!F93/1) | L13: =IF('Input Required'!$B$3<>"READY","",'Input Required'!F94/1) | M13: =IF('Input Required'!$B$3<>"READY","",'Input Required'!F95/1) | N13: =IF('Input Required'!$B$3<>"READY","",'Input Required'!F96/1000000) | O13: =IF('Biotech Model'!$B$4<>"READY","",SUMPRODUCT(P13:AX13,$P$3:$AX$3)-E13*N13) | P13: =IF('Biotech Model'!$B$4<>"READY","",IF(E13=0,0,IF(P$5<F13,0,G13*MIN(1,(P$5-F13+1)/H13)*IF(P$5<=I13,1,(1-J13)^(P$5-I13)))*K13*L13*M13)) | Q13: =IF('Biotech Model'!$B$4<>"READY","",IF(E13=0,0,IF(Q$5<F13,0,G13*MIN(1,(Q$5-F13+1)/H13)*IF(Q$5<=I13,1,(1-J13)^(Q$5-I13)))*K13*L13*M13)) | R13: =IF('Biotech Model'!$B$4<>"READY","",IF(E13=0,0,IF(R$5<F13,0,G13*MIN(1,(R$5-F13+1)/H13)*IF(R$5<=I13,1,(1-J13)^(R$5-I13)))*K13*L13*M13)) | S13: =IF('Biotech Model'!$B$4<>"READY","",IF(E13=0,0,IF(S$5<F13,0,G13*MIN(1,(S$5-F13+1)/H13)*IF(S$5<=I13,1,(1-J13)^(S$5-I13)))*K13*L13*M13)) | T13: =IF('Biotech Model'!$B$4<>"READY","",IF(E13=0,0,IF(T$5<F13,0,G13*MIN(1,(T$5-F13+1)/H13)*IF(T$5<=I13,1,(1-J13)^(T$5-I13)))*K13*L13*M13)) | U13: =IF('Biotech Model'!$B$4<>"READY","",IF(E13=0,0,IF(U$5<F13,0,G13*MIN(1,(U$5-F13+1)/H13)*IF(U$5<=I13,1,(1-J13)^(U$5-I13)))*K13*L13*M13)) | V13: =IF('Biotech Model'!$B$4<>"READY","",IF(E13=0,0,IF(V$5<F13,0,G13*MIN(1,(V$5-F13+1)/H13)*IF(V$5<=I13,1,(1-J13)^(V$5-I13)))*K13*L13*M13)) | W13: =IF('Biotech Model'!$B$4<>"READY","",IF(E13=0,0,IF(W$5<F13,0,G13*MIN(1,(W$5-F13+1)/H13)*IF(W$5<=I13,1,(1-J13)^(W$5-I13)))*K13*L13*M13)) | X13: =IF('Biotech Model'!$B$4<>"READY","",IF(E13=0,0,IF(X$5<F13,0,G13*MIN(1,(X$5-F13+1)/H13)*IF(X$5<=I13,1,(1-J13)^(X$5-I13)))*K13*L13*M13)) | Y13: =IF('Biotech Model'!$B$4<>"READY","",IF(E13=0,0,IF(Y$5<F13,0,G13*MIN(1,(Y$5-F13+1)/H13)*IF(Y$5<=I13,1,(1-J13)^(Y$5-I13)))*K13*L13*M13)) | Z13: =IF('Biotech Model'!$B$4<>"READY","",IF(E13=0,0,IF(Z$5<F13,0,G13*MIN(1,(Z$5-F13+1)/H13)*IF(Z$5<=I13,1,(1-J13)^(Z$5-I13)))*K13*L13*M13)) | AA13: =IF('Biotech Model'!$B$4<>"READY","",IF(E13=0,0,IF(AA$5<F13,0,G13*MIN(1,(AA$5-F13+1)/H13)*IF(AA$5<=I13,1,(1-J13)^(AA$5-I13)))*K13*L13*M13)) | AB13: =IF('Biotech Model'!$B$4<>"READY","",IF(E13=0,0,IF(AB$5<F13,0,G13*MIN(1,(AB$5-F13+1)/H13)*IF(AB$5<=I13,1,(1-J13)^(AB$5-I13)))*K13*L13*M13)) | AC13: =IF('Biotech Model'!$B$4<>"READY","",IF(E13=0,0,IF(AC$5<F13,0,G13*MIN(1,(AC$5-F13+1)/H13)*IF(AC$5<=I13,1,(1-J13)^(AC$5-I13)))*K13*L13*M13)) | AD13: =IF('Biotech Model'!$B$4<>"READY","",IF(E13=0,0,IF(AD$5<F13,0,G13*MIN(1,(AD$5-F13+1)/H13)*IF(AD$5<=I13,1,(1-J13)^(AD$5-I13)))*K13*L13*M13)) | AE13: =IF('Biotech Model'!$B$4<>"READY","",IF(E13=0,0,IF(AE$5<F13,0,G13*MIN(1,(AE$5-F13+1)/H13)*IF(AE$5<=I13,1,(1-J13)^(AE$5-I13)))*K13*L13*M13)) | AF13: =IF('Biotech Model'!$B$4<>"READY","",IF(E13=0,0,IF(AF$5<F13,0,G13*MIN(1,(AF$5-F13+1)/H13)*IF(AF$5<=I13,1,(1-J13)^(AF$5-I13)))*K13*L13*M13)) | AG13: =IF('Biotech Model'!$B$4<>"READY","",IF(E13=0,0,IF(AG$5<F13,0,G13*MIN(1,(AG$5-F13+1)/H13)*IF(AG$5<=I13,1,(1-J13)^(AG$5-I13)))*K13*L13*M13)) | AH13: =IF('Biotech Model'!$B$4<>"READY","",IF(E13=0,0,IF(AH$5<F13,0,G13*MIN(1,(AH$5-F13+1)/H13)*IF(AH$5<=I13,1,(1-J13)^(AH$5-I13)))*K13*L13*M13)) | AI13: =IF('Biotech Model'!$B$4<>"READY","",IF(E13=0,0,IF(AI$5<F13,0,G13*MIN(1,(AI$5-F13+1)/H13)*IF(AI$5<=I13,1,(1-J13)^(AI$5-I13)))*K13*L13*M13)) | AJ13: =IF('Biotech Model'!$B$4<>"READY","",IF(E13=0,0,IF(AJ$5<F13,0,G13*MIN(1,(AJ$5-F13+1)/H13)*IF(AJ$5<=I13,1,(1-J13)^(AJ$5-I13)))*K13*L13*M13)) | AK13: =IF('Biotech Model'!$B$4<>"READY","",IF(E13=0,0,IF(AK$5<F13,0,G13*MIN(1,(AK$5-F13+1)/H13)*IF(AK$5<=I13,1,(1-J13)^(AK$5-I13)))*K13*L13*M13)) | AL13: =IF('Biotech Model'!$B$4<>"READY","",IF(E13=0,0,IF(AL$5<F13,0,G13*MIN(1,(AL$5-F13+1)/H13)*IF(AL$5<=I13,1,(1-J13)^(AL$5-I13)))*K13*L13*M13)) | AM13: =IF('Biotech Model'!$B$4<>"READY","",IF(E13=0,0,IF(AM$5<F13,0,G13*MIN(1,(AM$5-F13+1)/H13)*IF(AM$5<=I13,1,(1-J13)^(AM$5-I13)))*K13*L13*M13)) | AN13: =IF('Biotech Model'!$B$4<>"READY","",IF(E13=0,0,IF(AN$5<F13,0,G13*MIN(1,(AN$5-F13+1)/H13)*IF(AN$5<=I13,1,(1-J13)^(AN$5-I13)))*K13*L13*M13)) | AO13: =IF('Biotech Model'!$B$4<>"READY","",IF(E13=0,0,IF(AO$5<F13,0,G13*MIN(1,(AO$5-F13+1)/H13)*IF(AO$5<=I13,1,(1-J13)^(AO$5-I13)))*K13*L13*M13)) | AP13: =IF('Biotech Model'!$B$4<>"READY","",IF(E13=0,0,IF(AP$5<F13,0,G13*MIN(1,(AP$5-F13+1)/H13)*IF(AP$5<=I13,1,(1-J13)^(AP$5-I13)))*K13*L13*M13)) | AQ13: =IF('Biotech Model'!$B$4<>"READY","",IF(E13=0,0,IF(AQ$5<F13,0,G13*MIN(1,(AQ$5-F13+1)/H13)*IF(AQ$5<=I13,1,(1-J13)^(AQ$5-I13)))*K13*L13*M13)) | AR13: =IF('Biotech Model'!$B$4<>"READY","",IF(E13=0,0,IF(AR$5<F13,0,G13*MIN(1,(AR$5-F13+1)/H13)*IF(AR$5<=I13,1,(1-J13)^(AR$5-I13)))*K13*L13*M13)) | AS13: =IF('Biotech Model'!$B$4<>"READY","",IF(E13=0,0,IF(AS$5<F13,0,G13*MIN(1,(AS$5-F13+1)/H13)*IF(AS$5<=I13,1,(1-J13)^(AS$5-I13)))*K13*L13*M13)) | AT13: =IF('Biotech Model'!$B$4<>"READY","",IF(E13=0,0,IF(AT$5<F13,0,G13*MIN(1,(AT$5-F13+1)/H13)*IF(AT$5<=I13,1,(1-J13)^(AT$5-I13)))*K13*L13*M13)) | AU13: =IF('Biotech Model'!$B$4<>"READY","",IF(E13=0,0,IF(AU$5<F13,0,G13*MIN(1,(AU$5-F13+1)/H13)*IF(AU$5<=I13,1,(1-J13)^(AU$5-I13)))*K13*L13*M13)) | AV13: =IF('Biotech Model'!$B$4<>"READY","",IF(E13=0,0,IF(AV$5<F13,0,G13*MIN(1,(AV$5-F13+1)/H13)*IF(AV$5<=I13,1,(1-J13)^(AV$5-I13)))*K13*L13*M13)) | AW13: =IF('Biotech Model'!$B$4<>"READY","",IF(E13=0,0,IF(AW$5<F13,0,G13*MIN(1,(AW$5-F13+1)/H13)*IF(AW$5<=I13,1,(1-J13)^(AW$5-I13)))*K13*L13*M13)) | AX13: =IF('Biotech Model'!$B$4<>"READY","",IF(E13=0,0,IF(AX$5<F13,0,G13*MIN(1,(AX$5-F13+1)/H13)*IF(AX$5<=I13,1,(1-J13)^(AX$5-I13)))*K13*L13*M13))
A14: mRNA-1195 | B14: mRNA-1195 | C14: Phase 2; disclosed | D14: SEC accession 0001682852-26-000033; filed 2026-02-20; report date 2025-12-31; 10-K; SEC 10-K Item 1, Business: 15 Table of Contents EBV vaccines (mRNA-1189 and mRNA-1195) Epstein-Barr virus (EBV) is a member of the herpesvirus family that infects approximately 90% of people in the U. | We are developing two mRNA candidates against EBV —a prophylactic vaccine to prevent infectious mononucleosis (mRNA-1189) and a therapeutic to treat multiple sclerosis (mRNA-1195). | mRNA-1195 encodes for entry glycoproteins and latent antigens aimed at inducing an antibody and T cell response, and will be investigated in the context of multiple sclerosis and post-transplant lymphoproliferative disorder. | We are currently conducting Phase 2, randomized, observer-blind, placebo-controlled studies of mRNA-1189 and mRNA-1195. | Our Phase 1 study for mRNA-1195 is fully enrolled, and in November 2025 we shared data that showed mRNA-1195 was immunogenic and generally well tolerated across all dose levels. | Our mRNA-119 | E14: =IF('Input Required'!$B$3<>"READY","",'Input Required'!F97/1) | F14: =IF('Input Required'!$B$3<>"READY","",'Input Required'!F98/1) | G14: =IF('Input Required'!$B$3<>"READY","",'Input Required'!F99/1000000) | H14: =IF('Input Required'!$B$3<>"READY","",'Input Required'!F100/1) | I14: =IF('Input Required'!$B$3<>"READY","",'Input Required'!F101/1) | J14: =IF('Input Required'!$B$3<>"READY","",'Input Required'!F102/1) | K14: =IF('Input Required'!$B$3<>"READY","",'Input Required'!F103/1) | L14: =IF('Input Required'!$B$3<>"READY","",'Input Required'!F104/1) | M14: =IF('Input Required'!$B$3<>"READY","",'Input Required'!F105/1) | N14: =IF('Input Required'!$B$3<>"READY","",'Input Required'!F106/1000000) | O14: =IF('Biotech Model'!$B$4<>"READY","",SUMPRODUCT(P14:AX14,$P$3:$AX$3)-E14*N14) | P14: =IF('Biotech Model'!$B$4<>"READY","",IF(E14=0,0,IF(P$5<F14,0,G14*MIN(1,(P$5-F14+1)/H14)*IF(P$5<=I14,1,(1-J14)^(P$5-I14)))*K14*L14*M14)) | Q14: =IF('Biotech Model'!$B$4<>"READY","",IF(E14=0,0,IF(Q$5<F14,0,G14*MIN(1,(Q$5-F14+1)/H14)*IF(Q$5<=I14,1,(1-J14)^(Q$5-I14)))*K14*L14*M14)) | R14: =IF('Biotech Model'!$B$4<>"READY","",IF(E14=0,0,IF(R$5<F14,0,G14*MIN(1,(R$5-F14+1)/H14)*IF(R$5<=I14,1,(1-J14)^(R$5-I14)))*K14*L14*M14)) | S14: =IF('Biotech Model'!$B$4<>"READY","",IF(E14=0,0,IF(S$5<F14,0,G14*MIN(1,(S$5-F14+1)/H14)*IF(S$5<=I14,1,(1-J14)^(S$5-I14)))*K14*L14*M14)) | T14: =IF('Biotech Model'!$B$4<>"READY","",IF(E14=0,0,IF(T$5<F14,0,G14*MIN(1,(T$5-F14+1)/H14)*IF(T$5<=I14,1,(1-J14)^(T$5-I14)))*K14*L14*M14)) | U14: =IF('Biotech Model'!$B$4<>"READY","",IF(E14=0,0,IF(U$5<F14,0,G14*MIN(1,(U$5-F14+1)/H14)*IF(U$5<=I14,1,(1-J14)^(U$5-I14)))*K14*L14*M14)) | V14: =IF('Biotech Model'!$B$4<>"READY","",IF(E14=0,0,IF(V$5<F14,0,G14*MIN(1,(V$5-F14+1)/H14)*IF(V$5<=I14,1,(1-J14)^(V$5-I14)))*K14*L14*M14)) | W14: =IF('Biotech Model'!$B$4<>"READY","",IF(E14=0,0,IF(W$5<F14,0,G14*MIN(1,(W$5-F14+1)/H14)*IF(W$5<=I14,1,(1-J14)^(W$5-I14)))*K14*L14*M14)) | X14: =IF('Biotech Model'!$B$4<>"READY","",IF(E14=0,0,IF(X$5<F14,0,G14*MIN(1,(X$5-F14+1)/H14)*IF(X$5<=I14,1,(1-J14)^(X$5-I14)))*K14*L14*M14)) | Y14: =IF('Biotech Model'!$B$4<>"READY","",IF(E14=0,0,IF(Y$5<F14,0,G14*MIN(1,(Y$5-F14+1)/H14)*IF(Y$5<=I14,1,(1-J14)^(Y$5-I14)))*K14*L14*M14)) | Z14: =IF('Biotech Model'!$B$4<>"READY","",IF(E14=0,0,IF(Z$5<F14,0,G14*MIN(1,(Z$5-F14+1)/H14)*IF(Z$5<=I14,1,(1-J14)^(Z$5-I14)))*K14*L14*M14)) | AA14: =IF('Biotech Model'!$B$4<>"READY","",IF(E14=0,0,IF(AA$5<F14,0,G14*MIN(1,(AA$5-F14+1)/H14)*IF(AA$5<=I14,1,(1-J14)^(AA$5-I14)))*K14*L14*M14)) | AB14: =IF('Biotech Model'!$B$4<>"READY","",IF(E14=0,0,IF(AB$5<F14,0,G14*MIN(1,(AB$5-F14+1)/H14)*IF(AB$5<=I14,1,(1-J14)^(AB$5-I14)))*K14*L14*M14)) | AC14: =IF('Biotech Model'!$B$4<>"READY","",IF(E14=0,0,IF(AC$5<F14,0,G14*MIN(1,(AC$5-F14+1)/H14)*IF(AC$5<=I14,1,(1-J14)^(AC$5-I14)))*K14*L14*M14)) | AD14: =IF('Biotech Model'!$B$4<>"READY","",IF(E14=0,0,IF(AD$5<F14,0,G14*MIN(1,(AD$5-F14+1)/H14)*IF(AD$5<=I14,1,(1-J14)^(AD$5-I14)))*K14*L14*M14)) | AE14: =IF('Biotech Model'!$B$4<>"READY","",IF(E14=0,0,IF(AE$5<F14,0,G14*MIN(1,(AE$5-F14+1)/H14)*IF(AE$5<=I14,1,(1-J14)^(AE$5-I14)))*K14*L14*M14)) | AF14: =IF('Biotech Model'!$B$4<>"READY","",IF(E14=0,0,IF(AF$5<F14,0,G14*MIN(1,(AF$5-F14+1)/H14)*IF(AF$5<=I14,1,(1-J14)^(AF$5-I14)))*K14*L14*M14)) | AG14: =IF('Biotech Model'!$B$4<>"READY","",IF(E14=0,0,IF(AG$5<F14,0,G14*MIN(1,(AG$5-F14+1)/H14)*IF(AG$5<=I14,1,(1-J14)^(AG$5-I14)))*K14*L14*M14)) | AH14: =IF('Biotech Model'!$B$4<>"READY","",IF(E14=0,0,IF(AH$5<F14,0,G14*MIN(1,(AH$5-F14+1)/H14)*IF(AH$5<=I14,1,(1-J14)^(AH$5-I14)))*K14*L14*M14)) | AI14: =IF('Biotech Model'!$B$4<>"READY","",IF(E14=0,0,IF(AI$5<F14,0,G14*MIN(1,(AI$5-F14+1)/H14)*IF(AI$5<=I14,1,(1-J14)^(AI$5-I14)))*K14*L14*M14)) | AJ14: =IF('Biotech Model'!$B$4<>"READY","",IF(E14=0,0,IF(AJ$5<F14,0,G14*MIN(1,(AJ$5-F14+1)/H14)*IF(AJ$5<=I14,1,(1-J14)^(AJ$5-I14)))*K14*L14*M14)) | AK14: =IF('Biotech Model'!$B$4<>"READY","",IF(E14=0,0,IF(AK$5<F14,0,G14*MIN(1,(AK$5-F14+1)/H14)*IF(AK$5<=I14,1,(1-J14)^(AK$5-I14)))*K14*L14*M14)) | AL14: =IF('Biotech Model'!$B$4<>"READY","",IF(E14=0,0,IF(AL$5<F14,0,G14*MIN(1,(AL$5-F14+1)/H14)*IF(AL$5<=I14,1,(1-J14)^(AL$5-I14)))*K14*L14*M14)) | AM14: =IF('Biotech Model'!$B$4<>"READY","",IF(E14=0,0,IF(AM$5<F14,0,G14*MIN(1,(AM$5-F14+1)/H14)*IF(AM$5<=I14,1,(1-J14)^(AM$5-I14)))*K14*L14*M14)) | AN14: =IF('Biotech Model'!$B$4<>"READY","",IF(E14=0,0,IF(AN$5<F14,0,G14*MIN(1,(AN$5-F14+1)/H14)*IF(AN$5<=I14,1,(1-J14)^(AN$5-I14)))*K14*L14*M14)) | AO14: =IF('Biotech Model'!$B$4<>"READY","",IF(E14=0,0,IF(AO$5<F14,0,G14*MIN(1,(AO$5-F14+1)/H14)*IF(AO$5<=I14,1,(1-J14)^(AO$5-I14)))*K14*L14*M14)) | AP14: =IF('Biotech Model'!$B$4<>"READY","",IF(E14=0,0,IF(AP$5<F14,0,G14*MIN(1,(AP$5-F14+1)/H14)*IF(AP$5<=I14,1,(1-J14)^(AP$5-I14)))*K14*L14*M14)) | AQ14: =IF('Biotech Model'!$B$4<>"READY","",IF(E14=0,0,IF(AQ$5<F14,0,G14*MIN(1,(AQ$5-F14+1)/H14)*IF(AQ$5<=I14,1,(1-J14)^(AQ$5-I14)))*K14*L14*M14)) | AR14: =IF('Biotech Model'!$B$4<>"READY","",IF(E14=0,0,IF(AR$5<F14,0,G14*MIN(1,(AR$5-F14+1)/H14)*IF(AR$5<=I14,1,(1-J14)^(AR$5-I14)))*K14*L14*M14)) | AS14: =IF('Biotech Model'!$B$4<>"READY","",IF(E14=0,0,IF(AS$5<F14,0,G14*MIN(1,(AS$5-F14+1)/H14)*IF(AS$5<=I14,1,(1-J14)^(AS$5-I14)))*K14*L14*M14)) | AT14: =IF('Biotech Model'!$B$4<>"READY","",IF(E14=0,0,IF(AT$5<F14,0,G14*MIN(1,(AT$5-F14+1)/H14)*IF(AT$5<=I14,1,(1-J14)^(AT$5-I14)))*K14*L14*M14)) | AU14: =IF('Biotech Model'!$B$4<>"READY","",IF(E14=0,0,IF(AU$5<F14,0,G14*MIN(1,(AU$5-F14+1)/H14)*IF(AU$5<=I14,1,(1-J14)^(AU$5-I14)))*K14*L14*M14)) | AV14: =IF('Biotech Model'!$B$4<>"READY","",IF(E14=0,0,IF(AV$5<F14,0,G14*MIN(1,(AV$5-F14+1)/H14)*IF(AV$5<=I14,1,(1-J14)^(AV$5-I14)))*K14*L14*M14)) | AW14: =IF('Biotech Model'!$B$4<>"READY","",IF(E14=0,0,IF(AW$5<F14,0,G14*MIN(1,(AW$5-F14+1)/H14)*IF(AW$5<=I14,1,(1-J14)^(AW$5-I14)))*K14*L14*M14)) | AX14: =IF('Biotech Model'!$B$4<>"READY","",IF(E14=0,0,IF(AX$5<F14,0,G14*MIN(1,(AX$5-F14+1)/H14)*IF(AX$5<=I14,1,(1-J14)^(AX$5-I14)))*K14*L14*M14))
A15: mRNA-1982 | B15: mRNA-1982 | C15: Phase 2; disclosed | D15: SEC accession 0001682852-26-000033; filed 2026-02-20; report date 2025-12-31; 10-K; SEC 10-K Item 1, Business: Bacterial vaccines Lyme vaccines (mRNA-1975 and mRNA-1982) Lyme disease is an illness caused by Borrelia bacteria transmitted by the bite of infected ticks. | This trial evaluates the safety and immunogenicity of a heptavalent (mRNA-1975) and monovalent (mRNA-1982) approach in parallel. | mRNA-1982 targets Borrelia burgdorferi, responsible for nearly all Lyme cases in North America, while mRNA-1975 targets the four major Borrelia species causing disease in North America and Europe. | The program will progress to a Phase 2 dose ranging study of mRNA-1982. | E15: =IF('Input Required'!$B$3<>"READY","",'Input Required'!F107/1) | F15: =IF('Input Required'!$B$3<>"READY","",'Input Required'!F108/1) | G15: =IF('Input Required'!$B$3<>"READY","",'Input Required'!F109/1000000) | H15: =IF('Input Required'!$B$3<>"READY","",'Input Required'!F110/1) | I15: =IF('Input Required'!$B$3<>"READY","",'Input Required'!F111/1) | J15: =IF('Input Required'!$B$3<>"READY","",'Input Required'!F112/1) | K15: =IF('Input Required'!$B$3<>"READY","",'Input Required'!F113/1) | L15: =IF('Input Required'!$B$3<>"READY","",'Input Required'!F114/1) | M15: =IF('Input Required'!$B$3<>"READY","",'Input Required'!F115/1) | N15: =IF('Input Required'!$B$3<>"READY","",'Input Required'!F116/1000000) | O15: =IF('Biotech Model'!$B$4<>"READY","",SUMPRODUCT(P15:AX15,$P$3:$AX$3)-E15*N15) | P15: =IF('Biotech Model'!$B$4<>"READY","",IF(E15=0,0,IF(P$5<F15,0,G15*MIN(1,(P$5-F15+1)/H15)*IF(P$5<=I15,1,(1-J15)^(P$5-I15)))*K15*L15*M15)) | Q15: =IF('Biotech Model'!$B$4<>"READY","",IF(E15=0,0,IF(Q$5<F15,0,G15*MIN(1,(Q$5-F15+1)/H15)*IF(Q$5<=I15,1,(1-J15)^(Q$5-I15)))*K15*L15*M15)) | R15: =IF('Biotech Model'!$B$4<>"READY","",IF(E15=0,0,IF(R$5<F15,0,G15*MIN(1,(R$5-F15+1)/H15)*IF(R$5<=I15,1,(1-J15)^(R$5-I15)))*K15*L15*M15)) | S15: =IF('Biotech Model'!$B$4<>"READY","",IF(E15=0,0,IF(S$5<F15,0,G15*MIN(1,(S$5-F15+1)/H15)*IF(S$5<=I15,1,(1-J15)^(S$5-I15)))*K15*L15*M15)) | T15: =IF('Biotech Model'!$B$4<>"READY","",IF(E15=0,0,IF(T$5<F15,0,G15*MIN(1,(T$5-F15+1)/H15)*IF(T$5<=I15,1,(1-J15)^(T$5-I15)))*K15*L15*M15)) | U15: =IF('Biotech Model'!$B$4<>"READY","",IF(E15=0,0,IF(U$5<F15,0,G15*MIN(1,(U$5-F15+1)/H15)*IF(U$5<=I15,1,(1-J15)^(U$5-I15)))*K15*L15*M15)) | V15: =IF('Biotech Model'!$B$4<>"READY","",IF(E15=0,0,IF(V$5<F15,0,G15*MIN(1,(V$5-F15+1)/H15)*IF(V$5<=I15,1,(1-J15)^(V$5-I15)))*K15*L15*M15)) | W15: =IF('Biotech Model'!$B$4<>"READY","",IF(E15=0,0,IF(W$5<F15,0,G15*MIN(1,(W$5-F15+1)/H15)*IF(W$5<=I15,1,(1-J15)^(W$5-I15)))*K15*L15*M15)) | X15: =IF('Biotech Model'!$B$4<>"READY","",IF(E15=0,0,IF(X$5<F15,0,G15*MIN(1,(X$5-F15+1)/H15)*IF(X$5<=I15,1,(1-J15)^(X$5-I15)))*K15*L15*M15)) | Y15: =IF('Biotech Model'!$B$4<>"READY","",IF(E15=0,0,IF(Y$5<F15,0,G15*MIN(1,(Y$5-F15+1)/H15)*IF(Y$5<=I15,1,(1-J15)^(Y$5-I15)))*K15*L15*M15)) | Z15: =IF('Biotech Model'!$B$4<>"READY","",IF(E15=0,0,IF(Z$5<F15,0,G15*MIN(1,(Z$5-F15+1)/H15)*IF(Z$5<=I15,1,(1-J15)^(Z$5-I15)))*K15*L15*M15)) | AA15: =IF('Biotech Model'!$B$4<>"READY","",IF(E15=0,0,IF(AA$5<F15,0,G15*MIN(1,(AA$5-F15+1)/H15)*IF(AA$5<=I15,1,(1-J15)^(AA$5-I15)))*K15*L15*M15)) | AB15: =IF('Biotech Model'!$B$4<>"READY","",IF(E15=0,0,IF(AB$5<F15,0,G15*MIN(1,(AB$5-F15+1)/H15)*IF(AB$5<=I15,1,(1-J15)^(AB$5-I15)))*K15*L15*M15)) | AC15: =IF('Biotech Model'!$B$4<>"READY","",IF(E15=0,0,IF(AC$5<F15,0,G15*MIN(1,(AC$5-F15+1)/H15)*IF(AC$5<=I15,1,(1-J15)^(AC$5-I15)))*K15*L15*M15)) | AD15: =IF('Biotech Model'!$B$4<>"READY","",IF(E15=0,0,IF(AD$5<F15,0,G15*MIN(1,(AD$5-F15+1)/H15)*IF(AD$5<=I15,1,(1-J15)^(AD$5-I15)))*K15*L15*M15)) | AE15: =IF('Biotech Model'!$B$4<>"READY","",IF(E15=0,0,IF(AE$5<F15,0,G15*MIN(1,(AE$5-F15+1)/H15)*IF(AE$5<=I15,1,(1-J15)^(AE$5-I15)))*K15*L15*M15)) | AF15: =IF('Biotech Model'!$B$4<>"READY","",IF(E15=0,0,IF(AF$5<F15,0,G15*MIN(1,(AF$5-F15+1)/H15)*IF(AF$5<=I15,1,(1-J15)^(AF$5-I15)))*K15*L15*M15)) | AG15: =IF('Biotech Model'!$B$4<>"READY","",IF(E15=0,0,IF(AG$5<F15,0,G15*MIN(1,(AG$5-F15+1)/H15)*IF(AG$5<=I15,1,(1-J15)^(AG$5-I15)))*K15*L15*M15)) | AH15: =IF('Biotech Model'!$B$4<>"READY","",IF(E15=0,0,IF(AH$5<F15,0,G15*MIN(1,(AH$5-F15+1)/H15)*IF(AH$5<=I15,1,(1-J15)^(AH$5-I15)))*K15*L15*M15)) | AI15: =IF('Biotech Model'!$B$4<>"READY","",IF(E15=0,0,IF(AI$5<F15,0,G15*MIN(1,(AI$5-F15+1)/H15)*IF(AI$5<=I15,1,(1-J15)^(AI$5-I15)))*K15*L15*M15)) | AJ15: =IF('Biotech Model'!$B$4<>"READY","",IF(E15=0,0,IF(AJ$5<F15,0,G15*MIN(1,(AJ$5-F15+1)/H15)*IF(AJ$5<=I15,1,(1-J15)^(AJ$5-I15)))*K15*L15*M15)) | AK15: =IF('Biotech Model'!$B$4<>"READY","",IF(E15=0,0,IF(AK$5<F15,0,G15*MIN(1,(AK$5-F15+1)/H15)*IF(AK$5<=I15,1,(1-J15)^(AK$5-I15)))*K15*L15*M15)) | AL15: =IF('Biotech Model'!$B$4<>"READY","",IF(E15=0,0,IF(AL$5<F15,0,G15*MIN(1,(AL$5-F15+1)/H15)*IF(AL$5<=I15,1,(1-J15)^(AL$5-I15)))*K15*L15*M15)) | AM15: =IF('Biotech Model'!$B$4<>"READY","",IF(E15=0,0,IF(AM$5<F15,0,G15*MIN(1,(AM$5-F15+1)/H15)*IF(AM$5<=I15,1,(1-J15)^(AM$5-I15)))*K15*L15*M15)) | AN15: =IF('Biotech Model'!$B$4<>"READY","",IF(E15=0,0,IF(AN$5<F15,0,G15*MIN(1,(AN$5-F15+1)/H15)*IF(AN$5<=I15,1,(1-J15)^(AN$5-I15)))*K15*L15*M15)) | AO15: =IF('Biotech Model'!$B$4<>"READY","",IF(E15=0,0,IF(AO$5<F15,0,G15*MIN(1,(AO$5-F15+1)/H15)*IF(AO$5<=I15,1,(1-J15)^(AO$5-I15)))*K15*L15*M15)) | AP15: =IF('Biotech Model'!$B$4<>"READY","",IF(E15=0,0,IF(AP$5<F15,0,G15*MIN(1,(AP$5-F15+1)/H15)*IF(AP$5<=I15,1,(1-J15)^(AP$5-I15)))*K15*L15*M15)) | AQ15: =IF('Biotech Model'!$B$4<>"READY","",IF(E15=0,0,IF(AQ$5<F15,0,G15*MIN(1,(AQ$5-F15+1)/H15)*IF(AQ$5<=I15,1,(1-J15)^(AQ$5-I15)))*K15*L15*M15)) | AR15: =IF('Biotech Model'!$B$4<>"READY","",IF(E15=0,0,IF(AR$5<F15,0,G15*MIN(1,(AR$5-F15+1)/H15)*IF(AR$5<=I15,1,(1-J15)^(AR$5-I15)))*K15*L15*M15)) | AS15: =IF('Biotech Model'!$B$4<>"READY","",IF(E15=0,0,IF(AS$5<F15,0,G15*MIN(1,(AS$5-F15+1)/H15)*IF(AS$5<=I15,1,(1-J15)^(AS$5-I15)))*K15*L15*M15)) | AT15: =IF('Biotech Model'!$B$4<>"READY","",IF(E15=0,0,IF(AT$5<F15,0,G15*MIN(1,(AT$5-F15+1)/H15)*IF(AT$5<=I15,1,(1-J15)^(AT$5-I15)))*K15*L15*M15)) | AU15: =IF('Biotech Model'!$B$4<>"READY","",IF(E15=0,0,IF(AU$5<F15,0,G15*MIN(1,(AU$5-F15+1)/H15)*IF(AU$5<=I15,1,(1-J15)^(AU$5-I15)))*K15*L15*M15)) | AV15: =IF('Biotech Model'!$B$4<>"READY","",IF(E15=0,0,IF(AV$5<F15,0,G15*MIN(1,(AV$5-F15+1)/H15)*IF(AV$5<=I15,1,(1-J15)^(AV$5-I15)))*K15*L15*M15)) | AW15: =IF('Biotech Model'!$B$4<>"READY","",IF(E15=0,0,IF(AW$5<F15,0,G15*MIN(1,(AW$5-F15+1)/H15)*IF(AW$5<=I15,1,(1-J15)^(AW$5-I15)))*K15*L15*M15)) | AX15: =IF('Biotech Model'!$B$4<>"READY","",IF(E15=0,0,IF(AX$5<F15,0,G15*MIN(1,(AX$5-F15+1)/H15)*IF(AX$5<=I15,1,(1-J15)^(AX$5-I15)))*K15*L15*M15))
A16: mRNA-1769 | B16: mRNA-1769 | C16: Phase 1/2; disclosed | D16: SEC accession 0001682852-26-000033; filed 2026-02-20; report date 2025-12-31; 10-K; SEC 10-K Item 1, Business: Mpox vaccine (mRNA-1769) Mpox (formerly known as monkeypox) is an infectious disease caused by the mpox virus, a member of the Orthopoxvirus genus, which also includes Variola virus, the virus that caused smallpox. | Our mpox vaccine candidate, mRNA-1769, is designed to express four antigens from the mpox virus. | In preclinical studies using a stringent non-human primate model, vaccination with mRNA-1769 resulted in fewer lesions, reduced viral replication, and stronger neutralizing and functional antibody responses compared with existing treatments. | The immune responses induced by mRNA-1769 also showed broad activity against several orthopoxviruses. | We conducted a randomized, placebo-controlled, dose-ranging Phase 1/2 study to evaluate the safety, tolerability, and immune response of three dose levels of mRNA-1769 in healthy adult participants. | Interim analysis showed that mRNA-1 | E16: =IF('Input Required'!$B$3<>"READY","",'Input Required'!F117/1) | F16: =IF('Input Required'!$B$3<>"READY","",'Input Required'!F118/1) | G16: =IF('Input Required'!$B$3<>"READY","",'Input Required'!F119/1000000) | H16: =IF('Input Required'!$B$3<>"READY","",'Input Required'!F120/1) | I16: =IF('Input Required'!$B$3<>"READY","",'Input Required'!F121/1) | J16: =IF('Input Required'!$B$3<>"READY","",'Input Required'!F122/1) | K16: =IF('Input Required'!$B$3<>"READY","",'Input Required'!F123/1) | L16: =IF('Input Required'!$B$3<>"READY","",'Input Required'!F124/1) | M16: =IF('Input Required'!$B$3<>"READY","",'Input Required'!F125/1) | N16: =IF('Input Required'!$B$3<>"READY","",'Input Required'!F126/1000000) | O16: =IF('Biotech Model'!$B$4<>"READY","",SUMPRODUCT(P16:AX16,$P$3:$AX$3)-E16*N16) | P16: =IF('Biotech Model'!$B$4<>"READY","",IF(E16=0,0,IF(P$5<F16,0,G16*MIN(1,(P$5-F16+1)/H16)*IF(P$5<=I16,1,(1-J16)^(P$5-I16)))*K16*L16*M16)) | Q16: =IF('Biotech Model'!$B$4<>"READY","",IF(E16=0,0,IF(Q$5<F16,0,G16*MIN(1,(Q$5-F16+1)/H16)*IF(Q$5<=I16,1,(1-J16)^(Q$5-I16)))*K16*L16*M16)) | R16: =IF('Biotech Model'!$B$4<>"READY","",IF(E16=0,0,IF(R$5<F16,0,G16*MIN(1,(R$5-F16+1)/H16)*IF(R$5<=I16,1,(1-J16)^(R$5-I16)))*K16*L16*M16)) | S16: =IF('Biotech Model'!$B$4<>"READY","",IF(E16=0,0,IF(S$5<F16,0,G16*MIN(1,(S$5-F16+1)/H16)*IF(S$5<=I16,1,(1-J16)^(S$5-I16)))*K16*L16*M16)) | T16: =IF('Biotech Model'!$B$4<>"READY","",IF(E16=0,0,IF(T$5<F16,0,G16*MIN(1,(T$5-F16+1)/H16)*IF(T$5<=I16,1,(1-J16)^(T$5-I16)))*K16*L16*M16)) | U16: =IF('Biotech Model'!$B$4<>"READY","",IF(E16=0,0,IF(U$5<F16,0,G16*MIN(1,(U$5-F16+1)/H16)*IF(U$5<=I16,1,(1-J16)^(U$5-I16)))*K16*L16*M16)) | V16: =IF('Biotech Model'!$B$4<>"READY","",IF(E16=0,0,IF(V$5<F16,0,G16*MIN(1,(V$5-F16+1)/H16)*IF(V$5<=I16,1,(1-J16)^(V$5-I16)))*K16*L16*M16)) | W16: =IF('Biotech Model'!$B$4<>"READY","",IF(E16=0,0,IF(W$5<F16,0,G16*MIN(1,(W$5-F16+1)/H16)*IF(W$5<=I16,1,(1-J16)^(W$5-I16)))*K16*L16*M16)) | X16: =IF('Biotech Model'!$B$4<>"READY","",IF(E16=0,0,IF(X$5<F16,0,G16*MIN(1,(X$5-F16+1)/H16)*IF(X$5<=I16,1,(1-J16)^(X$5-I16)))*K16*L16*M16)) | Y16: =IF('Biotech Model'!$B$4<>"READY","",IF(E16=0,0,IF(Y$5<F16,0,G16*MIN(1,(Y$5-F16+1)/H16)*IF(Y$5<=I16,1,(1-J16)^(Y$5-I16)))*K16*L16*M16)) | Z16: =IF('Biotech Model'!$B$4<>"READY","",IF(E16=0,0,IF(Z$5<F16,0,G16*MIN(1,(Z$5-F16+1)/H16)*IF(Z$5<=I16,1,(1-J16)^(Z$5-I16)))*K16*L16*M16)) | AA16: =IF('Biotech Model'!$B$4<>"READY","",IF(E16=0,0,IF(AA$5<F16,0,G16*MIN(1,(AA$5-F16+1)/H16)*IF(AA$5<=I16,1,(1-J16)^(AA$5-I16)))*K16*L16*M16)) | AB16: =IF('Biotech Model'!$B$4<>"READY","",IF(E16=0,0,IF(AB$5<F16,0,G16*MIN(1,(AB$5-F16+1)/H16)*IF(AB$5<=I16,1,(1-J16)^(AB$5-I16)))*K16*L16*M16)) | AC16: =IF('Biotech Model'!$B$4<>"READY","",IF(E16=0,0,IF(AC$5<F16,0,G16*MIN(1,(AC$5-F16+1)/H16)*IF(AC$5<=I16,1,(1-J16)^(AC$5-I16)))*K16*L16*M16)) | AD16: =IF('Biotech Model'!$B$4<>"READY","",IF(E16=0,0,IF(AD$5<F16,0,G16*MIN(1,(AD$5-F16+1)/H16)*IF(AD$5<=I16,1,(1-J16)^(AD$5-I16)))*K16*L16*M16)) | AE16: =IF('Biotech Model'!$B$4<>"READY","",IF(E16=0,0,IF(AE$5<F16,0,G16*MIN(1,(AE$5-F16+1)/H16)*IF(AE$5<=I16,1,(1-J16)^(AE$5-I16)))*K16*L16*M16)) | AF16: =IF('Biotech Model'!$B$4<>"READY","",IF(E16=0,0,IF(AF$5<F16,0,G16*MIN(1,(AF$5-F16+1)/H16)*IF(AF$5<=I16,1,(1-J16)^(AF$5-I16)))*K16*L16*M16)) | AG16: =IF('Biotech Model'!$B$4<>"READY","",IF(E16=0,0,IF(AG$5<F16,0,G16*MIN(1,(AG$5-F16+1)/H16)*IF(AG$5<=I16,1,(1-J16)^(AG$5-I16)))*K16*L16*M16)) | AH16: =IF('Biotech Model'!$B$4<>"READY","",IF(E16=0,0,IF(AH$5<F16,0,G16*MIN(1,(AH$5-F16+1)/H16)*IF(AH$5<=I16,1,(1-J16)^(AH$5-I16)))*K16*L16*M16)) | AI16: =IF('Biotech Model'!$B$4<>"READY","",IF(E16=0,0,IF(AI$5<F16,0,G16*MIN(1,(AI$5-F16+1)/H16)*IF(AI$5<=I16,1,(1-J16)^(AI$5-I16)))*K16*L16*M16)) | AJ16: =IF('Biotech Model'!$B$4<>"READY","",IF(E16=0,0,IF(AJ$5<F16,0,G16*MIN(1,(AJ$5-F16+1)/H16)*IF(AJ$5<=I16,1,(1-J16)^(AJ$5-I16)))*K16*L16*M16)) | AK16: =IF('Biotech Model'!$B$4<>"READY","",IF(E16=0,0,IF(AK$5<F16,0,G16*MIN(1,(AK$5-F16+1)/H16)*IF(AK$5<=I16,1,(1-J16)^(AK$5-I16)))*K16*L16*M16)) | AL16: =IF('Biotech Model'!$B$4<>"READY","",IF(E16=0,0,IF(AL$5<F16,0,G16*MIN(1,(AL$5-F16+1)/H16)*IF(AL$5<=I16,1,(1-J16)^(AL$5-I16)))*K16*L16*M16)) | AM16: =IF('Biotech Model'!$B$4<>"READY","",IF(E16=0,0,IF(AM$5<F16,0,G16*MIN(1,(AM$5-F16+1)/H16)*IF(AM$5<=I16,1,(1-J16)^(AM$5-I16)))*K16*L16*M16)) | AN16: =IF('Biotech Model'!$B$4<>"READY","",IF(E16=0,0,IF(AN$5<F16,0,G16*MIN(1,(AN$5-F16+1)/H16)*IF(AN$5<=I16,1,(1-J16)^(AN$5-I16)))*K16*L16*M16)) | AO16: =IF('Biotech Model'!$B$4<>"READY","",IF(E16=0,0,IF(AO$5<F16,0,G16*MIN(1,(AO$5-F16+1)/H16)*IF(AO$5<=I16,1,(1-J16)^(AO$5-I16)))*K16*L16*M16)) | AP16: =IF('Biotech Model'!$B$4<>"READY","",IF(E16=0,0,IF(AP$5<F16,0,G16*MIN(1,(AP$5-F16+1)/H16)*IF(AP$5<=I16,1,(1-J16)^(AP$5-I16)))*K16*L16*M16)) | AQ16: =IF('Biotech Model'!$B$4<>"READY","",IF(E16=0,0,IF(AQ$5<F16,0,G16*MIN(1,(AQ$5-F16+1)/H16)*IF(AQ$5<=I16,1,(1-J16)^(AQ$5-I16)))*K16*L16*M16)) | AR16: =IF('Biotech Model'!$B$4<>"READY","",IF(E16=0,0,IF(AR$5<F16,0,G16*MIN(1,(AR$5-F16+1)/H16)*IF(AR$5<=I16,1,(1-J16)^(AR$5-I16)))*K16*L16*M16)) | AS16: =IF('Biotech Model'!$B$4<>"READY","",IF(E16=0,0,IF(AS$5<F16,0,G16*MIN(1,(AS$5-F16+1)/H16)*IF(AS$5<=I16,1,(1-J16)^(AS$5-I16)))*K16*L16*M16)) | AT16: =IF('Biotech Model'!$B$4<>"READY","",IF(E16=0,0,IF(AT$5<F16,0,G16*MIN(1,(AT$5-F16+1)/H16)*IF(AT$5<=I16,1,(1-J16)^(AT$5-I16)))*K16*L16*M16)) | AU16: =IF('Biotech Model'!$B$4<>"READY","",IF(E16=0,0,IF(AU$5<F16,0,G16*MIN(1,(AU$5-F16+1)/H16)*IF(AU$5<=I16,1,(1-J16)^(AU$5-I16)))*K16*L16*M16)) | AV16: =IF('Biotech Model'!$B$4<>"READY","",IF(E16=0,0,IF(AV$5<F16,0,G16*MIN(1,(AV$5-F16+1)/H16)*IF(AV$5<=I16,1,(1-J16)^(AV$5-I16)))*K16*L16*M16)) | AW16: =IF('Biotech Model'!$B$4<>"READY","",IF(E16=0,0,IF(AW$5<F16,0,G16*MIN(1,(AW$5-F16+1)/H16)*IF(AW$5<=I16,1,(1-J16)^(AW$5-I16)))*K16*L16*M16)) | AX16: =IF('Biotech Model'!$B$4<>"READY","",IF(E16=0,0,IF(AX$5<F16,0,G16*MIN(1,(AX$5-F16+1)/H16)*IF(AX$5<=I16,1,(1-J16)^(AX$5-I16)))*K16*L16*M16))
A17: mRNA-4106 | B17: mRNA-4106 | C17: Phase 2; disclosed | D17: SEC accession 0001682852-26-000033; filed 2026-02-20; report date 2025-12-31; 10-K; SEC 10-K Item 1, Business: We have also expanded our oncology portfolio with early-stage programs, including mRNA-4106 (a cancer antigen therapy), mRNA-2808 (a T-cell engager), and mRNA-4203 (a cell-therapy enhancer). | The Phase 2 portion of the study includes cohorts in first-line metastatic melanoma, second-line+ metastatic melanoma and first-line metastatic NSCLC Cancer antigen therapy (mRNA-4106) mRNA-4106 is a cancer antigen therapy offering broad coverage across tumor types. | E17: =IF('Input Required'!$B$3<>"READY","",'Input Required'!F127/1) | F17: =IF('Input Required'!$B$3<>"READY","",'Input Required'!F128/1) | G17: =IF('Input Required'!$B$3<>"READY","",'Input Required'!F129/1000000) | H17: =IF('Input Required'!$B$3<>"READY","",'Input Required'!F130/1) | I17: =IF('Input Required'!$B$3<>"READY","",'Input Required'!F131/1) | J17: =IF('Input Required'!$B$3<>"READY","",'Input Required'!F132/1) | K17: =IF('Input Required'!$B$3<>"READY","",'Input Required'!F133/1) | L17: =IF('Input Required'!$B$3<>"READY","",'Input Required'!F134/1) | M17: =IF('Input Required'!$B$3<>"READY","",'Input Required'!F135/1) | N17: =IF('Input Required'!$B$3<>"READY","",'Input Required'!F136/1000000) | O17: =IF('Biotech Model'!$B$4<>"READY","",SUMPRODUCT(P17:AX17,$P$3:$AX$3)-E17*N17) | P17: =IF('Biotech Model'!$B$4<>"READY","",IF(E17=0,0,IF(P$5<F17,0,G17*MIN(1,(P$5-F17+1)/H17)*IF(P$5<=I17,1,(1-J17)^(P$5-I17)))*K17*L17*M17)) | Q17: =IF('Biotech Model'!$B$4<>"READY","",IF(E17=0,0,IF(Q$5<F17,0,G17*MIN(1,(Q$5-F17+1)/H17)*IF(Q$5<=I17,1,(1-J17)^(Q$5-I17)))*K17*L17*M17)) | R17: =IF('Biotech Model'!$B$4<>"READY","",IF(E17=0,0,IF(R$5<F17,0,G17*MIN(1,(R$5-F17+1)/H17)*IF(R$5<=I17,1,(1-J17)^(R$5-I17)))*K17*L17*M17)) | S17: =IF('Biotech Model'!$B$4<>"READY","",IF(E17=0,0,IF(S$5<F17,0,G17*MIN(1,(S$5-F17+1)/H17)*IF(S$5<=I17,1,(1-J17)^(S$5-I17)))*K17*L17*M17)) | T17: =IF('Biotech Model'!$B$4<>"READY","",IF(E17=0,0,IF(T$5<F17,0,G17*MIN(1,(T$5-F17+1)/H17)*IF(T$5<=I17,1,(1-J17)^(T$5-I17)))*K17*L17*M17)) | U17: =IF('Biotech Model'!$B$4<>"READY","",IF(E17=0,0,IF(U$5<F17,0,G17*MIN(1,(U$5-F17+1)/H17)*IF(U$5<=I17,1,(1-J17)^(U$5-I17)))*K17*L17*M17)) | V17: =IF('Biotech Model'!$B$4<>"READY","",IF(E17=0,0,IF(V$5<F17,0,G17*MIN(1,(V$5-F17+1)/H17)*IF(V$5<=I17,1,(1-J17)^(V$5-I17)))*K17*L17*M17)) | W17: =IF('Biotech Model'!$B$4<>"READY","",IF(E17=0,0,IF(W$5<F17,0,G17*MIN(1,(W$5-F17+1)/H17)*IF(W$5<=I17,1,(1-J17)^(W$5-I17)))*K17*L17*M17)) | X17: =IF('Biotech Model'!$B$4<>"READY","",IF(E17=0,0,IF(X$5<F17,0,G17*MIN(1,(X$5-F17+1)/H17)*IF(X$5<=I17,1,(1-J17)^(X$5-I17)))*K17*L17*M17)) | Y17: =IF('Biotech Model'!$B$4<>"READY","",IF(E17=0,0,IF(Y$5<F17,0,G17*MIN(1,(Y$5-F17+1)/H17)*IF(Y$5<=I17,1,(1-J17)^(Y$5-I17)))*K17*L17*M17)) | Z17: =IF('Biotech Model'!$B$4<>"READY","",IF(E17=0,0,IF(Z$5<F17,0,G17*MIN(1,(Z$5-F17+1)/H17)*IF(Z$5<=I17,1,(1-J17)^(Z$5-I17)))*K17*L17*M17)) | AA17: =IF('Biotech Model'!$B$4<>"READY","",IF(E17=0,0,IF(AA$5<F17,0,G17*MIN(1,(AA$5-F17+1)/H17)*IF(AA$5<=I17,1,(1-J17)^(AA$5-I17)))*K17*L17*M17)) | AB17: =IF('Biotech Model'!$B$4<>"READY","",IF(E17=0,0,IF(AB$5<F17,0,G17*MIN(1,(AB$5-F17+1)/H17)*IF(AB$5<=I17,1,(1-J17)^(AB$5-I17)))*K17*L17*M17)) | AC17: =IF('Biotech Model'!$B$4<>"READY","",IF(E17=0,0,IF(AC$5<F17,0,G17*MIN(1,(AC$5-F17+1)/H17)*IF(AC$5<=I17,1,(1-J17)^(AC$5-I17)))*K17*L17*M17)) | AD17: =IF('Biotech Model'!$B$4<>"READY","",IF(E17=0,0,IF(AD$5<F17,0,G17*MIN(1,(AD$5-F17+1)/H17)*IF(AD$5<=I17,1,(1-J17)^(AD$5-I17)))*K17*L17*M17)) | AE17: =IF('Biotech Model'!$B$4<>"READY","",IF(E17=0,0,IF(AE$5<F17,0,G17*MIN(1,(AE$5-F17+1)/H17)*IF(AE$5<=I17,1,(1-J17)^(AE$5-I17)))*K17*L17*M17)) | AF17: =IF('Biotech Model'!$B$4<>"READY","",IF(E17=0,0,IF(AF$5<F17,0,G17*MIN(1,(AF$5-F17+1)/H17)*IF(AF$5<=I17,1,(1-J17)^(AF$5-I17)))*K17*L17*M17)) | AG17: =IF('Biotech Model'!$B$4<>"READY","",IF(E17=0,0,IF(AG$5<F17,0,G17*MIN(1,(AG$5-F17+1)/H17)*IF(AG$5<=I17,1,(1-J17)^(AG$5-I17)))*K17*L17*M17)) | AH17: =IF('Biotech Model'!$B$4<>"READY","",IF(E17=0,0,IF(AH$5<F17,0,G17*MIN(1,(AH$5-F17+1)/H17)*IF(AH$5<=I17,1,(1-J17)^(AH$5-I17)))*K17*L17*M17)) | AI17: =IF('Biotech Model'!$B$4<>"READY","",IF(E17=0,0,IF(AI$5<F17,0,G17*MIN(1,(AI$5-F17+1)/H17)*IF(AI$5<=I17,1,(1-J17)^(AI$5-I17)))*K17*L17*M17)) | AJ17: =IF('Biotech Model'!$B$4<>"READY","",IF(E17=0,0,IF(AJ$5<F17,0,G17*MIN(1,(AJ$5-F17+1)/H17)*IF(AJ$5<=I17,1,(1-J17)^(AJ$5-I17)))*K17*L17*M17)) | AK17: =IF('Biotech Model'!$B$4<>"READY","",IF(E17=0,0,IF(AK$5<F17,0,G17*MIN(1,(AK$5-F17+1)/H17)*IF(AK$5<=I17,1,(1-J17)^(AK$5-I17)))*K17*L17*M17)) | AL17: =IF('Biotech Model'!$B$4<>"READY","",IF(E17=0,0,IF(AL$5<F17,0,G17*MIN(1,(AL$5-F17+1)/H17)*IF(AL$5<=I17,1,(1-J17)^(AL$5-I17)))*K17*L17*M17)) | AM17: =IF('Biotech Model'!$B$4<>"READY","",IF(E17=0,0,IF(AM$5<F17,0,G17*MIN(1,(AM$5-F17+1)/H17)*IF(AM$5<=I17,1,(1-J17)^(AM$5-I17)))*K17*L17*M17)) | AN17: =IF('Biotech Model'!$B$4<>"READY","",IF(E17=0,0,IF(AN$5<F17,0,G17*MIN(1,(AN$5-F17+1)/H17)*IF(AN$5<=I17,1,(1-J17)^(AN$5-I17)))*K17*L17*M17)) | AO17: =IF('Biotech Model'!$B$4<>"READY","",IF(E17=0,0,IF(AO$5<F17,0,G17*MIN(1,(AO$5-F17+1)/H17)*IF(AO$5<=I17,1,(1-J17)^(AO$5-I17)))*K17*L17*M17)) | AP17: =IF('Biotech Model'!$B$4<>"READY","",IF(E17=0,0,IF(AP$5<F17,0,G17*MIN(1,(AP$5-F17+1)/H17)*IF(AP$5<=I17,1,(1-J17)^(AP$5-I17)))*K17*L17*M17)) | AQ17: =IF('Biotech Model'!$B$4<>"READY","",IF(E17=0,0,IF(AQ$5<F17,0,G17*MIN(1,(AQ$5-F17+1)/H17)*IF(AQ$5<=I17,1,(1-J17)^(AQ$5-I17)))*K17*L17*M17)) | AR17: =IF('Biotech Model'!$B$4<>"READY","",IF(E17=0,0,IF(AR$5<F17,0,G17*MIN(1,(AR$5-F17+1)/H17)*IF(AR$5<=I17,1,(1-J17)^(AR$5-I17)))*K17*L17*M17)) | AS17: =IF('Biotech Model'!$B$4<>"READY","",IF(E17=0,0,IF(AS$5<F17,0,G17*MIN(1,(AS$5-F17+1)/H17)*IF(AS$5<=I17,1,(1-J17)^(AS$5-I17)))*K17*L17*M17)) | AT17: =IF('Biotech Model'!$B$4<>"READY","",IF(E17=0,0,IF(AT$5<F17,0,G17*MIN(1,(AT$5-F17+1)/H17)*IF(AT$5<=I17,1,(1-J17)^(AT$5-I17)))*K17*L17*M17)) | AU17: =IF('Biotech Model'!$B$4<>"READY","",IF(E17=0,0,IF(AU$5<F17,0,G17*MIN(1,(AU$5-F17+1)/H17)*IF(AU$5<=I17,1,(1-J17)^(AU$5-I17)))*K17*L17*M17)) | AV17: =IF('Biotech Model'!$B$4<>"READY","",IF(E17=0,0,IF(AV$5<F17,0,G17*MIN(1,(AV$5-F17+1)/H17)*IF(AV$5<=I17,1,(1-J17)^(AV$5-I17)))*K17*L17*M17)) | AW17: =IF('Biotech Model'!$B$4<>"READY","",IF(E17=0,0,IF(AW$5<F17,0,G17*MIN(1,(AW$5-F17+1)/H17)*IF(AW$5<=I17,1,(1-J17)^(AW$5-I17)))*K17*L17*M17)) | AX17: =IF('Biotech Model'!$B$4<>"READY","",IF(E17=0,0,IF(AX$5<F17,0,G17*MIN(1,(AX$5-F17+1)/H17)*IF(AX$5<=I17,1,(1-J17)^(AX$5-I17)))*K17*L17*M17))
A18: mRNA-2808 | B18: mRNA-2808 | C18: Phase 1 / 2; disclosed | D18: SEC accession 0001682852-26-000033; filed 2026-02-20; report date 2025-12-31; 10-K; SEC 10-K Item 1, Business: We have also expanded our oncology portfolio with early-stage programs, including mRNA-4106 (a cancer antigen therapy), mRNA-2808 (a T-cell engager), and mRNA-4203 (a cell-therapy enhancer). | T-cell engager (mRNA-2808) mRNA-2808 is a T-cell engager targeting surface antigens in multiple myeloma and is currently dosing in a Phase 1 / 2 clinical study. | E18: =IF('Input Required'!$B$3<>"READY","",'Input Required'!F137/1) | F18: =IF('Input Required'!$B$3<>"READY","",'Input Required'!F138/1) | G18: =IF('Input Required'!$B$3<>"READY","",'Input Required'!F139/1000000) | H18: =IF('Input Required'!$B$3<>"READY","",'Input Required'!F140/1) | I18: =IF('Input Required'!$B$3<>"READY","",'Input Required'!F141/1) | J18: =IF('Input Required'!$B$3<>"READY","",'Input Required'!F142/1) | K18: =IF('Input Required'!$B$3<>"READY","",'Input Required'!F143/1) | L18: =IF('Input Required'!$B$3<>"READY","",'Input Required'!F144/1) | M18: =IF('Input Required'!$B$3<>"READY","",'Input Required'!F145/1) | N18: =IF('Input Required'!$B$3<>"READY","",'Input Required'!F146/1000000) | O18: =IF('Biotech Model'!$B$4<>"READY","",SUMPRODUCT(P18:AX18,$P$3:$AX$3)-E18*N18) | P18: =IF('Biotech Model'!$B$4<>"READY","",IF(E18=0,0,IF(P$5<F18,0,G18*MIN(1,(P$5-F18+1)/H18)*IF(P$5<=I18,1,(1-J18)^(P$5-I18)))*K18*L18*M18)) | Q18: =IF('Biotech Model'!$B$4<>"READY","",IF(E18=0,0,IF(Q$5<F18,0,G18*MIN(1,(Q$5-F18+1)/H18)*IF(Q$5<=I18,1,(1-J18)^(Q$5-I18)))*K18*L18*M18)) | R18: =IF('Biotech Model'!$B$4<>"READY","",IF(E18=0,0,IF(R$5<F18,0,G18*MIN(1,(R$5-F18+1)/H18)*IF(R$5<=I18,1,(1-J18)^(R$5-I18)))*K18*L18*M18)) | S18: =IF('Biotech Model'!$B$4<>"READY","",IF(E18=0,0,IF(S$5<F18,0,G18*MIN(1,(S$5-F18+1)/H18)*IF(S$5<=I18,1,(1-J18)^(S$5-I18)))*K18*L18*M18)) | T18: =IF('Biotech Model'!$B$4<>"READY","",IF(E18=0,0,IF(T$5<F18,0,G18*MIN(1,(T$5-F18+1)/H18)*IF(T$5<=I18,1,(1-J18)^(T$5-I18)))*K18*L18*M18)) | U18: =IF('Biotech Model'!$B$4<>"READY","",IF(E18=0,0,IF(U$5<F18,0,G18*MIN(1,(U$5-F18+1)/H18)*IF(U$5<=I18,1,(1-J18)^(U$5-I18)))*K18*L18*M18)) | V18: =IF('Biotech Model'!$B$4<>"READY","",IF(E18=0,0,IF(V$5<F18,0,G18*MIN(1,(V$5-F18+1)/H18)*IF(V$5<=I18,1,(1-J18)^(V$5-I18)))*K18*L18*M18)) | W18: =IF('Biotech Model'!$B$4<>"READY","",IF(E18=0,0,IF(W$5<F18,0,G18*MIN(1,(W$5-F18+1)/H18)*IF(W$5<=I18,1,(1-J18)^(W$5-I18)))*K18*L18*M18)) | X18: =IF('Biotech Model'!$B$4<>"READY","",IF(E18=0,0,IF(X$5<F18,0,G18*MIN(1,(X$5-F18+1)/H18)*IF(X$5<=I18,1,(1-J18)^(X$5-I18)))*K18*L18*M18)) | Y18: =IF('Biotech Model'!$B$4<>"READY","",IF(E18=0,0,IF(Y$5<F18,0,G18*MIN(1,(Y$5-F18+1)/H18)*IF(Y$5<=I18,1,(1-J18)^(Y$5-I18)))*K18*L18*M18)) | Z18: =IF('Biotech Model'!$B$4<>"READY","",IF(E18=0,0,IF(Z$5<F18,0,G18*MIN(1,(Z$5-F18+1)/H18)*IF(Z$5<=I18,1,(1-J18)^(Z$5-I18)))*K18*L18*M18)) | AA18: =IF('Biotech Model'!$B$4<>"READY","",IF(E18=0,0,IF(AA$5<F18,0,G18*MIN(1,(AA$5-F18+1)/H18)*IF(AA$5<=I18,1,(1-J18)^(AA$5-I18)))*K18*L18*M18)) | AB18: =IF('Biotech Model'!$B$4<>"READY","",IF(E18=0,0,IF(AB$5<F18,0,G18*MIN(1,(AB$5-F18+1)/H18)*IF(AB$5<=I18,1,(1-J18)^(AB$5-I18)))*K18*L18*M18)) | AC18: =IF('Biotech Model'!$B$4<>"READY","",IF(E18=0,0,IF(AC$5<F18,0,G18*MIN(1,(AC$5-F18+1)/H18)*IF(AC$5<=I18,1,(1-J18)^(AC$5-I18)))*K18*L18*M18)) | AD18: =IF('Biotech Model'!$B$4<>"READY","",IF(E18=0,0,IF(AD$5<F18,0,G18*MIN(1,(AD$5-F18+1)/H18)*IF(AD$5<=I18,1,(1-J18)^(AD$5-I18)))*K18*L18*M18)) | AE18: =IF('Biotech Model'!$B$4<>"READY","",IF(E18=0,0,IF(AE$5<F18,0,G18*MIN(1,(AE$5-F18+1)/H18)*IF(AE$5<=I18,1,(1-J18)^(AE$5-I18)))*K18*L18*M18)) | AF18: =IF('Biotech Model'!$B$4<>"READY","",IF(E18=0,0,IF(AF$5<F18,0,G18*MIN(1,(AF$5-F18+1)/H18)*IF(AF$5<=I18,1,(1-J18)^(AF$5-I18)))*K18*L18*M18)) | AG18: =IF('Biotech Model'!$B$4<>"READY","",IF(E18=0,0,IF(AG$5<F18,0,G18*MIN(1,(AG$5-F18+1)/H18)*IF(AG$5<=I18,1,(1-J18)^(AG$5-I18)))*K18*L18*M18)) | AH18: =IF('Biotech Model'!$B$4<>"READY","",IF(E18=0,0,IF(AH$5<F18,0,G18*MIN(1,(AH$5-F18+1)/H18)*IF(AH$5<=I18,1,(1-J18)^(AH$5-I18)))*K18*L18*M18)) | AI18: =IF('Biotech Model'!$B$4<>"READY","",IF(E18=0,0,IF(AI$5<F18,0,G18*MIN(1,(AI$5-F18+1)/H18)*IF(AI$5<=I18,1,(1-J18)^(AI$5-I18)))*K18*L18*M18)) | AJ18: =IF('Biotech Model'!$B$4<>"READY","",IF(E18=0,0,IF(AJ$5<F18,0,G18*MIN(1,(AJ$5-F18+1)/H18)*IF(AJ$5<=I18,1,(1-J18)^(AJ$5-I18)))*K18*L18*M18)) | AK18: =IF('Biotech Model'!$B$4<>"READY","",IF(E18=0,0,IF(AK$5<F18,0,G18*MIN(1,(AK$5-F18+1)/H18)*IF(AK$5<=I18,1,(1-J18)^(AK$5-I18)))*K18*L18*M18)) | AL18: =IF('Biotech Model'!$B$4<>"READY","",IF(E18=0,0,IF(AL$5<F18,0,G18*MIN(1,(AL$5-F18+1)/H18)*IF(AL$5<=I18,1,(1-J18)^(AL$5-I18)))*K18*L18*M18)) | AM18: =IF('Biotech Model'!$B$4<>"READY","",IF(E18=0,0,IF(AM$5<F18,0,G18*MIN(1,(AM$5-F18+1)/H18)*IF(AM$5<=I18,1,(1-J18)^(AM$5-I18)))*K18*L18*M18)) | AN18: =IF('Biotech Model'!$B$4<>"READY","",IF(E18=0,0,IF(AN$5<F18,0,G18*MIN(1,(AN$5-F18+1)/H18)*IF(AN$5<=I18,1,(1-J18)^(AN$5-I18)))*K18*L18*M18)) | AO18: =IF('Biotech Model'!$B$4<>"READY","",IF(E18=0,0,IF(AO$5<F18,0,G18*MIN(1,(AO$5-F18+1)/H18)*IF(AO$5<=I18,1,(1-J18)^(AO$5-I18)))*K18*L18*M18)) | AP18: =IF('Biotech Model'!$B$4<>"READY","",IF(E18=0,0,IF(AP$5<F18,0,G18*MIN(1,(AP$5-F18+1)/H18)*IF(AP$5<=I18,1,(1-J18)^(AP$5-I18)))*K18*L18*M18)) | AQ18: =IF('Biotech Model'!$B$4<>"READY","",IF(E18=0,0,IF(AQ$5<F18,0,G18*MIN(1,(AQ$5-F18+1)/H18)*IF(AQ$5<=I18,1,(1-J18)^(AQ$5-I18)))*K18*L18*M18)) | AR18: =IF('Biotech Model'!$B$4<>"READY","",IF(E18=0,0,IF(AR$5<F18,0,G18*MIN(1,(AR$5-F18+1)/H18)*IF(AR$5<=I18,1,(1-J18)^(AR$5-I18)))*K18*L18*M18)) | AS18: =IF('Biotech Model'!$B$4<>"READY","",IF(E18=0,0,IF(AS$5<F18,0,G18*MIN(1,(AS$5-F18+1)/H18)*IF(AS$5<=I18,1,(1-J18)^(AS$5-I18)))*K18*L18*M18)) | AT18: =IF('Biotech Model'!$B$4<>"READY","",IF(E18=0,0,IF(AT$5<F18,0,G18*MIN(1,(AT$5-F18+1)/H18)*IF(AT$5<=I18,1,(1-J18)^(AT$5-I18)))*K18*L18*M18)) | AU18: =IF('Biotech Model'!$B$4<>"READY","",IF(E18=0,0,IF(AU$5<F18,0,G18*MIN(1,(AU$5-F18+1)/H18)*IF(AU$5<=I18,1,(1-J18)^(AU$5-I18)))*K18*L18*M18)) | AV18: =IF('Biotech Model'!$B$4<>"READY","",IF(E18=0,0,IF(AV$5<F18,0,G18*MIN(1,(AV$5-F18+1)/H18)*IF(AV$5<=I18,1,(1-J18)^(AV$5-I18)))*K18*L18*M18)) | AW18: =IF('Biotech Model'!$B$4<>"READY","",IF(E18=0,0,IF(AW$5<F18,0,G18*MIN(1,(AW$5-F18+1)/H18)*IF(AW$5<=I18,1,(1-J18)^(AW$5-I18)))*K18*L18*M18)) | AX18: =IF('Biotech Model'!$B$4<>"READY","",IF(E18=0,0,IF(AX$5<F18,0,G18*MIN(1,(AX$5-F18+1)/H18)*IF(AX$5<=I18,1,(1-J18)^(AX$5-I18)))*K18*L18*M18))
A19: mRNA-4349 | B19: mRNA-4349 | C19: Phase 1/2; disclosed | D19: SEC accession 0001682852-26-000033; filed 2026-02-20; report date 2025-12-31; 10-K; SEC 10-K Item 1, Business: The Phase 1/2 study of mRNA-4349 is ongoing. | E19: =IF('Input Required'!$B$3<>"READY","",'Input Required'!F147/1) | F19: =IF('Input Required'!$B$3<>"READY","",'Input Required'!F148/1) | G19: =IF('Input Required'!$B$3<>"READY","",'Input Required'!F149/1000000) | H19: =IF('Input Required'!$B$3<>"READY","",'Input Required'!F150/1) | I19: =IF('Input Required'!$B$3<>"READY","",'Input Required'!F151/1) | J19: =IF('Input Required'!$B$3<>"READY","",'Input Required'!F152/1) | K19: =IF('Input Required'!$B$3<>"READY","",'Input Required'!F153/1) | L19: =IF('Input Required'!$B$3<>"READY","",'Input Required'!F154/1) | M19: =IF('Input Required'!$B$3<>"READY","",'Input Required'!F155/1) | N19: =IF('Input Required'!$B$3<>"READY","",'Input Required'!F156/1000000) | O19: =IF('Biotech Model'!$B$4<>"READY","",SUMPRODUCT(P19:AX19,$P$3:$AX$3)-E19*N19) | P19: =IF('Biotech Model'!$B$4<>"READY","",IF(E19=0,0,IF(P$5<F19,0,G19*MIN(1,(P$5-F19+1)/H19)*IF(P$5<=I19,1,(1-J19)^(P$5-I19)))*K19*L19*M19)) | Q19: =IF('Biotech Model'!$B$4<>"READY","",IF(E19=0,0,IF(Q$5<F19,0,G19*MIN(1,(Q$5-F19+1)/H19)*IF(Q$5<=I19,1,(1-J19)^(Q$5-I19)))*K19*L19*M19)) | R19: =IF('Biotech Model'!$B$4<>"READY","",IF(E19=0,0,IF(R$5<F19,0,G19*MIN(1,(R$5-F19+1)/H19)*IF(R$5<=I19,1,(1-J19)^(R$5-I19)))*K19*L19*M19)) | S19: =IF('Biotech Model'!$B$4<>"READY","",IF(E19=0,0,IF(S$5<F19,0,G19*MIN(1,(S$5-F19+1)/H19)*IF(S$5<=I19,1,(1-J19)^(S$5-I19)))*K19*L19*M19)) | T19: =IF('Biotech Model'!$B$4<>"READY","",IF(E19=0,0,IF(T$5<F19,0,G19*MIN(1,(T$5-F19+1)/H19)*IF(T$5<=I19,1,(1-J19)^(T$5-I19)))*K19*L19*M19)) | U19: =IF('Biotech Model'!$B$4<>"READY","",IF(E19=0,0,IF(U$5<F19,0,G19*MIN(1,(U$5-F19+1)/H19)*IF(U$5<=I19,1,(1-J19)^(U$5-I19)))*K19*L19*M19)) | V19: =IF('Biotech Model'!$B$4<>"READY","",IF(E19=0,0,IF(V$5<F19,0,G19*MIN(1,(V$5-F19+1)/H19)*IF(V$5<=I19,1,(1-J19)^(V$5-I19)))*K19*L19*M19)) | W19: =IF('Biotech Model'!$B$4<>"READY","",IF(E19=0,0,IF(W$5<F19,0,G19*MIN(1,(W$5-F19+1)/H19)*IF(W$5<=I19,1,(1-J19)^(W$5-I19)))*K19*L19*M19)) | X19: =IF('Biotech Model'!$B$4<>"READY","",IF(E19=0,0,IF(X$5<F19,0,G19*MIN(1,(X$5-F19+1)/H19)*IF(X$5<=I19,1,(1-J19)^(X$5-I19)))*K19*L19*M19)) | Y19: =IF('Biotech Model'!$B$4<>"READY","",IF(E19=0,0,IF(Y$5<F19,0,G19*MIN(1,(Y$5-F19+1)/H19)*IF(Y$5<=I19,1,(1-J19)^(Y$5-I19)))*K19*L19*M19)) | Z19: =IF('Biotech Model'!$B$4<>"READY","",IF(E19=0,0,IF(Z$5<F19,0,G19*MIN(1,(Z$5-F19+1)/H19)*IF(Z$5<=I19,1,(1-J19)^(Z$5-I19)))*K19*L19*M19)) | AA19: =IF('Biotech Model'!$B$4<>"READY","",IF(E19=0,0,IF(AA$5<F19,0,G19*MIN(1,(AA$5-F19+1)/H19)*IF(AA$5<=I19,1,(1-J19)^(AA$5-I19)))*K19*L19*M19)) | AB19: =IF('Biotech Model'!$B$4<>"READY","",IF(E19=0,0,IF(AB$5<F19,0,G19*MIN(1,(AB$5-F19+1)/H19)*IF(AB$5<=I19,1,(1-J19)^(AB$5-I19)))*K19*L19*M19)) | AC19: =IF('Biotech Model'!$B$4<>"READY","",IF(E19=0,0,IF(AC$5<F19,0,G19*MIN(1,(AC$5-F19+1)/H19)*IF(AC$5<=I19,1,(1-J19)^(AC$5-I19)))*K19*L19*M19)) | AD19: =IF('Biotech Model'!$B$4<>"READY","",IF(E19=0,0,IF(AD$5<F19,0,G19*MIN(1,(AD$5-F19+1)/H19)*IF(AD$5<=I19,1,(1-J19)^(AD$5-I19)))*K19*L19*M19)) | AE19: =IF('Biotech Model'!$B$4<>"READY","",IF(E19=0,0,IF(AE$5<F19,0,G19*MIN(1,(AE$5-F19+1)/H19)*IF(AE$5<=I19,1,(1-J19)^(AE$5-I19)))*K19*L19*M19)) | AF19: =IF('Biotech Model'!$B$4<>"READY","",IF(E19=0,0,IF(AF$5<F19,0,G19*MIN(1,(AF$5-F19+1)/H19)*IF(AF$5<=I19,1,(1-J19)^(AF$5-I19)))*K19*L19*M19)) | AG19: =IF('Biotech Model'!$B$4<>"READY","",IF(E19=0,0,IF(AG$5<F19,0,G19*MIN(1,(AG$5-F19+1)/H19)*IF(AG$5<=I19,1,(1-J19)^(AG$5-I19)))*K19*L19*M19)) | AH19: =IF('Biotech Model'!$B$4<>"READY","",IF(E19=0,0,IF(AH$5<F19,0,G19*MIN(1,(AH$5-F19+1)/H19)*IF(AH$5<=I19,1,(1-J19)^(AH$5-I19)))*K19*L19*M19)) | AI19: =IF('Biotech Model'!$B$4<>"READY","",IF(E19=0,0,IF(AI$5<F19,0,G19*MIN(1,(AI$5-F19+1)/H19)*IF(AI$5<=I19,1,(1-J19)^(AI$5-I19)))*K19*L19*M19)) | AJ19: =IF('Biotech Model'!$B$4<>"READY","",IF(E19=0,0,IF(AJ$5<F19,0,G19*MIN(1,(AJ$5-F19+1)/H19)*IF(AJ$5<=I19,1,(1-J19)^(AJ$5-I19)))*K19*L19*M19)) | AK19: =IF('Biotech Model'!$B$4<>"READY","",IF(E19=0,0,IF(AK$5<F19,0,G19*MIN(1,(AK$5-F19+1)/H19)*IF(AK$5<=I19,1,(1-J19)^(AK$5-I19)))*K19*L19*M19)) | AL19: =IF('Biotech Model'!$B$4<>"READY","",IF(E19=0,0,IF(AL$5<F19,0,G19*MIN(1,(AL$5-F19+1)/H19)*IF(AL$5<=I19,1,(1-J19)^(AL$5-I19)))*K19*L19*M19)) | AM19: =IF('Biotech Model'!$B$4<>"READY","",IF(E19=0,0,IF(AM$5<F19,0,G19*MIN(1,(AM$5-F19+1)/H19)*IF(AM$5<=I19,1,(1-J19)^(AM$5-I19)))*K19*L19*M19)) | AN19: =IF('Biotech Model'!$B$4<>"READY","",IF(E19=0,0,IF(AN$5<F19,0,G19*MIN(1,(AN$5-F19+1)/H19)*IF(AN$5<=I19,1,(1-J19)^(AN$5-I19)))*K19*L19*M19)) | AO19: =IF('Biotech Model'!$B$4<>"READY","",IF(E19=0,0,IF(AO$5<F19,0,G19*MIN(1,(AO$5-F19+1)/H19)*IF(AO$5<=I19,1,(1-J19)^(AO$5-I19)))*K19*L19*M19)) | AP19: =IF('Biotech Model'!$B$4<>"READY","",IF(E19=0,0,IF(AP$5<F19,0,G19*MIN(1,(AP$5-F19+1)/H19)*IF(AP$5<=I19,1,(1-J19)^(AP$5-I19)))*K19*L19*M19)) | AQ19: =IF('Biotech Model'!$B$4<>"READY","",IF(E19=0,0,IF(AQ$5<F19,0,G19*MIN(1,(AQ$5-F19+1)/H19)*IF(AQ$5<=I19,1,(1-J19)^(AQ$5-I19)))*K19*L19*M19)) | AR19: =IF('Biotech Model'!$B$4<>"READY","",IF(E19=0,0,IF(AR$5<F19,0,G19*MIN(1,(AR$5-F19+1)/H19)*IF(AR$5<=I19,1,(1-J19)^(AR$5-I19)))*K19*L19*M19)) | AS19: =IF('Biotech Model'!$B$4<>"READY","",IF(E19=0,0,IF(AS$5<F19,0,G19*MIN(1,(AS$5-F19+1)/H19)*IF(AS$5<=I19,1,(1-J19)^(AS$5-I19)))*K19*L19*M19)) | AT19: =IF('Biotech Model'!$B$4<>"READY","",IF(E19=0,0,IF(AT$5<F19,0,G19*MIN(1,(AT$5-F19+1)/H19)*IF(AT$5<=I19,1,(1-J19)^(AT$5-I19)))*K19*L19*M19)) | AU19: =IF('Biotech Model'!$B$4<>"READY","",IF(E19=0,0,IF(AU$5<F19,0,G19*MIN(1,(AU$5-F19+1)/H19)*IF(AU$5<=I19,1,(1-J19)^(AU$5-I19)))*K19*L19*M19)) | AV19: =IF('Biotech Model'!$B$4<>"READY","",IF(E19=0,0,IF(AV$5<F19,0,G19*MIN(1,(AV$5-F19+1)/H19)*IF(AV$5<=I19,1,(1-J19)^(AV$5-I19)))*K19*L19*M19)) | AW19: =IF('Biotech Model'!$B$4<>"READY","",IF(E19=0,0,IF(AW$5<F19,0,G19*MIN(1,(AW$5-F19+1)/H19)*IF(AW$5<=I19,1,(1-J19)^(AW$5-I19)))*K19*L19*M19)) | AX19: =IF('Biotech Model'!$B$4<>"READY","",IF(E19=0,0,IF(AX$5<F19,0,G19*MIN(1,(AX$5-F19+1)/H19)*IF(AX$5<=I19,1,(1-J19)^(AX$5-I19)))*K19*L19*M19))
A22: Other SEC-listed assets — source-mapped rNPV inputs
A23: Asset ID | B23: SEC asset label | C23: Stage / status / partner | D23: SEC source and filing basis | E23: Include | F23: Analyst-entered rNPV (PV) | G23: Included rNPV
A24: mRNA-1011 | B24: mRNA-1011 | C24: explicitly_paused | D24: SEC accession 0001682852-26-000033; filed 2026-02-20; report date 2025-12-31; 10-K; SEC 10-K Item 1, Business: We have paused development of mRNA-1011, mRNA-1012, mRNA-1020, and mRNA-1030, which were flu vaccines that included additional antigens relative to what is included in mRNA-1010. | E24: =IF('Input Required'!$B$3<>"READY","",'Input Required'!F157/1) | F24: =IF('Input Required'!$B$3<>"READY","",'Input Required'!F158/1000000) | G24: =IF('Biotech Model'!$B$4<>"READY","",E24*F24)
A25: mRNA-1012 | B25: mRNA-1012 | C25: explicitly_paused | D25: SEC accession 0001682852-26-000033; filed 2026-02-20; report date 2025-12-31; 10-K; SEC 10-K Item 1, Business: We have paused development of mRNA-1011, mRNA-1012, mRNA-1020, and mRNA-1030, which were flu vaccines that included additional antigens relative to what is included in mRNA-1010. | E25: =IF('Input Required'!$B$3<>"READY","",'Input Required'!F159/1) | F25: =IF('Input Required'!$B$3<>"READY","",'Input Required'!F160/1000000) | G25: =IF('Biotech Model'!$B$4<>"READY","",E25*F25)
A26: mRNA-1020 | B26: mRNA-1020 | C26: explicitly_paused | D26: SEC accession 0001682852-26-000033; filed 2026-02-20; report date 2025-12-31; 10-K; SEC 10-K Item 1, Business: We have paused development of mRNA-1011, mRNA-1012, mRNA-1020, and mRNA-1030, which were flu vaccines that included additional antigens relative to what is included in mRNA-1010. | E26: =IF('Input Required'!$B$3<>"READY","",'Input Required'!F161/1) | F26: =IF('Input Required'!$B$3<>"READY","",'Input Required'!F162/1000000) | G26: =IF('Biotech Model'!$B$4<>"READY","",E26*F26)
A27: mRNA-1030 | B27: mRNA-1030 | C27: explicitly_paused | D27: SEC accession 0001682852-26-000033; filed 2026-02-20; report date 2025-12-31; 10-K; SEC 10-K Item 1, Business: We have paused development of mRNA-1011, mRNA-1012, mRNA-1020, and mRNA-1030, which were flu vaccines that included additional antigens relative to what is included in mRNA-1010. | E27: =IF('Input Required'!$B$3<>"READY","",'Input Required'!F163/1) | F27: =IF('Input Required'!$B$3<>"READY","",'Input Required'!F164/1000000) | G27: =IF('Biotech Model'!$B$4<>"READY","",E27*F27)
A28: mRNA-1365 | B28: mRNA-1365 | C28: Phase 1; disclosed | D28: SEC accession 0001682852-26-000033; filed 2026-02-20; report date 2025-12-31; 10-K; SEC 10-K Item 1, Business: Combination vaccines (mRNA-1083 and mRNA-1365) We are developing combination vaccine candidates to simplify and facilitate protection against a range of respiratory diseases. | In addition, safety follow-up continues in our Phase 1 study for mRNA-1365, our RSV and human metapneumovirus (hMPV) combination vaccine, in children five to 23 months of age. | We are also evaluating an updated version of mRNA-1365 in older adults. | E28: =IF('Input Required'!$B$3<>"READY","",'Input Required'!F165/1) | F28: =IF('Input Required'!$B$3<>"READY","",'Input Required'!F166/1000000) | G28: =IF('Biotech Model'!$B$4<>"READY","",E28*F28)
A29: mRNA-1647 | B29: mRNA-1647 | C29: Phase 3; explicitly_paused | D29: SEC accession 0001682852-26-000033; filed 2026-02-20; report date 2025-12-31; 10-K; SEC 10-K Item 1, Business: Vaccines against latent viruses CMV vaccine (mRNA-1647) Cytomegalovirus (CMV) is member of the herpes virus family and a common human pathogen that causes complications for people who are immunosuppressed or can be passed to babies during pregnancy and result in congenital malformation. | Our CMV vaccine candidate, mRNA-1647, combines six mRNAs in one vaccine. | mRNA-1647 is designed to produce an immune response against both pentamer and gB for the prevention of CMV infection. | We conducted a cCMV Phase 3 study of mRNA-1647 in women of childbearing age and announced in October 2025 that the study failed to reach its primary clinical endpoint. | mRNA-1647 has the potential to prevent CMV viral replication and/or disease in transplant populations. | A Phase 2 proof-of-concept study for mRNA-1647 in allogeneic hematopoietic cell transplant (HCT) patients is ongoing. | We do not have curre | E29: =IF('Input Required'!$B$3<>"READY","",'Input Required'!F167/1) | F29: =IF('Input Required'!$B$3<>"READY","",'Input Required'!F168/1000000) | G29: =IF('Biotech Model'!$B$4<>"READY","",E29*F29)
A30: mRNA-1189 | B30: mRNA-1189 | C30: Phase 1; disclosed | D30: SEC accession 0001682852-26-000033; filed 2026-02-20; report date 2025-12-31; 10-K; SEC 10-K Item 1, Business: 15 Table of Contents EBV vaccines (mRNA-1189 and mRNA-1195) Epstein-Barr virus (EBV) is a member of the herpesvirus family that infects approximately 90% of people in the U. | We are developing two mRNA candidates against EBV —a prophylactic vaccine to prevent infectious mononucleosis (mRNA-1189) and a therapeutic to treat multiple sclerosis (mRNA-1195). | mRNA-1189 is designed to elicit an immune response to EBV envelope glycoproteins, which are required for infection of both epithelial and B cells. | We are currently conducting Phase 2, randomized, observer-blind, placebo-controlled studies of mRNA-1189 and mRNA-1195. | In March 2024, we shared Phase 1 data for mRNA-1189, where the randomized, observer-blind, placebo-controlled study showed mRNA-1189 was immunogenic and generally well tolerated across all dose levels. | We have since fully enrolled a dose finding Phase 2 study for mRNA | E30: =IF('Input Required'!$B$3<>"READY","",'Input Required'!F169/1) | F30: =IF('Input Required'!$B$3<>"READY","",'Input Required'!F170/1000000) | G30: =IF('Biotech Model'!$B$4<>"READY","",E30*F30)
A31: mRNA-1645 | B31: mRNA-1645 | C31: Phase 1; disclosed | D31: SEC accession 0001682852-26-000033; filed 2026-02-20; report date 2025-12-31; 10-K; SEC 10-K Item 1, Business: HIV vaccine (mRNA-1645) Human immunodeficiency virus (HIV) is responsible for acquired immunodeficiency syndrome (AIDS), a lifelong, progressive illness with no effective cure. | Our HIV vaccine candidate (mRNA-1645) is being studied in Phase 1 clinical trials, sponsored by IAVI, to determine the optimal design to induce broadly neutralizing antibodies capable of addressing the genetic diversity of HIV that is necessary in future proof of concept studies. | E31: =IF('Input Required'!$B$3<>"READY","",'Input Required'!F171/1) | F31: =IF('Input Required'!$B$3<>"READY","",'Input Required'!F172/1000000) | G31: =IF('Biotech Model'!$B$4<>"READY","",E31*F31)
A32: mRNA-1405 | B32: mRNA-1405 | C32: disclosed | D32: SEC accession 0001682852-26-000033; filed 2026-02-20; report date 2025-12-31; 10-K; SEC 10-K Item 1, Business: Vaccines against enteric viruses Norovirus vaccines (mRNA-1403 and mRNA-1405) Norovirus is a leading cause of acute gastroenteritis (AGE), responsible for approximately 18% of all AGE cases worldwide and imposing a substantial global health care burden. | We are currently developing pentavalent (mRNA-1405) and trivalent (mRNA-1403) vaccine candidates for norovirus. | E32: =IF('Input Required'!$B$3<>"READY","",'Input Required'!F173/1) | F32: =IF('Input Required'!$B$3<>"READY","",'Input Required'!F174/1000000) | G32: =IF('Biotech Model'!$B$4<>"READY","",E32*F32)
A33: mRNA-1975 | B33: mRNA-1975 | C33: disclosed | D33: SEC accession 0001682852-26-000033; filed 2026-02-20; report date 2025-12-31; 10-K; SEC 10-K Item 1, Business: Bacterial vaccines Lyme vaccines (mRNA-1975 and mRNA-1982) Lyme disease is an illness caused by Borrelia bacteria transmitted by the bite of infected ticks. | This trial evaluates the safety and immunogenicity of a heptavalent (mRNA-1975) and monovalent (mRNA-1982) approach in parallel. | mRNA-1982 targets Borrelia burgdorferi, responsible for nearly all Lyme cases in North America, while mRNA-1975 targets the four major Borrelia species causing disease in North America and Europe. | No safety concerns have been identified across the evaluated dose levels for three injections of mRNA-1975/1982. | Furthermore, three injections of mRNA-1975/1982 elicit robust anti-OspA IgG antibody responses, with titers up to ~1,300 times above baseline for OspA serotype 1 of Borrelia burgdorferi. | E33: =IF('Input Required'!$B$3<>"READY","",'Input Required'!F175/1) | F33: =IF('Input Required'!$B$3<>"READY","",'Input Required'!F176/1000000) | G33: =IF('Biotech Model'!$B$4<>"READY","",E33*F33)
A34: mRNA-1215 | B34: mRNA-1215 | C34: Phase 1; disclosed | D34: SEC accession 0001682852-26-000033; filed 2026-02-20; report date 2025-12-31; 10-K; SEC 10-K Item 1, Business: Public health vaccines Nipah vaccine (mRNA-1215) Nipah virus (NiV) is a zoonotic virus transmitted to humans from animals, contaminated food or through direct human-to-human transmission and causes a range of illnesses including fatal encephalitis. | 17 Table of Contents In collaboration with the NIH-Vaccine Research Center (VRC), we conducted a Phase 1 clinical trial of mRNA-1215, our vaccine candidate against NiV, and testing was focused on pandemic preparedness. | This Phase 1 dose-escalation, open-label clinical trial was the first study of mRNA-1215 in healthy adults to evaluate the safety, tolerability and immunogenicity of a NiV mRNA vaccine candidate. | E34: =IF('Input Required'!$B$3<>"READY","",'Input Required'!F177/1) | F34: =IF('Input Required'!$B$3<>"READY","",'Input Required'!F178/1000000) | G34: =IF('Biotech Model'!$B$4<>"READY","",E34*F34)
A35: mRNA-4203 | B35: mRNA-4203 | C35: disclosed | D35: SEC accession 0001682852-26-000033; filed 2026-02-20; report date 2025-12-31; 10-K; SEC 10-K Item 1, Business: We have also expanded our oncology portfolio with early-stage programs, including mRNA-4106 (a cancer antigen therapy), mRNA-2808 (a T-cell engager), and mRNA-4203 (a cell-therapy enhancer). | mRNA-4203 is being developed in collaboration with Immatics. | Cell therapy enhancer (mRNA-4203 and Anzu-cel (IMA203)) mRNA-4203 is a cell therapy enhancer that encodes for the target of an ex-vivo cell therapy to enhance the persistence and efficacy of the cell therapy. | mRNA-4203 is being developed in collaboration with Immatics and is dosed in combination with Immatics’ IMA203. | E35: =IF('Input Required'!$B$3<>"READY","",'Input Required'!F179/1) | F35: =IF('Input Required'!$B$3<>"READY","",'Input Required'!F180/1000000) | G35: =IF('Biotech Model'!$B$4<>"READY","",E35*F35)
A36: mRNA-3692 | B36: mRNA-3692 | C36: disclosed | D36: SEC accession 0001682852-26-000033; filed 2026-02-20; report date 2025-12-31; 10-K; SEC 10-K Item 1, Business: Cystic Fibrosis (mRNA-3692/VX-522) Cystic Fibrosis (CF) is a rare genetic disease, which is progressive from birth and leads to multi-organ damage and early death due to lung dysfunction. | We are collaborating with Vertex on our CF candidate, mRNA-3692/VX-522, which is designed to treat the underlying cause of CF by enabling cells in the lungs to produce functional CFTR protein for the treatment of the over 5,000 patients who do not produce any modulator-responsive CFTR protein. | Representative relationships and associated programs include those with Merck, for our intismeran programs (mRNA-4157), and Vertex, for our CF program (mRNA-3692). | E36: =IF('Input Required'!$B$3<>"READY","",'Input Required'!F181/1) | F36: =IF('Input Required'!$B$3<>"READY","",'Input Required'!F182/1000000) | G36: =IF('Biotech Model'!$B$4<>"READY","",E36*F36)
A37: mRNA-1608 | B37: mRNA-1608 | C37: Phase 2; explicitly_paused | D37: SEC accession 0001682852-26-000033; filed 2026-02-20; report date 2025-12-31; 10-K; SEC 10-K Item 1, Business: We do not have current plans for future development of the following programs: • mRNA-1647: CMV in congenital CMV (we plan to continue to evaluate mRNA-1647 in an ongoing Phase 2 trial of bone marrow transplant patients) • mRNA-1608: Herpes simplex virus (HSV) vaccine • mRNA-1468: Varicella-Zoster virus (VZV) vaccine • mRNA-3745: Glycogen Storage Disease Type 1a (GSD1a) therapeutic • mRNA-3210: Phenylketonuria (PKU) therapeutic MANUFACTURING Our m anufacturing capabilities play a critical role in our value chain and support every stage of the development of our products, from discovery to commercialization. | E37: =IF('Input Required'!$B$3<>"READY","",'Input Required'!F183/1) | F37: =IF('Input Required'!$B$3<>"READY","",'Input Required'!F184/1000000) | G37: =IF('Biotech Model'!$B$4<>"READY","",E37*F37)
A38: mRNA-1468 | B38: mRNA-1468 | C38: Phase 2; explicitly_paused | D38: SEC accession 0001682852-26-000033; filed 2026-02-20; report date 2025-12-31; 10-K; SEC 10-K Item 1, Business: We do not have current plans for future development of the following programs: • mRNA-1647: CMV in congenital CMV (we plan to continue to evaluate mRNA-1647 in an ongoing Phase 2 trial of bone marrow transplant patients) • mRNA-1608: Herpes simplex virus (HSV) vaccine • mRNA-1468: Varicella-Zoster virus (VZV) vaccine • mRNA-3745: Glycogen Storage Disease Type 1a (GSD1a) therapeutic • mRNA-3210: Phenylketonuria (PKU) therapeutic MANUFACTURING Our m anufacturing capabilities play a critical role in our value chain and support every stage of the development of our products, from discovery to commercialization. | E38: =IF('Input Required'!$B$3<>"READY","",'Input Required'!F185/1) | F38: =IF('Input Required'!$B$3<>"READY","",'Input Required'!F186/1000000) | G38: =IF('Biotech Model'!$B$4<>"READY","",E38*F38)
A39: mRNA-3745 | B39: mRNA-3745 | C39: Phase 2; explicitly_paused | D39: SEC accession 0001682852-26-000033; filed 2026-02-20; report date 2025-12-31; 10-K; SEC 10-K Item 1, Business: We do not have current plans for future development of the following programs: • mRNA-1647: CMV in congenital CMV (we plan to continue to evaluate mRNA-1647 in an ongoing Phase 2 trial of bone marrow transplant patients) • mRNA-1608: Herpes simplex virus (HSV) vaccine • mRNA-1468: Varicella-Zoster virus (VZV) vaccine • mRNA-3745: Glycogen Storage Disease Type 1a (GSD1a) therapeutic • mRNA-3210: Phenylketonuria (PKU) therapeutic MANUFACTURING Our m anufacturing capabilities play a critical role in our value chain and support every stage of the development of our products, from discovery to commercialization. | E39: =IF('Input Required'!$B$3<>"READY","",'Input Required'!F187/1) | F39: =IF('Input Required'!$B$3<>"READY","",'Input Required'!F188/1000000) | G39: =IF('Biotech Model'!$B$4<>"READY","",E39*F39)
A40: mRNA-3210 | B40: mRNA-3210 | C40: Phase 2; explicitly_paused | D40: SEC accession 0001682852-26-000033; filed 2026-02-20; report date 2025-12-31; 10-K; SEC 10-K Item 1, Business: We do not have current plans for future development of the following programs: • mRNA-1647: CMV in congenital CMV (we plan to continue to evaluate mRNA-1647 in an ongoing Phase 2 trial of bone marrow transplant patients) • mRNA-1608: Herpes simplex virus (HSV) vaccine • mRNA-1468: Varicella-Zoster virus (VZV) vaccine • mRNA-3745: Glycogen Storage Disease Type 1a (GSD1a) therapeutic • mRNA-3210: Phenylketonuria (PKU) therapeutic MANUFACTURING Our m anufacturing capabilities play a critical role in our value chain and support every stage of the development of our products, from discovery to commercialization. | E40: =IF('Input Required'!$B$3<>"READY","",'Input Required'!F189/1) | F40: =IF('Input Required'!$B$3<>"READY","",'Input Required'!F190/1000000) | G40: =IF('Biotech Model'!$B$4<>"READY","",E40*F40)
A41: mRNA-3351 | B41: mRNA-3351 | C41: disclosed | D41: SEC accession 0001682852-26-000033; filed 2026-02-20; report date 2025-12-31; 10-K; SEC 10-K Item 1, Business: Institute for Life Changing Medicines (ILCM) In September 2021, we entered into a collaboration agreement with the ILCM to develop a new mRNA therapeutic (mRNA-3351) for type 1 Crigler-Najjar syndrome (CN-1). | Under the terms of the agreement, we agreed to license mRNA-3351 to ILCM with no upfront fees, and without any downstream payments. | ILCM will be responsible for the clinical development of mRNA-3351. | E41: =IF('Input Required'!$B$3<>"READY","",'Input Required'!F191/1) | F41: =IF('Input Required'!$B$3<>"READY","",'Input Required'!F192/1000000) | G41: =IF('Biotech Model'!$B$4<>"READY","",E41*F41)

Sheet Input Required
A1: INCOMPLETE MODEL — Moderna, Inc. (MRNA)
A2: Model family: biotech_pipeline_rnpv. No valuation has been calculated because required inputs are missing.
A3: Model status | B3: =IF(COUNTIF('Data Review'!$C$5:$C$195,"INPUT ERROR")>0,"INPUT ERROR — check required inputs",IF(COUNTIF('Data Review'!$C$5:$C$195,"INPUT REQUIRED")+COUNTIF('Data Review'!$C$5:$C$195,"SOURCE REQUIRED")>0,"INCOMPLETE — fill required inputs","READY")) -> INCOMPLETE — fill required inputs
A5: Input key | B5: Required input | C5: Period | D5: Unit | E5: Why required | F5: Enter value | G5: Source / reference | H5: Source required
A6: commercial_revenue_growth | B6: Commercial franchise revenue growth | C6: FY2026 | D6: ratio | E6: MRNA pipeline rNPV uses its live 10-K program list, but commercial forecasts, success probabilities, launch timing, partner economics, and remaining development costs are not reported as valuation inputs. Enter a source or valuation rationale for each input. Forecast FY2026; the filed revenue base includes product and collaboration revenue. | H6: Yes
A7: commercial_revenue_growth | B7: Commercial franchise revenue growth | C7: FY2027 | D7: ratio | E7: MRNA pipeline rNPV uses its live 10-K program list, but commercial forecasts, success probabilities, launch timing, partner economics, and remaining development costs are not reported as valuation inputs. Enter a source or valuation rationale for each input. Forecast FY2027; the filed revenue base includes product and collaboration revenue. | H7: Yes
A8: commercial_revenue_growth | B8: Commercial franchise revenue growth | C8: FY2028 | D8: ratio | E8: MRNA pipeline rNPV uses its live 10-K program list, but commercial forecasts, success probabilities, launch timing, partner economics, and remaining development costs are not reported as valuation inputs. Enter a source or valuation rationale for each input. Forecast FY2028; the filed revenue base includes product and collaboration revenue. | H8: Yes
A9: commercial_revenue_growth | B9: Commercial franchise revenue growth | C9: FY2029 | D9: ratio | E9: MRNA pipeline rNPV uses its live 10-K program list, but commercial forecasts, success probabilities, launch timing, partner economics, and remaining development costs are not reported as valuation inputs. Enter a source or valuation rationale for each input. Forecast FY2029; the filed revenue base includes product and collaboration revenue. | H9: Yes
A10: commercial_revenue_growth | B10: Commercial franchise revenue growth | C10: FY2030 | D10: ratio | E10: MRNA pipeline rNPV uses its live 10-K program list, but commercial forecasts, success probabilities, launch timing, partner economics, and remaining development costs are not reported as valuation inputs. Enter a source or valuation rationale for each input. Forecast FY2030; the filed revenue base includes product and collaboration revenue. | H10: Yes
A11: commercial_revenue_growth | B11: Commercial franchise revenue growth | C11: FY2031 | D11: ratio | E11: MRNA pipeline rNPV uses its live 10-K program list, but commercial forecasts, success probabilities, launch timing, partner economics, and remaining development costs are not reported as valuation inputs. Enter a source or valuation rationale for each input. Forecast FY2031; the filed revenue base includes product and collaboration revenue. | H11: Yes
A12: commercial_revenue_growth | B12: Commercial franchise revenue growth | C12: FY2032 | D12: ratio | E12: MRNA pipeline rNPV uses its live 10-K program list, but commercial forecasts, success probabilities, launch timing, partner economics, and remaining development costs are not reported as valuation inputs. Enter a source or valuation rationale for each input. Forecast FY2032; the filed revenue base includes product and collaboration revenue. | H12: Yes
A13: commercial_revenue_growth | B13: Commercial franchise revenue growth | C13: FY2033 | D13: ratio | E13: MRNA pipeline rNPV uses its live 10-K program list, but commercial forecasts, success probabilities, launch timing, partner economics, and remaining development costs are not reported as valuation inputs. Enter a source or valuation rationale for each input. Forecast FY2033; the filed revenue base includes product and collaboration revenue. | H13: Yes
A14: commercial_revenue_growth | B14: Commercial franchise revenue growth | C14: FY2034 | D14: ratio | E14: MRNA pipeline rNPV uses its live 10-K program list, but commercial forecasts, success probabilities, launch timing, partner economics, and remaining development costs are not reported as valuation inputs. Enter a source or valuation rationale for each input. Forecast FY2034; the filed revenue base includes product and collaboration revenue. | H14: Yes
A15: commercial_revenue_growth | B15: Commercial franchise revenue growth | C15: FY2035 | D15: ratio | E15: MRNA pipeline rNPV uses its live 10-K program list, but commercial forecasts, success probabilities, launch timing, partner economics, and remaining development costs are not reported as valuation inputs. Enter a source or valuation rationale for each input. Forecast FY2035; the filed revenue base includes product and collaboration revenue. | H15: Yes
A16: commercial_fcf_margin | B16: Existing commercial portfolio post-tax cash margin | D16: ratio | E16: MRNA pipeline rNPV uses its live 10-K program list, but commercial forecasts, success probabilities, launch timing, partner economics, and remaining development costs are not reported as valuation inputs. Enter a source or valuation rationale for each input. This margin excludes the separately modeled pipeline development costs. | H16: Yes
A17: asset_include:mRNA-4157 | B17: mRNA-4157 include in rNPV | D17: 0 or 1 | E17: MRNA pipeline rNPV uses its live 10-K program list, but commercial forecasts, success probabilities, launch timing, partner economics, and remaining development costs are not reported as valuation inputs. Enter a source or valuation rationale for each input. SEC filing lists mRNA-4157 at Phase 2 with Merck. | H17: Yes
A18: asset_launch_year:mRNA-4157 | B18: mRNA-4157 expected launch year | D18: calendar year | E18: MRNA pipeline rNPV uses its live 10-K program list, but commercial forecasts, success probabilities, launch timing, partner economics, and remaining development costs are not reported as valuation inputs. Enter a source or valuation rationale for each input. SEC filing lists mRNA-4157 at Phase 2 with Merck. | H18: Yes
A19: asset_peak_sales:mRNA-4157 | B19: mRNA-4157 peak annual sales | D19: USD actual | E19: MRNA pipeline rNPV uses its live 10-K program list, but commercial forecasts, success probabilities, launch timing, partner economics, and remaining development costs are not reported as valuation inputs. Enter a source or valuation rationale for each input. SEC filing lists mRNA-4157 at Phase 2 with Merck. | H19: Yes
A20: asset_years_to_peak:mRNA-4157 | B20: mRNA-4157 years from launch to peak sales | D20: years | E20: MRNA pipeline rNPV uses its live 10-K program list, but commercial forecasts, success probabilities, launch timing, partner economics, and remaining development costs are not reported as valuation inputs. Enter a source or valuation rationale for each input. SEC filing lists mRNA-4157 at Phase 2 with Merck. | H20: Yes
A21: asset_exclusivity_year:mRNA-4157 | B21: mRNA-4157 expected loss-of-exclusivity year | D21: calendar year | E21: MRNA pipeline rNPV uses its live 10-K program list, but commercial forecasts, success probabilities, launch timing, partner economics, and remaining development costs are not reported as valuation inputs. Enter a source or valuation rationale for each input. SEC filing lists mRNA-4157 at Phase 2 with Merck. | H21: Yes
A22: asset_post_loe_erosion:mRNA-4157 | B22: mRNA-4157 post-LOE annual sales erosion | D22: ratio | E22: MRNA pipeline rNPV uses its live 10-K program list, but commercial forecasts, success probabilities, launch timing, partner economics, and remaining development costs are not reported as valuation inputs. Enter a source or valuation rationale for each input. SEC filing lists mRNA-4157 at Phase 2 with Merck. | H22: Yes
A23: asset_probability_of_success:mRNA-4157 | B23: mRNA-4157 probability of success | D23: ratio | E23: MRNA pipeline rNPV uses its live 10-K program list, but commercial forecasts, success probabilities, launch timing, partner economics, and remaining development costs are not reported as valuation inputs. Enter a source or valuation rationale for each input. SEC filing lists mRNA-4157 at Phase 2 with Merck. | H23: Yes
A24: asset_retained_share:mRNA-4157 | B24: mRNA-4157 retained economics after partner share | D24: ratio | E24: MRNA pipeline rNPV uses its live 10-K program list, but commercial forecasts, success probabilities, launch timing, partner economics, and remaining development costs are not reported as valuation inputs. Enter a source or valuation rationale for each input. SEC filing lists mRNA-4157 at Phase 2 with Merck. | H24: Yes
A25: asset_contribution_margin:mRNA-4157 | B25: mRNA-4157 post-tax cash contribution margin | D25: ratio | E25: MRNA pipeline rNPV uses its live 10-K program list, but commercial forecasts, success probabilities, launch timing, partner economics, and remaining development costs are not reported as valuation inputs. Enter a source or valuation rationale for each input. SEC filing lists mRNA-4157 at Phase 2 with Merck. | H25: Yes
A26: asset_development_cost_pv:mRNA-4157 | B26: mRNA-4157 remaining development-cost PV | D26: USD actual | E26: MRNA pipeline rNPV uses its live 10-K program list, but commercial forecasts, success probabilities, launch timing, partner economics, and remaining development costs are not reported as valuation inputs. Enter a source or valuation rationale for each input. SEC filing lists mRNA-4157 at Phase 2 with Merck. | H26: Yes
A27: asset_include:mRNA-4359 | B27: mRNA-4359 include in rNPV | D27: 0 or 1 | E27: MRNA pipeline rNPV uses its live 10-K program list, but commercial forecasts, success probabilities, launch timing, partner economics, and remaining development costs are not reported as valuation inputs. Enter a source or valuation rationale for each input. SEC filing lists mRNA-4359 at Phase 1/2. | H27: Yes
... A196: terminal_growth_rate | B196: Commercial franchise terminal growth | D196: ratio | E196: MRNA pipeline rNPV uses its live 10-K program list, but commercial forecasts, success probabilities, launch timing, partner economics, and remaining development costs are not reported as valuation inputs. Enter a source or valuation rationale for each input. Keep terminal growth below cost of equity (14.55%). | H196: Yes

Sheet Data Review
A1: Required input review
A2: Fill blue input cells on Input Required. Reported facts require a source reference; missing values are not zero.
A4: Input key | B4: Required input | C4: Status | D4: Source status | E4: Period | F4: Unit | G4: Reason | H4: Workbook cell | I4: Source / reference
A5: commercial_revenue_growth | B5: Commercial franchise revenue growth | C5: =IF('Input Required'!F6="","INPUT REQUIRED",IF(AND('Input Required'!H6="Yes",'Input Required'!G6=""),"SOURCE REQUIRED",IF(OR(AND('Input Required'!F6<>"",NOT(ISNUMBER('Input Required'!F6))),AND(ISNUMBER('Input Required'!F6),'Input Required'!F6<-0.95),AND(ISNUMBER('Input Required'!F6),'Input Required'!F6>2)),"INPUT ERROR","READY"))) -> INPUT REQUIRED | D5: missing | E5: FY2026 | F5: ratio | G5: MRNA pipeline rNPV uses its live 10-K program list, but commercial forecasts, success probabilities, launch timing, partner economics, and remaining development costs are not reported as valuation inputs. Enter a source or valuation rationale for each input. Forecast FY2026; the filed revenue base includes product and collaboration revenue. | H5: Input Required!F6 | I5: ='Input Required'!G6 -> 0
A6: commercial_revenue_growth | B6: Commercial franchise revenue growth | C6: =IF('Input Required'!F7="","INPUT REQUIRED",IF(AND('Input Required'!H7="Yes",'Input Required'!G7=""),"SOURCE REQUIRED",IF(OR(AND('Input Required'!F7<>"",NOT(ISNUMBER('Input Required'!F7))),AND(ISNUMBER('Input Required'!F7),'Input Required'!F7<-0.95),AND(ISNUMBER('Input Required'!F7),'Input Required'!F7>2)),"INPUT ERROR","READY"))) -> INPUT REQUIRED | D6: missing | E6: FY2027 | F6: ratio | G6: MRNA pipeline rNPV uses its live 10-K program list, but commercial forecasts, success probabilities, launch timing, partner economics, and remaining development costs are not reported as valuation inputs. Enter a source or valuation rationale for each input. Forecast FY2027; the filed revenue base includes product and collaboration revenue. | H6: Input Required!F7 | I6: ='Input Required'!G7 -> 0
A7: commercial_revenue_growth | B7: Commercial franchise revenue growth | C7: =IF('Input Required'!F8="","INPUT REQUIRED",IF(AND('Input Required'!H8="Yes",'Input Required'!G8=""),"SOURCE REQUIRED",IF(OR(AND('Input Required'!F8<>"",NOT(ISNUMBER('Input Required'!F8))),AND(ISNUMBER('Input Required'!F8),'Input Required'!F8<-0.95),AND(ISNUMBER('Input Required'!F8),'Input Required'!F8>2)),"INPUT ERROR","READY"))) -> INPUT REQUIRED | D7: missing | E7: FY2028 | F7: ratio | G7: MRNA pipeline rNPV uses its live 10-K program list, but commercial forecasts, success probabilities, launch timing, partner economics, and remaining development costs are not reported as valuation inputs. Enter a source or valuation rationale for each input. Forecast FY2028; the filed revenue base includes product and collaboration revenue. | H7: Input Required!F8 | I7: ='Input Required'!G8 -> 0
A8: commercial_revenue_growth | B8: Commercial franchise revenue growth | C8: =IF('Input Required'!F9="","INPUT REQUIRED",IF(AND('Input Required'!H9="Yes",'Input Required'!G9=""),"SOURCE REQUIRED",IF(OR(AND('Input Required'!F9<>"",NOT(ISNUMBER('Input Required'!F9))),AND(ISNUMBER('Input Required'!F9),'Input Required'!F9<-0.95),AND(ISNUMBER('Input Required'!F9),'Input Required'!F9>2)),"INPUT ERROR","READY"))) -> INPUT REQUIRED | D8: missing | E8: FY2029 | F8: ratio | G8: MRNA pipeline rNPV uses its live 10-K program list, but commercial forecasts, success probabilities, launch timing, partner economics, and remaining development costs are not reported as valuation inputs. Enter a source or valuation rationale for each input. Forecast FY2029; the filed revenue base includes product and collaboration revenue. | H8: Input Required!F9 | I8: ='Input Required'!G9 -> 0
A9: commercial_revenue_growth | B9: Commercial franchise revenue growth | C9: =IF('Input Required'!F10="","INPUT REQUIRED",IF(AND('Input Required'!H10="Yes",'Input Required'!G10=""),"SOURCE REQUIRED",IF(OR(AND('Input Required'!F10<>"",NOT(ISNUMBER('Input Required'!F10))),AND(ISNUMBER('Input Required'!F10),'Input Required'!F10<-0.95),AND(ISNUMBER('Input Required'!F10),'Input Required'!F10>2)),"INPUT ERROR","READY"))) -> INPUT REQUIRED | D9: missing | E9: FY2030 | F9: ratio | G9: MRNA pipeline rNPV uses its live 10-K program list, but commercial forecasts, success probabilities, launch timing, partner economics, and remaining development costs are not reported as valuation inputs. Enter a source or valuation rationale for each input. Forecast FY2030; the filed revenue base includes product and collaboration revenue. | H9: Input Required!F10 | I9: ='Input Required'!G10 -> 0
A10: commercial_revenue_growth | B10: Commercial franchise revenue growth | C10: =IF('Input Required'!F11="","INPUT REQUIRED",IF(AND('Input Required'!H11="Yes",'Input Required'!G11=""),"SOURCE REQUIRED",IF(OR(AND('Input Required'!F11<>"",NOT(ISNUMBER('Input Required'!F11))),AND(ISNUMBER('Input Required'!F11),'Input Required'!F11<-0.95),AND(ISNUMBER('Input Required'!F11),'Input Required'!F11>2)),"INPUT ERROR","READY"))) -> INPUT REQUIRED | D10: missing | E10: FY2031 | F10: ratio | G10: MRNA pipeline rNPV uses its live 10-K program list, but commercial forecasts, success probabilities, launch timing, partner economics, and remaining development costs are not reported as valuation inputs. Enter a source or valuation rationale for each input. Forecast FY2031; the filed revenue base includes product and collaboration revenue. | H10: Input Required!F11 | I10: ='Input Required'!G11 -> 0
A11: commercial_revenue_growth | B11: Commercial franchise revenue growth | C11: =IF('Input Required'!F12="","INPUT REQUIRED",IF(AND('Input Required'!H12="Yes",'Input Required'!G12=""),"SOURCE REQUIRED",IF(OR(AND('Input Required'!F12<>"",NOT(ISNUMBER('Input Required'!F12))),AND(ISNUMBER('Input Required'!F12),'Input Required'!F12<-0.95),AND(ISNUMBER('Input Required'!F12),'Input Required'!F12>2)),"INPUT ERROR","READY"))) -> INPUT REQUIRED | D11: missing | E11: FY2032 | F11: ratio | G11: MRNA pipeline rNPV uses its live 10-K program list, but commercial forecasts, success probabilities, launch timing, partner economics, and remaining development costs are not reported as valuation inputs. Enter a source or valuation rationale for each input. Forecast FY2032; the filed revenue base includes product and collaboration revenue. | H11: Input Required!F12 | I11: ='Input Required'!G12 -> 0
A12: commercial_revenue_growth | B12: Commercial franchise revenue growth | C12: =IF('Input Required'!F13="","INPUT REQUIRED",IF(AND('Input Required'!H13="Yes",'Input Required'!G13=""),"SOURCE REQUIRED",IF(OR(AND('Input Required'!F13<>"",NOT(ISNUMBER('Input Required'!F13))),AND(ISNUMBER('Input Required'!F13),'Input Required'!F13<-0.95),AND(ISNUMBER('Input Required'!F13),'Input Required'!F13>2)),"INPUT ERROR","READY"))) -> INPUT REQUIRED | D12: missing | E12: FY2033 | F12: ratio | G12: MRNA pipeline rNPV uses its live 10-K program list, but commercial forecasts, success probabilities, launch timing, partner economics, and remaining development costs are not reported as valuation inputs. Enter a source or valuation rationale for each input. Forecast FY2033; the filed revenue base includes product and collaboration revenue. | H12: Input Required!F13 | I12: ='Input Required'!G13 -> 0
A13: commercial_revenue_growth | B13: Commercial franchise revenue growth | C13: =IF('Input Required'!F14="","INPUT REQUIRED",IF(AND('Input Required'!H14="Yes",'Input Required'!G14=""),"SOURCE REQUIRED",IF(OR(AND('Input Required'!F14<>"",NOT(ISNUMBER('Input Required'!F14))),AND(ISNUMBER('Input Required'!F14),'Input Required'!F14<-0.95),AND(ISNUMBER('Input Required'!F14),'Input Required'!F14>2)),"INPUT ERROR","READY"))) -> INPUT REQUIRED | D13: missing | E13: FY2034 | F13: ratio | G13: MRNA pipeline rNPV uses its live 10-K program list, but commercial forecasts, success probabilities, launch timing, partner economics, and remaining development costs are not reported as valuation inputs. Enter a source or valuation rationale for each input. Forecast FY2034; the filed revenue base includes product and collaboration revenue. | H13: Input Required!F14 | I13: ='Input Required'!G14 -> 0
A14: commercial_revenue_growth | B14: Commercial franchise revenue growth | C14: =IF('Input Required'!F15="","INPUT REQUIRED",IF(AND('Input Required'!H15="Yes",'Input Required'!G15=""),"SOURCE REQUIRED",IF(OR(AND('Input Required'!F15<>"",NOT(ISNUMBER('Input Required'!F15))),AND(ISNUMBER('Input Required'!F15),'Input Required'!F15<-0.95),AND(ISNUMBER('Input Required'!F15),'Input Required'!F15>2)),"INPUT ERROR","READY"))) -> INPUT REQUIRED | D14: missing | E14: FY2035 | F14: ratio | G14: MRNA pipeline rNPV uses its live 10-K program list, but commercial forecasts, success probabilities, launch timing, partner economics, and remaining development costs are not reported as valuation inputs. Enter a source or valuation rationale for each input. Forecast FY2035; the filed revenue base includes product and collaboration revenue. | H14: Input Required!F15 | I14: ='Input Required'!G15 -> 0
A15: commercial_fcf_margin | B15: Existing commercial portfolio post-tax cash margin | C15: =IF('Input Required'!F16="","INPUT REQUIRED",IF(AND('Input Required'!H16="Yes",'Input Required'!G16=""),"SOURCE REQUIRED",IF(OR(AND('Input Required'!F16<>"",NOT(ISNUMBER('Input Required'!F16))),AND(ISNUMBER('Input Required'!F16),'Input Required'!F16<-1),AND(ISNUMBER('Input Required'!F16),'Input Required'!F16>1)),"INPUT ERROR","READY"))) -> INPUT REQUIRED | D15: missing | F15: ratio | G15: MRNA pipeline rNPV uses its live 10-K program list, but commercial forecasts, success probabilities, launch timing, partner economics, and remaining development costs are not reported as valuation inputs. Enter a source or valuation rationale for each input. This margin excludes the separately modeled pipeline development costs. | H15: Input Required!F16 | I15: ='Input Required'!G16 -> 0
A16: asset_include:mRNA-4157 | B16: mRNA-4157 include in rNPV | C16: =IF('Input Required'!F17="","INPUT REQUIRED",IF(AND('Input Required'!H17="Yes",'Input Required'!G17=""),"SOURCE REQUIRED",IF(OR(AND('Input Required'!F17<>"",NOT(ISNUMBER('Input Required'!F17))),AND(ISNUMBER('Input Required'!F17),NOT(OR('Input Required'!F17=0,'Input Required'!F17=1))),AND(ISNUMBER('Input Required'!F17),'Input Required'!F17<0),AND(ISNUMBER('Input Required'!F17),'Input Required'!F17>1)),"INPUT ERROR","READY"))) -> INPUT REQUIRED | D16: missing | F16: 0 or 1 | G16: MRNA pipeline rNPV uses its live 10-K program list, but commercial forecasts, success probabilities, launch timing, partner economics, and remaining development costs are not reported as valuation inputs. Enter a source or valuation rationale for each input. SEC filing lists mRNA-4157 at Phase 2 with Merck. | H16: Input Required!F17 | I16: ='Input Required'!G17 -> 0
A17: asset_launch_year:mRNA-4157 | B17: mRNA-4157 expected launch year | C17: =IF('Input Required'!F18="","INPUT REQUIRED",IF(AND('Input Required'!H18="Yes",'Input Required'!G18=""),"SOURCE REQUIRED",IF(OR(AND('Input Required'!F18<>"",NOT(ISNUMBER('Input Required'!F18))),AND(ISNUMBER('Input Required'!F18),'Input Required'!F18<2026),AND(ISNUMBER('Input Required'!F18),'Input Required'!F18>2035)),"INPUT ERROR","READY"))) -> INPUT REQUIRED | D17: missing | F17: calendar year | G17: MRNA pipeline rNPV uses its live 10-K program list, but commercial forecasts, success probabilities, launch timing, partner economics, and remaining development costs are not reported as valuation inputs. Enter a source or valuation rationale for each input. SEC filing lists mRNA-4157 at Phase 2 with Merck. | H17: Input Required!F18 | I17: ='Input Required'!G18 -> 0
A18: asset_peak_sales:mRNA-4157 | B18: mRNA-4157 peak annual sales | C18: =IF('Input Required'!F19="","INPUT REQUIRED",IF(AND('Input Required'!H19="Yes",'Input Required'!G19=""),"SOURCE REQUIRED",IF(OR(AND('Input Required'!F19<>"",NOT(ISNUMBER('Input Required'!F19))),AND(ISNUMBER('Input Required'!F19),'Input Required'!F19<0)),"INPUT ERROR","READY"))) -> INPUT REQUIRED | D18: missing | F18: USD actual | G18: MRNA pipeline rNPV uses its live 10-K program list, but commercial forecasts, success probabilities, launch timing, partner economics, and remaining development costs are not reported as valuation inputs. Enter a source or valuation rationale for each input. SEC filing lists mRNA-4157 at Phase 2 with Merck. | H18: Input Required!F19 | I18: ='Input Required'!G19 -> 0
A19: asset_years_to_peak:mRNA-4157 | B19: mRNA-4157 years from launch to peak sales | C19: =IF('Input Required'!F20="","INPUT REQUIRED",IF(AND('Input Required'!H20="Yes",'Input Required'!G20=""),"SOURCE REQUIRED",IF(OR(AND('Input Required'!F20<>"",NOT(ISNUMBER('Input Required'!F20))),AND(ISNUMBER('Input Required'!F20),'Input Required'!F20<1),AND(ISNUMBER('Input Required'!F20),'Input Required'!F20>10)),"INPUT ERROR","READY"))) -> INPUT REQUIRED | D19: missing | F19: years | G19: MRNA pipeline rNPV uses its live 10-K program list, but commercial forecasts, success probabilities, launch timing, partner economics, and remaining development costs are not reported as valuation inputs. Enter a source or valuation rationale for each input. SEC filing lists mRNA-4157 at Phase 2 with Merck. | H19: Input Required!F20 | I19: ='Input Required'!G20 -> 0
A20: asset_exclusivity_year:mRNA-4157 | B20: mRNA-4157 expected loss-of-exclusivity year | C20: =IF('Input Required'!F21="","INPUT REQUIRED",IF(AND('Input Required'!H21="Yes",'Input Required'!G21=""),"SOURCE REQUIRED",IF(OR(AND('Input Required'!F21<>"",NOT(ISNUMBER('Input Required'!F21))),AND(ISNUMBER('Input Required'!F21),'Input Required'!F21<2026),AND(ISNUMBER('Input Required'!F21),'Input Required'!F21>2050)),"INPUT ERROR","READY"))) -> INPUT REQUIRED | D20: missing | F20: calendar year | G20: MRNA pipeline rNPV uses its live 10-K program list, but commercial forecasts, success probabilities, launch timing, partner economics, and remaining development costs are not reported as valuation inputs. Enter a source or valuation rationale for each input. SEC filing lists mRNA-4157 at Phase 2 with Merck. | H20: Input Required!F21 | I20: ='Input Required'!G21 -> 0
A21: asset_post_loe_erosion:mRNA-4157 | B21: mRNA-4157 post-LOE annual sales erosion | C21: =IF('Input Required'!F22="","INPUT REQUIRED",IF(AND('Input Required'!H22="Yes",'Input Required'!G22=""),"SOURCE REQUIRED",IF(OR(AND('Input Required'!F22<>"",NOT(ISNUMBER('Input Required'!F22))),AND(ISNUMBER('Input Required'!F22),'Input Required'!F22<0),AND(ISNUMBER('Input Required'!F22),'Input Required'!F22>0.99)),"INPUT ERROR","READY"))) -> INPUT REQUIRED | D21: missing | F21: ratio | G21: MRNA pipeline rNPV uses its live 10-K program list, but commercial forecasts, success probabilities, launch timing, partner economics, and remaining development costs are not reported as valuation inputs. Enter a source or valuation rationale for each input. SEC filing lists mRNA-4157 at Phase 2 with Merck. | H21: Input Required!F22 | I21: ='Input Required'!G22 -> 0
A22: asset_probability_of_success:mRNA-4157 | B22: mRNA-4157 probability of success | C22: =IF('Input Required'!F23="","INPUT REQUIRED",IF(AND('Input Required'!H23="Yes",'Input Required'!G23=""),"SOURCE REQUIRED",IF(OR(AND('Input Required'!F23<>"",NOT(ISNUMBER('Input Required'!F23))),AND(ISNUMBER('Input Required'!F23),'Input Required'!F23<0),AND(ISNUMBER('Input Required'!F23),'Input Required'!F23>1)),"INPUT ERROR","READY"))) -> INPUT REQUIRED | D22: missing | F22: ratio | G22: MRNA pipeline rNPV uses its live 10-K program list, but commercial forecasts, success probabilities, launch timing, partner economics, and remaining development costs are not reported as valuation inputs. Enter a source or valuation rationale for each input. SEC filing lists mRNA-4157 at Phase 2 with Merck. | H22: Input Required!F23 | I22: ='Input Required'!G23 -> 0
A23: asset_retained_share:mRNA-4157 | B23: mRNA-4157 retained economics after partner share | C23: =IF('Input Required'!F24="","INPUT REQUIRED",IF(AND('Input Required'!H24="Yes",'Input Required'!G24=""),"SOURCE REQUIRED",IF(OR(AND('Input Required'!F24<>"",NOT(ISNUMBER('Input Required'!F24))),AND(ISNUMBER('Input Required'!F24),'Input Required'!F24<0),AND(ISNUMBER('Input Required'!F24),'Input Required'!F24>1)),"INPUT ERROR","READY"))) -> INPUT REQUIRED | D23: missing | F23: ratio | G23: MRNA pipeline rNPV uses its live 10-K program list, but commercial forecasts, success probabilities, launch timing, partner economics, and remaining development costs are not reported as valuation inputs. Enter a source or valuation rationale for each input. SEC filing lists mRNA-4157 at Phase 2 with Merck. | H23: Input Required!F24 | I23: ='Input Required'!G24 -> 0
A24: asset_contribution_margin:mRNA-4157 | B24: mRNA-4157 post-tax cash contribution margin | C24: =IF('Input Required'!F25="","INPUT REQUIRED",IF(AND('Input Required'!H25="Yes",'Input Required'!G25=""),"SOURCE REQUIRED",IF(OR(AND('Input Required'!F25<>"",NOT(ISNUMBER('Input Required'!F25))),AND(ISNUMBER('Input Required'!F25),'Input Required'!F25<-1),AND(ISNUMBER('Input Required'!F25),'Input Required'!F25>1)),"INPUT ERROR","READY"))) -> INPUT REQUIRED | D24: missing | F24: ratio | G24: MRNA pipeline rNPV uses its live 10-K program list, but commercial forecasts, success probabilities, launch timing, partner economics, and remaining development costs are not reported as valuation inputs. Enter a source or valuation rationale for each input. SEC filing lists mRNA-4157 at Phase 2 with Merck. | H24: Input Required!F25 | I24: ='Input Required'!G25 -> 0
A25: asset_development_cost_pv:mRNA-4157 | B25: mRNA-4157 remaining development-cost PV | C25: =IF('Input Required'!F26="","INPUT REQUIRED",IF(AND('Input Required'!H26="Yes",'Input Required'!G26=""),"SOURCE REQUIRED",IF(OR(AND('Input Required'!F26<>"",NOT(ISNUMBER('Input Required'!F26))),AND(ISNUMBER('Input Required'!F26),'Input Required'!F26<0)),"INPUT ERROR","READY"))) -> INPUT REQUIRED | D25: missing | F25: USD actual | G25: MRNA pipeline rNPV uses its live 10-K program list, but commercial forecasts, success probabilities, launch timing, partner economics, and remaining development costs are not reported as valuation inputs. Enter a source or valuation rationale for each input. SEC filing lists mRNA-4157 at Phase 2 with Merck. | H25: Input Required!F26 | I25: ='Input Required'!G26 -> 0
A26: asset_include:mRNA-4359 | B26: mRNA-4359 include in rNPV | C26: =IF('Input Required'!F27="","INPUT REQUIRED",IF(AND('Input Required'!H27="Yes",'Input Required'!G27=""),"SOURCE REQUIRED",IF(OR(AND('Input Required'!F27<>"",NOT(ISNUMBER('Input Required'!F27))),AND(ISNUMBER('Input Required'!F27),NOT(OR('Input Required'!F27=0,'Input Required'!F27=1))),AND(ISNUMBER('Input Required'!F27),'Input Required'!F27<0),AND(ISNUMBER('Input Required'!F27),'Input Required'!F27>1)),"INPUT ERROR","READY"))) -> INPUT REQUIRED | D26: missing | F26: 0 or 1 | G26: MRNA pipeline rNPV uses its live 10-K program list, but commercial forecasts, success probabilities, launch timing, partner economics, and remaining development costs are not reported as valuation inputs. Enter a source or valuation rationale for each input. SEC filing lists mRNA-4359 at Phase 1/2. | H26: Input Required!F27 | I26: ='Input Required'!G27 -> 0
A27: asset_launch_year:mRNA-4359 | B27: mRNA-4359 expected launch year | C27: =IF('Input Required'!F28="","INPUT REQUIRED",IF(AND('Input Required'!H28="Yes",'Input Required'!G28=""),"SOURCE REQUIRED",IF(OR(AND('Input Required'!F28<>"",NOT(ISNUMBER('Input Required'!F28))),AND(ISNUMBER('Input Required'!F28),'Input Required'!F28<2026),AND(ISNUMBER('Input Required'!F28),'Input Required'!F28>2035)),"INPUT ERROR","READY"))) -> INPUT REQUIRED | D27: missing | F27: calendar year | G27: MRNA pipeline rNPV uses its live 10-K program list, but commercial forecasts, success probabilities, launch timing, partner economics, and remaining development costs are not reported as valuation inputs. Enter a source or valuation rationale for each input. SEC filing lists mRNA-4359 at Phase 1/2. | H27: Input Required!F28 | I27: ='Input Required'!G28 -> 0
